Workbook
Name Billion: N!$F$18
Name Con_End: Inputs!$E$12
Name Con_Start: Inputs!$E$10
Name Days_Yr: N!$F$11
Name Grams_Oz: N!$F$21
Name Master_Integrity: Inputs!$E$112
Name Million: N!$F$17
Name Model_Start: Inputs!$E$7
Name Months_Qtr: N!$F$14
Name Months_Yr: N!$F$12
Name Name_Company: N!$F$6
Name Name_Model: N!$F$7
Name Name_Project: N!$F$8
Name Ops_End: Inputs!$E$17
Name Ops_Start: Inputs!$E$15
Name Qtrs_Yr: N!$F$13
Name Thousand: N!$F$16
Name Verysmallnumber: N!$F$19

Sheet   
B13: =Name_Model -> New Modelling Standards
B14: Corality Training Model
B16: Sydney, 1 April 2013
B22: Contact Details:
B23: Tim Heng
B24: Email | C24: tim.heng@corality.com
B25: Phone | C25: +61 2 9229 7457
B34: Level 7 | 33 York Street | Sydney NSW 2000 Australia | Phone +612 9222 9222 | | J34: Web www.corality.com

Sheet Corality
B50: Level 8 | 200 George Street | Sydney NSW 2000 Australia | Phone +612 9222 9222 | Web www.corality.com

Sheet Inputs
A1: Assumptions
A2: =Name_Project -> Gold Mining Project
A3: Master Integrity | D3: =Master_Integrity -> 0
C5: Timing
C6: Start
C7: Model Start Date | D7: Date | E7: 40908
C9: Construction
C10: Start | D10: Date | E10: =Model_Start+1 -> 40909
C11: Duration | D11: Qtr(s) | E11: 4
C12: End | D12: Date | E12: =EOMONTH(E10,E11*Months_Qtr-1) -> 41274
C14: Operations
C15: Start | D15: Date | E15: =E12+1 -> 41275
C16: Duration | D16: Yr(s) | E16: 10
C17: End | D17: Date | E17: =EOMONTH(E15,E16*Months_Yr-1) -> 44926
C19: Construction
C20: Categories
C21: Development Costs | E21: Contract Cost | G21: Total | H21: 1 | I21: =H21+1 -> 2 | J21: =I21+1 -> 3 | K21: =J21+1 -> 4 | L21: =K21+1 -> 5 | M21: =L21+1 -> 6 | N21: =M21+1 -> 7 | O21: =N21+1 -> 8 | P21: =O21+1 -> 9 | ... S21: =R21+1 -> 12
C22: Infrastructure | D22: AUD M | E22: 30 | G22: =SUM(H22:AK22) -> 1 | H22: 0.25 | I22: 0.25 | J22: 0.25 | K22: 0.25
C23: Overburden | D23: AUD M | E23: 15 | G23: =SUM(H23:AK23) -> 1 | I23: 0.25 | J23: 0.25 | K23: 0.5
C24: Processing Plant | D24: AUD M | E24: 75 | G24: =SUM(H24:AK24) -> 1 | J24: 0.5 | K24: 0.5
C25: Storage Dam | D25: AUD M | E25: 20 | G25: =SUM(H25:AK25) -> 1 | J25: 0.3 | K25: 0.7
C26: Civil Works | D26: AUD M | E26: 15 | G26: =SUM(H26:AK26) -> 1 | I26: 0.5 | J26: 0.25 | K26: 0.25
C27: Spare | D27: AUD M | E27: 0 | G27: =SUM(H27:AK27) -> 0
C28: Spare | D28: AUD M | E28: 0 | G28: =SUM(H28:AK28) -> 0
C29: Total | D29: AUD M | E29: =SUM(E21:E28) -> 155
C31: Contingency | D31: % | E31: 0.1
C33: Operations
C34: Production
C35: Period | F35: 1 | G35: 2 | H35: 3 | I35: 4
C36: Ore Mined | D36: t p.a. | F36: 500000 | G36: 1250000 | H36: 1250000 | I36: 1250000
C38: Strip Ratio | D38: x | F38: 2.5 | G38: 2.5 | H38: 1.5 | I38: 1.5
C40: Grade
C41: Period | F41: 1 | G41: 2 | H41: 3 | I41: 4
C42: Grams per Tonne | D42: g/t | F42: 5 | G42: 5 | H42: 4.5 | I42: 4
C44: Milling
C45: Recovery Rate | D45: % | F45: 0.85
C47: Revenue
C48: Price
C49: Period | F49: 2011 | G49: 2012 | H49: 2013 | I49: 2014
C50: Price | D50: USD / Oz | F50: 1000 | G50: 1000 | H50: 1500 | I50: 1000
C52: Operational Expenditure
C53: Fixed Costs
C54: Labour | D54: AUD M p.a. | F54: 2
C55: Leasing | D55: AUD M p.a. | F55: 5
C56: Head Office | D56: AUD M p.a. | F56: 1.5
C57: Insurance | D57: AUD M p.a. | F57: 1
C58: Fixed O&M | D58: AUD M p.a. | F58: 4
C59: Laboratory | D59: AUD M p.a. | F59: 1
C60: Spare | D60: AUD M p.a.
C61: Spare | D61: AUD M p.a.
C63: Variable Costs
C64: Mining | D64: AUD / Tonne Mined | F64: 10
C65: Processing | D65: AUD / Tonne Milled | F65: 20
C66: Waste Transport | D66: AUD / Tonne Waste | F66: 5
C68: Funding
C69: Senior Debt
C70: Gearing Ratio | D70: % | F70: 0.7
C71: Total Funding Required | D71: AUD M | F71: =E29*(1+E31)*F70 -> 119.35
C73: Period | F73: Cons | G73: 1 | H73: 2 | I73: 3 | J73: 4
C74: Margin | D74: % p.a. | F74: 0.035 | G74: 0.025 | H74: 0.025 | I74: 0.025 | J74: 0.025
C76: Repayment Terms | H76: From | I76: To
C77: Tenor | D77: Yr(s) | F77: 6 | H77: =E15 -> 41275 | I77: =EOMONTH(H77,F77*Months_Yr-1) -> 43465
C79: Equity
C80: Returns
C81: Discount Rate | D81: % p.a. | F81: 0.15
C83: Macroeconomics
C84: Interest Rate
C85: Calendar Year | D85: # | F85: 2011 | G85: 2012 | H85: 2013 | I85: 2014
C86: Base Rate | D86: % p.a. | F86: 0.036 | G86: 0.03 | H86: 0.029 | I86: 0.03
C88: Exchange Rate
C89: Calendar Year | D89: # | F89: 2011 | G89: 2012 | H89: 2013 | I89: 2014
C90: AUD to USD | D90: FX | F90: 1.02 | G90: 1.02 | H90: 1.02 | I90: 1.02
C92: Cost Escalation
C93: Calendar Year | D93: # | F93: 2011 | G93: 2012 | H93: 2013 | I93: 2014
C94: Escalation Rate | D94: % p.a. | F94: 0.02 | G94: 0.02 | H94: 0.02 | I94: 0.02
C96: Working Capital
C97: Debtor Days | D97: Days | F97: 30
C98: Creditor Days | D98: Days | F98: 40
C100: Taxation
C101: Tax Rate | D101: % | F101: 0.3
C103: Infrastructure
C104: Integrity Checks
C106: Spare
C107: Spare
C108: Spare
C109: Spare
C110: Spare
C111: Spare
C112: Master Check | E112: =ROUND(SUM(E106:E111),8) -> 0

Sheet One Line
A1: Calculations
A2: =Name_Project -> Gold Mining Project
A3: Master Integrity | D3: =Master_Integrity -> 0
A4: Period Start | J4: =I5+1 -> 40909 | K4: =J5+1 -> 41000 | L4: =K5+1 -> 41091 | M4: =L5+1 -> 41183 | N4: =M5+1 -> 41275 | O4: =N5+1 -> 41365 | P4: =O5+1 -> 41456 | Q4: =P5+1 -> 41548 | ... BI4: =BH5+1 -> 45566
A5: Period End | I5: =Model_Start -> 40908 | J5: =EOMONTH(J4,Months_Qtr-1) -> 40999 | K5: =EOMONTH(K4,Months_Qtr-1) -> 41090 | L5: =EOMONTH(L4,Months_Qtr-1) -> 41182 | M5: =EOMONTH(M4,Months_Qtr-1) -> 41274 | N5: =EOMONTH(N4,Months_Qtr-1) -> 41364 | O5: =EOMONTH(O4,Months_Qtr-1) -> 41455 | P5: =EOMONTH(P4,Months_Qtr-1) -> 41547 | Q5: =EOMONTH(Q4,Months_Qtr-1) -> 41639 | ... BI5: =EOMONTH(BI4,Months_Qtr-1) -> 45657
A6: Construction | J6: =IF(AND(J$4>=Con_Start,J$5<=Con_End),1,0) -> 1 | K6: =IF(AND(K$4>=Con_Start,K$5<=Con_End),1,0) -> 1 | L6: =IF(AND(L$4>=Con_Start,L$5<=Con_End),1,0) -> 1 | M6: =IF(AND(M$4>=Con_Start,M$5<=Con_End),1,0) -> 1 | N6: =IF(AND(N$4>=Con_Start,N$5<=Con_End),1,0) -> 0 | O6: =IF(AND(O$4>=Con_Start,O$5<=Con_End),1,0) -> 0 | P6: =IF(AND(P$4>=Con_Start,P$5<=Con_End),1,0) -> 0 | Q6: =IF(AND(Q$4>=Con_Start,Q$5<=Con_End),1,0) -> 0 | ... BI6: =IF(AND(BI$4>=Con_Start,BI$5<=Con_End),1,0) -> 0
A7: Operations | J7: =IF(AND(J$4>=Ops_Start,J$5<=Ops_End),1,0) -> 0 | K7: =IF(AND(K$4>=Ops_Start,K$5<=Ops_End),1,0) -> 0 | L7: =IF(AND(L$4>=Ops_Start,L$5<=Ops_End),1,0) -> 0 | M7: =IF(AND(M$4>=Ops_Start,M$5<=Ops_End),1,0) -> 0 | N7: =IF(AND(N$4>=Ops_Start,N$5<=Ops_End),1,0) -> 1 | O7: =IF(AND(O$4>=Ops_Start,O$5<=Ops_End),1,0) -> 1 | P7: =IF(AND(P$4>=Ops_Start,P$5<=Ops_End),1,0) -> 1 | Q7: =IF(AND(Q$4>=Ops_Start,Q$5<=Ops_End),1,0) -> 1 | ... BI7: =IF(AND(BI$4>=Ops_Start,BI$5<=Ops_End),1,0) -> 0
C9: Calculations
C10: Equity | E10: NPV
C11: Cashflow Available for Equity | D11: AUD M | E11: =XNPV(Inputs!F81,$I$11:$BI$11,$I$5:$BI$5) -> 103.39827 | I11: 0 | J11: =(((IF(ROUNDUP(SUM($J$7:J$7)*J$7/Qtrs_Yr,0)=0,0,LOOKUP(ROUNDUP(SUM($J$7:J$7)*J$7/Qtrs_Yr,0),Inputs!$F$35:$I$35,Inputs!$F$36:$I$36))/Thousand/Qtrs_Yr)*IF(ROUNDUP(SUM($J$7:J$7)*J$7/Qtrs_Yr,0)=0,0,LOOKUP(ROUNDUP(SUM($J$7:J$7)*J$7/Qtrs_Yr,0),Inputs!$F$41:$I$41,Inputs!$F$42:$I$42))/Grams_Oz*Inputs!$F$45)*LOOKUP(YEAR(J$5),Inputs!$F$49:$I$49,Inputs!$F$50:$I$50)/Thousand/LOOKUP(YEAR(J$5),Inputs!$F$89:$I$89,Inputs!$F$90:$I$90)*(J5-I5-Inputs!$F$97)/(J5-I5)+((IF(ROUNDUP(SUM($I$7:I$7)*I$7/Qtrs_Yr,0)=0,0,LOOKUP(ROUNDUP(SUM($I$7:I$7)*I$7/Qtrs_Yr,0),Inputs!$F$35:$I$35,Inputs!$F$36:$I$36))/Thousand/Qtrs_Yr)*IF(ROUNDUP(SUM($I$7:I$7)*I$7/Qtrs_Yr,0)=0,0,LOOKUP(ROUNDUP(SUM($I$7:I$7)*I$7/Qtrs_Yr,0),Inputs!$F$41:$I$41,Inputs!$F$42:$I$42))/Grams_Oz*Inputs!$F$45)*LOOKUP(YEAR(I$5),Inputs!$F$49:$I$49,Inputs!$F$50:$I$50)/Thousand/LOOKUP(YEAR(I$5),Inputs!$F$89:$I$89,Inputs!$F$90:$I$90)*Inputs!$F$97/(I5-H5))-(((Inputs!$F$64*(IF(ROUNDUP(SUM($J$7:J$7)*J$7/Qtrs_Yr,0)=0,0,LOOKUP(ROUNDUP(SUM($J$7:J$7)*J$7/Qtrs_Yr,0),Inputs!$F$35:$I$35,Inputs!$F$36:$I$36))/Thousand/Qtrs_Yr+IF(ROUNDUP(SUM($J$7:J$7)*J$7/Qtrs_Yr,0)=0,0,LOOKUP(ROUNDUP(SUM($J$7:J$7)*J$7/Qtrs_Yr,0),Inputs!$F$35:$I$35,Inputs!$F$38:$I$38)*LOOKUP(ROUNDUP(SUM($J$7:J$7)*J$7/Qtrs_Yr,0),Inputs!$F$35:$I$35,Inputs!$F$36:$I$36))/Thousand/Qtrs_Yr)+Inputs!$F$65*(IF(ROUNDUP(SUM($J$7:J$7)*J$7/Qtrs_Yr,0)=0,0,LOOKUP(ROUNDUP(SUM($J$7:J$7)*J$7/Qtrs_Yr,0),Inputs!$F$35:$I$35,Inputs!$F$36:$I$36))/Thousand/Qtrs_Yr)+Inputs!$F$66*(IF(ROUNDUP(SUM($J$7:J$7)*J$7/Qtrs_Yr,0)=0,0,LOOKUP(ROUNDUP(SUM($J$7:J$7)*J$7/Qtrs_Yr,0),Inputs!$F$35:$I$35,Inputs!$F$38:$I$38)*LOOKUP(ROUNDUP(SUM($J$7:J$7)*J$7/Qtrs_Yr,0),Inputs!$F$35:$I$35,Inputs!$F$36:$I$36))/Thousand/Qtrs_Yr))/Thousand+SUM(Inputs!$F$54:$F$61)*J$7/Qtrs_Yr)*(1+LOOKUP(YEAR(J$5),Inputs!$F$93:$I$93,Inputs!$F$94:$I$94)/Qtrs_Yr)^(COUNT($J$7:J7))*(J5-I5-Inputs!$F$98)/(J5-I5)+((Inputs!$F$64*(IF(ROUNDUP(SUM($I$7:I$7)*I$7/Qtrs_Yr,0)=0,0,LOOKUP(ROUNDUP(SUM($I$7:I$7)*I$7/Qtrs_Yr,0),Inputs!$F$35:$I$35,Inputs!$F$36:$I$36))/Thousand/Qtrs_Yr+IF(ROUNDUP(SUM($I$7:I$7)*I$7/Qtrs_Yr,0)=0,0,LOOKUP(ROUNDUP(SUM($I$7:I$7)*I$7/Qtrs_Yr,0),Inputs!$F$35:$I$35,Inputs!$F$38:$I$38)*LOOKUP(ROUNDUP(SUM($I$7:I$7)*I$7/Qtrs_Yr,0),Inputs!$F$35:$I$35,Inputs!$F$36:$I$36))/Thousand/Qtrs_Yr)+Inputs!$F$65*(IF(ROUNDUP(SUM($I$7:I$7)*I$7/Qtrs_Yr,0)=0,0,LOOKUP(ROUNDUP(SUM($I$7:I$7)*I$7/Qtrs_Yr,0),Inputs!$F$35:$I$35,Inputs!$F$36:$I$36))/Thousand/Qtrs_Yr)+Inputs!$F$66*(IF(ROUNDUP(SUM($I$7:I$7)*I$7/Qtrs_Yr,0)=0,0,LOOKUP(ROUNDUP(SUM($I$7:I$7)*I$7/Qtrs_Yr,0),Inputs!$F$35:$I$35,Inputs!$F$38:$I$38)*LOOKUP(ROUNDUP(SUM($I$7:I$7)*I$7/Qtrs_Yr,0),Inputs!$F$35:$I$35,Inputs!$F$36:$I$36))/Thousand/Qtrs_Yr))/Thousand+SUM(Inputs!$F$54:$F$61)*I$7/Qtrs_Yr)*(1+LOOKUP(YEAR(J$5),Inputs!$F$93:$I$93,Inputs!$F$94:$I$94)/Qtrs_Yr)^(COUNT($I$7:I7))*Inputs!$F$98/(I5-H5))-(((IF(ROUNDUP(SUM($J$7:J$7)*J$7/Qtrs_Yr,0)=0,0,LOOKUP(ROUNDUP(SUM($J$7:J$7)*J$7/Qtrs_Yr,0),Inputs!$F$35:$I$35,Inputs!$F$36:$I$36))/Thousand/Qtrs_Yr)*IF(ROUNDUP(SUM($J$7:J$7)*J$7/Qtrs_Yr,0)=0,0,LOOKUP(ROUNDUP(SUM($J$7:J$7)*J$7/Qtrs_Yr,0),Inputs!$F$41:$I$41,Inputs!$F$42:$I$42))/Grams_Oz*Inputs!$F$45)*LOOKUP(YEAR(J$5),Inputs!$F$49:$I$49,Inputs!$F$50:$I$50)/Thousand/LOOKUP(YEAR(J$5),Inputs!$F$89:$I$89,Inputs!$F$90:$I$90)-((Inputs!$F$64*(IF(ROUNDUP(SUM($J$7:J$7)*J$7/Qtrs_Yr,0)=0,0,LOOKUP(ROUNDUP(SUM($J$7:J$7)*J$7/Qtrs_Yr,0),Inputs!$F$35:$I$35,Inputs!$F$36:$I$36))/Thousand/Qtrs_Yr+IF(ROUNDUP(SUM($J$7:J$7)*J$7/Qtrs_Yr,0)=0,0,LOOKUP(ROUNDUP(SUM($J$7:J$7)*J$7/Qtrs_Yr,0),Inputs!$F$35:$I$35,Inputs!$F$38:$I$38)*LOOKUP(ROUNDUP(SUM($J$7:J$7)*J$7/Qtrs_Yr,0),Inputs!$F$35:$I$35,Inputs!$F$36:$I$36))/Thousand/Qtrs_Yr)+Inputs!$F$65*(IF(ROUNDUP(SUM($J$7:J$7)*J$7/Qtrs_Yr,0)=0,0,LOOKUP(ROUNDUP(SUM($J$7:J$7)*J$7/Qtrs_Yr,0),Inputs!$F$35:$I$35,Inputs!$F$36:$I$36))/Thousand/Qtrs_Yr)+Inputs!$F$66*(IF(ROUNDUP(SUM($J$7:J$7)*J$7/Qtrs_Yr,0)=0,0,LOOKUP(ROUNDUP(SUM($J$7:J$7)*J$7/Qtrs_Yr,0),Inputs!$F$35:$I$35,Inputs!$F$38:$I$38)*LOOKUP(ROUNDUP(SUM($J$7:J$7)*J$7/Qtrs_Yr,0),Inputs!$F$35:$I$35,Inputs!$F$36:$I$36))/Thousand/Qtrs_Yr))/Thousand+SUM(Inputs!$F$54:$F$61)*J$7/Qtrs_Yr)*(1+LOOKUP(YEAR(J$5),Inputs!$F$93:$I$93,Inputs!$F$94:$I$94)/Qtrs_Yr)^(COUNT($J$7:J7))-Inputs!$E$29*(1+Inputs!$E$31)*J$7/Inputs!$E$16/Qtrs_Yr-IF(OR(J$7=0,SUM($J7:J7)*J7>Inputs!$F$77*Qtrs_Yr),0,(Inputs!$F$71-SUM($J7:J7,-1)*J7*Inputs!$F$71/Inputs!$F$77/Qtrs_Yr)*(LOOKUP(YEAR(K$5),Inputs!$F$85:$I$85,Inputs!$F$86:$I$86)+LOOKUP(ROUNDUP(SUM($J7:K7)*K7/Qtrs_Yr,0),Inputs!$G$73:$J$73,Inputs!$G$74:$J$74))/Qtrs_Yr))*Inputs!$F$101-IF(OR(J$7=0,SUM($J7:J7)*J7>Inputs!$F$77*Qtrs_Yr),0,(Inputs!$F$71-SUM($J7:J7,-1)*J7*Inputs!$F$71/Inputs!$F$77/Qtrs_Yr)*(LOOKUP(YEAR(K$5),Inputs!$F$85:$I$85,Inputs!$F$86:$I$86)+LOOKUP(ROUNDUP(SUM($J7:K7)*K7/Qtrs_Yr,0),Inputs!$G$73:$J$73,Inputs!$G$74:$J$74))/Qtrs_Yr)-IF(OR(J$7=0,SUM($J7:J7)*J7>Inputs!$F$77*Qtrs_Yr),0,Inputs!$F$71/Inputs!$F$77/Qtrs_Yr) -> 0 | K11: =(((IF(ROUNDUP(SUM($J$7:K$7)*K$7/Qtrs_Yr,0)=0,0,LOOKUP(ROUNDUP(SUM($J$7:K$7)*K$7/Qtrs_Yr,0),Inputs!$F$35:$I$35,Inputs!$F$36:$I$36))/Thousand/Qtrs_Yr)*IF(ROUNDUP(SUM($J$7:K$7)*K$7/Qtrs_Yr,0)=0,0,LOOKUP(ROUNDUP(SUM($J$7:K$7)*K$7/Qtrs_Yr,0),Inputs!$F$41:$I$41,Inputs!$F$42:$I$42))/Grams_Oz*Inputs!$F$45)*LOOKUP(YEAR(K$5),Inputs!$F$49:$I$49,Inputs!$F$50:$I$50)/Thousand/LOOKUP(YEAR(K$5),Inputs!$F$89:$I$89,Inputs!$F$90:$I$90)*(K5-J5-Inputs!$F$97)/(K5-J5)+((IF(ROUNDUP(SUM($I$7:J$7)*J$7/Qtrs_Yr,0)=0,0,LOOKUP(ROUNDUP(SUM($I$7:J$7)*J$7/Qtrs_Yr,0),Inputs!$F$35:$I$35,Inputs!$F$36:$I$36))/Thousand/Qtrs_Yr)*IF(ROUNDUP(SUM($I$7:J$7)*J$7/Qtrs_Yr,0)=0,0,LOOKUP(ROUNDUP(SUM($I$7:J$7)*J$7/Qtrs_Yr,0),Inputs!$F$41:$I$41,Inputs!$F$42:$I$42))/Grams_Oz*Inputs!$F$45)*LOOKUP(YEAR(J$5),Inputs!$F$49:$I$49,Inputs!$F$50:$I$50)/Thousand/LOOKUP(YEAR(J$5),Inputs!$F$89:$I$89,Inputs!$F$90:$I$90)*Inputs!$F$97/(J5-I5))-(((Inputs!$F$64*(IF(ROUNDUP(SUM($J$7:K$7)*K$7/Qtrs_Yr,0)=0,0,LOOKUP(ROUNDUP(SUM($J$7:K$7)*K$7/Qtrs_Yr,0),Inputs!$F$35:$I$35,Inputs!$F$36:$I$36))/Thousand/Qtrs_Yr+IF(ROUNDUP(SUM($J$7:K$7)*K$7/Qtrs_Yr,0)=0,0,LOOKUP(ROUNDUP(SUM($J$7:K$7)*K$7/Qtrs_Yr,0),Inputs!$F$35:$I$35,Inputs!$F$38:$I$38)*LOOKUP(ROUNDUP(SUM($J$7:K$7)*K$7/Qtrs_Yr,0),Inputs!$F$35:$I$35,Inputs!$F$36:$I$36))/Thousand/Qtrs_Yr)+Inputs!$F$65*(IF(ROUNDUP(SUM($J$7:K$7)*K$7/Qtrs_Yr,0)=0,0,LOOKUP(ROUNDUP(SUM($J$7:K$7)*K$7/Qtrs_Yr,0),Inputs!$F$35:$I$35,Inputs!$F$36:$I$36))/Thousand/Qtrs_Yr)+Inputs!$F$66*(IF(ROUNDUP(SUM($J$7:K$7)*K$7/Qtrs_Yr,0)=0,0,LOOKUP(ROUNDUP(SUM($J$7:K$7)*K$7/Qtrs_Yr,0),Inputs!$F$35:$I$35,Inputs!$F$38:$I$38)*LOOKUP(ROUNDUP(SUM($J$7:K$7)*K$7/Qtrs_Yr,0),Inputs!$F$35:$I$35,Inputs!$F$36:$I$36))/Thousand/Qtrs_Yr))/Thousand+SUM(Inputs!$F$54:$F$61)*K$7/Qtrs_Yr)*(1+LOOKUP(YEAR(K$5),Inputs!$F$93:$I$93,Inputs!$F$94:$I$94)/Qtrs_Yr)^(COUNT($J$7:K7))*(K5-J5-Inputs!$F$98)/(K5-J5)+((Inputs!$F$64*(IF(ROUNDUP(SUM($I$7:J$7)*J$7/Qtrs_Yr,0)=0,0,LOOKUP(ROUNDUP(SUM($I$7:J$7)*J$7/Qtrs_Yr,0),Inputs!$F$35:$I$35,Inputs!$F$36:$I$36))/Thousand/Qtrs_Yr+IF(ROUNDUP(SUM($I$7:J$7)*J$7/Qtrs_Yr,0)=0,0,LOOKUP(ROUNDUP(SUM($I$7:J$7)*J$7/Qtrs_Yr,0),Inputs!$F$35:$I$35,Inputs!$F$38:$I$38)*LOOKUP(ROUNDUP(SUM($I$7:J$7)*J$7/Qtrs_Yr,0),Inputs!$F$35:$I$35,Inputs!$F$36:$I$36))/Thousand/Qtrs_Yr)+Inputs!$F$65*(IF(ROUNDUP(SUM($I$7:J$7)*J$7/Qtrs_Yr,0)=0,0,LOOKUP(ROUNDUP(SUM($I$7:J$7)*J$7/Qtrs_Yr,0),Inputs!$F$35:$I$35,Inputs!$F$36:$I$36))/Thousand/Qtrs_Yr)+Inputs!$F$66*(IF(ROUNDUP(SUM($I$7:J$7)*J$7/Qtrs_Yr,0)=0,0,LOOKUP(ROUNDUP(SUM($I$7:J$7)*J$7/Qtrs_Yr,0),Inputs!$F$35:$I$35,Inputs!$F$38:$I$38)*LOOKUP(ROUNDUP(SUM($I$7:J$7)*J$7/Qtrs_Yr,0),Inputs!$F$35:$I$35,Inputs!$F$36:$I$36))/Thousand/Qtrs_Yr))/Thousand+SUM(Inputs!$F$54:$F$61)*J$7/Qtrs_Yr)*(1+LOOKUP(YEAR(K$5),Inputs!$F$93:$I$93,Inputs!$F$94:$I$94)/Qtrs_Yr)^(COUNT($I$7:J7))*Inputs!$F$98/(J5-I5))-(((IF(ROUNDUP(SUM($J$7:K$7)*K$7/Qtrs_Yr,0)=0,0,LOOKUP(ROUNDUP(SUM($J$7:K$7)*K$7/Qtrs_Yr,0),Inputs!$F$35:$I$35,Inputs!$F$36:$I$36))/Thousand/Qtrs_Yr)*IF(ROUNDUP(SUM($J$7:K$7)*K$7/Qtrs_Yr,0)=0,0,LOOKUP(ROUNDUP(SUM($J$7:K$7)*K$7/Qtrs_Yr,0),Inputs!$F$41:$I$41,Inputs!$F$42:$I$42))/Grams_Oz*Inputs!$F$45)*LOOKUP(YEAR(K$5),Inputs!$F$49:$I$49,Inputs!$F$50:$I$50)/Thousand/LOOKUP(YEAR(K$5),Inputs!$F$89:$I$89,Inputs!$F$90:$I$90)-((Inputs!$F$64*(IF(ROUNDUP(SUM($J$7:K$7)*K$7/Qtrs_Yr,0)=0,0,LOOKUP(ROUNDUP(SUM($J$7:K$7)*K$7/Qtrs_Yr,0),Inputs!$F$35:$I$35,Inputs!$F$36:$I$36))/Thousand/Qtrs_Yr+IF(ROUNDUP(SUM($J$7:K$7)*K$7/Qtrs_Yr,0)=0,0,LOOKUP(ROUNDUP(SUM($J$7:K$7)*K$7/Qtrs_Yr,0),Inputs!$F$35:$I$35,Inputs!$F$38:$I$38)*LOOKUP(ROUNDUP(SUM($J$7:K$7)*K$7/Qtrs_Yr,0),Inputs!$F$35:$I$35,Inputs!$F$36:$I$36))/Thousand/Qtrs_Yr)+Inputs!$F$65*(IF(ROUNDUP(SUM($J$7:K$7)*K$7/Qtrs_Yr,0)=0,0,LOOKUP(ROUNDUP(SUM($J$7:K$7)*K$7/Qtrs_Yr,0),Inputs!$F$35:$I$35,Inputs!$F$36:$I$36))/Thousand/Qtrs_Yr)+Inputs!$F$66*(IF(ROUNDUP(SUM($J$7:K$7)*K$7/Qtrs_Yr,0)=0,0,LOOKUP(ROUNDUP(SUM($J$7:K$7)*K$7/Qtrs_Yr,0),Inputs!$F$35:$I$35,Inputs!$F$38:$I$38)*LOOKUP(ROUNDUP(SUM($J$7:K$7)*K$7/Qtrs_Yr,0),Inputs!$F$35:$I$35,Inputs!$F$36:$I$36))/Thousand/Qtrs_Yr))/Thousand+SUM(Inputs!$F$54:$F$61)*K$7/Qtrs_Yr)*(1+LOOKUP(YEAR(K$5),Inputs!$F$93:$I$93,Inputs!$F$94:$I$94)/Qtrs_Yr)^(COUNT($J$7:K7))-Inputs!$E$29*(1+Inputs!$E$31)*K$7/Inputs!$E$16/Qtrs_Yr-IF(OR(K$7=0,SUM($J7:K7)*K7>Inputs!$F$77*Qtrs_Yr),0,(Inputs!$F$71-SUM($J7:K7,-1)*K7*Inputs!$F$71/Inputs!$F$77/Qtrs_Yr)*(LOOKUP(YEAR(L$5),Inputs!$F$85:$I$85,Inputs!$F$86:$I$86)+LOOKUP(ROUNDUP(SUM($J7:L7)*L7/Qtrs_Yr,0),Inputs!$G$73:$J$73,Inputs!$G$74:$J$74))/Qtrs_Yr))*Inputs!$F$101-IF(OR(K$7=0,SUM($J7:K7)*K7>Inputs!$F$77*Qtrs_Yr),0,(Inputs!$F$71-SUM($J7:K7,-1)*K7*Inputs!$F$71/Inputs!$F$77/Qtrs_Yr)*(LOOKUP(YEAR(L$5),Inputs!$F$85:$I$85,Inputs!$F$86:$I$86)+LOOKUP(ROUNDUP(SUM($J7:L7)*L7/Qtrs_Yr,0),Inputs!$G$73:$J$73,Inputs!$G$74:$J$74))/Qtrs_Yr)-IF(OR(K$7=0,SUM($J7:K7)*K7>Inputs!$F$77*Qtrs_Yr),0,Inputs!$F$71/Inputs!$F$77/Qtrs_Yr) -> 0 | L11: =(((IF(ROUNDUP(SUM($J$7:L$7)*L$7/Qtrs_Yr,0)=0,0,LOOKUP(ROUNDUP(SUM($J$7:L$7)*L$7/Qtrs_Yr,0),Inputs!$F$35:$I$35,Inputs!$F$36:$I$36))/Thousand/Qtrs_Yr)*IF(ROUNDUP(SUM($J$7:L$7)*L$7/Qtrs_Yr,0)=0,0,LOOKUP(ROUNDUP(SUM($J$7:L$7)*L$7/Qtrs_Yr,0),Inputs!$F$41:$I$41,Inputs!$F$42:$I$42))/Grams_Oz*Inputs!$F$45)*LOOKUP(YEAR(L$5),Inputs!$F$49:$I$49,Inputs!$F$50:$I$50)/Thousand/LOOKUP(YEAR(L$5),Inputs!$F$89:$I$89,Inputs!$F$90:$I$90)*(L5-K5-Inputs!$F$97)/(L5-K5)+((IF(ROUNDUP(SUM($I$7:K$7)*K$7/Qtrs_Yr,0)=0,0,LOOKUP(ROUNDUP(SUM($I$7:K$7)*K$7/Qtrs_Yr,0),Inputs!$F$35:$I$35,Inputs!$F$36:$I$36))/Thousand/Qtrs_Yr)*IF(ROUNDUP(SUM($I$7:K$7)*K$7/Qtrs_Yr,0)=0,0,LOOKUP(ROUNDUP(SUM($I$7:K$7)*K$7/Qtrs_Yr,0),Inputs!$F$41:$I$41,Inputs!$F$42:$I$42))/Grams_Oz*Inputs!$F$45)*LOOKUP(YEAR(K$5),Inputs!$F$49:$I$49,Inputs!$F$50:$I$50)/Thousand/LOOKUP(YEAR(K$5),Inputs!$F$89:$I$89,Inputs!$F$90:$I$90)*Inputs!$F$97/(K5-J5))-(((Inputs!$F$64*(IF(ROUNDUP(SUM($J$7:L$7)*L$7/Qtrs_Yr,0)=0,0,LOOKUP(ROUNDUP(SUM($J$7:L$7)*L$7/Qtrs_Yr,0),Inputs!$F$35:$I$35,Inputs!$F$36:$I$36))/Thousand/Qtrs_Yr+IF(ROUNDUP(SUM($J$7:L$7)*L$7/Qtrs_Yr,0)=0,0,LOOKUP(ROUNDUP(SUM($J$7:L$7)*L$7/Qtrs_Yr,0),Inputs!$F$35:$I$35,Inputs!$F$38:$I$38)*LOOKUP(ROUNDUP(SUM($J$7:L$7)*L$7/Qtrs_Yr,0),Inputs!$F$35:$I$35,Inputs!$F$36:$I$36))/Thousand/Qtrs_Yr)+Inputs!$F$65*(IF(ROUNDUP(SUM($J$7:L$7)*L$7/Qtrs_Yr,0)=0,0,LOOKUP(ROUNDUP(SUM($J$7:L$7)*L$7/Qtrs_Yr,0),Inputs!$F$35:$I$35,Inputs!$F$36:$I$36))/Thousand/Qtrs_Yr)+Inputs!$F$66*(IF(ROUNDUP(SUM($J$7:L$7)*L$7/Qtrs_Yr,0)=0,0,LOOKUP(ROUNDUP(SUM($J$7:L$7)*L$7/Qtrs_Yr,0),Inputs!$F$35:$I$35,Inputs!$F$38:$I$38)*LOOKUP(ROUNDUP(SUM($J$7:L$7)*L$7/Qtrs_Yr,0),Inputs!$F$35:$I$35,Inputs!$F$36:$I$36))/Thousand/Qtrs_Yr))/Thousand+SUM(Inputs!$F$54:$F$61)*L$7/Qtrs_Yr)*(1+LOOKUP(YEAR(L$5),Inputs!$F$93:$I$93,Inputs!$F$94:$I$94)/Qtrs_Yr)^(COUNT($J$7:L7))*(L5-K5-Inputs!$F$98)/(L5-K5)+((Inputs!$F$64*(IF(ROUNDUP(SUM($I$7:K$7)*K$7/Qtrs_Yr,0)=0,0,LOOKUP(ROUNDUP(SUM($I$7:K$7)*K$7/Qtrs_Yr,0),Inputs!$F$35:$I$35,Inputs!$F$36:$I$36))/Thousand/Qtrs_Yr+IF(ROUNDUP(SUM($I$7:K$7)*K$7/Qtrs_Yr,0)=0,0,LOOKUP(ROUNDUP(SUM($I$7:K$7)*K$7/Qtrs_Yr,0),Inputs!$F$35:$I$35,Inputs!$F$38:$I$38)*LOOKUP(ROUNDUP(SUM($I$7:K$7)*K$7/Qtrs_Yr,0),Inputs!$F$35:$I$35,Inputs!$F$36:$I$36))/Thousand/Qtrs_Yr)+Inputs!$F$65*(IF(ROUNDUP(SUM($I$7:K$7)*K$7/Qtrs_Yr,0)=0,0,LOOKUP(ROUNDUP(SUM($I$7:K$7)*K$7/Qtrs_Yr,0),Inputs!$F$35:$I$35,Inputs!$F$36:$I$36))/Thousand/Qtrs_Yr)+Inputs!$F$66*(IF(ROUNDUP(SUM($I$7:K$7)*K$7/Qtrs_Yr,0)=0,0,LOOKUP(ROUNDUP(SUM($I$7:K$7)*K$7/Qtrs_Yr,0),Inputs!$F$35:$I$35,Inputs!$F$38:$I$38)*LOOKUP(ROUNDUP(SUM($I$7:K$7)*K$7/Qtrs_Yr,0),Inputs!$F$35:$I$35,Inputs!$F$36:$I$36))/Thousand/Qtrs_Yr))/Thousand+SUM(Inputs!$F$54:$F$61)*K$7/Qtrs_Yr)*(1+LOOKUP(YEAR(L$5),Inputs!$F$93:$I$93,Inputs!$F$94:$I$94)/Qtrs_Yr)^(COUNT($I$7:K7))*Inputs!$F$98/(K5-J5))-(((IF(ROUNDUP(SUM($J$7:L$7)*L$7/Qtrs_Yr,0)=0,0,LOOKUP(ROUNDUP(SUM($J$7:L$7)*L$7/Qtrs_Yr,0),Inputs!$F$35:$I$35,Inputs!$F$36:$I$36))/Thousand/Qtrs_Yr)*IF(ROUNDUP(SUM($J$7:L$7)*L$7/Qtrs_Yr,0)=0,0,LOOKUP(ROUNDUP(SUM($J$7:L$7)*L$7/Qtrs_Yr,0),Inputs!$F$41:$I$41,Inputs!$F$42:$I$42))/Grams_Oz*Inputs!$F$45)*LOOKUP(YEAR(L$5),Inputs!$F$49:$I$49,Inputs!$F$50:$I$50)/Thousand/LOOKUP(YEAR(L$5),Inputs!$F$89:$I$89,Inputs!$F$90:$I$90)-((Inputs!$F$64*(IF(ROUNDUP(SUM($J$7:L$7)*L$7/Qtrs_Yr,0)=0,0,LOOKUP(ROUNDUP(SUM($J$7:L$7)*L$7/Qtrs_Yr,0),Inputs!$F$35:$I$35,Inputs!$F$36:$I$36))/Thousand/Qtrs_Yr+IF(ROUNDUP(SUM($J$7:L$7)*L$7/Qtrs_Yr,0)=0,0,LOOKUP(ROUNDUP(SUM($J$7:L$7)*L$7/Qtrs_Yr,0),Inputs!$F$35:$I$35,Inputs!$F$38:$I$38)*LOOKUP(ROUNDUP(SUM($J$7:L$7)*L$7/Qtrs_Yr,0),Inputs!$F$35:$I$35,Inputs!$F$36:$I$36))/Thousand/Qtrs_Yr)+Inputs!$F$65*(IF(ROUNDUP(SUM($J$7:L$7)*L$7/Qtrs_Yr,0)=0,0,LOOKUP(ROUNDUP(SUM($J$7:L$7)*L$7/Qtrs_Yr,0),Inputs!$F$35:$I$35,Inputs!$F$36:$I$36))/Thousand/Qtrs_Yr)+Inputs!$F$66*(IF(ROUNDUP(SUM($J$7:L$7)*L$7/Qtrs_Yr,0)=0,0,LOOKUP(ROUNDUP(SUM($J$7:L$7)*L$7/Qtrs_Yr,0),Inputs!$F$35:$I$35,Inputs!$F$38:$I$38)*LOOKUP(ROUNDUP(SUM($J$7:L$7)*L$7/Qtrs_Yr,0),Inputs!$F$35:$I$35,Inputs!$F$36:$I$36))/Thousand/Qtrs_Yr))/Thousand+SUM(Inputs!$F$54:$F$61)*L$7/Qtrs_Yr)*(1+LOOKUP(YEAR(L$5),Inputs!$F$93:$I$93,Inputs!$F$94:$I$94)/Qtrs_Yr)^(COUNT($J$7:L7))-Inputs!$E$29*(1+Inputs!$E$31)*L$7/Inputs!$E$16/Qtrs_Yr-IF(OR(L$7=0,SUM($J7:L7)*L7>Inputs!$F$77*Qtrs_Yr),0,(Inputs!$F$71-SUM($J7:L7,-1)*L7*Inputs!$F$71/Inputs!$F$77/Qtrs_Yr)*(LOOKUP(YEAR(M$5),Inputs!$F$85:$I$85,Inputs!$F$86:$I$86)+LOOKUP(ROUNDUP(SUM($J7:M7)*M7/Qtrs_Yr,0),Inputs!$G$73:$J$73,Inputs!$G$74:$J$74))/Qtrs_Yr))*Inputs!$F$101-IF(OR(L$7=0,SUM($J7:L7)*L7>Inputs!$F$77*Qtrs_Yr),0,(Inputs!$F$71-SUM($J7:L7,-1)*L7*Inputs!$F$71/Inputs!$F$77/Qtrs_Yr)*(LOOKUP(YEAR(M$5),Inputs!$F$85:$I$85,Inputs!$F$86:$I$86)+LOOKUP(ROUNDUP(SUM($J7:M7)*M7/Qtrs_Yr,0),Inputs!$G$73:$J$73,Inputs!$G$74:$J$74))/Qtrs_Yr)-IF(OR(L$7=0,SUM($J7:L7)*L7>Inputs!$F$77*Qtrs_Yr),0,Inputs!$F$71/Inputs!$F$77/Qtrs_Yr) -> 0 | M11: =(((IF(ROUNDUP(SUM($J$7:M$7)*M$7/Qtrs_Yr,0)=0,0,LOOKUP(ROUNDUP(SUM($J$7:M$7)*M$7/Qtrs_Yr,0),Inputs!$F$35:$I$35,Inputs!$F$36:$I$36))/Thousand/Qtrs_Yr)*IF(ROUNDUP(SUM($J$7:M$7)*M$7/Qtrs_Yr,0)=0,0,LOOKUP(ROUNDUP(SUM($J$7:M$7)*M$7/Qtrs_Yr,0),Inputs!$F$41:$I$41,Inputs!$F$42:$I$42))/Grams_Oz*Inputs!$F$45)*LOOKUP(YEAR(M$5),Inputs!$F$49:$I$49,Inputs!$F$50:$I$50)/Thousand/LOOKUP(YEAR(M$5),Inputs!$F$89:$I$89,Inputs!$F$90:$I$90)*(M5-L5-Inputs!$F$97)/(M5-L5)+((IF(ROUNDUP(SUM($I$7:L$7)*L$7/Qtrs_Yr,0)=0,0,LOOKUP(ROUNDUP(SUM($I$7:L$7)*L$7/Qtrs_Yr,0),Inputs!$F$35:$I$35,Inputs!$F$36:$I$36))/Thousand/Qtrs_Yr)*IF(ROUNDUP(SUM($I$7:L$7)*L$7/Qtrs_Yr,0)=0,0,LOOKUP(ROUNDUP(SUM($I$7:L$7)*L$7/Qtrs_Yr,0),Inputs!$F$41:$I$41,Inputs!$F$42:$I$42))/Grams_Oz*Inputs!$F$45)*LOOKUP(YEAR(L$5),Inputs!$F$49:$I$49,Inputs!$F$50:$I$50)/Thousand/LOOKUP(YEAR(L$5),Inputs!$F$89:$I$89,Inputs!$F$90:$I$90)*Inputs!$F$97/(L5-K5))-(((Inputs!$F$64*(IF(ROUNDUP(SUM($J$7:M$7)*M$7/Qtrs_Yr,0)=0,0,LOOKUP(ROUNDUP(SUM($J$7:M$7)*M$7/Qtrs_Yr,0),Inputs!$F$35:$I$35,Inputs!$F$36:$I$36))/Thousand/Qtrs_Yr+IF(ROUNDUP(SUM($J$7:M$7)*M$7/Qtrs_Yr,0)=0,0,LOOKUP(ROUNDUP(SUM($J$7:M$7)*M$7/Qtrs_Yr,0),Inputs!$F$35:$I$35,Inputs!$F$38:$I$38)*LOOKUP(ROUNDUP(SUM($J$7:M$7)*M$7/Qtrs_Yr,0),Inputs!$F$35:$I$35,Inputs!$F$36:$I$36))/Thousand/Qtrs_Yr)+Inputs!$F$65*(IF(ROUNDUP(SUM($J$7:M$7)*M$7/Qtrs_Yr,0)=0,0,LOOKUP(ROUNDUP(SUM($J$7:M$7)*M$7/Qtrs_Yr,0),Inputs!$F$35:$I$35,Inputs!$F$36:$I$36))/Thousand/Qtrs_Yr)+Inputs!$F$66*(IF(ROUNDUP(SUM($J$7:M$7)*M$7/Qtrs_Yr,0)=0,0,LOOKUP(ROUNDUP(SUM($J$7:M$7)*M$7/Qtrs_Yr,0),Inputs!$F$35:$I$35,Inputs!$F$38:$I$38)*LOOKUP(ROUNDUP(SUM($J$7:M$7)*M$7/Qtrs_Yr,0),Inputs!$F$35:$I$35,Inputs!$F$36:$I$36))/Thousand/Qtrs_Yr))/Thousand+SUM(Inputs!$F$54:$F$61)*M$7/Qtrs_Yr)*(1+LOOKUP(YEAR(M$5),Inputs!$F$93:$I$93,Inputs!$F$94:$I$94)/Qtrs_Yr)^(COUNT($J$7:M7))*(M5-L5-Inputs!$F$98)/(M5-L5)+((Inputs!$F$64*(IF(ROUNDUP(SUM($I$7:L$7)*L$7/Qtrs_Yr,0)=0,0,LOOKUP(ROUNDUP(SUM($I$7:L$7)*L$7/Qtrs_Yr,0),Inputs!$F$35:$I$35,Inputs!$F$36:$I$36))/Thousand/Qtrs_Yr+IF(ROUNDUP(SUM($I$7:L$7)*L$7/Qtrs_Yr,0)=0,0,LOOKUP(ROUNDUP(SUM($I$7:L$7)*L$7/Qtrs_Yr,0),Inputs!$F$35:$I$35,Inputs!$F$38:$I$38)*LOOKUP(ROUNDUP(SUM($I$7:L$7)*L$7/Qtrs_Yr,0),Inputs!$F$35:$I$35,Inputs!$F$36:$I$36))/Thousand/Qtrs_Yr)+Inputs!$F$65*(IF(ROUNDUP(SUM($I$7:L$7)*L$7/Qtrs_Yr,0)=0,0,LOOKUP(ROUNDUP(SUM($I$7:L$7)*L$7/Qtrs_Yr,0),Inputs!$F$35:$I$35,Inputs!$F$36:$I$36))/Thousand/Qtrs_Yr)+Inputs!$F$66*(IF(ROUNDUP(SUM($I$7:L$7)*L$7/Qtrs_Yr,0)=0,0,LOOKUP(ROUNDUP(SUM($I$7:L$7)*L$7/Qtrs_Yr,0),Inputs!$F$35:$I$35,Inputs!$F$38:$I$38)*LOOKUP(ROUNDUP(SUM($I$7:L$7)*L$7/Qtrs_Yr,0),Inputs!$F$35:$I$35,Inputs!$F$36:$I$36))/Thousand/Qtrs_Yr))/Thousand+SUM(Inputs!$F$54:$F$61)*L$7/Qtrs_Yr)*(1+LOOKUP(YEAR(M$5),Inputs!$F$93:$I$93,Inputs!$F$94:$I$94)/Qtrs_Yr)^(COUNT($I$7:L7))*Inputs!$F$98/(L5-K5))-(((IF(ROUNDUP(SUM($J$7:M$7)*M$7/Qtrs_Yr,0)=0,0,LOOKUP(ROUNDUP(SUM($J$7:M$7)*M$7/Qtrs_Yr,0),Inputs!$F$35:$I$35,Inputs!$F$36:$I$36))/Thousand/Qtrs_Yr)*IF(ROUNDUP(SUM($J$7:M$7)*M$7/Qtrs_Yr,0)=0,0,LOOKUP(ROUNDUP(SUM($J$7:M$7)*M$7/Qtrs_Yr,0),Inputs!$F$41:$I$41,Inputs!$F$42:$I$42))/Grams_Oz*Inputs!$F$45)*LOOKUP(YEAR(M$5),Inputs!$F$49:$I$49,Inputs!$F$50:$I$50)/Thousand/LOOKUP(YEAR(M$5),Inputs!$F$89:$I$89,Inputs!$F$90:$I$90)-((Inputs!$F$64*(IF(ROUNDUP(SUM($J$7:M$7)*M$7/Qtrs_Yr,0)=0,0,LOOKUP(ROUNDUP(SUM($J$7:M$7)*M$7/Qtrs_Yr,0),Inputs!$F$35:$I$35,Inputs!$F$36:$I$36))/Thousand/Qtrs_Yr+IF(ROUNDUP(SUM($J$7:M$7)*M$7/Qtrs_Yr,0)=0,0,LOOKUP(ROUNDUP(SUM($J$7:M$7)*M$7/Qtrs_Yr,0),Inputs!$F$35:$I$35,Inputs!$F$38:$I$38)*LOOKUP(ROUNDUP(SUM($J$7:M$7)*M$7/Qtrs_Yr,0),Inputs!$F$35:$I$35,Inputs!$F$36:$I$36))/Thousand/Qtrs_Yr)+Inputs!$F$65*(IF(ROUNDUP(SUM($J$7:M$7)*M$7/Qtrs_Yr,0)=0,0,LOOKUP(ROUNDUP(SUM($J$7:M$7)*M$7/Qtrs_Yr,0),Inputs!$F$35:$I$35,Inputs!$F$36:$I$36))/Thousand/Qtrs_Yr)+Inputs!$F$66*(IF(ROUNDUP(SUM($J$7:M$7)*M$7/Qtrs_Yr,0)=0,0,LOOKUP(ROUNDUP(SUM($J$7:M$7)*M$7/Qtrs_Yr,0),Inputs!$F$35:$I$35,Inputs!$F$38:$I$38)*LOOKUP(ROUNDUP(SUM($J$7:M$7)*M$7/Qtrs_Yr,0),Inputs!$F$35:$I$35,Inputs!$F$36:$I$36))/Thousand/Qtrs_Yr))/Thousand+SUM(Inputs!$F$54:$F$61)*M$7/Qtrs_Yr)*(1+LOOKUP(YEAR(M$5),Inputs!$F$93:$I$93,Inputs!$F$94:$I$94)/Qtrs_Yr)^(COUNT($J$7:M7))-Inputs!$E$29*(1+Inputs!$E$31)*M$7/Inputs!$E$16/Qtrs_Yr-IF(OR(M$7=0,SUM($J7:M7)*M7>Inputs!$F$77*Qtrs_Yr),0,(Inputs!$F$71-SUM($J7:M7,-1)*M7*Inputs!$F$71/Inputs!$F$77/Qtrs_Yr)*(LOOKUP(YEAR(N$5),Inputs!$F$85:$I$85,Inputs!$F$86:$I$86)+LOOKUP(ROUNDUP(SUM($J7:N7)*N7/Qtrs_Yr,0),Inputs!$G$73:$J$73,Inputs!$G$74:$J$74))/Qtrs_Yr))*Inputs!$F$101-IF(OR(M$7=0,SUM($J7:M7)*M7>Inputs!$F$77*Qtrs_Yr),0,(Inputs!$F$71-SUM($J7:M7,-1)*M7*Inputs!$F$71/Inputs!$F$77/Qtrs_Yr)*(LOOKUP(YEAR(N$5),Inputs!$F$85:$I$85,Inputs!$F$86:$I$86)+LOOKUP(ROUNDUP(SUM($J7:N7)*N7/Qtrs_Yr,0),Inputs!$G$73:$J$73,Inputs!$G$74:$J$74))/Qtrs_Yr)-IF(OR(M$7=0,SUM($J7:M7)*M7>Inputs!$F$77*Qtrs_Yr),0,Inputs!$F$71/Inputs!$F$77/Qtrs_Yr) -> 0 | N11: =(((IF(ROUNDUP(SUM($J$7:N$7)*N$7/Qtrs_Yr,0)=0,0,LOOKUP(ROUNDUP(SUM($J$7:N$7)*N$7/Qtrs_Yr,0),Inputs!$F$35:$I$35,Inputs!$F$36:$I$36))/Thousand/Qtrs_Yr)*IF(ROUNDUP(SUM($J$7:N$7)*N$7/Qtrs_Yr,0)=0,0,LOOKUP(ROUNDUP(SUM($J$7:N$7)*N$7/Qtrs_Yr,0),Inputs!$F$41:$I$41,Inputs!$F$42:$I$42))/Grams_Oz*Inputs!$F$45)*LOOKUP(YEAR(N$5),Inputs!$F$49:$I$49,Inputs!$F$50:$I$50)/Thousand/LOOKUP(YEAR(N$5),Inputs!$F$89:$I$89,Inputs!$F$90:$I$90)*(N5-M5-Inputs!$F$97)/(N5-M5)+((IF(ROUNDUP(SUM($I$7:M$7)*M$7/Qtrs_Yr,0)=0,0,LOOKUP(ROUNDUP(SUM($I$7:M$7)*M$7/Qtrs_Yr,0),Inputs!$F$35:$I$35,Inputs!$F$36:$I$36))/Thousand/Qtrs_Yr)*IF(ROUNDUP(SUM($I$7:M$7)*M$7/Qtrs_Yr,0)=0,0,LOOKUP(ROUNDUP(SUM($I$7:M$7)*M$7/Qtrs_Yr,0),Inputs!$F$41:$I$41,Inputs!$F$42:$I$42))/Grams_Oz*Inputs!$F$45)*LOOKUP(YEAR(M$5),Inputs!$F$49:$I$49,Inputs!$F$50:$I$50)/Thousand/LOOKUP(YEAR(M$5),Inputs!$F$89:$I$89,Inputs!$F$90:$I$90)*Inputs!$F$97/(M5-L5))-(((Inputs!$F$64*(IF(ROUNDUP(SUM($J$7:N$7)*N$7/Qtrs_Yr,0)=0,0,LOOKUP(ROUNDUP(SUM($J$7:N$7)*N$7/Qtrs_Yr,0),Inputs!$F$35:$I$35,Inputs!$F$36:$I$36))/Thousand/Qtrs_Yr+IF(ROUNDUP(SUM($J$7:N$7)*N$7/Qtrs_Yr,0)=0,0,LOOKUP(ROUNDUP(SUM($J$7:N$7)*N$7/Qtrs_Yr,0),Inputs!$F$35:$I$35,Inputs!$F$38:$I$38)*LOOKUP(ROUNDUP(SUM($J$7:N$7)*N$7/Qtrs_Yr,0),Inputs!$F$35:$I$35,Inputs!$F$36:$I$36))/Thousand/Qtrs_Yr)+Inputs!$F$65*(IF(ROUNDUP(SUM($J$7:N$7)*N$7/Qtrs_Yr,0)=0,0,LOOKUP(ROUNDUP(SUM($J$7:N$7)*N$7/Qtrs_Yr,0),Inputs!$F$35:$I$35,Inputs!$F$36:$I$36))/Thousand/Qtrs_Yr)+Inputs!$F$66*(IF(ROUNDUP(SUM($J$7:N$7)*N$7/Qtrs_Yr,0)=0,0,LOOKUP(ROUNDUP(SUM($J$7:N$7)*N$7/Qtrs_Yr,0),Inputs!$F$35:$I$35,Inputs!$F$38:$I$38)*LOOKUP(ROUNDUP(SUM($J$7:N$7)*N$7/Qtrs_Yr,0),Inputs!$F$35:$I$35,Inputs!$F$36:$I$36))/Thousand/Qtrs_Yr))/Thousand+SUM(Inputs!$F$54:$F$61)*N$7/Qtrs_Yr)*(1+LOOKUP(YEAR(N$5),Inputs!$F$93:$I$93,Inputs!$F$94:$I$94)/Qtrs_Yr)^(COUNT($J$7:N7))*(N5-M5-Inputs!$F$98)/(N5-M5)+((Inputs!$F$64*(IF(ROUNDUP(SUM($I$7:M$7)*M$7/Qtrs_Yr,0)=0,0,LOOKUP(ROUNDUP(SUM($I$7:M$7)*M$7/Qtrs_Yr,0),Inputs!$F$35:$I$35,Inputs!$F$36:$I$36))/Thousand/Qtrs_Yr+IF(ROUNDUP(SUM($I$7:M$7)*M$7/Qtrs_Yr,0)=0,0,LOOKUP(ROUNDUP(SUM($I$7:M$7)*M$7/Qtrs_Yr,0),Inputs!$F$35:$I$35,Inputs!$F$38:$I$38)*LOOKUP(ROUNDUP(SUM($I$7:M$7)*M$7/Qtrs_Yr,0),Inputs!$F$35:$I$35,Inputs!$F$36:$I$36))/Thousand/Qtrs_Yr)+Inputs!$F$65*(IF(ROUNDUP(SUM($I$7:M$7)*M$7/Qtrs_Yr,0)=0,0,LOOKUP(ROUNDUP(SUM($I$7:M$7)*M$7/Qtrs_Yr,0),Inputs!$F$35:$I$35,Inputs!$F$36:$I$36))/Thousand/Qtrs_Yr)+Inputs!$F$66*(IF(ROUNDUP(SUM($I$7:M$7)*M$7/Qtrs_Yr,0)=0,0,LOOKUP(ROUNDUP(SUM($I$7:M$7)*M$7/Qtrs_Yr,0),Inputs!$F$35:$I$35,Inputs!$F$38:$I$38)*LOOKUP(ROUNDUP(SUM($I$7:M$7)*M$7/Qtrs_Yr,0),Inputs!$F$35:$I$35,Inputs!$F$36:$I$36))/Thousand/Qtrs_Yr))/Thousand+SUM(Inputs!$F$54:$F$61)*M$7/Qtrs_Yr)*(1+LOOKUP(YEAR(N$5),Inputs!$F$93:$I$93,Inputs!$F$94:$I$94)/Qtrs_Yr)^(COUNT($I$7:M7))*Inputs!$F$98/(M5-L5))-(((IF(ROUNDUP(SUM($J$7:N$7)*N$7/Qtrs_Yr,0)=0,0,LOOKUP(ROUNDUP(SUM($J$7:N$7)*N$7/Qtrs_Yr,0),Inputs!$F$35:$I$35,Inputs!$F$36:$I$36))/Thousand/Qtrs_Yr)*IF(ROUNDUP(SUM($J$7:N$7)*N$7/Qtrs_Yr,0)=0,0,LOOKUP(ROUNDUP(SUM($J$7:N$7)*N$7/Qtrs_Yr,0),Inputs!$F$41:$I$41,Inputs!$F$42:$I$42))/Grams_Oz*Inputs!$F$45)*LOOKUP(YEAR(N$5),Inputs!$F$49:$I$49,Inputs!$F$50:$I$50)/Thousand/LOOKUP(YEAR(N$5),Inputs!$F$89:$I$89,Inputs!$F$90:$I$90)-((Inputs!$F$64*(IF(ROUNDUP(SUM($J$7:N$7)*N$7/Qtrs_Yr,0)=0,0,LOOKUP(ROUNDUP(SUM($J$7:N$7)*N$7/Qtrs_Yr,0),Inputs!$F$35:$I$35,Inputs!$F$36:$I$36))/Thousand/Qtrs_Yr+IF(ROUNDUP(SUM($J$7:N$7)*N$7/Qtrs_Yr,0)=0,0,LOOKUP(ROUNDUP(SUM($J$7:N$7)*N$7/Qtrs_Yr,0),Inputs!$F$35:$I$35,Inputs!$F$38:$I$38)*LOOKUP(ROUNDUP(SUM($J$7:N$7)*N$7/Qtrs_Yr,0),Inputs!$F$35:$I$35,Inputs!$F$36:$I$36))/Thousand/Qtrs_Yr)+Inputs!$F$65*(IF(ROUNDUP(SUM($J$7:N$7)*N$7/Qtrs_Yr,0)=0,0,LOOKUP(ROUNDUP(SUM($J$7:N$7)*N$7/Qtrs_Yr,0),Inputs!$F$35:$I$35,Inputs!$F$36:$I$36))/Thousand/Qtrs_Yr)+Inputs!$F$66*(IF(ROUNDUP(SUM($J$7:N$7)*N$7/Qtrs_Yr,0)=0,0,LOOKUP(ROUNDUP(SUM($J$7:N$7)*N$7/Qtrs_Yr,0),Inputs!$F$35:$I$35,Inputs!$F$38:$I$38)*LOOKUP(ROUNDUP(SUM($J$7:N$7)*N$7/Qtrs_Yr,0),Inputs!$F$35:$I$35,Inputs!$F$36:$I$36))/Thousand/Qtrs_Yr))/Thousand+SUM(Inputs!$F$54:$F$61)*N$7/Qtrs_Yr)*(1+LOOKUP(YEAR(N$5),Inputs!$F$93:$I$93,Inputs!$F$94:$I$94)/Qtrs_Yr)^(COUNT($J$7:N7))-Inputs!$E$29*(1+Inputs!$E$31)*N$7/Inputs!$E$16/Qtrs_Yr-IF(OR(N$7=0,SUM($J7:N7)*N7>Inputs!$F$77*Qtrs_Yr),0,(Inputs!$F$71-SUM($J7:N7,-1)*N7*Inputs!$F$71/Inputs!$F$77/Qtrs_Yr)*(LOOKUP(YEAR(O$5),Inputs!$F$85:$I$85,Inputs!$F$86:$I$86)+LOOKUP(ROUNDUP(SUM($J7:O7)*O7/Qtrs_Yr,0),Inputs!$G$73:$J$73,Inputs!$G$74:$J$74))/Qtrs_Yr))*Inputs!$F$101-IF(OR(N$7=0,SUM($J7:N7)*N7>Inputs!$F$77*Qtrs_Yr),0,(Inputs!$F$71-SUM($J7:N7,-1)*N7*Inputs!$F$71/Inputs!$F$77/Qtrs_Yr)*(LOOKUP(YEAR(O$5),Inputs!$F$85:$I$85,Inputs!$F$86:$I$86)+LOOKUP(ROUNDUP(SUM($J7:O7)*O7/Qtrs_Yr,0),Inputs!$G$73:$J$73,Inputs!$G$74:$J$74))/Qtrs_Yr)-IF(OR(N$7=0,SUM($J7:N7)*N7>Inputs!$F$77*Qtrs_Yr),0,Inputs!$F$71/Inputs!$F$77/Qtrs_Yr) -> 1.2273457 | O11: =(((IF(ROUNDUP(SUM($J$7:O$7)*O$7/Qtrs_Yr,0)=0,0,LOOKUP(ROUNDUP(SUM($J$7:O$7)*O$7/Qtrs_Yr,0),Inputs!$F$35:$I$35,Inputs!$F$36:$I$36))/Thousand/Qtrs_Yr)*IF(ROUNDUP(SUM($J$7:O$7)*O$7/Qtrs_Yr,0)=0,0,LOOKUP(ROUNDUP(SUM($J$7:O$7)*O$7/Qtrs_Yr,0),Inputs!$F$41:$I$41,Inputs!$F$42:$I$42))/Grams_Oz*Inputs!$F$45)*LOOKUP(YEAR(O$5),Inputs!$F$49:$I$49,Inputs!$F$50:$I$50)/Thousand/LOOKUP(YEAR(O$5),Inputs!$F$89:$I$89,Inputs!$F$90:$I$90)*(O5-N5-Inputs!$F$97)/(O5-N5)+((IF(ROUNDUP(SUM($I$7:N$7)*N$7/Qtrs_Yr,0)=0,0,LOOKUP(ROUNDUP(SUM($I$7:N$7)*N$7/Qtrs_Yr,0),Inputs!$F$35:$I$35,Inputs!$F$36:$I$36))/Thousand/Qtrs_Yr)*IF(ROUNDUP(SUM($I$7:N$7)*N$7/Qtrs_Yr,0)=0,0,LOOKUP(ROUNDUP(SUM($I$7:N$7)*N$7/Qtrs_Yr,0),Inputs!$F$41:$I$41,Inputs!$F$42:$I$42))/Grams_Oz*Inputs!$F$45)*LOOKUP(YEAR(N$5),Inputs!$F$49:$I$49,Inputs!$F$50:$I$50)/Thousand/LOOKUP(YEAR(N$5),Inputs!$F$89:$I$89,Inputs!$F$90:$I$90)*Inputs!$F$97/(N5-M5))-(((Inputs!$F$64*(IF(ROUNDUP(SUM($J$7:O$7)*O$7/Qtrs_Yr,0)=0,0,LOOKUP(ROUNDUP(SUM($J$7:O$7)*O$7/Qtrs_Yr,0),Inputs!$F$35:$I$35,Inputs!$F$36:$I$36))/Thousand/Qtrs_Yr+IF(ROUNDUP(SUM($J$7:O$7)*O$7/Qtrs_Yr,0)=0,0,LOOKUP(ROUNDUP(SUM($J$7:O$7)*O$7/Qtrs_Yr,0),Inputs!$F$35:$I$35,Inputs!$F$38:$I$38)*LOOKUP(ROUNDUP(SUM($J$7:O$7)*O$7/Qtrs_Yr,0),Inputs!$F$35:$I$35,Inputs!$F$36:$I$36))/Thousand/Qtrs_Yr)+Inputs!$F$65*(IF(ROUNDUP(SUM($J$7:O$7)*O$7/Qtrs_Yr,0)=0,0,LOOKUP(ROUNDUP(SUM($J$7:O$7)*O$7/Qtrs_Yr,0),Inputs!$F$35:$I$35,Inputs!$F$36:$I$36))/Thousand/Qtrs_Yr)+Inputs!$F$66*(IF(ROUNDUP(SUM($J$7:O$7)*O$7/Qtrs_Yr,0)=0,0,LOOKUP(ROUNDUP(SUM($J$7:O$7)*O$7/Qtrs_Yr,0),Inputs!$F$35:$I$35,Inputs!$F$38:$I$38)*LOOKUP(ROUNDUP(SUM($J$7:O$7)*O$7/Qtrs_Yr,0),Inputs!$F$35:$I$35,Inputs!$F$36:$I$36))/Thousand/Qtrs_Yr))/Thousand+SUM(Inputs!$F$54:$F$61)*O$7/Qtrs_Yr)*(1+LOOKUP(YEAR(O$5),Inputs!$F$93:$I$93,Inputs!$F$94:$I$94)/Qtrs_Yr)^(COUNT($J$7:O7))*(O5-N5-Inputs!$F$98)/(O5-N5)+((Inputs!$F$64*(IF(ROUNDUP(SUM($I$7:N$7)*N$7/Qtrs_Yr,0)=0,0,LOOKUP(ROUNDUP(SUM($I$7:N$7)*N$7/Qtrs_Yr,0),Inputs!$F$35:$I$35,Inputs!$F$36:$I$36))/Thousand/Qtrs_Yr+IF(ROUNDUP(SUM($I$7:N$7)*N$7/Qtrs_Yr,0)=0,0,LOOKUP(ROUNDUP(SUM($I$7:N$7)*N$7/Qtrs_Yr,0),Inputs!$F$35:$I$35,Inputs!$F$38:$I$38)*LOOKUP(ROUNDUP(SUM($I$7:N$7)*N$7/Qtrs_Yr,0),Inputs!$F$35:$I$35,Inputs!$F$36:$I$36))/Thousand/Qtrs_Yr)+Inputs!$F$65*(IF(ROUNDUP(SUM($I$7:N$7)*N$7/Qtrs_Yr,0)=0,0,LOOKUP(ROUNDUP(SUM($I$7:N$7)*N$7/Qtrs_Yr,0),Inputs!$F$35:$I$35,Inputs!$F$36:$I$36))/Thousand/Qtrs_Yr)+Inputs!$F$66*(IF(ROUNDUP(SUM($I$7:N$7)*N$7/Qtrs_Yr,0)=0,0,LOOKUP(ROUNDUP(SUM($I$7:N$7)*N$7/Qtrs_Yr,0),Inputs!$F$35:$I$35,Inputs!$F$38:$I$38)*LOOKUP(ROUNDUP(SUM($I$7:N$7)*N$7/Qtrs_Yr,0),Inputs!$F$35:$I$35,Inputs!$F$36:$I$36))/Thousand/Qtrs_Yr))/Thousand+SUM(Inputs!$F$54:$F$61)*N$7/Qtrs_Yr)*(1+LOOKUP(YEAR(O$5),Inputs!$F$93:$I$93,Inputs!$F$94:$I$94)/Qtrs_Yr)^(COUNT($I$7:N7))*Inputs!$F$98/(N5-M5))-(((IF(ROUNDUP(SUM($J$7:O$7)*O$7/Qtrs_Yr,0)=0,0,LOOKUP(ROUNDUP(SUM($J$7:O$7)*O$7/Qtrs_Yr,0),Inputs!$F$35:$I$35,Inputs!$F$36:$I$36))/Thousand/Qtrs_Yr)*IF(ROUNDUP(SUM($J$7:O$7)*O$7/Qtrs_Yr,0)=0,0,LOOKUP(ROUNDUP(SUM($J$7:O$7)*O$7/Qtrs_Yr,0),Inputs!$F$41:$I$41,Inputs!$F$42:$I$42))/Grams_Oz*Inputs!$F$45)*LOOKUP(YEAR(O$5),Inputs!$F$49:$I$49,Inputs!$F$50:$I$50)/Thousand/LOOKUP(YEAR(O$5),Inputs!$F$89:$I$89,Inputs!$F$90:$I$90)-((Inputs!$F$64*(IF(ROUNDUP(SUM($J$7:O$7)*O$7/Qtrs_Yr,0)=0,0,LOOKUP(ROUNDUP(SUM($J$7:O$7)*O$7/Qtrs_Yr,0),Inputs!$F$35:$I$35,Inputs!$F$36:$I$36))/Thousand/Qtrs_Yr+IF(ROUNDUP(SUM($J$7:O$7)*O$7/Qtrs_Yr,0)=0,0,LOOKUP(ROUNDUP(SUM($J$7:O$7)*O$7/Qtrs_Yr,0),Inputs!$F$35:$I$35,Inputs!$F$38:$I$38)*LOOKUP(ROUNDUP(SUM($J$7:O$7)*O$7/Qtrs_Yr,0),Inputs!$F$35:$I$35,Inputs!$F$36:$I$36))/Thousand/Qtrs_Yr)+Inputs!$F$65*(IF(ROUNDUP(SUM($J$7:O$7)*O$7/Qtrs_Yr,0)=0,0,LOOKUP(ROUNDUP(SUM($J$7:O$7)*O$7/Qtrs_Yr,0),Inputs!$F$35:$I$35,Inputs!$F$36:$I$36))/Thousand/Qtrs_Yr)+Inputs!$F$66*(IF(ROUNDUP(SUM($J$7:O$7)*O$7/Qtrs_Yr,0)=0,0,LOOKUP(ROUNDUP(SUM($J$7:O$7)*O$7/Qtrs_Yr,0),Inputs!$F$35:$I$35,Inputs!$F$38:$I$38)*LOOKUP(ROUNDUP(SUM($J$7:O$7)*O$7/Qtrs_Yr,0),Inputs!$F$35:$I$35,Inputs!$F$36:$I$36))/Thousand/Qtrs_Yr))/Thousand+SUM(Inputs!$F$54:$F$61)*O$7/Qtrs_Yr)*(1+LOOKUP(YEAR(O$5),Inputs!$F$93:$I$93,Inputs!$F$94:$I$94)/Qtrs_Yr)^(COUNT($J$7:O7))-Inputs!$E$29*(1+Inputs!$E$31)*O$7/Inputs!$E$16/Qtrs_Yr-IF(OR(O$7=0,SUM($J7:O7)*O7>Inputs!$F$77*Qtrs_Yr),0,(Inputs!$F$71-SUM($J7:O7,-1)*O7*Inputs!$F$71/Inputs!$F$77/Qtrs_Yr)*(LOOKUP(YEAR(P$5),Inputs!$F$85:$I$85,Inputs!$F$86:$I$86)+LOOKUP(ROUNDUP(SUM($J7:P7)*P7/Qtrs_Yr,0),Inputs!$G$73:$J$73,Inputs!$G$74:$J$74))/Qtrs_Yr))*Inputs!$F$101-IF(OR(O$7=0,SUM($J7:O7)*O7>Inputs!$F$77*Qtrs_Yr),0,(Inputs!$F$71-SUM($J7:O7,-1)*O7*Inputs!$F$71/Inputs!$F$77/Qtrs_Yr)*(LOOKUP(YEAR(P$5),Inputs!$F$85:$I$85,Inputs!$F$86:$I$86)+LOOKUP(ROUNDUP(SUM($J7:P7)*P7/Qtrs_Yr,0),Inputs!$G$73:$J$73,Inputs!$G$74:$J$74))/Qtrs_Yr)-IF(OR(O$7=0,SUM($J7:O7)*O7>Inputs!$F$77*Qtrs_Yr),0,Inputs!$F$71/Inputs!$F$77/Qtrs_Yr) -> 4.1659453 | P11: =(((IF(ROUNDUP(SUM($J$7:P$7)*P$7/Qtrs_Yr,0)=0,0,LOOKUP(ROUNDUP(SUM($J$7:P$7)*P$7/Qtrs_Yr,0),Inputs!$F$35:$I$35,Inputs!$F$36:$I$36))/Thousand/Qtrs_Yr)*IF(ROUNDUP(SUM($J$7:P$7)*P$7/Qtrs_Yr,0)=0,0,LOOKUP(ROUNDUP(SUM($J$7:P$7)*P$7/Qtrs_Yr,0),Inputs!$F$41:$I$41,Inputs!$F$42:$I$42))/Grams_Oz*Inputs!$F$45)*LOOKUP(YEAR(P$5),Inputs!$F$49:$I$49,Inputs!$F$50:$I$50)/Thousand/LOOKUP(YEAR(P$5),Inputs!$F$89:$I$89,Inputs!$F$90:$I$90)*(P5-O5-Inputs!$F$97)/(P5-O5)+((IF(ROUNDUP(SUM($I$7:O$7)*O$7/Qtrs_Yr,0)=0,0,LOOKUP(ROUNDUP(SUM($I$7:O$7)*O$7/Qtrs_Yr,0),Inputs!$F$35:$I$35,Inputs!$F$36:$I$36))/Thousand/Qtrs_Yr)*IF(ROUNDUP(SUM($I$7:O$7)*O$7/Qtrs_Yr,0)=0,0,LOOKUP(ROUNDUP(SUM($I$7:O$7)*O$7/Qtrs_Yr,0),Inputs!$F$41:$I$41,Inputs!$F$42:$I$42))/Grams_Oz*Inputs!$F$45)*LOOKUP(YEAR(O$5),Inputs!$F$49:$I$49,Inputs!$F$50:$I$50)/Thousand/LOOKUP(YEAR(O$5),Inputs!$F$89:$I$89,Inputs!$F$90:$I$90)*Inputs!$F$97/(O5-N5))-(((Inputs!$F$64*(IF(ROUNDUP(SUM($J$7:P$7)*P$7/Qtrs_Yr,0)=0,0,LOOKUP(ROUNDUP(SUM($J$7:P$7)*P$7/Qtrs_Yr,0),Inputs!$F$35:$I$35,Inputs!$F$36:$I$36))/Thousand/Qtrs_Yr+IF(ROUNDUP(SUM($J$7:P$7)*P$7/Qtrs_Yr,0)=0,0,LOOKUP(ROUNDUP(SUM($J$7:P$7)*P$7/Qtrs_Yr,0),Inputs!$F$35:$I$35,Inputs!$F$38:$I$38)*LOOKUP(ROUNDUP(SUM($J$7:P$7)*P$7/Qtrs_Yr,0),Inputs!$F$35:$I$35,Inputs!$F$36:$I$36))/Thousand/Qtrs_Yr)+Inputs!$F$65*(IF(ROUNDUP(SUM($J$7:P$7)*P$7/Qtrs_Yr,0)=0,0,LOOKUP(ROUNDUP(SUM($J$7:P$7)*P$7/Qtrs_Yr,0),Inputs!$F$35:$I$35,Inputs!$F$36:$I$36))/Thousand/Qtrs_Yr)+Inputs!$F$66*(IF(ROUNDUP(SUM($J$7:P$7)*P$7/Qtrs_Yr,0)=0,0,LOOKUP(ROUNDUP(SUM($J$7:P$7)*P$7/Qtrs_Yr,0),Inputs!$F$35:$I$35,Inputs!$F$38:$I$38)*LOOKUP(ROUNDUP(SUM($J$7:P$7)*P$7/Qtrs_Yr,0),Inputs!$F$35:$I$35,Inputs!$F$36:$I$36))/Thousand/Qtrs_Yr))/Thousand+SUM(Inputs!$F$54:$F$61)*P$7/Qtrs_Yr)*(1+LOOKUP(YEAR(P$5),Inputs!$F$93:$I$93,Inputs!$F$94:$I$94)/Qtrs_Yr)^(COUNT($J$7:P7))*(P5-O5-Inputs!$F$98)/(P5-O5)+((Inputs!$F$64*(IF(ROUNDUP(SUM($I$7:O$7)*O$7/Qtrs_Yr,0)=0,0,LOOKUP(ROUNDUP(SUM($I$7:O$7)*O$7/Qtrs_Yr,0),Inputs!$F$35:$I$35,Inputs!$F$36:$I$36))/Thousand/Qtrs_Yr+IF(ROUNDUP(SUM($I$7:O$7)*O$7/Qtrs_Yr,0)=0,0,LOOKUP(ROUNDUP(SUM($I$7:O$7)*O$7/Qtrs_Yr,0),Inputs!$F$35:$I$35,Inputs!$F$38:$I$38)*LOOKUP(ROUNDUP(SUM($I$7:O$7)*O$7/Qtrs_Yr,0),Inputs!$F$35:$I$35,Inputs!$F$36:$I$36))/Thousand/Qtrs_Yr)+Inputs!$F$65*(IF(ROUNDUP(SUM($I$7:O$7)*O$7/Qtrs_Yr,0)=0,0,LOOKUP(ROUNDUP(SUM($I$7:O$7)*O$7/Qtrs_Yr,0),Inputs!$F$35:$I$35,Inputs!$F$36:$I$36))/Thousand/Qtrs_Yr)+Inputs!$F$66*(IF(ROUNDUP(SUM($I$7:O$7)*O$7/Qtrs_Yr,0)=0,0,LOOKUP(ROUNDUP(SUM($I$7:O$7)*O$7/Qtrs_Yr,0),Inputs!$F$35:$I$35,Inputs!$F$38:$I$38)*LOOKUP(ROUNDUP(SUM($I$7:O$7)*O$7/Qtrs_Yr,0),Inputs!$F$35:$I$35,Inputs!$F$36:$I$36))/Thousand/Qtrs_Yr))/Thousand+SUM(Inputs!$F$54:$F$61)*O$7/Qtrs_Yr)*(1+LOOKUP(YEAR(P$5),Inputs!$F$93:$I$93,Inputs!$F$94:$I$94)/Qtrs_Yr)^(COUNT($I$7:O7))*Inputs!$F$98/(O5-N5))-(((IF(ROUNDUP(SUM($J$7:P$7)*P$7/Qtrs_Yr,0)=0,0,LOOKUP(ROUNDUP(SUM($J$7:P$7)*P$7/Qtrs_Yr,0),Inputs!$F$35:$I$35,Inputs!$F$36:$I$36))/Thousand/Qtrs_Yr)*IF(ROUNDUP(SUM($J$7:P$7)*P$7/Qtrs_Yr,0)=0,0,LOOKUP(ROUNDUP(SUM($J$7:P$7)*P$7/Qtrs_Yr,0),Inputs!$F$41:$I$41,Inputs!$F$42:$I$42))/Grams_Oz*Inputs!$F$45)*LOOKUP(YEAR(P$5),Inputs!$F$49:$I$49,Inputs!$F$50:$I$50)/Thousand/LOOKUP(YEAR(P$5),Inputs!$F$89:$I$89,Inputs!$F$90:$I$90)-((Inputs!$F$64*(IF(ROUNDUP(SUM($J$7:P$7)*P$7/Qtrs_Yr,0)=0,0,LOOKUP(ROUNDUP(SUM($J$7:P$7)*P$7/Qtrs_Yr,0),Inputs!$F$35:$I$35,Inputs!$F$36:$I$36))/Thousand/Qtrs_Yr+IF(ROUNDUP(SUM($J$7:P$7)*P$7/Qtrs_Yr,0)=0,0,LOOKUP(ROUNDUP(SUM($J$7:P$7)*P$7/Qtrs_Yr,0),Inputs!$F$35:$I$35,Inputs!$F$38:$I$38)*LOOKUP(ROUNDUP(SUM($J$7:P$7)*P$7/Qtrs_Yr,0),Inputs!$F$35:$I$35,Inputs!$F$36:$I$36))/Thousand/Qtrs_Yr)+Inputs!$F$65*(IF(ROUNDUP(SUM($J$7:P$7)*P$7/Qtrs_Yr,0)=0,0,LOOKUP(ROUNDUP(SUM($J$7:P$7)*P$7/Qtrs_Yr,0),Inputs!$F$35:$I$35,Inputs!$F$36:$I$36))/Thousand/Qtrs_Yr)+Inputs!$F$66*(IF(ROUNDUP(SUM($J$7:P$7)*P$7/Qtrs_Yr,0)=0,0,LOOKUP(ROUNDUP(SUM($J$7:P$7)*P$7/Qtrs_Yr,0),Inputs!$F$35:$I$35,Inputs!$F$38:$I$38)*LOOKUP(ROUNDUP(SUM($J$7:P$7)*P$7/Qtrs_Yr,0),Inputs!$F$35:$I$35,Inputs!$F$36:$I$36))/Thousand/Qtrs_Yr))/Thousand+SUM(Inputs!$F$54:$F$61)*P$7/Qtrs_Yr)*(1+LOOKUP(YEAR(P$5),Inputs!$F$93:$I$93,Inputs!$F$94:$I$94)/Qtrs_Yr)^(COUNT($J$7:P7))-Inputs!$E$29*(1+Inputs!$E$31)*P$7/Inputs!$E$16/Qtrs_Yr-IF(OR(P$7=0,SUM($J7:P7)*P7>Inputs!$F$77*Qtrs_Yr),0,(Inputs!$F$71-SUM($J7:P7,-1)*P7*Inputs!$F$71/Inputs!$F$77/Qtrs_Yr)*(LOOKUP(YEAR(Q$5),Inputs!$F$85:$I$85,Inputs!$F$86:$I$86)+LOOKUP(ROUNDUP(SUM($J7:Q7)*Q7/Qtrs_Yr,0),Inputs!$G$73:$J$73,Inputs!$G$74:$J$74))/Qtrs_Yr))*Inputs!$F$101-IF(OR(P$7=0,SUM($J7:P7)*P7>Inputs!$F$77*Qtrs_Yr),0,(Inputs!$F$71-SUM($J7:P7,-1)*P7*Inputs!$F$71/Inputs!$F$77/Qtrs_Yr)*(LOOKUP(YEAR(Q$5),Inputs!$F$85:$I$85,Inputs!$F$86:$I$86)+LOOKUP(ROUNDUP(SUM($J7:Q7)*Q7/Qtrs_Yr,0),Inputs!$G$73:$J$73,Inputs!$G$74:$J$74))/Qtrs_Yr)-IF(OR(P$7=0,SUM($J7:P7)*P7>Inputs!$F$77*Qtrs_Yr),0,Inputs!$F$71/Inputs!$F$77/Qtrs_Yr) -> 4.1682946 | Q11: =(((IF(ROUNDUP(SUM($J$7:Q$7)*Q$7/Qtrs_Yr,0)=0,0,LOOKUP(ROUNDUP(SUM($J$7:Q$7)*Q$7/Qtrs_Yr,0),Inputs!$F$35:$I$35,Inputs!$F$36:$I$36))/Thousand/Qtrs_Yr)*IF(ROUNDUP(SUM($J$7:Q$7)*Q$7/Qtrs_Yr,0)=0,0,LOOKUP(ROUNDUP(SUM($J$7:Q$7)*Q$7/Qtrs_Yr,0),Inputs!$F$41:$I$41,Inputs!$F$42:$I$42))/Grams_Oz*Inputs!$F$45)*LOOKUP(YEAR(Q$5),Inputs!$F$49:$I$49,Inputs!$F$50:$I$50)/Thousand/LOOKUP(YEAR(Q$5),Inputs!$F$89:$I$89,Inputs!$F$90:$I$90)*(Q5-P5-Inputs!$F$97)/(Q5-P5)+((IF(ROUNDUP(SUM($I$7:P$7)*P$7/Qtrs_Yr,0)=0,0,LOOKUP(ROUNDUP(SUM($I$7:P$7)*P$7/Qtrs_Yr,0),Inputs!$F$35:$I$35,Inputs!$F$36:$I$36))/Thousand/Qtrs_Yr)*IF(ROUNDUP(SUM($I$7:P$7)*P$7/Qtrs_Yr,0)=0,0,LOOKUP(ROUNDUP(SUM($I$7:P$7)*P$7/Qtrs_Yr,0),Inputs!$F$41:$I$41,Inputs!$F$42:$I$42))/Grams_Oz*Inputs!$F$45)*LOOKUP(YEAR(P$5),Inputs!$F$49:$I$49,Inputs!$F$50:$I$50)/Thousand/LOOKUP(YEAR(P$5),Inputs!$F$89:$I$89,Inputs!$F$90:$I$90)*Inputs!$F$97/(P5-O5))-(((Inputs!$F$64*(IF(ROUNDUP(SUM($J$7:Q$7)*Q$7/Qtrs_Yr,0)=0,0,LOOKUP(ROUNDUP(SUM($J$7:Q$7)*Q$7/Qtrs_Yr,0),Inputs!$F$35:$I$35,Inputs!$F$36:$I$36))/Thousand/Qtrs_Yr+IF(ROUNDUP(SUM($J$7:Q$7)*Q$7/Qtrs_Yr,0)=0,0,LOOKUP(ROUNDUP(SUM($J$7:Q$7)*Q$7/Qtrs_Yr,0),Inputs!$F$35:$I$35,Inputs!$F$38:$I$38)*LOOKUP(ROUNDUP(SUM($J$7:Q$7)*Q$7/Qtrs_Yr,0),Inputs!$F$35:$I$35,Inputs!$F$36:$I$36))/Thousand/Qtrs_Yr)+Inputs!$F$65*(IF(ROUNDUP(SUM($J$7:Q$7)*Q$7/Qtrs_Yr,0)=0,0,LOOKUP(ROUNDUP(SUM($J$7:Q$7)*Q$7/Qtrs_Yr,0),Inputs!$F$35:$I$35,Inputs!$F$36:$I$36))/Thousand/Qtrs_Yr)+Inputs!$F$66*(IF(ROUNDUP(SUM($J$7:Q$7)*Q$7/Qtrs_Yr,0)=0,0,LOOKUP(ROUNDUP(SUM($J$7:Q$7)*Q$7/Qtrs_Yr,0),Inputs!$F$35:$I$35,Inputs!$F$38:$I$38)*LOOKUP(ROUNDUP(SUM($J$7:Q$7)*Q$7/Qtrs_Yr,0),Inputs!$F$35:$I$35,Inputs!$F$36:$I$36))/Thousand/Qtrs_Yr))/Thousand+SUM(Inputs!$F$54:$F$61)*Q$7/Qtrs_Yr)*(1+LOOKUP(YEAR(Q$5),Inputs!$F$93:$I$93,Inputs!$F$94:$I$94)/Qtrs_Yr)^(COUNT($J$7:Q7))*(Q5-P5-Inputs!$F$98)/(Q5-P5)+((Inputs!$F$64*(IF(ROUNDUP(SUM($I$7:P$7)*P$7/Qtrs_Yr,0)=0,0,LOOKUP(ROUNDUP(SUM($I$7:P$7)*P$7/Qtrs_Yr,0),Inputs!$F$35:$I$35,Inputs!$F$36:$I$36))/Thousand/Qtrs_Yr+IF(ROUNDUP(SUM($I$7:P$7)*P$7/Qtrs_Yr,0)=0,0,LOOKUP(ROUNDUP(SUM($I$7:P$7)*P$7/Qtrs_Yr,0),Inputs!$F$35:$I$35,Inputs!$F$38:$I$38)*LOOKUP(ROUNDUP(SUM($I$7:P$7)*P$7/Qtrs_Yr,0),Inputs!$F$35:$I$35,Inputs!$F$36:$I$36))/Thousand/Qtrs_Yr)+Inputs!$F$65*(IF(ROUNDUP(SUM($I$7:P$7)*P$7/Qtrs_Yr,0)=0,0,LOOKUP(ROUNDUP(SUM($I$7:P$7)*P$7/Qtrs_Yr,0),Inputs!$F$35:$I$35,Inputs!$F$36:$I$36))/Thousand/Qtrs_Yr)+Inputs!$F$66*(IF(ROUNDUP(SUM($I$7:P$7)*P$7/Qtrs_Yr,0)=0,0,LOOKUP(ROUNDUP(SUM($I$7:P$7)*P$7/Qtrs_Yr,0),Inputs!$F$35:$I$35,Inputs!$F$38:$I$38)*LOOKUP(ROUNDUP(SUM($I$7:P$7)*P$7/Qtrs_Yr,0),Inputs!$F$35:$I$35,Inputs!$F$36:$I$36))/Thousand/Qtrs_Yr))/Thousand+SUM(Inputs!$F$54:$F$61)*P$7/Qtrs_Yr)*(1+LOOKUP(YEAR(Q$5),Inputs!$F$93:$I$93,Inputs!$F$94:$I$94)/Qtrs_Yr)^(COUNT($I$7:P7))*Inputs!$F$98/(P5-O5))-(((IF(ROUNDUP(SUM($J$7:Q$7)*Q$7/Qtrs_Yr,0)=0,0,LOOKUP(ROUNDUP(SUM($J$7:Q$7)*Q$7/Qtrs_Yr,0),Inputs!$F$35:$I$35,Inputs!$F$36:$I$36))/Thousand/Qtrs_Yr)*IF(ROUNDUP(SUM($J$7:Q$7)*Q$7/Qtrs_Yr,0)=0,0,LOOKUP(ROUNDUP(SUM($J$7:Q$7)*Q$7/Qtrs_Yr,0),Inputs!$F$41:$I$41,Inputs!$F$42:$I$42))/Grams_Oz*Inputs!$F$45)*LOOKUP(YEAR(Q$5),Inputs!$F$49:$I$49,Inputs!$F$50:$I$50)/Thousand/LOOKUP(YEAR(Q$5),Inputs!$F$89:$I$89,Inputs!$F$90:$I$90)-((Inputs!$F$64*(IF(ROUNDUP(SUM($J$7:Q$7)*Q$7/Qtrs_Yr,0)=0,0,LOOKUP(ROUNDUP(SUM($J$7:Q$7)*Q$7/Qtrs_Yr,0),Inputs!$F$35:$I$35,Inputs!$F$36:$I$36))/Thousand/Qtrs_Yr+IF(ROUNDUP(SUM($J$7:Q$7)*Q$7/Qtrs_Yr,0)=0,0,LOOKUP(ROUNDUP(SUM($J$7:Q$7)*Q$7/Qtrs_Yr,0),Inputs!$F$35:$I$35,Inputs!$F$38:$I$38)*LOOKUP(ROUNDUP(SUM($J$7:Q$7)*Q$7/Qtrs_Yr,0),Inputs!$F$35:$I$35,Inputs!$F$36:$I$36))/Thousand/Qtrs_Yr)+Inputs!$F$65*(IF(ROUNDUP(SUM($J$7:Q$7)*Q$7/Qtrs_Yr,0)=0,0,LOOKUP(ROUNDUP(SUM($J$7:Q$7)*Q$7/Qtrs_Yr,0),Inputs!$F$35:$I$35,Inputs!$F$36:$I$36))/Thousand/Qtrs_Yr)+Inputs!$F$66*(IF(ROUNDUP(SUM($J$7:Q$7)*Q$7/Qtrs_Yr,0)=0,0,LOOKUP(ROUNDUP(SUM($J$7:Q$7)*Q$7/Qtrs_Yr,0),Inputs!$F$35:$I$35,Inputs!$F$38:$I$38)*LOOKUP(ROUNDUP(SUM($J$7:Q$7)*Q$7/Qtrs_Yr,0),Inputs!$F$35:$I$35,Inputs!$F$36:$I$36))/Thousand/Qtrs_Yr))/Thousand+SUM(Inputs!$F$54:$F$61)*Q$7/Qtrs_Yr)*(1+LOOKUP(YEAR(Q$5),Inputs!$F$93:$I$93,Inputs!$F$94:$I$94)/Qtrs_Yr)^(COUNT($J$7:Q7))-Inputs!$E$29*(1+Inputs!$E$31)*Q$7/Inputs!$E$16/Qtrs_Yr-IF(OR(Q$7=0,SUM($J7:Q7)*Q7>Inputs!$F$77*Qtrs_Yr),0,(Inputs!$F$71-SUM($J7:Q7,-1)*Q7*Inputs!$F$71/Inputs!$F$77/Qtrs_Yr)*(LOOKUP(YEAR(R$5),Inputs!$F$85:$I$85,Inputs!$F$86:$I$86)+LOOKUP(ROUNDUP(SUM($J7:R7)*R7/Qtrs_Yr,0),Inputs!$G$73:$J$73,Inputs!$G$74:$J$74))/Qtrs_Yr))*Inputs!$F$101-IF(OR(Q$7=0,SUM($J7:Q7)*Q7>Inputs!$F$77*Qtrs_Yr),0,(Inputs!$F$71-SUM($J7:Q7,-1)*Q7*Inputs!$F$71/Inputs!$F$77/Qtrs_Yr)*(LOOKUP(YEAR(R$5),Inputs!$F$85:$I$85,Inputs!$F$86:$I$86)+LOOKUP(ROUNDUP(SUM($J7:R7)*R7/Qtrs_Yr,0),Inputs!$G$73:$J$73,Inputs!$G$74:$J$74))/Qtrs_Yr)-IF(OR(Q$7=0,SUM($J7:Q7)*Q7>Inputs!$F$77*Qtrs_Yr),0,Inputs!$F$71/Inputs!$F$77/Qtrs_Yr) -> 4.1228065 | ... BI11: =(((IF(ROUNDUP(SUM($J$7:BI$7)*BI$7/Qtrs_Yr,0)=0,0,LOOKUP(ROUNDUP(SUM($J$7:BI$7)*BI$7/Qtrs_Yr,0),Inputs!$F$35:$I$35,Inputs!$F$36:$I$36))/Thousand/Qtrs_Yr)*IF(ROUNDUP(SUM($J$7:BI$7)*BI$7/Qtrs_Yr,0)=0,0,LOOKUP(ROUNDUP(SUM($J$7:BI$7)*BI$7/Qtrs_Yr,0),Inputs!$F$41:$I$41,Inputs!$F$42:$I$42))/Grams_Oz*Inputs!$F$45)*LOOKUP(YEAR(BI$5),Inputs!$F$49:$I$49,Inputs!$F$50:$I$50)/Thousand/LOOKUP(YEAR(BI$5),Inputs!$F$89:$I$89,Inputs!$F$90:$I$90)*(BI5-BH5-Inputs!$F$97)/(BI5-BH5)+((IF(ROUNDUP(SUM($I$7:BH$7)*BH$7/Qtrs_Yr,0)=0,0,LOOKUP(ROUNDUP(SUM($I$7:BH$7)*BH$7/Qtrs_Yr,0),Inputs!$F$35:$I$35,Inputs!$F$36:$I$36))/Thousand/Qtrs_Yr)*IF(ROUNDUP(SUM($I$7:BH$7)*BH$7/Qtrs_Yr,0)=0,0,LOOKUP(ROUNDUP(SUM($I$7:BH$7)*BH$7/Qtrs_Yr,0),Inputs!$F$41:$I$41,Inputs!$F$42:$I$42))/Grams_Oz*Inputs!$F$45)*LOOKUP(YEAR(BH$5),Inputs!$F$49:$I$49,Inputs!$F$50:$I$50)/Thousand/LOOKUP(YEAR(BH$5),Inputs!$F$89:$I$89,Inputs!$F$90:$I$90)*Inputs!$F$97/(BH5-BG5))-(((Inputs!$F$64*(IF(ROUNDUP(SUM($J$7:BI$7)*BI$7/Qtrs_Yr,0)=0,0,LOOKUP(ROUNDUP(SUM($J$7:BI$7)*BI$7/Qtrs_Yr,0),Inputs!$F$35:$I$35,Inputs!$F$36:$I$36))/Thousand/Qtrs_Yr+IF(ROUNDUP(SUM($J$7:BI$7)*BI$7/Qtrs_Yr,0)=0,0,LOOKUP(ROUNDUP(SUM($J$7:BI$7)*BI$7/Qtrs_Yr,0),Inputs!$F$35:$I$35,Inputs!$F$38:$I$38)*LOOKUP(ROUNDUP(SUM($J$7:BI$7)*BI$7/Qtrs_Yr,0),Inputs!$F$35:$I$35,Inputs!$F$36:$I$36))/Thousand/Qtrs_Yr)+Inputs!$F$65*(IF(ROUNDUP(SUM($J$7:BI$7)*BI$7/Qtrs_Yr,0)=0,0,LOOKUP(ROUNDUP(SUM($J$7:BI$7)*BI$7/Qtrs_Yr,0),Inputs!$F$35:$I$35,Inputs!$F$36:$I$36))/Thousand/Qtrs_Yr)+Inputs!$F$66*(IF(ROUNDUP(SUM($J$7:BI$7)*BI$7/Qtrs_Yr,0)=0,0,LOOKUP(ROUNDUP(SUM($J$7:BI$7)*BI$7/Qtrs_Yr,0),Inputs!$F$35:$I$35,Inputs!$F$38:$I$38)*LOOKUP(ROUNDUP(SUM($J$7:BI$7)*BI$7/Qtrs_Yr,0),Inputs!$F$35:$I$35,Inputs!$F$36:$I$36))/Thousand/Qtrs_Yr))/Thousand+SUM(Inputs!$F$54:$F$61)*BI$7/Qtrs_Yr)*(1+LOOKUP(YEAR(BI$5),Inputs!$F$93:$I$93,Inputs!$F$94:$I$94)/Qtrs_Yr)^(COUNT($J$7:BI7))*(BI5-BH5-Inputs!$F$98)/(BI5-BH5)+((Inputs!$F$64*(IF(ROUNDUP(SUM($I$7:BH$7)*BH$7/Qtrs_Yr,0)=0,0,LOOKUP(ROUNDUP(SUM($I$7:BH$7)*BH$7/Qtrs_Yr,0),Inputs!$F$35:$I$35,Inputs!$F$36:$I$36))/Thousand/Qtrs_Yr+IF(ROUNDUP(SUM($I$7:BH$7)*BH$7/Qtrs_Yr,0)=0,0,LOOKUP(ROUNDUP(SUM($I$7:BH$7)*BH$7/Qtrs_Yr,0),Inputs!$F$35:$I$35,Inputs!$F$38:$I$38)*LOOKUP(ROUNDUP(SUM($I$7:BH$7)*BH$7/Qtrs_Yr,0),Inputs!$F$35:$I$35,Inputs!$F$36:$I$36))/Thousand/Qtrs_Yr)+Inputs!$F$65*(IF(ROUNDUP(SUM($I$7:BH$7)*BH$7/Qtrs_Yr,0)=0,0,LOOKUP(ROUNDUP(SUM($I$7:BH$7)*BH$7/Qtrs_Yr,0),Inputs!$F$35:$I$35,Inputs!$F$36:$I$36))/Thousand/Qtrs_Yr)+Inputs!$F$66*(IF(ROUNDUP(SUM($I$7:BH$7)*BH$7/Qtrs_Yr,0)=0,0,LOOKUP(ROUNDUP(SUM($I$7:BH$7)*BH$7/Qtrs_Yr,0),Inputs!$F$35:$I$35,Inputs!$F$38:$I$38)*LOOKUP(ROUNDUP(SUM($I$7:BH$7)*BH$7/Qtrs_Yr,0),Inputs!$F$35:$I$35,Inputs!$F$36:$I$36))/Thousand/Qtrs_Yr))/Thousand+SUM(Inputs!$F$54:$F$61)*BH$7/Qtrs_Yr)*(1+LOOKUP(YEAR(BI$5),Inputs!$F$93:$I$93,Inputs!$F$94:$I$94)/Qtrs_Yr)^(COUNT($I$7:BH7))*Inputs!$F$98/(BH5-BG5))-(((IF(ROUNDUP(SUM($J$7:BI$7)*BI$7/Qtrs_Yr,0)=0,0,LOOKUP(ROUNDUP(SUM($J$7:BI$7)*BI$7/Qtrs_Yr,0),Inputs!$F$35:$I$35,Inputs!$F$36:$I$36))/Thousand/Qtrs_Yr)*IF(ROUNDUP(SUM($J$7:BI$7)*BI$7/Qtrs_Yr,0)=0,0,LOOKUP(ROUNDUP(SUM($J$7:BI$7)*BI$7/Qtrs_Yr,0),Inputs!$F$41:$I$41,Inputs!$F$42:$I$42))/Grams_Oz*Inputs!$F$45)*LOOKUP(YEAR(BI$5),Inputs!$F$49:$I$49,Inputs!$F$50:$I$50)/Thousand/LOOKUP(YEAR(BI$5),Inputs!$F$89:$I$89,Inputs!$F$90:$I$90)-((Inputs!$F$64*(IF(ROUNDUP(SUM($J$7:BI$7)*BI$7/Qtrs_Yr,0)=0,0,LOOKUP(ROUNDUP(SUM($J$7:BI$7)*BI$7/Qtrs_Yr,0),Inputs!$F$35:$I$35,Inputs!$F$36:$I$36))/Thousand/Qtrs_Yr+IF(ROUNDUP(SUM($J$7:BI$7)*BI$7/Qtrs_Yr,0)=0,0,LOOKUP(ROUNDUP(SUM($J$7:BI$7)*BI$7/Qtrs_Yr,0),Inputs!$F$35:$I$35,Inputs!$F$38:$I$38)*LOOKUP(ROUNDUP(SUM($J$7:BI$7)*BI$7/Qtrs_Yr,0),Inputs!$F$35:$I$35,Inputs!$F$36:$I$36))/Thousand/Qtrs_Yr)+Inputs!$F$65*(IF(ROUNDUP(SUM($J$7:BI$7)*BI$7/Qtrs_Yr,0)=0,0,LOOKUP(ROUNDUP(SUM($J$7:BI$7)*BI$7/Qtrs_Yr,0),Inputs!$F$35:$I$35,Inputs!$F$36:$I$36))/Thousand/Qtrs_Yr)+Inputs!$F$66*(IF(ROUNDUP(SUM($J$7:BI$7)*BI$7/Qtrs_Yr,0)=0,0,LOOKUP(ROUNDUP(SUM($J$7:BI$7)*BI$7/Qtrs_Yr,0),Inputs!$F$35:$I$35,Inputs!$F$38:$I$38)*LOOKUP(ROUNDUP(SUM($J$7:BI$7)*BI$7/Qtrs_Yr,0),Inputs!$F$35:$I$35,Inputs!$F$36:$I$36))/Thousand/Qtrs_Yr))/Thousand+SUM(Inputs!$F$54:$F$61)*BI$7/Qtrs_Yr)*(1+LOOKUP(YEAR(BI$5),Inputs!$F$93:$I$93,Inputs!$F$94:$I$94)/Qtrs_Yr)^(COUNT($J$7:BI7))-Inputs!$E$29*(1+Inputs!$E$31)*BI$7/Inputs!$E$16/Qtrs_Yr-IF(OR(BI$7=0,SUM($J7:BI7)*BI7>Inputs!$F$77*Qtrs_Yr),0,(Inputs!$F$71-SUM($J7:BI7,-1)*BI7*Inputs!$F$71/Inputs!$F$77/Qtrs_Yr)*(LOOKUP(YEAR(BJ$5),Inputs!$F$85:$I$85,Inputs!$F$86:$I$86)+LOOKUP(ROUNDUP(SUM($J7:BJ7)*BJ7/Qtrs_Yr,0),Inputs!$G$73:$J$73,Inputs!$G$74:$J$74))/Qtrs_Yr))*Inputs!$F$101-IF(OR(BI$7=0,SUM($J7:BI7)*BI7>Inputs!$F$77*Qtrs_Yr),0,(Inputs!$F$71-SUM($J7:BI7,-1)*BI7*Inputs!$F$71/Inputs!$F$77/Qtrs_Yr)*(LOOKUP(YEAR(BJ$5),Inputs!$F$85:$I$85,Inputs!$F$86:$I$86)+LOOKUP(ROUNDUP(SUM($J7:BJ7)*BJ7/Qtrs_Yr,0),Inputs!$G$73:$J$73,Inputs!$G$74:$J$74))/Qtrs_Yr)-IF(OR(BI$7=0,SUM($J7:BI7)*BI7>Inputs!$F$77*Qtrs_Yr),0,Inputs!$F$71/Inputs!$F$77/Qtrs_Yr) -> 0
C13: Debt | E13: Min DSCR
C14: DSCR | D14: x | E14: {=MIN(IF(J14:BI14<>0,J14:BI14))} -> 1.1864094 | J14: =IF((IF(OR(J$7=0,SUM($J7:J7)*J7>Inputs!$F$77*Qtrs_Yr),0,(Inputs!$F$71-SUM($J7:J7,-1)*J7*Inputs!$F$71/Inputs!$F$77/Qtrs_Yr)*(LOOKUP(YEAR(K$5),Inputs!$F$85:$I$85,Inputs!$F$86:$I$86)+LOOKUP(ROUNDUP(SUM($J7:K7)*K7/Qtrs_Yr,0),Inputs!$G$73:$J$73,Inputs!$G$74:$J$74))/Qtrs_Yr)+IF(OR(J$7=0,SUM($J7:J7)*J7>Inputs!$F$77*Qtrs_Yr),0,Inputs!$F$71/Inputs!$F$77/Qtrs_Yr))=0,0,((((IF(ROUNDUP(SUM($J$7:J$7)*J$7/Qtrs_Yr,0)=0,0,LOOKUP(ROUNDUP(SUM($J$7:J$7)*J$7/Qtrs_Yr,0),Inputs!$F$35:$I$35,Inputs!$F$36:$I$36))/Thousand/Qtrs_Yr)*IF(ROUNDUP(SUM($J$7:J$7)*J$7/Qtrs_Yr,0)=0,0,LOOKUP(ROUNDUP(SUM($J$7:J$7)*J$7/Qtrs_Yr,0),Inputs!$F$41:$I$41,Inputs!$F$42:$I$42))/Grams_Oz*Inputs!$F$45)*LOOKUP(YEAR(J$5),Inputs!$F$49:$I$49,Inputs!$F$50:$I$50)/Thousand/LOOKUP(YEAR(J$5),Inputs!$F$89:$I$89,Inputs!$F$90:$I$90)*(J5-I5-Inputs!$F$97)/(J5-I5)+((IF(ROUNDUP(SUM($I$7:I$7)*I$7/Qtrs_Yr,0)=0,0,LOOKUP(ROUNDUP(SUM($I$7:I$7)*I$7/Qtrs_Yr,0),Inputs!$F$35:$I$35,Inputs!$F$36:$I$36))/Thousand/Qtrs_Yr)*IF(ROUNDUP(SUM($I$7:I$7)*I$7/Qtrs_Yr,0)=0,0,LOOKUP(ROUNDUP(SUM($I$7:I$7)*I$7/Qtrs_Yr,0),Inputs!$F$41:$I$41,Inputs!$F$42:$I$42))/Grams_Oz*Inputs!$F$45)*LOOKUP(YEAR(I$5),Inputs!$F$49:$I$49,Inputs!$F$50:$I$50)/Thousand /LOOKUP(YEAR(I$5),Inputs!$F$89:$I$89,Inputs!$F$90:$I$90)*Inputs!$F$97/(I5-H5))-(((Inputs!$F$64*(IF(ROUNDUP(SUM($J$7:J$7)*J$7/Qtrs_Yr,0)=0,0,LOOKUP(ROUNDUP(SUM($J$7:J$7)*J$7/Qtrs_Yr,0),Inputs!$F$35:$I$35,Inputs!$F$36:$I$36))/Thousand/Qtrs_Yr+IF(ROUNDUP(SUM($J$7:J$7)*J$7/Qtrs_Yr,0)=0,0,LOOKUP(ROUNDUP(SUM($J$7:J$7)*J$7/Qtrs_Yr,0),Inputs!$F$35:$I$35,Inputs!$F$38:$I$38)*LOOKUP(ROUNDUP(SUM($J$7:J$7)*J$7/Qtrs_Yr,0),Inputs!$F$35:$I$35,Inputs!$F$36:$I$36))/Thousand/Qtrs_Yr)+Inputs!$F$65*(IF(ROUNDUP(SUM($J$7:J$7)*J$7/Qtrs_Yr,0)=0,0,LOOKUP(ROUNDUP(SUM($J$7:J$7)*J$7/Qtrs_Yr,0),Inputs!$F$35:$I$35,Inputs!$F$36:$I$36))/Thousand/Qtrs_Yr)+Inputs!$F$66*(IF(ROUNDUP(SUM($J$7:J$7)*J$7/Qtrs_Yr,0)=0,0,LOOKUP(ROUNDUP(SUM($J$7:J$7)*J$7/Qtrs_Yr,0),Inputs!$F$35:$I$35,Inputs!$F$38:$I$38)*LOOKUP(ROUNDUP(SUM($J$7:J$7)*J$7/Qtrs_Yr,0),Inputs!$F$35:$I$35,Inputs!$F$36:$I$36))/Thousand/Qtrs_Yr))/Thousand+SUM(Inputs!$F$54:$F$61)*J$7/Qtrs_Yr)*(1+LOOKUP(YEAR(J$5),Inputs!$F$93:$I$93,Inputs!$F$94:$I$94)/Qtrs_Yr)^(COUNT($J$7:J7))*(J5-I5-Inputs!$F$98)/(J5-I5)+((Inputs!$F$64*(IF(ROUNDUP(SUM($I$7:I$7)*I$7/Qtrs_Yr,0)=0,0,LOOKUP(ROUNDUP(SUM($I$7:I$7)*I$7/Qtrs_Yr,0),Inputs!$F$35:$I$35,Inputs!$F$36:$I$36))/Thousand/Qtrs_Yr+IF(ROUNDUP(SUM($I$7:I$7)*I$7/Qtrs_Yr,0)=0,0,LOOKUP(ROUNDUP(SUM($I$7:I$7)*I$7/Qtrs_Yr,0),Inputs!$F$35:$I$35,Inputs!$F$38:$I$38)*LOOKUP(ROUNDUP(SUM($I$7:I$7)*I$7/Qtrs_Yr,0),Inputs!$F$35:$I$35,Inputs!$F$36:$I$36))/Thousand/Qtrs_Yr)+Inputs!$F$65*(IF(ROUNDUP(SUM($I$7:I$7)*I$7/Qtrs_Yr,0)=0,0,LOOKUP(ROUNDUP(SUM($I$7:I$7)*I$7/Qtrs_Yr,0),Inputs!$F$35:$I$35,Inputs!$F$36:$I$36))/Thousand/Qtrs_Yr)+Inputs!$F$66*(IF(ROUNDUP(SUM($I$7:I$7)*I$7/Qtrs_Yr,0)=0,0,LOOKUP(ROUNDUP(SUM($I$7:I$7)*I$7/Qtrs_Yr,0),Inputs!$F$35:$I$35,Inputs!$F$38:$I$38)*LOOKUP(ROUNDUP(SUM($I$7:I$7)*I$7/Qtrs_Yr,0),Inputs!$F$35:$I$35,Inputs!$F$36:$I$36))/Thousand/Qtrs_Yr))/Thousand+SUM(Inputs!$F$54:$F$61)*I$7/Qtrs_Yr)*(1+LOOKUP(YEAR(J$5),Inputs!$F$93:$I$93,Inputs!$F$94:$I$94)/Qtrs_Yr)^(COUNT($I$7:I7))*Inputs!$F$98/(I5-H5))-(((IF(ROUNDUP(SUM($J$7:J$7)*J$7/Qtrs_Yr,0)=0,0,LOOKUP(ROUNDUP(SUM($J$7:J$7)*J$7/Qtrs_Yr,0),Inputs!$F$35:$I$35,Inputs!$F$36:$I$36))/Thousand/Qtrs_Yr)*IF(ROUNDUP(SUM($J$7:J$7)*J$7/Qtrs_Yr,0)=0,0,LOOKUP(ROUNDUP(SUM($J$7:J$7)*J$7/Qtrs_Yr,0),Inputs!$F$41:$I$41,Inputs!$F$42:$I$42))/Grams_Oz*Inputs!$F$45)*LOOKUP(YEAR(J$5),Inputs!$F$49:$I$49,Inputs!$F$50:$I$50)/Thousand /LOOKUP(YEAR(J$5),Inputs!$F$89:$I$89,Inputs!$F$90:$I$90)-((Inputs!$F$64*(IF(ROUNDUP(SUM($J$7:J$7)*J$7/Qtrs_Yr,0)=0,0,LOOKUP(ROUNDUP(SUM($J$7:J$7)*J$7/Qtrs_Yr,0),Inputs!$F$35:$I$35,Inputs!$F$36:$I$36))/Thousand/Qtrs_Yr+IF(ROUNDUP(SUM($J$7:J$7)*J$7/Qtrs_Yr,0)=0,0,LOOKUP(ROUNDUP(SUM($J$7:J$7)*J$7/Qtrs_Yr,0),Inputs!$F$35:$I$35,Inputs!$F$38:$I$38)*LOOKUP(ROUNDUP(SUM($J$7:J$7)*J$7/Qtrs_Yr,0),Inputs!$F$35:$I$35,Inputs!$F$36:$I$36))/Thousand/Qtrs_Yr)+Inputs!$F$65*(IF(ROUNDUP(SUM($J$7:J$7)*J$7/Qtrs_Yr,0)=0,0,LOOKUP(ROUNDUP(SUM($J$7:J$7)*J$7/Qtrs_Yr,0),Inputs!$F$35:$I$35,Inputs!$F$36:$I$36))/Thousand/Qtrs_Yr)+Inputs!$F$66*(IF(ROUNDUP(SUM($J$7:J$7)*J$7/Qtrs_Yr,0)=0,0,LOOKUP(ROUNDUP(SUM($J$7:J$7)*J$7/Qtrs_Yr,0),Inputs!$F$35:$I$35,Inputs!$F$38:$I$38)*LOOKUP(ROUNDUP(SUM($J$7:J$7)*J$7/Qtrs_Yr,0),Inputs!$F$35:$I$35,Inputs!$F$36:$I$36))/Thousand/Qtrs_Yr))/Thousand+SUM(Inputs!$F$54:$F$61)*J$7/Qtrs_Yr)*(1+LOOKUP(YEAR(J$5),Inputs!$F$93:$I$93,Inputs!$F$94:$I$94)/Qtrs_Yr)^(COUNT($J$7:J7))-Inputs!$E$29*(1+Inputs!$E$31)*J$7/Inputs!$E$16/Qtrs_Yr-IF(OR(J$7=0,SUM($J7:J7)*J7>Inputs!$F$77*Qtrs_Yr),0,(Inputs!$F$71-SUM($J7:J7,-1)*J7*Inputs!$F$71/Inputs!$F$77/Qtrs_Yr)*(LOOKUP(YEAR(K$5),Inputs!$F$85:$I$85,Inputs!$F$86:$I$86)+LOOKUP(ROUNDUP(SUM($J7:K7)*K7/Qtrs_Yr,0),Inputs!$G$73:$J$73,Inputs!$G$74:$J$74))/Qtrs_Yr))*Inputs!$F$101)/(IF(OR(J$7=0,SUM($J7:J7)*J7>Inputs!$F$77*Qtrs_Yr),0,(Inputs!$F$71-SUM($J7:J7,-1)*J7*Inputs!$F$71/Inputs!$F$77/Qtrs_Yr)*(LOOKUP(YEAR(K$5),Inputs!$F$85:$I$85,Inputs!$F$86:$I$86)+LOOKUP(ROUNDUP(SUM($J7:K7)*K7/Qtrs_Yr,0),Inputs!$G$73:$J$73,Inputs!$G$74:$J$74))/Qtrs_Yr)+IF(OR(J$7=0,SUM($J7:J7)*J7>Inputs!$F$77*Qtrs_Yr),0,Inputs!$F$71/Inputs!$F$77/Qtrs_Yr))) -> 0 | K14: =IF((IF(OR(K$7=0,SUM($J7:K7)*K7>Inputs!$F$77*Qtrs_Yr),0,(Inputs!$F$71-SUM($J7:K7,-1)*K7*Inputs!$F$71/Inputs!$F$77/Qtrs_Yr)*(LOOKUP(YEAR(L$5),Inputs!$F$85:$I$85,Inputs!$F$86:$I$86)+LOOKUP(ROUNDUP(SUM($J7:L7)*L7/Qtrs_Yr,0),Inputs!$G$73:$J$73,Inputs!$G$74:$J$74))/Qtrs_Yr)+IF(OR(K$7=0,SUM($J7:K7)*K7>Inputs!$F$77*Qtrs_Yr),0,Inputs!$F$71/Inputs!$F$77/Qtrs_Yr))=0,0,((((IF(ROUNDUP(SUM($J$7:K$7)*K$7/Qtrs_Yr,0)=0,0,LOOKUP(ROUNDUP(SUM($J$7:K$7)*K$7/Qtrs_Yr,0),Inputs!$F$35:$I$35,Inputs!$F$36:$I$36))/Thousand/Qtrs_Yr)*IF(ROUNDUP(SUM($J$7:K$7)*K$7/Qtrs_Yr,0)=0,0,LOOKUP(ROUNDUP(SUM($J$7:K$7)*K$7/Qtrs_Yr,0),Inputs!$F$41:$I$41,Inputs!$F$42:$I$42))/Grams_Oz*Inputs!$F$45)*LOOKUP(YEAR(K$5),Inputs!$F$49:$I$49,Inputs!$F$50:$I$50)/Thousand/LOOKUP(YEAR(K$5),Inputs!$F$89:$I$89,Inputs!$F$90:$I$90)*(K5-J5-Inputs!$F$97)/(K5-J5)+((IF(ROUNDUP(SUM($I$7:J$7)*J$7/Qtrs_Yr,0)=0,0,LOOKUP(ROUNDUP(SUM($I$7:J$7)*J$7/Qtrs_Yr,0),Inputs!$F$35:$I$35,Inputs!$F$36:$I$36))/Thousand/Qtrs_Yr)*IF(ROUNDUP(SUM($I$7:J$7)*J$7/Qtrs_Yr,0)=0,0,LOOKUP(ROUNDUP(SUM($I$7:J$7)*J$7/Qtrs_Yr,0),Inputs!$F$41:$I$41,Inputs!$F$42:$I$42))/Grams_Oz*Inputs!$F$45)*LOOKUP(YEAR(J$5),Inputs!$F$49:$I$49,Inputs!$F$50:$I$50)/Thousand /LOOKUP(YEAR(J$5),Inputs!$F$89:$I$89,Inputs!$F$90:$I$90)*Inputs!$F$97/(J5-I5))-(((Inputs!$F$64*(IF(ROUNDUP(SUM($J$7:K$7)*K$7/Qtrs_Yr,0)=0,0,LOOKUP(ROUNDUP(SUM($J$7:K$7)*K$7/Qtrs_Yr,0),Inputs!$F$35:$I$35,Inputs!$F$36:$I$36))/Thousand/Qtrs_Yr+IF(ROUNDUP(SUM($J$7:K$7)*K$7/Qtrs_Yr,0)=0,0,LOOKUP(ROUNDUP(SUM($J$7:K$7)*K$7/Qtrs_Yr,0),Inputs!$F$35:$I$35,Inputs!$F$38:$I$38)*LOOKUP(ROUNDUP(SUM($J$7:K$7)*K$7/Qtrs_Yr,0),Inputs!$F$35:$I$35,Inputs!$F$36:$I$36))/Thousand/Qtrs_Yr)+Inputs!$F$65*(IF(ROUNDUP(SUM($J$7:K$7)*K$7/Qtrs_Yr,0)=0,0,LOOKUP(ROUNDUP(SUM($J$7:K$7)*K$7/Qtrs_Yr,0),Inputs!$F$35:$I$35,Inputs!$F$36:$I$36))/Thousand/Qtrs_Yr)+Inputs!$F$66*(IF(ROUNDUP(SUM($J$7:K$7)*K$7/Qtrs_Yr,0)=0,0,LOOKUP(ROUNDUP(SUM($J$7:K$7)*K$7/Qtrs_Yr,0),Inputs!$F$35:$I$35,Inputs!$F$38:$I$38)*LOOKUP(ROUNDUP(SUM($J$7:K$7)*K$7/Qtrs_Yr,0),Inputs!$F$35:$I$35,Inputs!$F$36:$I$36))/Thousand/Qtrs_Yr))/Thousand+SUM(Inputs!$F$54:$F$61)*K$7/Qtrs_Yr)*(1+LOOKUP(YEAR(K$5),Inputs!$F$93:$I$93,Inputs!$F$94:$I$94)/Qtrs_Yr)^(COUNT($J$7:K7))*(K5-J5-Inputs!$F$98)/(K5-J5)+((Inputs!$F$64*(IF(ROUNDUP(SUM($I$7:J$7)*J$7/Qtrs_Yr,0)=0,0,LOOKUP(ROUNDUP(SUM($I$7:J$7)*J$7/Qtrs_Yr,0),Inputs!$F$35:$I$35,Inputs!$F$36:$I$36))/Thousand/Qtrs_Yr+IF(ROUNDUP(SUM($I$7:J$7)*J$7/Qtrs_Yr,0)=0,0,LOOKUP(ROUNDUP(SUM($I$7:J$7)*J$7/Qtrs_Yr,0),Inputs!$F$35:$I$35,Inputs!$F$38:$I$38)*LOOKUP(ROUNDUP(SUM($I$7:J$7)*J$7/Qtrs_Yr,0),Inputs!$F$35:$I$35,Inputs!$F$36:$I$36))/Thousand/Qtrs_Yr)+Inputs!$F$65*(IF(ROUNDUP(SUM($I$7:J$7)*J$7/Qtrs_Yr,0)=0,0,LOOKUP(ROUNDUP(SUM($I$7:J$7)*J$7/Qtrs_Yr,0),Inputs!$F$35:$I$35,Inputs!$F$36:$I$36))/Thousand/Qtrs_Yr)+Inputs!$F$66*(IF(ROUNDUP(SUM($I$7:J$7)*J$7/Qtrs_Yr,0)=0,0,LOOKUP(ROUNDUP(SUM($I$7:J$7)*J$7/Qtrs_Yr,0),Inputs!$F$35:$I$35,Inputs!$F$38:$I$38)*LOOKUP(ROUNDUP(SUM($I$7:J$7)*J$7/Qtrs_Yr,0),Inputs!$F$35:$I$35,Inputs!$F$36:$I$36))/Thousand/Qtrs_Yr))/Thousand+SUM(Inputs!$F$54:$F$61)*J$7/Qtrs_Yr)*(1+LOOKUP(YEAR(K$5),Inputs!$F$93:$I$93,Inputs!$F$94:$I$94)/Qtrs_Yr)^(COUNT($I$7:J7))*Inputs!$F$98/(J5-I5))-(((IF(ROUNDUP(SUM($J$7:K$7)*K$7/Qtrs_Yr,0)=0,0,LOOKUP(ROUNDUP(SUM($J$7:K$7)*K$7/Qtrs_Yr,0),Inputs!$F$35:$I$35,Inputs!$F$36:$I$36))/Thousand/Qtrs_Yr)*IF(ROUNDUP(SUM($J$7:K$7)*K$7/Qtrs_Yr,0)=0,0,LOOKUP(ROUNDUP(SUM($J$7:K$7)*K$7/Qtrs_Yr,0),Inputs!$F$41:$I$41,Inputs!$F$42:$I$42))/Grams_Oz*Inputs!$F$45)*LOOKUP(YEAR(K$5),Inputs!$F$49:$I$49,Inputs!$F$50:$I$50)/Thousand /LOOKUP(YEAR(K$5),Inputs!$F$89:$I$89,Inputs!$F$90:$I$90)-((Inputs!$F$64*(IF(ROUNDUP(SUM($J$7:K$7)*K$7/Qtrs_Yr,0)=0,0,LOOKUP(ROUNDUP(SUM($J$7:K$7)*K$7/Qtrs_Yr,0),Inputs!$F$35:$I$35,Inputs!$F$36:$I$36))/Thousand/Qtrs_Yr+IF(ROUNDUP(SUM($J$7:K$7)*K$7/Qtrs_Yr,0)=0,0,LOOKUP(ROUNDUP(SUM($J$7:K$7)*K$7/Qtrs_Yr,0),Inputs!$F$35:$I$35,Inputs!$F$38:$I$38)*LOOKUP(ROUNDUP(SUM($J$7:K$7)*K$7/Qtrs_Yr,0),Inputs!$F$35:$I$35,Inputs!$F$36:$I$36))/Thousand/Qtrs_Yr)+Inputs!$F$65*(IF(ROUNDUP(SUM($J$7:K$7)*K$7/Qtrs_Yr,0)=0,0,LOOKUP(ROUNDUP(SUM($J$7:K$7)*K$7/Qtrs_Yr,0),Inputs!$F$35:$I$35,Inputs!$F$36:$I$36))/Thousand/Qtrs_Yr)+Inputs!$F$66*(IF(ROUNDUP(SUM($J$7:K$7)*K$7/Qtrs_Yr,0)=0,0,LOOKUP(ROUNDUP(SUM($J$7:K$7)*K$7/Qtrs_Yr,0),Inputs!$F$35:$I$35,Inputs!$F$38:$I$38)*LOOKUP(ROUNDUP(SUM($J$7:K$7)*K$7/Qtrs_Yr,0),Inputs!$F$35:$I$35,Inputs!$F$36:$I$36))/Thousand/Qtrs_Yr))/Thousand+SUM(Inputs!$F$54:$F$61)*K$7/Qtrs_Yr)*(1+LOOKUP(YEAR(K$5),Inputs!$F$93:$I$93,Inputs!$F$94:$I$94)/Qtrs_Yr)^(COUNT($J$7:K7))-Inputs!$E$29*(1+Inputs!$E$31)*K$7/Inputs!$E$16/Qtrs_Yr-IF(OR(K$7=0,SUM($J7:K7)*K7>Inputs!$F$77*Qtrs_Yr),0,(Inputs!$F$71-SUM($J7:K7,-1)*K7*Inputs!$F$71/Inputs!$F$77/Qtrs_Yr)*(LOOKUP(YEAR(L$5),Inputs!$F$85:$I$85,Inputs!$F$86:$I$86)+LOOKUP(ROUNDUP(SUM($J7:L7)*L7/Qtrs_Yr,0),Inputs!$G$73:$J$73,Inputs!$G$74:$J$74))/Qtrs_Yr))*Inputs!$F$101)/(IF(OR(K$7=0,SUM($J7:K7)*K7>Inputs!$F$77*Qtrs_Yr),0,(Inputs!$F$71-SUM($J7:K7,-1)*K7*Inputs!$F$71/Inputs!$F$77/Qtrs_Yr)*(LOOKUP(YEAR(L$5),Inputs!$F$85:$I$85,Inputs!$F$86:$I$86)+LOOKUP(ROUNDUP(SUM($J7:L7)*L7/Qtrs_Yr,0),Inputs!$G$73:$J$73,Inputs!$G$74:$J$74))/Qtrs_Yr)+IF(OR(K$7=0,SUM($J7:K7)*K7>Inputs!$F$77*Qtrs_Yr),0,Inputs!$F$71/Inputs!$F$77/Qtrs_Yr))) -> 0 | L14: =IF((IF(OR(L$7=0,SUM($J7:L7)*L7>Inputs!$F$77*Qtrs_Yr),0,(Inputs!$F$71-SUM($J7:L7,-1)*L7*Inputs!$F$71/Inputs!$F$77/Qtrs_Yr)*(LOOKUP(YEAR(M$5),Inputs!$F$85:$I$85,Inputs!$F$86:$I$86)+LOOKUP(ROUNDUP(SUM($J7:M7)*M7/Qtrs_Yr,0),Inputs!$G$73:$J$73,Inputs!$G$74:$J$74))/Qtrs_Yr)+IF(OR(L$7=0,SUM($J7:L7)*L7>Inputs!$F$77*Qtrs_Yr),0,Inputs!$F$71/Inputs!$F$77/Qtrs_Yr))=0,0,((((IF(ROUNDUP(SUM($J$7:L$7)*L$7/Qtrs_Yr,0)=0,0,LOOKUP(ROUNDUP(SUM($J$7:L$7)*L$7/Qtrs_Yr,0),Inputs!$F$35:$I$35,Inputs!$F$36:$I$36))/Thousand/Qtrs_Yr)*IF(ROUNDUP(SUM($J$7:L$7)*L$7/Qtrs_Yr,0)=0,0,LOOKUP(ROUNDUP(SUM($J$7:L$7)*L$7/Qtrs_Yr,0),Inputs!$F$41:$I$41,Inputs!$F$42:$I$42))/Grams_Oz*Inputs!$F$45)*LOOKUP(YEAR(L$5),Inputs!$F$49:$I$49,Inputs!$F$50:$I$50)/Thousand/LOOKUP(YEAR(L$5),Inputs!$F$89:$I$89,Inputs!$F$90:$I$90)*(L5-K5-Inputs!$F$97)/(L5-K5)+((IF(ROUNDUP(SUM($I$7:K$7)*K$7/Qtrs_Yr,0)=0,0,LOOKUP(ROUNDUP(SUM($I$7:K$7)*K$7/Qtrs_Yr,0),Inputs!$F$35:$I$35,Inputs!$F$36:$I$36))/Thousand/Qtrs_Yr)*IF(ROUNDUP(SUM($I$7:K$7)*K$7/Qtrs_Yr,0)=0,0,LOOKUP(ROUNDUP(SUM($I$7:K$7)*K$7/Qtrs_Yr,0),Inputs!$F$41:$I$41,Inputs!$F$42:$I$42))/Grams_Oz*Inputs!$F$45)*LOOKUP(YEAR(K$5),Inputs!$F$49:$I$49,Inputs!$F$50:$I$50)/Thousand /LOOKUP(YEAR(K$5),Inputs!$F$89:$I$89,Inputs!$F$90:$I$90)*Inputs!$F$97/(K5-J5))-(((Inputs!$F$64*(IF(ROUNDUP(SUM($J$7:L$7)*L$7/Qtrs_Yr,0)=0,0,LOOKUP(ROUNDUP(SUM($J$7:L$7)*L$7/Qtrs_Yr,0),Inputs!$F$35:$I$35,Inputs!$F$36:$I$36))/Thousand/Qtrs_Yr+IF(ROUNDUP(SUM($J$7:L$7)*L$7/Qtrs_Yr,0)=0,0,LOOKUP(ROUNDUP(SUM($J$7:L$7)*L$7/Qtrs_Yr,0),Inputs!$F$35:$I$35,Inputs!$F$38:$I$38)*LOOKUP(ROUNDUP(SUM($J$7:L$7)*L$7/Qtrs_Yr,0),Inputs!$F$35:$I$35,Inputs!$F$36:$I$36))/Thousand/Qtrs_Yr)+Inputs!$F$65*(IF(ROUNDUP(SUM($J$7:L$7)*L$7/Qtrs_Yr,0)=0,0,LOOKUP(ROUNDUP(SUM($J$7:L$7)*L$7/Qtrs_Yr,0),Inputs!$F$35:$I$35,Inputs!$F$36:$I$36))/Thousand/Qtrs_Yr)+Inputs!$F$66*(IF(ROUNDUP(SUM($J$7:L$7)*L$7/Qtrs_Yr,0)=0,0,LOOKUP(ROUNDUP(SUM($J$7:L$7)*L$7/Qtrs_Yr,0),Inputs!$F$35:$I$35,Inputs!$F$38:$I$38)*LOOKUP(ROUNDUP(SUM($J$7:L$7)*L$7/Qtrs_Yr,0),Inputs!$F$35:$I$35,Inputs!$F$36:$I$36))/Thousand/Qtrs_Yr))/Thousand+SUM(Inputs!$F$54:$F$61)*L$7/Qtrs_Yr)*(1+LOOKUP(YEAR(L$5),Inputs!$F$93:$I$93,Inputs!$F$94:$I$94)/Qtrs_Yr)^(COUNT($J$7:L7))*(L5-K5-Inputs!$F$98)/(L5-K5)+((Inputs!$F$64*(IF(ROUNDUP(SUM($I$7:K$7)*K$7/Qtrs_Yr,0)=0,0,LOOKUP(ROUNDUP(SUM($I$7:K$7)*K$7/Qtrs_Yr,0),Inputs!$F$35:$I$35,Inputs!$F$36:$I$36))/Thousand/Qtrs_Yr+IF(ROUNDUP(SUM($I$7:K$7)*K$7/Qtrs_Yr,0)=0,0,LOOKUP(ROUNDUP(SUM($I$7:K$7)*K$7/Qtrs_Yr,0),Inputs!$F$35:$I$35,Inputs!$F$38:$I$38)*LOOKUP(ROUNDUP(SUM($I$7:K$7)*K$7/Qtrs_Yr,0),Inputs!$F$35:$I$35,Inputs!$F$36:$I$36))/Thousand/Qtrs_Yr)+Inputs!$F$65*(IF(ROUNDUP(SUM($I$7:K$7)*K$7/Qtrs_Yr,0)=0,0,LOOKUP(ROUNDUP(SUM($I$7:K$7)*K$7/Qtrs_Yr,0),Inputs!$F$35:$I$35,Inputs!$F$36:$I$36))/Thousand/Qtrs_Yr)+Inputs!$F$66*(IF(ROUNDUP(SUM($I$7:K$7)*K$7/Qtrs_Yr,0)=0,0,LOOKUP(ROUNDUP(SUM($I$7:K$7)*K$7/Qtrs_Yr,0),Inputs!$F$35:$I$35,Inputs!$F$38:$I$38)*LOOKUP(ROUNDUP(SUM($I$7:K$7)*K$7/Qtrs_Yr,0),Inputs!$F$35:$I$35,Inputs!$F$36:$I$36))/Thousand/Qtrs_Yr))/Thousand+SUM(Inputs!$F$54:$F$61)*K$7/Qtrs_Yr)*(1+LOOKUP(YEAR(L$5),Inputs!$F$93:$I$93,Inputs!$F$94:$I$94)/Qtrs_Yr)^(COUNT($I$7:K7))*Inputs!$F$98/(K5-J5))-(((IF(ROUNDUP(SUM($J$7:L$7)*L$7/Qtrs_Yr,0)=0,0,LOOKUP(ROUNDUP(SUM($J$7:L$7)*L$7/Qtrs_Yr,0),Inputs!$F$35:$I$35,Inputs!$F$36:$I$36))/Thousand/Qtrs_Yr)*IF(ROUNDUP(SUM($J$7:L$7)*L$7/Qtrs_Yr,0)=0,0,LOOKUP(ROUNDUP(SUM($J$7:L$7)*L$7/Qtrs_Yr,0),Inputs!$F$41:$I$41,Inputs!$F$42:$I$42))/Grams_Oz*Inputs!$F$45)*LOOKUP(YEAR(L$5),Inputs!$F$49:$I$49,Inputs!$F$50:$I$50)/Thousand /LOOKUP(YEAR(L$5),Inputs!$F$89:$I$89,Inputs!$F$90:$I$90)-((Inputs!$F$64*(IF(ROUNDUP(SUM($J$7:L$7)*L$7/Qtrs_Yr,0)=0,0,LOOKUP(ROUNDUP(SUM($J$7:L$7)*L$7/Qtrs_Yr,0),Inputs!$F$35:$I$35,Inputs!$F$36:$I$36))/Thousand/Qtrs_Yr+IF(ROUNDUP(SUM($J$7:L$7)*L$7/Qtrs_Yr,0)=0,0,LOOKUP(ROUNDUP(SUM($J$7:L$7)*L$7/Qtrs_Yr,0),Inputs!$F$35:$I$35,Inputs!$F$38:$I$38)*LOOKUP(ROUNDUP(SUM($J$7:L$7)*L$7/Qtrs_Yr,0),Inputs!$F$35:$I$35,Inputs!$F$36:$I$36))/Thousand/Qtrs_Yr)+Inputs!$F$65*(IF(ROUNDUP(SUM($J$7:L$7)*L$7/Qtrs_Yr,0)=0,0,LOOKUP(ROUNDUP(SUM($J$7:L$7)*L$7/Qtrs_Yr,0),Inputs!$F$35:$I$35,Inputs!$F$36:$I$36))/Thousand/Qtrs_Yr)+Inputs!$F$66*(IF(ROUNDUP(SUM($J$7:L$7)*L$7/Qtrs_Yr,0)=0,0,LOOKUP(ROUNDUP(SUM($J$7:L$7)*L$7/Qtrs_Yr,0),Inputs!$F$35:$I$35,Inputs!$F$38:$I$38)*LOOKUP(ROUNDUP(SUM($J$7:L$7)*L$7/Qtrs_Yr,0),Inputs!$F$35:$I$35,Inputs!$F$36:$I$36))/Thousand/Qtrs_Yr))/Thousand+SUM(Inputs!$F$54:$F$61)*L$7/Qtrs_Yr)*(1+LOOKUP(YEAR(L$5),Inputs!$F$93:$I$93,Inputs!$F$94:$I$94)/Qtrs_Yr)^(COUNT($J$7:L7))-Inputs!$E$29*(1+Inputs!$E$31)*L$7/Inputs!$E$16/Qtrs_Yr-IF(OR(L$7=0,SUM($J7:L7)*L7>Inputs!$F$77*Qtrs_Yr),0,(Inputs!$F$71-SUM($J7:L7,-1)*L7*Inputs!$F$71/Inputs!$F$77/Qtrs_Yr)*(LOOKUP(YEAR(M$5),Inputs!$F$85:$I$85,Inputs!$F$86:$I$86)+LOOKUP(ROUNDUP(SUM($J7:M7)*M7/Qtrs_Yr,0),Inputs!$G$73:$J$73,Inputs!$G$74:$J$74))/Qtrs_Yr))*Inputs!$F$101)/(IF(OR(L$7=0,SUM($J7:L7)*L7>Inputs!$F$77*Qtrs_Yr),0,(Inputs!$F$71-SUM($J7:L7,-1)*L7*Inputs!$F$71/Inputs!$F$77/Qtrs_Yr)*(LOOKUP(YEAR(M$5),Inputs!$F$85:$I$85,Inputs!$F$86:$I$86)+LOOKUP(ROUNDUP(SUM($J7:M7)*M7/Qtrs_Yr,0),Inputs!$G$73:$J$73,Inputs!$G$74:$J$74))/Qtrs_Yr)+IF(OR(L$7=0,SUM($J7:L7)*L7>Inputs!$F$77*Qtrs_Yr),0,Inputs!$F$71/Inputs!$F$77/Qtrs_Yr))) -> 0 | M14: =IF((IF(OR(M$7=0,SUM($J7:M7)*M7>Inputs!$F$77*Qtrs_Yr),0,(Inputs!$F$71-SUM($J7:M7,-1)*M7*Inputs!$F$71/Inputs!$F$77/Qtrs_Yr)*(LOOKUP(YEAR(N$5),Inputs!$F$85:$I$85,Inputs!$F$86:$I$86)+LOOKUP(ROUNDUP(SUM($J7:N7)*N7/Qtrs_Yr,0),Inputs!$G$73:$J$73,Inputs!$G$74:$J$74))/Qtrs_Yr)+IF(OR(M$7=0,SUM($J7:M7)*M7>Inputs!$F$77*Qtrs_Yr),0,Inputs!$F$71/Inputs!$F$77/Qtrs_Yr))=0,0,((((IF(ROUNDUP(SUM($J$7:M$7)*M$7/Qtrs_Yr,0)=0,0,LOOKUP(ROUNDUP(SUM($J$7:M$7)*M$7/Qtrs_Yr,0),Inputs!$F$35:$I$35,Inputs!$F$36:$I$36))/Thousand/Qtrs_Yr)*IF(ROUNDUP(SUM($J$7:M$7)*M$7/Qtrs_Yr,0)=0,0,LOOKUP(ROUNDUP(SUM($J$7:M$7)*M$7/Qtrs_Yr,0),Inputs!$F$41:$I$41,Inputs!$F$42:$I$42))/Grams_Oz*Inputs!$F$45)*LOOKUP(YEAR(M$5),Inputs!$F$49:$I$49,Inputs!$F$50:$I$50)/Thousand/LOOKUP(YEAR(M$5),Inputs!$F$89:$I$89,Inputs!$F$90:$I$90)*(M5-L5-Inputs!$F$97)/(M5-L5)+((IF(ROUNDUP(SUM($I$7:L$7)*L$7/Qtrs_Yr,0)=0,0,LOOKUP(ROUNDUP(SUM($I$7:L$7)*L$7/Qtrs_Yr,0),Inputs!$F$35:$I$35,Inputs!$F$36:$I$36))/Thousand/Qtrs_Yr)*IF(ROUNDUP(SUM($I$7:L$7)*L$7/Qtrs_Yr,0)=0,0,LOOKUP(ROUNDUP(SUM($I$7:L$7)*L$7/Qtrs_Yr,0),Inputs!$F$41:$I$41,Inputs!$F$42:$I$42))/Grams_Oz*Inputs!$F$45)*LOOKUP(YEAR(L$5),Inputs!$F$49:$I$49,Inputs!$F$50:$I$50)/Thousand /LOOKUP(YEAR(L$5),Inputs!$F$89:$I$89,Inputs!$F$90:$I$90)*Inputs!$F$97/(L5-K5))-(((Inputs!$F$64*(IF(ROUNDUP(SUM($J$7:M$7)*M$7/Qtrs_Yr,0)=0,0,LOOKUP(ROUNDUP(SUM($J$7:M$7)*M$7/Qtrs_Yr,0),Inputs!$F$35:$I$35,Inputs!$F$36:$I$36))/Thousand/Qtrs_Yr+IF(ROUNDUP(SUM($J$7:M$7)*M$7/Qtrs_Yr,0)=0,0,LOOKUP(ROUNDUP(SUM($J$7:M$7)*M$7/Qtrs_Yr,0),Inputs!$F$35:$I$35,Inputs!$F$38:$I$38)*LOOKUP(ROUNDUP(SUM($J$7:M$7)*M$7/Qtrs_Yr,0),Inputs!$F$35:$I$35,Inputs!$F$36:$I$36))/Thousand/Qtrs_Yr)+Inputs!$F$65*(IF(ROUNDUP(SUM($J$7:M$7)*M$7/Qtrs_Yr,0)=0,0,LOOKUP(ROUNDUP(SUM($J$7:M$7)*M$7/Qtrs_Yr,0),Inputs!$F$35:$I$35,Inputs!$F$36:$I$36))/Thousand/Qtrs_Yr)+Inputs!$F$66*(IF(ROUNDUP(SUM($J$7:M$7)*M$7/Qtrs_Yr,0)=0,0,LOOKUP(ROUNDUP(SUM($J$7:M$7)*M$7/Qtrs_Yr,0),Inputs!$F$35:$I$35,Inputs!$F$38:$I$38)*LOOKUP(ROUNDUP(SUM($J$7:M$7)*M$7/Qtrs_Yr,0),Inputs!$F$35:$I$35,Inputs!$F$36:$I$36))/Thousand/Qtrs_Yr))/Thousand+SUM(Inputs!$F$54:$F$61)*M$7/Qtrs_Yr)*(1+LOOKUP(YEAR(M$5),Inputs!$F$93:$I$93,Inputs!$F$94:$I$94)/Qtrs_Yr)^(COUNT($J$7:M7))*(M5-L5-Inputs!$F$98)/(M5-L5)+((Inputs!$F$64*(IF(ROUNDUP(SUM($I$7:L$7)*L$7/Qtrs_Yr,0)=0,0,LOOKUP(ROUNDUP(SUM($I$7:L$7)*L$7/Qtrs_Yr,0),Inputs!$F$35:$I$35,Inputs!$F$36:$I$36))/Thousand/Qtrs_Yr+IF(ROUNDUP(SUM($I$7:L$7)*L$7/Qtrs_Yr,0)=0,0,LOOKUP(ROUNDUP(SUM($I$7:L$7)*L$7/Qtrs_Yr,0),Inputs!$F$35:$I$35,Inputs!$F$38:$I$38)*LOOKUP(ROUNDUP(SUM($I$7:L$7)*L$7/Qtrs_Yr,0),Inputs!$F$35:$I$35,Inputs!$F$36:$I$36))/Thousand/Qtrs_Yr)+Inputs!$F$65*(IF(ROUNDUP(SUM($I$7:L$7)*L$7/Qtrs_Yr,0)=0,0,LOOKUP(ROUNDUP(SUM($I$7:L$7)*L$7/Qtrs_Yr,0),Inputs!$F$35:$I$35,Inputs!$F$36:$I$36))/Thousand/Qtrs_Yr)+Inputs!$F$66*(IF(ROUNDUP(SUM($I$7:L$7)*L$7/Qtrs_Yr,0)=0,0,LOOKUP(ROUNDUP(SUM($I$7:L$7)*L$7/Qtrs_Yr,0),Inputs!$F$35:$I$35,Inputs!$F$38:$I$38)*LOOKUP(ROUNDUP(SUM($I$7:L$7)*L$7/Qtrs_Yr,0),Inputs!$F$35:$I$35,Inputs!$F$36:$I$36))/Thousand/Qtrs_Yr))/Thousand+SUM(Inputs!$F$54:$F$61)*L$7/Qtrs_Yr)*(1+LOOKUP(YEAR(M$5),Inputs!$F$93:$I$93,Inputs!$F$94:$I$94)/Qtrs_Yr)^(COUNT($I$7:L7))*Inputs!$F$98/(L5-K5))-(((IF(ROUNDUP(SUM($J$7:M$7)*M$7/Qtrs_Yr,0)=0,0,LOOKUP(ROUNDUP(SUM($J$7:M$7)*M$7/Qtrs_Yr,0),Inputs!$F$35:$I$35,Inputs!$F$36:$I$36))/Thousand/Qtrs_Yr)*IF(ROUNDUP(SUM($J$7:M$7)*M$7/Qtrs_Yr,0)=0,0,LOOKUP(ROUNDUP(SUM($J$7:M$7)*M$7/Qtrs_Yr,0),Inputs!$F$41:$I$41,Inputs!$F$42:$I$42))/Grams_Oz*Inputs!$F$45)*LOOKUP(YEAR(M$5),Inputs!$F$49:$I$49,Inputs!$F$50:$I$50)/Thousand /LOOKUP(YEAR(M$5),Inputs!$F$89:$I$89,Inputs!$F$90:$I$90)-((Inputs!$F$64*(IF(ROUNDUP(SUM($J$7:M$7)*M$7/Qtrs_Yr,0)=0,0,LOOKUP(ROUNDUP(SUM($J$7:M$7)*M$7/Qtrs_Yr,0),Inputs!$F$35:$I$35,Inputs!$F$36:$I$36))/Thousand/Qtrs_Yr+IF(ROUNDUP(SUM($J$7:M$7)*M$7/Qtrs_Yr,0)=0,0,LOOKUP(ROUNDUP(SUM($J$7:M$7)*M$7/Qtrs_Yr,0),Inputs!$F$35:$I$35,Inputs!$F$38:$I$38)*LOOKUP(ROUNDUP(SUM($J$7:M$7)*M$7/Qtrs_Yr,0),Inputs!$F$35:$I$35,Inputs!$F$36:$I$36))/Thousand/Qtrs_Yr)+Inputs!$F$65*(IF(ROUNDUP(SUM($J$7:M$7)*M$7/Qtrs_Yr,0)=0,0,LOOKUP(ROUNDUP(SUM($J$7:M$7)*M$7/Qtrs_Yr,0),Inputs!$F$35:$I$35,Inputs!$F$36:$I$36))/Thousand/Qtrs_Yr)+Inputs!$F$66*(IF(ROUNDUP(SUM($J$7:M$7)*M$7/Qtrs_Yr,0)=0,0,LOOKUP(ROUNDUP(SUM($J$7:M$7)*M$7/Qtrs_Yr,0),Inputs!$F$35:$I$35,Inputs!$F$38:$I$38)*LOOKUP(ROUNDUP(SUM($J$7:M$7)*M$7/Qtrs_Yr,0),Inputs!$F$35:$I$35,Inputs!$F$36:$I$36))/Thousand/Qtrs_Yr))/Thousand+SUM(Inputs!$F$54:$F$61)*M$7/Qtrs_Yr)*(1+LOOKUP(YEAR(M$5),Inputs!$F$93:$I$93,Inputs!$F$94:$I$94)/Qtrs_Yr)^(COUNT($J$7:M7))-Inputs!$E$29*(1+Inputs!$E$31)*M$7/Inputs!$E$16/Qtrs_Yr-IF(OR(M$7=0,SUM($J7:M7)*M7>Inputs!$F$77*Qtrs_Yr),0,(Inputs!$F$71-SUM($J7:M7,-1)*M7*Inputs!$F$71/Inputs!$F$77/Qtrs_Yr)*(LOOKUP(YEAR(N$5),Inputs!$F$85:$I$85,Inputs!$F$86:$I$86)+LOOKUP(ROUNDUP(SUM($J7:N7)*N7/Qtrs_Yr,0),Inputs!$G$73:$J$73,Inputs!$G$74:$J$74))/Qtrs_Yr))*Inputs!$F$101)/(IF(OR(M$7=0,SUM($J7:M7)*M7>Inputs!$F$77*Qtrs_Yr),0,(Inputs!$F$71-SUM($J7:M7,-1)*M7*Inputs!$F$71/Inputs!$F$77/Qtrs_Yr)*(LOOKUP(YEAR(N$5),Inputs!$F$85:$I$85,Inputs!$F$86:$I$86)+LOOKUP(ROUNDUP(SUM($J7:N7)*N7/Qtrs_Yr,0),Inputs!$G$73:$J$73,Inputs!$G$74:$J$74))/Qtrs_Yr)+IF(OR(M$7=0,SUM($J7:M7)*M7>Inputs!$F$77*Qtrs_Yr),0,Inputs!$F$71/Inputs!$F$77/Qtrs_Yr))) -> 0 | N14: =IF((IF(OR(N$7=0,SUM($J7:N7)*N7>Inputs!$F$77*Qtrs_Yr),0,(Inputs!$F$71-SUM($J7:N7,-1)*N7*Inputs!$F$71/Inputs!$F$77/Qtrs_Yr)*(LOOKUP(YEAR(O$5),Inputs!$F$85:$I$85,Inputs!$F$86:$I$86)+LOOKUP(ROUNDUP(SUM($J7:O7)*O7/Qtrs_Yr,0),Inputs!$G$73:$J$73,Inputs!$G$74:$J$74))/Qtrs_Yr)+IF(OR(N$7=0,SUM($J7:N7)*N7>Inputs!$F$77*Qtrs_Yr),0,Inputs!$F$71/Inputs!$F$77/Qtrs_Yr))=0,0,((((IF(ROUNDUP(SUM($J$7:N$7)*N$7/Qtrs_Yr,0)=0,0,LOOKUP(ROUNDUP(SUM($J$7:N$7)*N$7/Qtrs_Yr,0),Inputs!$F$35:$I$35,Inputs!$F$36:$I$36))/Thousand/Qtrs_Yr)*IF(ROUNDUP(SUM($J$7:N$7)*N$7/Qtrs_Yr,0)=0,0,LOOKUP(ROUNDUP(SUM($J$7:N$7)*N$7/Qtrs_Yr,0),Inputs!$F$41:$I$41,Inputs!$F$42:$I$42))/Grams_Oz*Inputs!$F$45)*LOOKUP(YEAR(N$5),Inputs!$F$49:$I$49,Inputs!$F$50:$I$50)/Thousand/LOOKUP(YEAR(N$5),Inputs!$F$89:$I$89,Inputs!$F$90:$I$90)*(N5-M5-Inputs!$F$97)/(N5-M5)+((IF(ROUNDUP(SUM($I$7:M$7)*M$7/Qtrs_Yr,0)=0,0,LOOKUP(ROUNDUP(SUM($I$7:M$7)*M$7/Qtrs_Yr,0),Inputs!$F$35:$I$35,Inputs!$F$36:$I$36))/Thousand/Qtrs_Yr)*IF(ROUNDUP(SUM($I$7:M$7)*M$7/Qtrs_Yr,0)=0,0,LOOKUP(ROUNDUP(SUM($I$7:M$7)*M$7/Qtrs_Yr,0),Inputs!$F$41:$I$41,Inputs!$F$42:$I$42))/Grams_Oz*Inputs!$F$45)*LOOKUP(YEAR(M$5),Inputs!$F$49:$I$49,Inputs!$F$50:$I$50)/Thousand /LOOKUP(YEAR(M$5),Inputs!$F$89:$I$89,Inputs!$F$90:$I$90)*Inputs!$F$97/(M5-L5))-(((Inputs!$F$64*(IF(ROUNDUP(SUM($J$7:N$7)*N$7/Qtrs_Yr,0)=0,0,LOOKUP(ROUNDUP(SUM($J$7:N$7)*N$7/Qtrs_Yr,0),Inputs!$F$35:$I$35,Inputs!$F$36:$I$36))/Thousand/Qtrs_Yr+IF(ROUNDUP(SUM($J$7:N$7)*N$7/Qtrs_Yr,0)=0,0,LOOKUP(ROUNDUP(SUM($J$7:N$7)*N$7/Qtrs_Yr,0),Inputs!$F$35:$I$35,Inputs!$F$38:$I$38)*LOOKUP(ROUNDUP(SUM($J$7:N$7)*N$7/Qtrs_Yr,0),Inputs!$F$35:$I$35,Inputs!$F$36:$I$36))/Thousand/Qtrs_Yr)+Inputs!$F$65*(IF(ROUNDUP(SUM($J$7:N$7)*N$7/Qtrs_Yr,0)=0,0,LOOKUP(ROUNDUP(SUM($J$7:N$7)*N$7/Qtrs_Yr,0),Inputs!$F$35:$I$35,Inputs!$F$36:$I$36))/Thousand/Qtrs_Yr)+Inputs!$F$66*(IF(ROUNDUP(SUM($J$7:N$7)*N$7/Qtrs_Yr,0)=0,0,LOOKUP(ROUNDUP(SUM($J$7:N$7)*N$7/Qtrs_Yr,0),Inputs!$F$35:$I$35,Inputs!$F$38:$I$38)*LOOKUP(ROUNDUP(SUM($J$7:N$7)*N$7/Qtrs_Yr,0),Inputs!$F$35:$I$35,Inputs!$F$36:$I$36))/Thousand/Qtrs_Yr))/Thousand+SUM(Inputs!$F$54:$F$61)*N$7/Qtrs_Yr)*(1+LOOKUP(YEAR(N$5),Inputs!$F$93:$I$93,Inputs!$F$94:$I$94)/Qtrs_Yr)^(COUNT($J$7:N7))*(N5-M5-Inputs!$F$98)/(N5-M5)+((Inputs!$F$64*(IF(ROUNDUP(SUM($I$7:M$7)*M$7/Qtrs_Yr,0)=0,0,LOOKUP(ROUNDUP(SUM($I$7:M$7)*M$7/Qtrs_Yr,0),Inputs!$F$35:$I$35,Inputs!$F$36:$I$36))/Thousand/Qtrs_Yr+IF(ROUNDUP(SUM($I$7:M$7)*M$7/Qtrs_Yr,0)=0,0,LOOKUP(ROUNDUP(SUM($I$7:M$7)*M$7/Qtrs_Yr,0),Inputs!$F$35:$I$35,Inputs!$F$38:$I$38)*LOOKUP(ROUNDUP(SUM($I$7:M$7)*M$7/Qtrs_Yr,0),Inputs!$F$35:$I$35,Inputs!$F$36:$I$36))/Thousand/Qtrs_Yr)+Inputs!$F$65*(IF(ROUNDUP(SUM($I$7:M$7)*M$7/Qtrs_Yr,0)=0,0,LOOKUP(ROUNDUP(SUM($I$7:M$7)*M$7/Qtrs_Yr,0),Inputs!$F$35:$I$35,Inputs!$F$36:$I$36))/Thousand/Qtrs_Yr)+Inputs!$F$66*(IF(ROUNDUP(SUM($I$7:M$7)*M$7/Qtrs_Yr,0)=0,0,LOOKUP(ROUNDUP(SUM($I$7:M$7)*M$7/Qtrs_Yr,0),Inputs!$F$35:$I$35,Inputs!$F$38:$I$38)*LOOKUP(ROUNDUP(SUM($I$7:M$7)*M$7/Qtrs_Yr,0),Inputs!$F$35:$I$35,Inputs!$F$36:$I$36))/Thousand/Qtrs_Yr))/Thousand+SUM(Inputs!$F$54:$F$61)*M$7/Qtrs_Yr)*(1+LOOKUP(YEAR(N$5),Inputs!$F$93:$I$93,Inputs!$F$94:$I$94)/Qtrs_Yr)^(COUNT($I$7:M7))*Inputs!$F$98/(M5-L5))-(((IF(ROUNDUP(SUM($J$7:N$7)*N$7/Qtrs_Yr,0)=0,0,LOOKUP(ROUNDUP(SUM($J$7:N$7)*N$7/Qtrs_Yr,0),Inputs!$F$35:$I$35,Inputs!$F$36:$I$36))/Thousand/Qtrs_Yr)*IF(ROUNDUP(SUM($J$7:N$7)*N$7/Qtrs_Yr,0)=0,0,LOOKUP(ROUNDUP(SUM($J$7:N$7)*N$7/Qtrs_Yr,0),Inputs!$F$41:$I$41,Inputs!$F$42:$I$42))/Grams_Oz*Inputs!$F$45)*LOOKUP(YEAR(N$5),Inputs!$F$49:$I$49,Inputs!$F$50:$I$50)/Thousand /LOOKUP(YEAR(N$5),Inputs!$F$89:$I$89,Inputs!$F$90:$I$90)-((Inputs!$F$64*(IF(ROUNDUP(SUM($J$7:N$7)*N$7/Qtrs_Yr,0)=0,0,LOOKUP(ROUNDUP(SUM($J$7:N$7)*N$7/Qtrs_Yr,0),Inputs!$F$35:$I$35,Inputs!$F$36:$I$36))/Thousand/Qtrs_Yr+IF(ROUNDUP(SUM($J$7:N$7)*N$7/Qtrs_Yr,0)=0,0,LOOKUP(ROUNDUP(SUM($J$7:N$7)*N$7/Qtrs_Yr,0),Inputs!$F$35:$I$35,Inputs!$F$38:$I$38)*LOOKUP(ROUNDUP(SUM($J$7:N$7)*N$7/Qtrs_Yr,0),Inputs!$F$35:$I$35,Inputs!$F$36:$I$36))/Thousand/Qtrs_Yr)+Inputs!$F$65*(IF(ROUNDUP(SUM($J$7:N$7)*N$7/Qtrs_Yr,0)=0,0,LOOKUP(ROUNDUP(SUM($J$7:N$7)*N$7/Qtrs_Yr,0),Inputs!$F$35:$I$35,Inputs!$F$36:$I$36))/Thousand/Qtrs_Yr)+Inputs!$F$66*(IF(ROUNDUP(SUM($J$7:N$7)*N$7/Qtrs_Yr,0)=0,0,LOOKUP(ROUNDUP(SUM($J$7:N$7)*N$7/Qtrs_Yr,0),Inputs!$F$35:$I$35,Inputs!$F$38:$I$38)*LOOKUP(ROUNDUP(SUM($J$7:N$7)*N$7/Qtrs_Yr,0),Inputs!$F$35:$I$35,Inputs!$F$36:$I$36))/Thousand/Qtrs_Yr))/Thousand+SUM(Inputs!$F$54:$F$61)*N$7/Qtrs_Yr)*(1+LOOKUP(YEAR(N$5),Inputs!$F$93:$I$93,Inputs!$F$94:$I$94)/Qtrs_Yr)^(COUNT($J$7:N7))-Inputs!$E$29*(1+Inputs!$E$31)*N$7/Inputs!$E$16/Qtrs_Yr-IF(OR(N$7=0,SUM($J7:N7)*N7>Inputs!$F$77*Qtrs_Yr),0,(Inputs!$F$71-SUM($J7:N7,-1)*N7*Inputs!$F$71/Inputs!$F$77/Qtrs_Yr)*(LOOKUP(YEAR(O$5),Inputs!$F$85:$I$85,Inputs!$F$86:$I$86)+LOOKUP(ROUNDUP(SUM($J7:O7)*O7/Qtrs_Yr,0),Inputs!$G$73:$J$73,Inputs!$G$74:$J$74))/Qtrs_Yr))*Inputs!$F$101)/(IF(OR(N$7=0,SUM($J7:N7)*N7>Inputs!$F$77*Qtrs_Yr),0,(Inputs!$F$71-SUM($J7:N7,-1)*N7*Inputs!$F$71/Inputs!$F$77/Qtrs_Yr)*(LOOKUP(YEAR(O$5),Inputs!$F$85:$I$85,Inputs!$F$86:$I$86)+LOOKUP(ROUNDUP(SUM($J7:O7)*O7/Qtrs_Yr,0),Inputs!$G$73:$J$73,Inputs!$G$74:$J$74))/Qtrs_Yr)+IF(OR(N$7=0,SUM($J7:N7)*N7>Inputs!$F$77*Qtrs_Yr),0,Inputs!$F$71/Inputs!$F$77/Qtrs_Yr))) -> 1.1864094 | O14: =IF((IF(OR(O$7=0,SUM($J7:O7)*O7>Inputs!$F$77*Qtrs_Yr),0,(Inputs!$F$71-SUM($J7:O7,-1)*O7*Inputs!$F$71/Inputs!$F$77/Qtrs_Yr)*(LOOKUP(YEAR(P$5),Inputs!$F$85:$I$85,Inputs!$F$86:$I$86)+LOOKUP(ROUNDUP(SUM($J7:P7)*P7/Qtrs_Yr,0),Inputs!$G$73:$J$73,Inputs!$G$74:$J$74))/Qtrs_Yr)+IF(OR(O$7=0,SUM($J7:O7)*O7>Inputs!$F$77*Qtrs_Yr),0,Inputs!$F$71/Inputs!$F$77/Qtrs_Yr))=0,0,((((IF(ROUNDUP(SUM($J$7:O$7)*O$7/Qtrs_Yr,0)=0,0,LOOKUP(ROUNDUP(SUM($J$7:O$7)*O$7/Qtrs_Yr,0),Inputs!$F$35:$I$35,Inputs!$F$36:$I$36))/Thousand/Qtrs_Yr)*IF(ROUNDUP(SUM($J$7:O$7)*O$7/Qtrs_Yr,0)=0,0,LOOKUP(ROUNDUP(SUM($J$7:O$7)*O$7/Qtrs_Yr,0),Inputs!$F$41:$I$41,Inputs!$F$42:$I$42))/Grams_Oz*Inputs!$F$45)*LOOKUP(YEAR(O$5),Inputs!$F$49:$I$49,Inputs!$F$50:$I$50)/Thousand/LOOKUP(YEAR(O$5),Inputs!$F$89:$I$89,Inputs!$F$90:$I$90)*(O5-N5-Inputs!$F$97)/(O5-N5)+((IF(ROUNDUP(SUM($I$7:N$7)*N$7/Qtrs_Yr,0)=0,0,LOOKUP(ROUNDUP(SUM($I$7:N$7)*N$7/Qtrs_Yr,0),Inputs!$F$35:$I$35,Inputs!$F$36:$I$36))/Thousand/Qtrs_Yr)*IF(ROUNDUP(SUM($I$7:N$7)*N$7/Qtrs_Yr,0)=0,0,LOOKUP(ROUNDUP(SUM($I$7:N$7)*N$7/Qtrs_Yr,0),Inputs!$F$41:$I$41,Inputs!$F$42:$I$42))/Grams_Oz*Inputs!$F$45)*LOOKUP(YEAR(N$5),Inputs!$F$49:$I$49,Inputs!$F$50:$I$50)/Thousand /LOOKUP(YEAR(N$5),Inputs!$F$89:$I$89,Inputs!$F$90:$I$90)*Inputs!$F$97/(N5-M5))-(((Inputs!$F$64*(IF(ROUNDUP(SUM($J$7:O$7)*O$7/Qtrs_Yr,0)=0,0,LOOKUP(ROUNDUP(SUM($J$7:O$7)*O$7/Qtrs_Yr,0),Inputs!$F$35:$I$35,Inputs!$F$36:$I$36))/Thousand/Qtrs_Yr+IF(ROUNDUP(SUM($J$7:O$7)*O$7/Qtrs_Yr,0)=0,0,LOOKUP(ROUNDUP(SUM($J$7:O$7)*O$7/Qtrs_Yr,0),Inputs!$F$35:$I$35,Inputs!$F$38:$I$38)*LOOKUP(ROUNDUP(SUM($J$7:O$7)*O$7/Qtrs_Yr,0),Inputs!$F$35:$I$35,Inputs!$F$36:$I$36))/Thousand/Qtrs_Yr)+Inputs!$F$65*(IF(ROUNDUP(SUM($J$7:O$7)*O$7/Qtrs_Yr,0)=0,0,LOOKUP(ROUNDUP(SUM($J$7:O$7)*O$7/Qtrs_Yr,0),Inputs!$F$35:$I$35,Inputs!$F$36:$I$36))/Thousand/Qtrs_Yr)+Inputs!$F$66*(IF(ROUNDUP(SUM($J$7:O$7)*O$7/Qtrs_Yr,0)=0,0,LOOKUP(ROUNDUP(SUM($J$7:O$7)*O$7/Qtrs_Yr,0),Inputs!$F$35:$I$35,Inputs!$F$38:$I$38)*LOOKUP(ROUNDUP(SUM($J$7:O$7)*O$7/Qtrs_Yr,0),Inputs!$F$35:$I$35,Inputs!$F$36:$I$36))/Thousand/Qtrs_Yr))/Thousand+SUM(Inputs!$F$54:$F$61)*O$7/Qtrs_Yr)*(1+LOOKUP(YEAR(O$5),Inputs!$F$93:$I$93,Inputs!$F$94:$I$94)/Qtrs_Yr)^(COUNT($J$7:O7))*(O5-N5-Inputs!$F$98)/(O5-N5)+((Inputs!$F$64*(IF(ROUNDUP(SUM($I$7:N$7)*N$7/Qtrs_Yr,0)=0,0,LOOKUP(ROUNDUP(SUM($I$7:N$7)*N$7/Qtrs_Yr,0),Inputs!$F$35:$I$35,Inputs!$F$36:$I$36))/Thousand/Qtrs_Yr+IF(ROUNDUP(SUM($I$7:N$7)*N$7/Qtrs_Yr,0)=0,0,LOOKUP(ROUNDUP(SUM($I$7:N$7)*N$7/Qtrs_Yr,0),Inputs!$F$35:$I$35,Inputs!$F$38:$I$38)*LOOKUP(ROUNDUP(SUM($I$7:N$7)*N$7/Qtrs_Yr,0),Inputs!$F$35:$I$35,Inputs!$F$36:$I$36))/Thousand/Qtrs_Yr)+Inputs!$F$65*(IF(ROUNDUP(SUM($I$7:N$7)*N$7/Qtrs_Yr,0)=0,0,LOOKUP(ROUNDUP(SUM($I$7:N$7)*N$7/Qtrs_Yr,0),Inputs!$F$35:$I$35,Inputs!$F$36:$I$36))/Thousand/Qtrs_Yr)+Inputs!$F$66*(IF(ROUNDUP(SUM($I$7:N$7)*N$7/Qtrs_Yr,0)=0,0,LOOKUP(ROUNDUP(SUM($I$7:N$7)*N$7/Qtrs_Yr,0),Inputs!$F$35:$I$35,Inputs!$F$38:$I$38)*LOOKUP(ROUNDUP(SUM($I$7:N$7)*N$7/Qtrs_Yr,0),Inputs!$F$35:$I$35,Inputs!$F$36:$I$36))/Thousand/Qtrs_Yr))/Thousand+SUM(Inputs!$F$54:$F$61)*N$7/Qtrs_Yr)*(1+LOOKUP(YEAR(O$5),Inputs!$F$93:$I$93,Inputs!$F$94:$I$94)/Qtrs_Yr)^(COUNT($I$7:N7))*Inputs!$F$98/(N5-M5))-(((IF(ROUNDUP(SUM($J$7:O$7)*O$7/Qtrs_Yr,0)=0,0,LOOKUP(ROUNDUP(SUM($J$7:O$7)*O$7/Qtrs_Yr,0),Inputs!$F$35:$I$35,Inputs!$F$36:$I$36))/Thousand/Qtrs_Yr)*IF(ROUNDUP(SUM($J$7:O$7)*O$7/Qtrs_Yr,0)=0,0,LOOKUP(ROUNDUP(SUM($J$7:O$7)*O$7/Qtrs_Yr,0),Inputs!$F$41:$I$41,Inputs!$F$42:$I$42))/Grams_Oz*Inputs!$F$45)*LOOKUP(YEAR(O$5),Inputs!$F$49:$I$49,Inputs!$F$50:$I$50)/Thousand /LOOKUP(YEAR(O$5),Inputs!$F$89:$I$89,Inputs!$F$90:$I$90)-((Inputs!$F$64*(IF(ROUNDUP(SUM($J$7:O$7)*O$7/Qtrs_Yr,0)=0,0,LOOKUP(ROUNDUP(SUM($J$7:O$7)*O$7/Qtrs_Yr,0),Inputs!$F$35:$I$35,Inputs!$F$36:$I$36))/Thousand/Qtrs_Yr+IF(ROUNDUP(SUM($J$7:O$7)*O$7/Qtrs_Yr,0)=0,0,LOOKUP(ROUNDUP(SUM($J$7:O$7)*O$7/Qtrs_Yr,0),Inputs!$F$35:$I$35,Inputs!$F$38:$I$38)*LOOKUP(ROUNDUP(SUM($J$7:O$7)*O$7/Qtrs_Yr,0),Inputs!$F$35:$I$35,Inputs!$F$36:$I$36))/Thousand/Qtrs_Yr)+Inputs!$F$65*(IF(ROUNDUP(SUM($J$7:O$7)*O$7/Qtrs_Yr,0)=0,0,LOOKUP(ROUNDUP(SUM($J$7:O$7)*O$7/Qtrs_Yr,0),Inputs!$F$35:$I$35,Inputs!$F$36:$I$36))/Thousand/Qtrs_Yr)+Inputs!$F$66*(IF(ROUNDUP(SUM($J$7:O$7)*O$7/Qtrs_Yr,0)=0,0,LOOKUP(ROUNDUP(SUM($J$7:O$7)*O$7/Qtrs_Yr,0),Inputs!$F$35:$I$35,Inputs!$F$38:$I$38)*LOOKUP(ROUNDUP(SUM($J$7:O$7)*O$7/Qtrs_Yr,0),Inputs!$F$35:$I$35,Inputs!$F$36:$I$36))/Thousand/Qtrs_Yr))/Thousand+SUM(Inputs!$F$54:$F$61)*O$7/Qtrs_Yr)*(1+LOOKUP(YEAR(O$5),Inputs!$F$93:$I$93,Inputs!$F$94:$I$94)/Qtrs_Yr)^(COUNT($J$7:O7))-Inputs!$E$29*(1+Inputs!$E$31)*O$7/Inputs!$E$16/Qtrs_Yr-IF(OR(O$7=0,SUM($J7:O7)*O7>Inputs!$F$77*Qtrs_Yr),0,(Inputs!$F$71-SUM($J7:O7,-1)*O7*Inputs!$F$71/Inputs!$F$77/Qtrs_Yr)*(LOOKUP(YEAR(P$5),Inputs!$F$85:$I$85,Inputs!$F$86:$I$86)+LOOKUP(ROUNDUP(SUM($J7:P7)*P7/Qtrs_Yr,0),Inputs!$G$73:$J$73,Inputs!$G$74:$J$74))/Qtrs_Yr))*Inputs!$F$101)/(IF(OR(O$7=0,SUM($J7:O7)*O7>Inputs!$F$77*Qtrs_Yr),0,(Inputs!$F$71-SUM($J7:O7,-1)*O7*Inputs!$F$71/Inputs!$F$77/Qtrs_Yr)*(LOOKUP(YEAR(P$5),Inputs!$F$85:$I$85,Inputs!$F$86:$I$86)+LOOKUP(ROUNDUP(SUM($J7:P7)*P7/Qtrs_Yr,0),Inputs!$G$73:$J$73,Inputs!$G$74:$J$74))/Qtrs_Yr)+IF(OR(O$7=0,SUM($J7:O7)*O7>Inputs!$F$77*Qtrs_Yr),0,Inputs!$F$71/Inputs!$F$77/Qtrs_Yr))) -> 1.6392421 | P14: =IF((IF(OR(P$7=0,SUM($J7:P7)*P7>Inputs!$F$77*Qtrs_Yr),0,(Inputs!$F$71-SUM($J7:P7,-1)*P7*Inputs!$F$71/Inputs!$F$77/Qtrs_Yr)*(LOOKUP(YEAR(Q$5),Inputs!$F$85:$I$85,Inputs!$F$86:$I$86)+LOOKUP(ROUNDUP(SUM($J7:Q7)*Q7/Qtrs_Yr,0),Inputs!$G$73:$J$73,Inputs!$G$74:$J$74))/Qtrs_Yr)+IF(OR(P$7=0,SUM($J7:P7)*P7>Inputs!$F$77*Qtrs_Yr),0,Inputs!$F$71/Inputs!$F$77/Qtrs_Yr))=0,0,((((IF(ROUNDUP(SUM($J$7:P$7)*P$7/Qtrs_Yr,0)=0,0,LOOKUP(ROUNDUP(SUM($J$7:P$7)*P$7/Qtrs_Yr,0),Inputs!$F$35:$I$35,Inputs!$F$36:$I$36))/Thousand/Qtrs_Yr)*IF(ROUNDUP(SUM($J$7:P$7)*P$7/Qtrs_Yr,0)=0,0,LOOKUP(ROUNDUP(SUM($J$7:P$7)*P$7/Qtrs_Yr,0),Inputs!$F$41:$I$41,Inputs!$F$42:$I$42))/Grams_Oz*Inputs!$F$45)*LOOKUP(YEAR(P$5),Inputs!$F$49:$I$49,Inputs!$F$50:$I$50)/Thousand/LOOKUP(YEAR(P$5),Inputs!$F$89:$I$89,Inputs!$F$90:$I$90)*(P5-O5-Inputs!$F$97)/(P5-O5)+((IF(ROUNDUP(SUM($I$7:O$7)*O$7/Qtrs_Yr,0)=0,0,LOOKUP(ROUNDUP(SUM($I$7:O$7)*O$7/Qtrs_Yr,0),Inputs!$F$35:$I$35,Inputs!$F$36:$I$36))/Thousand/Qtrs_Yr)*IF(ROUNDUP(SUM($I$7:O$7)*O$7/Qtrs_Yr,0)=0,0,LOOKUP(ROUNDUP(SUM($I$7:O$7)*O$7/Qtrs_Yr,0),Inputs!$F$41:$I$41,Inputs!$F$42:$I$42))/Grams_Oz*Inputs!$F$45)*LOOKUP(YEAR(O$5),Inputs!$F$49:$I$49,Inputs!$F$50:$I$50)/Thousand /LOOKUP(YEAR(O$5),Inputs!$F$89:$I$89,Inputs!$F$90:$I$90)*Inputs!$F$97/(O5-N5))-(((Inputs!$F$64*(IF(ROUNDUP(SUM($J$7:P$7)*P$7/Qtrs_Yr,0)=0,0,LOOKUP(ROUNDUP(SUM($J$7:P$7)*P$7/Qtrs_Yr,0),Inputs!$F$35:$I$35,Inputs!$F$36:$I$36))/Thousand/Qtrs_Yr+IF(ROUNDUP(SUM($J$7:P$7)*P$7/Qtrs_Yr,0)=0,0,LOOKUP(ROUNDUP(SUM($J$7:P$7)*P$7/Qtrs_Yr,0),Inputs!$F$35:$I$35,Inputs!$F$38:$I$38)*LOOKUP(ROUNDUP(SUM($J$7:P$7)*P$7/Qtrs_Yr,0),Inputs!$F$35:$I$35,Inputs!$F$36:$I$36))/Thousand/Qtrs_Yr)+Inputs!$F$65*(IF(ROUNDUP(SUM($J$7:P$7)*P$7/Qtrs_Yr,0)=0,0,LOOKUP(ROUNDUP(SUM($J$7:P$7)*P$7/Qtrs_Yr,0),Inputs!$F$35:$I$35,Inputs!$F$36:$I$36))/Thousand/Qtrs_Yr)+Inputs!$F$66*(IF(ROUNDUP(SUM($J$7:P$7)*P$7/Qtrs_Yr,0)=0,0,LOOKUP(ROUNDUP(SUM($J$7:P$7)*P$7/Qtrs_Yr,0),Inputs!$F$35:$I$35,Inputs!$F$38:$I$38)*LOOKUP(ROUNDUP(SUM($J$7:P$7)*P$7/Qtrs_Yr,0),Inputs!$F$35:$I$35,Inputs!$F$36:$I$36))/Thousand/Qtrs_Yr))/Thousand+SUM(Inputs!$F$54:$F$61)*P$7/Qtrs_Yr)*(1+LOOKUP(YEAR(P$5),Inputs!$F$93:$I$93,Inputs!$F$94:$I$94)/Qtrs_Yr)^(COUNT($J$7:P7))*(P5-O5-Inputs!$F$98)/(P5-O5)+((Inputs!$F$64*(IF(ROUNDUP(SUM($I$7:O$7)*O$7/Qtrs_Yr,0)=0,0,LOOKUP(ROUNDUP(SUM($I$7:O$7)*O$7/Qtrs_Yr,0),Inputs!$F$35:$I$35,Inputs!$F$36:$I$36))/Thousand/Qtrs_Yr+IF(ROUNDUP(SUM($I$7:O$7)*O$7/Qtrs_Yr,0)=0,0,LOOKUP(ROUNDUP(SUM($I$7:O$7)*O$7/Qtrs_Yr,0),Inputs!$F$35:$I$35,Inputs!$F$38:$I$38)*LOOKUP(ROUNDUP(SUM($I$7:O$7)*O$7/Qtrs_Yr,0),Inputs!$F$35:$I$35,Inputs!$F$36:$I$36))/Thousand/Qtrs_Yr)+Inputs!$F$65*(IF(ROUNDUP(SUM($I$7:O$7)*O$7/Qtrs_Yr,0)=0,0,LOOKUP(ROUNDUP(SUM($I$7:O$7)*O$7/Qtrs_Yr,0),Inputs!$F$35:$I$35,Inputs!$F$36:$I$36))/Thousand/Qtrs_Yr)+Inputs!$F$66*(IF(ROUNDUP(SUM($I$7:O$7)*O$7/Qtrs_Yr,0)=0,0,LOOKUP(ROUNDUP(SUM($I$7:O$7)*O$7/Qtrs_Yr,0),Inputs!$F$35:$I$35,Inputs!$F$38:$I$38)*LOOKUP(ROUNDUP(SUM($I$7:O$7)*O$7/Qtrs_Yr,0),Inputs!$F$35:$I$35,Inputs!$F$36:$I$36))/Thousand/Qtrs_Yr))/Thousand+SUM(Inputs!$F$54:$F$61)*O$7/Qtrs_Yr)*(1+LOOKUP(YEAR(P$5),Inputs!$F$93:$I$93,Inputs!$F$94:$I$94)/Qtrs_Yr)^(COUNT($I$7:O7))*Inputs!$F$98/(O5-N5))-(((IF(ROUNDUP(SUM($J$7:P$7)*P$7/Qtrs_Yr,0)=0,0,LOOKUP(ROUNDUP(SUM($J$7:P$7)*P$7/Qtrs_Yr,0),Inputs!$F$35:$I$35,Inputs!$F$36:$I$36))/Thousand/Qtrs_Yr)*IF(ROUNDUP(SUM($J$7:P$7)*P$7/Qtrs_Yr,0)=0,0,LOOKUP(ROUNDUP(SUM($J$7:P$7)*P$7/Qtrs_Yr,0),Inputs!$F$41:$I$41,Inputs!$F$42:$I$42))/Grams_Oz*Inputs!$F$45)*LOOKUP(YEAR(P$5),Inputs!$F$49:$I$49,Inputs!$F$50:$I$50)/Thousand /LOOKUP(YEAR(P$5),Inputs!$F$89:$I$89,Inputs!$F$90:$I$90)-((Inputs!$F$64*(IF(ROUNDUP(SUM($J$7:P$7)*P$7/Qtrs_Yr,0)=0,0,LOOKUP(ROUNDUP(SUM($J$7:P$7)*P$7/Qtrs_Yr,0),Inputs!$F$35:$I$35,Inputs!$F$36:$I$36))/Thousand/Qtrs_Yr+IF(ROUNDUP(SUM($J$7:P$7)*P$7/Qtrs_Yr,0)=0,0,LOOKUP(ROUNDUP(SUM($J$7:P$7)*P$7/Qtrs_Yr,0),Inputs!$F$35:$I$35,Inputs!$F$38:$I$38)*LOOKUP(ROUNDUP(SUM($J$7:P$7)*P$7/Qtrs_Yr,0),Inputs!$F$35:$I$35,Inputs!$F$36:$I$36))/Thousand/Qtrs_Yr)+Inputs!$F$65*(IF(ROUNDUP(SUM($J$7:P$7)*P$7/Qtrs_Yr,0)=0,0,LOOKUP(ROUNDUP(SUM($J$7:P$7)*P$7/Qtrs_Yr,0),Inputs!$F$35:$I$35,Inputs!$F$36:$I$36))/Thousand/Qtrs_Yr)+Inputs!$F$66*(IF(ROUNDUP(SUM($J$7:P$7)*P$7/Qtrs_Yr,0)=0,0,LOOKUP(ROUNDUP(SUM($J$7:P$7)*P$7/Qtrs_Yr,0),Inputs!$F$35:$I$35,Inputs!$F$38:$I$38)*LOOKUP(ROUNDUP(SUM($J$7:P$7)*P$7/Qtrs_Yr,0),Inputs!$F$35:$I$35,Inputs!$F$36:$I$36))/Thousand/Qtrs_Yr))/Thousand+SUM(Inputs!$F$54:$F$61)*P$7/Qtrs_Yr)*(1+LOOKUP(YEAR(P$5),Inputs!$F$93:$I$93,Inputs!$F$94:$I$94)/Qtrs_Yr)^(COUNT($J$7:P7))-Inputs!$E$29*(1+Inputs!$E$31)*P$7/Inputs!$E$16/Qtrs_Yr-IF(OR(P$7=0,SUM($J7:P7)*P7>Inputs!$F$77*Qtrs_Yr),0,(Inputs!$F$71-SUM($J7:P7,-1)*P7*Inputs!$F$71/Inputs!$F$77/Qtrs_Yr)*(LOOKUP(YEAR(Q$5),Inputs!$F$85:$I$85,Inputs!$F$86:$I$86)+LOOKUP(ROUNDUP(SUM($J7:Q7)*Q7/Qtrs_Yr,0),Inputs!$G$73:$J$73,Inputs!$G$74:$J$74))/Qtrs_Yr))*Inputs!$F$101)/(IF(OR(P$7=0,SUM($J7:P7)*P7>Inputs!$F$77*Qtrs_Yr),0,(Inputs!$F$71-SUM($J7:P7,-1)*P7*Inputs!$F$71/Inputs!$F$77/Qtrs_Yr)*(LOOKUP(YEAR(Q$5),Inputs!$F$85:$I$85,Inputs!$F$86:$I$86)+LOOKUP(ROUNDUP(SUM($J7:Q7)*Q7/Qtrs_Yr,0),Inputs!$G$73:$J$73,Inputs!$G$74:$J$74))/Qtrs_Yr)+IF(OR(P$7=0,SUM($J7:P7)*P7>Inputs!$F$77*Qtrs_Yr),0,Inputs!$F$71/Inputs!$F$77/Qtrs_Yr))) -> 1.64626 | Q14: =IF((IF(OR(Q$7=0,SUM($J7:Q7)*Q7>Inputs!$F$77*Qtrs_Yr),0,(Inputs!$F$71-SUM($J7:Q7,-1)*Q7*Inputs!$F$71/Inputs!$F$77/Qtrs_Yr)*(LOOKUP(YEAR(R$5),Inputs!$F$85:$I$85,Inputs!$F$86:$I$86)+LOOKUP(ROUNDUP(SUM($J7:R7)*R7/Qtrs_Yr,0),Inputs!$G$73:$J$73,Inputs!$G$74:$J$74))/Qtrs_Yr)+IF(OR(Q$7=0,SUM($J7:Q7)*Q7>Inputs!$F$77*Qtrs_Yr),0,Inputs!$F$71/Inputs!$F$77/Qtrs_Yr))=0,0,((((IF(ROUNDUP(SUM($J$7:Q$7)*Q$7/Qtrs_Yr,0)=0,0,LOOKUP(ROUNDUP(SUM($J$7:Q$7)*Q$7/Qtrs_Yr,0),Inputs!$F$35:$I$35,Inputs!$F$36:$I$36))/Thousand/Qtrs_Yr)*IF(ROUNDUP(SUM($J$7:Q$7)*Q$7/Qtrs_Yr,0)=0,0,LOOKUP(ROUNDUP(SUM($J$7:Q$7)*Q$7/Qtrs_Yr,0),Inputs!$F$41:$I$41,Inputs!$F$42:$I$42))/Grams_Oz*Inputs!$F$45)*LOOKUP(YEAR(Q$5),Inputs!$F$49:$I$49,Inputs!$F$50:$I$50)/Thousand/LOOKUP(YEAR(Q$5),Inputs!$F$89:$I$89,Inputs!$F$90:$I$90)*(Q5-P5-Inputs!$F$97)/(Q5-P5)+((IF(ROUNDUP(SUM($I$7:P$7)*P$7/Qtrs_Yr,0)=0,0,LOOKUP(ROUNDUP(SUM($I$7:P$7)*P$7/Qtrs_Yr,0),Inputs!$F$35:$I$35,Inputs!$F$36:$I$36))/Thousand/Qtrs_Yr)*IF(ROUNDUP(SUM($I$7:P$7)*P$7/Qtrs_Yr,0)=0,0,LOOKUP(ROUNDUP(SUM($I$7:P$7)*P$7/Qtrs_Yr,0),Inputs!$F$41:$I$41,Inputs!$F$42:$I$42))/Grams_Oz*Inputs!$F$45)*LOOKUP(YEAR(P$5),Inputs!$F$49:$I$49,Inputs!$F$50:$I$50)/Thousand /LOOKUP(YEAR(P$5),Inputs!$F$89:$I$89,Inputs!$F$90:$I$90)*Inputs!$F$97/(P5-O5))-(((Inputs!$F$64*(IF(ROUNDUP(SUM($J$7:Q$7)*Q$7/Qtrs_Yr,0)=0,0,LOOKUP(ROUNDUP(SUM($J$7:Q$7)*Q$7/Qtrs_Yr,0),Inputs!$F$35:$I$35,Inputs!$F$36:$I$36))/Thousand/Qtrs_Yr+IF(ROUNDUP(SUM($J$7:Q$7)*Q$7/Qtrs_Yr,0)=0,0,LOOKUP(ROUNDUP(SUM($J$7:Q$7)*Q$7/Qtrs_Yr,0),Inputs!$F$35:$I$35,Inputs!$F$38:$I$38)*LOOKUP(ROUNDUP(SUM($J$7:Q$7)*Q$7/Qtrs_Yr,0),Inputs!$F$35:$I$35,Inputs!$F$36:$I$36))/Thousand/Qtrs_Yr)+Inputs!$F$65*(IF(ROUNDUP(SUM($J$7:Q$7)*Q$7/Qtrs_Yr,0)=0,0,LOOKUP(ROUNDUP(SUM($J$7:Q$7)*Q$7/Qtrs_Yr,0),Inputs!$F$35:$I$35,Inputs!$F$36:$I$36))/Thousand/Qtrs_Yr)+Inputs!$F$66*(IF(ROUNDUP(SUM($J$7:Q$7)*Q$7/Qtrs_Yr,0)=0,0,LOOKUP(ROUNDUP(SUM($J$7:Q$7)*Q$7/Qtrs_Yr,0),Inputs!$F$35:$I$35,Inputs!$F$38:$I$38)*LOOKUP(ROUNDUP(SUM($J$7:Q$7)*Q$7/Qtrs_Yr,0),Inputs!$F$35:$I$35,Inputs!$F$36:$I$36))/Thousand/Qtrs_Yr))/Thousand+SUM(Inputs!$F$54:$F$61)*Q$7/Qtrs_Yr)*(1+LOOKUP(YEAR(Q$5),Inputs!$F$93:$I$93,Inputs!$F$94:$I$94)/Qtrs_Yr)^(COUNT($J$7:Q7))*(Q5-P5-Inputs!$F$98)/(Q5-P5)+((Inputs!$F$64*(IF(ROUNDUP(SUM($I$7:P$7)*P$7/Qtrs_Yr,0)=0,0,LOOKUP(ROUNDUP(SUM($I$7:P$7)*P$7/Qtrs_Yr,0),Inputs!$F$35:$I$35,Inputs!$F$36:$I$36))/Thousand/Qtrs_Yr+IF(ROUNDUP(SUM($I$7:P$7)*P$7/Qtrs_Yr,0)=0,0,LOOKUP(ROUNDUP(SUM($I$7:P$7)*P$7/Qtrs_Yr,0),Inputs!$F$35:$I$35,Inputs!$F$38:$I$38)*LOOKUP(ROUNDUP(SUM($I$7:P$7)*P$7/Qtrs_Yr,0),Inputs!$F$35:$I$35,Inputs!$F$36:$I$36))/Thousand/Qtrs_Yr)+Inputs!$F$65*(IF(ROUNDUP(SUM($I$7:P$7)*P$7/Qtrs_Yr,0)=0,0,LOOKUP(ROUNDUP(SUM($I$7:P$7)*P$7/Qtrs_Yr,0),Inputs!$F$35:$I$35,Inputs!$F$36:$I$36))/Thousand/Qtrs_Yr)+Inputs!$F$66*(IF(ROUNDUP(SUM($I$7:P$7)*P$7/Qtrs_Yr,0)=0,0,LOOKUP(ROUNDUP(SUM($I$7:P$7)*P$7/Qtrs_Yr,0),Inputs!$F$35:$I$35,Inputs!$F$38:$I$38)*LOOKUP(ROUNDUP(SUM($I$7:P$7)*P$7/Qtrs_Yr,0),Inputs!$F$35:$I$35,Inputs!$F$36:$I$36))/Thousand/Qtrs_Yr))/Thousand+SUM(Inputs!$F$54:$F$61)*P$7/Qtrs_Yr)*(1+LOOKUP(YEAR(Q$5),Inputs!$F$93:$I$93,Inputs!$F$94:$I$94)/Qtrs_Yr)^(COUNT($I$7:P7))*Inputs!$F$98/(P5-O5))-(((IF(ROUNDUP(SUM($J$7:Q$7)*Q$7/Qtrs_Yr,0)=0,0,LOOKUP(ROUNDUP(SUM($J$7:Q$7)*Q$7/Qtrs_Yr,0),Inputs!$F$35:$I$35,Inputs!$F$36:$I$36))/Thousand/Qtrs_Yr)*IF(ROUNDUP(SUM($J$7:Q$7)*Q$7/Qtrs_Yr,0)=0,0,LOOKUP(ROUNDUP(SUM($J$7:Q$7)*Q$7/Qtrs_Yr,0),Inputs!$F$41:$I$41,Inputs!$F$42:$I$42))/Grams_Oz*Inputs!$F$45)*LOOKUP(YEAR(Q$5),Inputs!$F$49:$I$49,Inputs!$F$50:$I$50)/Thousand /LOOKUP(YEAR(Q$5),Inputs!$F$89:$I$89,Inputs!$F$90:$I$90)-((Inputs!$F$64*(IF(ROUNDUP(SUM($J$7:Q$7)*Q$7/Qtrs_Yr,0)=0,0,LOOKUP(ROUNDUP(SUM($J$7:Q$7)*Q$7/Qtrs_Yr,0),Inputs!$F$35:$I$35,Inputs!$F$36:$I$36))/Thousand/Qtrs_Yr+IF(ROUNDUP(SUM($J$7:Q$7)*Q$7/Qtrs_Yr,0)=0,0,LOOKUP(ROUNDUP(SUM($J$7:Q$7)*Q$7/Qtrs_Yr,0),Inputs!$F$35:$I$35,Inputs!$F$38:$I$38)*LOOKUP(ROUNDUP(SUM($J$7:Q$7)*Q$7/Qtrs_Yr,0),Inputs!$F$35:$I$35,Inputs!$F$36:$I$36))/Thousand/Qtrs_Yr)+Inputs!$F$65*(IF(ROUNDUP(SUM($J$7:Q$7)*Q$7/Qtrs_Yr,0)=0,0,LOOKUP(ROUNDUP(SUM($J$7:Q$7)*Q$7/Qtrs_Yr,0),Inputs!$F$35:$I$35,Inputs!$F$36:$I$36))/Thousand/Qtrs_Yr)+Inputs!$F$66*(IF(ROUNDUP(SUM($J$7:Q$7)*Q$7/Qtrs_Yr,0)=0,0,LOOKUP(ROUNDUP(SUM($J$7:Q$7)*Q$7/Qtrs_Yr,0),Inputs!$F$35:$I$35,Inputs!$F$38:$I$38)*LOOKUP(ROUNDUP(SUM($J$7:Q$7)*Q$7/Qtrs_Yr,0),Inputs!$F$35:$I$35,Inputs!$F$36:$I$36))/Thousand/Qtrs_Yr))/Thousand+SUM(Inputs!$F$54:$F$61)*Q$7/Qtrs_Yr)*(1+LOOKUP(YEAR(Q$5),Inputs!$F$93:$I$93,Inputs!$F$94:$I$94)/Qtrs_Yr)^(COUNT($J$7:Q7))-Inputs!$E$29*(1+Inputs!$E$31)*Q$7/Inputs!$E$16/Qtrs_Yr-IF(OR(Q$7=0,SUM($J7:Q7)*Q7>Inputs!$F$77*Qtrs_Yr),0,(Inputs!$F$71-SUM($J7:Q7,-1)*Q7*Inputs!$F$71/Inputs!$F$77/Qtrs_Yr)*(LOOKUP(YEAR(R$5),Inputs!$F$85:$I$85,Inputs!$F$86:$I$86)+LOOKUP(ROUNDUP(SUM($J7:R7)*R7/Qtrs_Yr,0),Inputs!$G$73:$J$73,Inputs!$G$74:$J$74))/Qtrs_Yr))*Inputs!$F$101)/(IF(OR(Q$7=0,SUM($J7:Q7)*Q7>Inputs!$F$77*Qtrs_Yr),0,(Inputs!$F$71-SUM($J7:Q7,-1)*Q7*Inputs!$F$71/Inputs!$F$77/Qtrs_Yr)*(LOOKUP(YEAR(R$5),Inputs!$F$85:$I$85,Inputs!$F$86:$I$86)+LOOKUP(ROUNDUP(SUM($J7:R7)*R7/Qtrs_Yr,0),Inputs!$G$73:$J$73,Inputs!$G$74:$J$74))/Qtrs_Yr)+IF(OR(Q$7=0,SUM($J7:Q7)*Q7>Inputs!$F$77*Qtrs_Yr),0,Inputs!$F$71/Inputs!$F$77/Qtrs_Yr))) -> 1.6432993 | ... BI14: =IF((IF(OR(BI$7=0,SUM($J7:BI7)*BI7>Inputs!$F$77*Qtrs_Yr),0,(Inputs!$F$71-SUM($J7:BI7,-1)*BI7*Inputs!$F$71/Inputs!$F$77/Qtrs_Yr)*(LOOKUP(YEAR(BJ$5),Inputs!$F$85:$I$85,Inputs!$F$86:$I$86)+LOOKUP(ROUNDUP(SUM($J7:BJ7)*BJ7/Qtrs_Yr,0),Inputs!$G$73:$J$73,Inputs!$G$74:$J$74))/Qtrs_Yr)+IF(OR(BI$7=0,SUM($J7:BI7)*BI7>Inputs!$F$77*Qtrs_Yr),0,Inputs!$F$71/Inputs!$F$77/Qtrs_Yr))=0,0,((((IF(ROUNDUP(SUM($J$7:BI$7)*BI$7/Qtrs_Yr,0)=0,0,LOOKUP(ROUNDUP(SUM($J$7:BI$7)*BI$7/Qtrs_Yr,0),Inputs!$F$35:$I$35,Inputs!$F$36:$I$36))/Thousand/Qtrs_Yr)*IF(ROUNDUP(SUM($J$7:BI$7)*BI$7/Qtrs_Yr,0)=0,0,LOOKUP(ROUNDUP(SUM($J$7:BI$7)*BI$7/Qtrs_Yr,0),Inputs!$F$41:$I$41,Inputs!$F$42:$I$42))/Grams_Oz*Inputs!$F$45)*LOOKUP(YEAR(BI$5),Inputs!$F$49:$I$49,Inputs!$F$50:$I$50)/Thousand/LOOKUP(YEAR(BI$5),Inputs!$F$89:$I$89,Inputs!$F$90:$I$90)*(BI5-BH5-Inputs!$F$97)/(BI5-BH5)+((IF(ROUNDUP(SUM($I$7:BH$7)*BH$7/Qtrs_Yr,0)=0,0,LOOKUP(ROUNDUP(SUM($I$7:BH$7)*BH$7/Qtrs_Yr,0),Inputs!$F$35:$I$35,Inputs!$F$36:$I$36))/Thousand/Qtrs_Yr)*IF(ROUNDUP(SUM($I$7:BH$7)*BH$7/Qtrs_Yr,0)=0,0,LOOKUP(ROUNDUP(SUM($I$7:BH$7)*BH$7/Qtrs_Yr,0),Inputs!$F$41:$I$41,Inputs!$F$42:$I$42))/Grams_Oz*Inputs!$F$45)*LOOKUP(YEAR(BH$5),Inputs!$F$49:$I$49,Inputs!$F$50:$I$50)/Thousand /LOOKUP(YEAR(BH$5),Inputs!$F$89:$I$89,Inputs!$F$90:$I$90)*Inputs!$F$97/(BH5-BG5))-(((Inputs!$F$64*(IF(ROUNDUP(SUM($J$7:BI$7)*BI$7/Qtrs_Yr,0)=0,0,LOOKUP(ROUNDUP(SUM($J$7:BI$7)*BI$7/Qtrs_Yr,0),Inputs!$F$35:$I$35,Inputs!$F$36:$I$36))/Thousand/Qtrs_Yr+IF(ROUNDUP(SUM($J$7:BI$7)*BI$7/Qtrs_Yr,0)=0,0,LOOKUP(ROUNDUP(SUM($J$7:BI$7)*BI$7/Qtrs_Yr,0),Inputs!$F$35:$I$35,Inputs!$F$38:$I$38)*LOOKUP(ROUNDUP(SUM($J$7:BI$7)*BI$7/Qtrs_Yr,0),Inputs!$F$35:$I$35,Inputs!$F$36:$I$36))/Thousand/Qtrs_Yr)+Inputs!$F$65*(IF(ROUNDUP(SUM($J$7:BI$7)*BI$7/Qtrs_Yr,0)=0,0,LOOKUP(ROUNDUP(SUM($J$7:BI$7)*BI$7/Qtrs_Yr,0),Inputs!$F$35:$I$35,Inputs!$F$36:$I$36))/Thousand/Qtrs_Yr)+Inputs!$F$66*(IF(ROUNDUP(SUM($J$7:BI$7)*BI$7/Qtrs_Yr,0)=0,0,LOOKUP(ROUNDUP(SUM($J$7:BI$7)*BI$7/Qtrs_Yr,0),Inputs!$F$35:$I$35,Inputs!$F$38:$I$38)*LOOKUP(ROUNDUP(SUM($J$7:BI$7)*BI$7/Qtrs_Yr,0),Inputs!$F$35:$I$35,Inputs!$F$36:$I$36))/Thousand/Qtrs_Yr))/Thousand+SUM(Inputs!$F$54:$F$61)*BI$7/Qtrs_Yr)*(1+LOOKUP(YEAR(BI$5),Inputs!$F$93:$I$93,Inputs!$F$94:$I$94)/Qtrs_Yr)^(COUNT($J$7:BI7))*(BI5-BH5-Inputs!$F$98)/(BI5-BH5)+((Inputs!$F$64*(IF(ROUNDUP(SUM($I$7:BH$7)*BH$7/Qtrs_Yr,0)=0,0,LOOKUP(ROUNDUP(SUM($I$7:BH$7)*BH$7/Qtrs_Yr,0),Inputs!$F$35:$I$35,Inputs!$F$36:$I$36))/Thousand/Qtrs_Yr+IF(ROUNDUP(SUM($I$7:BH$7)*BH$7/Qtrs_Yr,0)=0,0,LOOKUP(ROUNDUP(SUM($I$7:BH$7)*BH$7/Qtrs_Yr,0),Inputs!$F$35:$I$35,Inputs!$F$38:$I$38)*LOOKUP(ROUNDUP(SUM($I$7:BH$7)*BH$7/Qtrs_Yr,0),Inputs!$F$35:$I$35,Inputs!$F$36:$I$36))/Thousand/Qtrs_Yr)+Inputs!$F$65*(IF(ROUNDUP(SUM($I$7:BH$7)*BH$7/Qtrs_Yr,0)=0,0,LOOKUP(ROUNDUP(SUM($I$7:BH$7)*BH$7/Qtrs_Yr,0),Inputs!$F$35:$I$35,Inputs!$F$36:$I$36))/Thousand/Qtrs_Yr)+Inputs!$F$66*(IF(ROUNDUP(SUM($I$7:BH$7)*BH$7/Qtrs_Yr,0)=0,0,LOOKUP(ROUNDUP(SUM($I$7:BH$7)*BH$7/Qtrs_Yr,0),Inputs!$F$35:$I$35,Inputs!$F$38:$I$38)*LOOKUP(ROUNDUP(SUM($I$7:BH$7)*BH$7/Qtrs_Yr,0),Inputs!$F$35:$I$35,Inputs!$F$36:$I$36))/Thousand/Qtrs_Yr))/Thousand+SUM(Inputs!$F$54:$F$61)*BH$7/Qtrs_Yr)*(1+LOOKUP(YEAR(BI$5),Inputs!$F$93:$I$93,Inputs!$F$94:$I$94)/Qtrs_Yr)^(COUNT($I$7:BH7))*Inputs!$F$98/(BH5-BG5))-(((IF(ROUNDUP(SUM($J$7:BI$7)*BI$7/Qtrs_Yr,0)=0,0,LOOKUP(ROUNDUP(SUM($J$7:BI$7)*BI$7/Qtrs_Yr,0),Inputs!$F$35:$I$35,Inputs!$F$36:$I$36))/Thousand/Qtrs_Yr)*IF(ROUNDUP(SUM($J$7:BI$7)*BI$7/Qtrs_Yr,0)=0,0,LOOKUP(ROUNDUP(SUM($J$7:BI$7)*BI$7/Qtrs_Yr,0),Inputs!$F$41:$I$41,Inputs!$F$42:$I$42))/Grams_Oz*Inputs!$F$45)*LOOKUP(YEAR(BI$5),Inputs!$F$49:$I$49,Inputs!$F$50:$I$50)/Thousand /LOOKUP(YEAR(BI$5),Inputs!$F$89:$I$89,Inputs!$F$90:$I$90)-((Inputs!$F$64*(IF(ROUNDUP(SUM($J$7:BI$7)*BI$7/Qtrs_Yr,0)=0,0,LOOKUP(ROUNDUP(SUM($J$7:BI$7)*BI$7/Qtrs_Yr,0),Inputs!$F$35:$I$35,Inputs!$F$36:$I$36))/Thousand/Qtrs_Yr+IF(ROUNDUP(SUM($J$7:BI$7)*BI$7/Qtrs_Yr,0)=0,0,LOOKUP(ROUNDUP(SUM($J$7:BI$7)*BI$7/Qtrs_Yr,0),Inputs!$F$35:$I$35,Inputs!$F$38:$I$38)*LOOKUP(ROUNDUP(SUM($J$7:BI$7)*BI$7/Qtrs_Yr,0),Inputs!$F$35:$I$35,Inputs!$F$36:$I$36))/Thousand/Qtrs_Yr)+Inputs!$F$65*(IF(ROUNDUP(SUM($J$7:BI$7)*BI$7/Qtrs_Yr,0)=0,0,LOOKUP(ROUNDUP(SUM($J$7:BI$7)*BI$7/Qtrs_Yr,0),Inputs!$F$35:$I$35,Inputs!$F$36:$I$36))/Thousand/Qtrs_Yr)+Inputs!$F$66*(IF(ROUNDUP(SUM($J$7:BI$7)*BI$7/Qtrs_Yr,0)=0,0,LOOKUP(ROUNDUP(SUM($J$7:BI$7)*BI$7/Qtrs_Yr,0),Inputs!$F$35:$I$35,Inputs!$F$38:$I$38)*LOOKUP(ROUNDUP(SUM($J$7:BI$7)*BI$7/Qtrs_Yr,0),Inputs!$F$35:$I$35,Inputs!$F$36:$I$36))/Thousand/Qtrs_Yr))/Thousand+SUM(Inputs!$F$54:$F$61)*BI$7/Qtrs_Yr)*(1+LOOKUP(YEAR(BI$5),Inputs!$F$93:$I$93,Inputs!$F$94:$I$94)/Qtrs_Yr)^(COUNT($J$7:BI7))-Inputs!$E$29*(1+Inputs!$E$31)*BI$7/Inputs!$E$16/Qtrs_Yr-IF(OR(BI$7=0,SUM($J7:BI7)*BI7>Inputs!$F$77*Qtrs_Yr),0,(Inputs!$F$71-SUM($J7:BI7,-1)*BI7*Inputs!$F$71/Inputs!$F$77/Qtrs_Yr)*(LOOKUP(YEAR(BJ$5),Inputs!$F$85:$I$85,Inputs!$F$86:$I$86)+LOOKUP(ROUNDUP(SUM($J7:BJ7)*BJ7/Qtrs_Yr,0),Inputs!$G$73:$J$73,Inputs!$G$74:$J$74))/Qtrs_Yr))*Inputs!$F$101)/(IF(OR(BI$7=0,SUM($J7:BI7)*BI7>Inputs!$F$77*Qtrs_Yr),0,(Inputs!$F$71-SUM($J7:BI7,-1)*BI7*Inputs!$F$71/Inputs!$F$77/Qtrs_Yr)*(LOOKUP(YEAR(BJ$5),Inputs!$F$85:$I$85,Inputs!$F$86:$I$86)+LOOKUP(ROUNDUP(SUM($J7:BJ7)*BJ7/Qtrs_Yr,0),Inputs!$G$73:$J$73,Inputs!$G$74:$J$74))/Qtrs_Yr)+IF(OR(BI$7=0,SUM($J7:BI7)*BI7>Inputs!$F$77*Qtrs_Yr),0,Inputs!$F$71/Inputs!$F$77/Qtrs_Yr))) -> 0

Sheet Dynamic Array
A1: Calculations
A2: =Name_Project -> Gold Mining Project
A3: Master Integrity | D3: =Master_Integrity -> 0
A4: Period Start | J4: {=EOMONTH($I$5,+(_xlfn.ANCHORARRAY(J6)-1)*Months_Qtr)+1} -> 40909 | K4: 41000 | L4: 41091 | M4: 41183 | N4: 41275 | O4: 41365 | P4: 41456 | Q4: 41548 | R4: 41640 | S4: 41730 | T4: 41821 | U4: 41913 | V4: 42005 | W4: 42095 | X4: 42186 | Y4: 42278 | Z4: 42370 | AA4: 42461 | AB4: 42552 | AC4: 42644 | AD4: 42736 | AE4: 42826 | AF4: 42917 | AG4: 43009 | AH4: 43101 | AI4: 43191 | AJ4: 43282 | AK4: 43374 | AL4: 43466 | AM4: 43556 | AN4: 43647 | AO4: 43739 | AP4: 43831 | AQ4: 43922 | AR4: 44013 | AS4: 44105 | AT4: 44197 | AU4: 44287 | AV4: 44378 | AW4: 44470 | AX4: 44562 | AY4: 44652 | AZ4: 44743 | BA4: 44835 | BB4: 44927 | BC4: 45017 | BD4: 45108 | BE4: 45200 | BF4: 45292 | BG4: 45383 | BH4: 45474 | BI4: 45566
A5: Period End | I5: =Model_Start -> 40908 | J5: {=EOMONTH($I$5,+_xlfn.ANCHORARRAY(J6)*Months_Qtr)} -> 40999 | K5: 41090 | L5: 41182 | M5: 41274 | N5: 41364 | O5: 41455 | P5: 41547 | Q5: 41639 | R5: 41729 | S5: 41820 | T5: 41912 | U5: 42004 | V5: 42094 | W5: 42185 | X5: 42277 | Y5: 42369 | Z5: 42460 | AA5: 42551 | AB5: 42643 | AC5: 42735 | AD5: 42825 | AE5: 42916 | AF5: 43008 | AG5: 43100 | AH5: 43190 | AI5: 43281 | AJ5: 43373 | AK5: 43465 | AL5: 43555 | AM5: 43646 | AN5: 43738 | AO5: 43830 | AP5: 43921 | AQ5: 44012 | AR5: 44104 | AS5: 44196 | AT5: 44286 | AU5: 44377 | AV5: 44469 | AW5: 44561 | AX5: 44651 | AY5: 44742 | AZ5: 44834 | BA5: 44926 | BB5: 45016 | BC5: 45107 | BD5: 45199 | BE5: 45291 | BF5: 45382 | BG5: 45473 | BH5: 45565 | BI5: 45657
A6: Counter | D6: 52 | J6: {=_xlfn.SEQUENCE(1,$D$6)} -> 1 | K6: 2 | L6: 3 | M6: 4 | N6: 5 | O6: 6 | P6: 7 | Q6: 8 | R6: 9 | S6: 10 | T6: 11 | U6: 12 | V6: 13 | W6: 14 | X6: 15 | Y6: 16 | Z6: 17 | AA6: 18 | AB6: 19 | AC6: 20 | AD6: 21 | AE6: 22 | AF6: 23 | AG6: 24 | AH6: 25 | AI6: 26 | AJ6: 27 | AK6: 28 | AL6: 29 | AM6: 30 | AN6: 31 | AO6: 32 | AP6: 33 | AQ6: 34 | AR6: 35 | AS6: 36 | AT6: 37 | AU6: 38 | AV6: 39 | AW6: 40 | AX6: 41 | AY6: 42 | AZ6: 43 | BA6: 44 | BB6: 45 | BC6: 46 | BD6: 47 | BE6: 48 | BF6: 49 | BG6: 50 | BH6: 51 | BI6: 52
A7: Construction | J7: {=(_xlfn.ANCHORARRAY(J$4)>=Con_Start)*(_xlfn.ANCHORARRAY(J$5)<=Con_End)} -> 1 | K7: 1 | L7: 1 | M7: 1 | N7: 0 | O7: 0 | P7: 0 | Q7: 0 | R7: 0 | S7: 0 | T7: 0 | U7: 0 | V7: 0 | W7: 0 | X7: 0 | Y7: 0 | Z7: 0 | AA7: 0 | AB7: 0 | AC7: 0 | AD7: 0 | AE7: 0 | AF7: 0 | AG7: 0 | AH7: 0 | AI7: 0 | AJ7: 0 | AK7: 0 | AL7: 0 | AM7: 0 | AN7: 0 | AO7: 0 | AP7: 0 | AQ7: 0 | AR7: 0 | AS7: 0 | AT7: 0 | AU7: 0 | AV7: 0 | AW7: 0 | AX7: 0 | AY7: 0 | AZ7: 0 | BA7: 0 | BB7: 0 | BC7: 0 | BD7: 0 | BE7: 0 | BF7: 0 | BG7: 0 | BH7: 0 | BI7: 0
A8: Operations | J8: {=(_xlfn.ANCHORARRAY(J$4)>=Ops_Start)*(_xlfn.ANCHORARRAY(J$5)<=Ops_End)} -> 0 | K8: 0 | L8: 0 | M8: 0 | N8: 1 | O8: 1 | P8: 1 | Q8: 1 | R8: 1 | S8: 1 | T8: 1 | U8: 1 | V8: 1 | W8: 1 | X8: 1 | Y8: 1 | Z8: 1 | AA8: 1 | AB8: 1 | AC8: 1 | AD8: 1 | AE8: 1 | AF8: 1 | AG8: 1 | AH8: 1 | AI8: 1 | AJ8: 1 | AK8: 1 | AL8: 1 | AM8: 1 | AN8: 1 | AO8: 1 | AP8: 1 | AQ8: 1 | AR8: 1 | AS8: 1 | AT8: 1 | AU8: 1 | AV8: 1 | AW8: 1 | AX8: 1 | AY8: 1 | AZ8: 1 | BA8: 1 | BB8: 0 | BC8: 0 | BD8: 0 | BE8: 0 | BF8: 0 | BG8: 0 | BH8: 0 | BI8: 0
C10: Counters
C11: Construction counter | D11: # | J11: {=IF(_xlfn.ANCHORARRAY(J7),_xlfn.ANCHORARRAY(J6),0)} -> 1 | K11: 2 | L11: 3 | M11: 4 | N11: 0 | O11: 0 | P11: 0 | Q11: 0 | R11: 0 | S11: 0 | T11: 0 | U11: 0 | V11: 0 | W11: 0 | X11: 0 | Y11: 0 | Z11: 0 | AA11: 0 | AB11: 0 | AC11: 0 | AD11: 0 | AE11: 0 | AF11: 0 | AG11: 0 | AH11: 0 | AI11: 0 | AJ11: 0 | AK11: 0 | AL11: 0 | AM11: 0 | AN11: 0 | AO11: 0 | AP11: 0 | AQ11: 0 | AR11: 0 | AS11: 0 | AT11: 0 | AU11: 0 | AV11: 0 | AW11: 0 | AX11: 0 | AY11: 0 | AZ11: 0 | BA11: 0 | BB11: 0 | BC11: 0 | BD11: 0 | BE11: 0 | BF11: 0 | BG11: 0 | BH11: 0 | BI11: 0
C12: Operations counter | D12: # | J12: {=IF(_xlfn.ANCHORARRAY(J8),_xlfn.ANCHORARRAY(J6)-MATCH(1,_xlfn.ANCHORARRAY(J8),0)+1,0)} -> 0 | K12: 0 | L12: 0 | M12: 0 | N12: 1 | O12: 2 | P12: 3 | Q12: 4 | R12: 5 | S12: 6 | T12: 7 | U12: 8 | V12: 9 | W12: 10 | X12: 11 | Y12: 12 | Z12: 13 | AA12: 14 | AB12: 15 | AC12: 16 | AD12: 17 | AE12: 18 | AF12: 19 | AG12: 20 | AH12: 21 | AI12: 22 | AJ12: 23 | AK12: 24 | AL12: 25 | AM12: 26 | AN12: 27 | AO12: 28 | AP12: 29 | AQ12: 30 | AR12: 31 | AS12: 32 | AT12: 33 | AU12: 34 | AV12: 35 | AW12: 36 | AX12: 37 | AY12: 38 | AZ12: 39 | BA12: 40 | BB12: 0 | BC12: 0 | BD12: 0 | BE12: 0 | BF12: 0 | BG12: 0 | BH12: 0 | BI12: 0
C13: Year | D13: # | J13: {=YEAR(_xlfn.ANCHORARRAY(J5))} -> 2012 | K13: 2012 | L13: 2012 | M13: 2012 | N13: 2013 | O13: 2013 | P13: 2013 | Q13: 2013 | R13: 2014 | S13: 2014 | T13: 2014 | U13: 2014 | V13: 2015 | W13: 2015 | X13: 2015 | Y13: 2015 | Z13: 2016 | AA13: 2016 | AB13: 2016 | AC13: 2016 | AD13: 2017 | AE13: 2017 | AF13: 2017 | AG13: 2017 | AH13: 2018 | AI13: 2018 | AJ13: 2018 | AK13: 2018 | AL13: 2019 | AM13: 2019 | AN13: 2019 | AO13: 2019 | AP13: 2020 | AQ13: 2020 | AR13: 2020 | AS13: 2020 | AT13: 2021 | AU13: 2021 | AV13: 2021 | AW13: 2021 | AX13: 2022 | AY13: 2022 | AZ13: 2022 | BA13: 2022 | BB13: 2023 | BC13: 2023 | BD13: 2023 | BE13: 2023 | BF13: 2024 | BG13: 2024 | BH13: 2024 | BI13: 2024
C14: Month | D14: # | J14: {=MONTH(_xlfn.ANCHORARRAY(J5))} -> 3 | K14: 6 | L14: 9 | M14: 12 | N14: 3 | O14: 6 | P14: 9 | Q14: 12 | R14: 3 | S14: 6 | T14: 9 | U14: 12 | V14: 3 | W14: 6 | X14: 9 | Y14: 12 | Z14: 3 | AA14: 6 | AB14: 9 | AC14: 12 | AD14: 3 | AE14: 6 | AF14: 9 | AG14: 12 | AH14: 3 | AI14: 6 | AJ14: 9 | AK14: 12 | AL14: 3 | AM14: 6 | AN14: 9 | AO14: 12 | AP14: 3 | AQ14: 6 | AR14: 9 | AS14: 12 | AT14: 3 | AU14: 6 | AV14: 9 | AW14: 12 | AX14: 3 | AY14: 6 | AZ14: 9 | BA14: 12 | BB14: 3 | BC14: 6 | BD14: 9 | BE14: 12 | BF14: 3 | BG14: 6 | BH14: 9 | BI14: 12
C15: Days in period | D15: # | J15: {=_xlfn.ANCHORARRAY(J5)-_xlfn.ANCHORARRAY(J4)+1} -> 91 | K15: 91 | L15: 92 | M15: 92 | N15: 90 | O15: 91 | P15: 92 | Q15: 92 | R15: 90 | S15: 91 | T15: 92 | U15: 92 | V15: 90 | W15: 91 | X15: 92 | Y15: 92 | Z15: 91 | AA15: 91 | AB15: 92 | AC15: 92 | AD15: 90 | AE15: 91 | AF15: 92 | AG15: 92 | AH15: 90 | AI15: 91 | AJ15: 92 | AK15: 92 | AL15: 90 | AM15: 91 | AN15: 92 | AO15: 92 | AP15: 91 | AQ15: 91 | AR15: 92 | AS15: 92 | AT15: 90 | AU15: 91 | AV15: 92 | AW15: 92 | AX15: 90 | AY15: 91 | AZ15: 92 | BA15: 92 | BB15: 90 | BC15: 91 | BD15: 92 | BE15: 92 | BF15: 91 | BG15: 91 | BH15: 92 | BI15: 92
C17: Construction
C18: Development profile
C19: {=Inputs!C22:C28} -> Infrastructure | D19: % | J19: {=IF(_xlfn.ANCHORARRAY(J$11)=0,0,_xlfn.XLOOKUP(_xlfn.ANCHORARRAY(J$11),Inputs!$H$21:$S$21,Inputs!$H22:$S22))} -> 0.25 | K19: 0.25 | L19: 0.25 | M19: 0.25 | N19: 0 | O19: 0 | P19: 0 | Q19: 0 | R19: 0 | S19: 0 | T19: 0 | U19: 0 | V19: 0 | W19: 0 | X19: 0 | Y19: 0 | Z19: 0 | AA19: 0 | AB19: 0 | AC19: 0 | AD19: 0 | AE19: 0 | AF19: 0 | AG19: 0 | AH19: 0 | AI19: 0 | AJ19: 0 | AK19: 0 | AL19: 0 | AM19: 0 | AN19: 0 | AO19: 0 | AP19: 0 | AQ19: 0 | AR19: 0 | AS19: 0 | AT19: 0 | AU19: 0 | AV19: 0 | AW19: 0 | AX19: 0 | AY19: 0 | AZ19: 0 | BA19: 0 | BB19: 0 | BC19: 0 | BD19: 0 | BE19: 0 | BF19: 0 | BG19: 0 | BH19: 0 | BI19: 0
C20: Overburden | D20: % | J20: {=IF(_xlfn.ANCHORARRAY(J$11)=0,0,_xlfn.XLOOKUP(_xlfn.ANCHORARRAY(J$11),Inputs!$H$21:$S$21,Inputs!$H23:$S23))} -> 0 | K20: 0.25 | L20: 0.25 | M20: 0.5 | N20: 0 | O20: 0 | P20: 0 | Q20: 0 | R20: 0 | S20: 0 | T20: 0 | U20: 0 | V20: 0 | W20: 0 | X20: 0 | Y20: 0 | Z20: 0 | AA20: 0 | AB20: 0 | AC20: 0 | AD20: 0 | AE20: 0 | AF20: 0 | AG20: 0 | AH20: 0 | AI20: 0 | AJ20: 0 | AK20: 0 | AL20: 0 | AM20: 0 | AN20: 0 | AO20: 0 | AP20: 0 | AQ20: 0 | AR20: 0 | AS20: 0 | AT20: 0 | AU20: 0 | AV20: 0 | AW20: 0 | AX20: 0 | AY20: 0 | AZ20: 0 | BA20: 0 | BB20: 0 | BC20: 0 | BD20: 0 | BE20: 0 | BF20: 0 | BG20: 0 | BH20: 0 | BI20: 0
C21: Processing Plant | D21: % | J21: {=IF(_xlfn.ANCHORARRAY(J$11)=0,0,_xlfn.XLOOKUP(_xlfn.ANCHORARRAY(J$11),Inputs!$H$21:$S$21,Inputs!$H24:$S24))} -> 0 | K21: 0 | L21: 0.5 | M21: 0.5 | N21: 0 | O21: 0 | P21: 0 | Q21: 0 | R21: 0 | S21: 0 | T21: 0 | U21: 0 | V21: 0 | W21: 0 | X21: 0 | Y21: 0 | Z21: 0 | AA21: 0 | AB21: 0 | AC21: 0 | AD21: 0 | AE21: 0 | AF21: 0 | AG21: 0 | AH21: 0 | AI21: 0 | AJ21: 0 | AK21: 0 | AL21: 0 | AM21: 0 | AN21: 0 | AO21: 0 | AP21: 0 | AQ21: 0 | AR21: 0 | AS21: 0 | AT21: 0 | AU21: 0 | AV21: 0 | AW21: 0 | AX21: 0 | AY21: 0 | AZ21: 0 | BA21: 0 | BB21: 0 | BC21: 0 | BD21: 0 | BE21: 0 | BF21: 0 | BG21: 0 | BH21: 0 | BI21: 0
C22: Storage Dam | D22: % | J22: {=IF(_xlfn.ANCHORARRAY(J$11)=0,0,_xlfn.XLOOKUP(_xlfn.ANCHORARRAY(J$11),Inputs!$H$21:$S$21,Inputs!$H25:$S25))} -> 0 | K22: 0 | L22: 0.3 | M22: 0.7 | N22: 0 | O22: 0 | P22: 0 | Q22: 0 | R22: 0 | S22: 0 | T22: 0 | U22: 0 | V22: 0 | W22: 0 | X22: 0 | Y22: 0 | Z22: 0 | AA22: 0 | AB22: 0 | AC22: 0 | AD22: 0 | AE22: 0 | AF22: 0 | AG22: 0 | AH22: 0 | AI22: 0 | AJ22: 0 | AK22: 0 | AL22: 0 | AM22: 0 | AN22: 0 | AO22: 0 | AP22: 0 | AQ22: 0 | AR22: 0 | AS22: 0 | AT22: 0 | AU22: 0 | AV22: 0 | AW22: 0 | AX22: 0 | AY22: 0 | AZ22: 0 | BA22: 0 | BB22: 0 | BC22: 0 | BD22: 0 | BE22: 0 | BF22: 0 | BG22: 0 | BH22: 0 | BI22: 0
C23: Civil Works | D23: % | J23: {=IF(_xlfn.ANCHORARRAY(J$11)=0,0,_xlfn.XLOOKUP(_xlfn.ANCHORARRAY(J$11),Inputs!$H$21:$S$21,Inputs!$H26:$S26))} -> 0 | K23: 0.5 | L23: 0.25 | M23: 0.25 | N23: 0 | O23: 0 | P23: 0 | Q23: 0 | R23: 0 | S23: 0 | T23: 0 | U23: 0 | V23: 0 | W23: 0 | X23: 0 | Y23: 0 | Z23: 0 | AA23: 0 | AB23: 0 | AC23: 0 | AD23: 0 | AE23: 0 | AF23: 0 | AG23: 0 | AH23: 0 | AI23: 0 | AJ23: 0 | AK23: 0 | AL23: 0 | AM23: 0 | AN23: 0 | AO23: 0 | AP23: 0 | AQ23: 0 | AR23: 0 | AS23: 0 | AT23: 0 | AU23: 0 | AV23: 0 | AW23: 0 | AX23: 0 | AY23: 0 | AZ23: 0 | BA23: 0 | BB23: 0 | BC23: 0 | BD23: 0 | BE23: 0 | BF23: 0 | BG23: 0 | BH23: 0 | BI23: 0
C24: Spare | D24: % | J24: {=IF(_xlfn.ANCHORARRAY(J$11)=0,0,_xlfn.XLOOKUP(_xlfn.ANCHORARRAY(J$11),Inputs!$H$21:$S$21,Inputs!$H27:$S27))} -> 0 | K24: 0 | L24: 0 | M24: 0 | N24: 0 | O24: 0 | P24: 0 | Q24: 0 | R24: 0 | S24: 0 | T24: 0 | U24: 0 | V24: 0 | W24: 0 | X24: 0 | Y24: 0 | Z24: 0 | AA24: 0 | AB24: 0 | AC24: 0 | AD24: 0 | AE24: 0 | AF24: 0 | AG24: 0 | AH24: 0 | AI24: 0 | AJ24: 0 | AK24: 0 | AL24: 0 | AM24: 0 | AN24: 0 | AO24: 0 | AP24: 0 | AQ24: 0 | AR24: 0 | AS24: 0 | AT24: 0 | AU24: 0 | AV24: 0 | AW24: 0 | AX24: 0 | AY24: 0 | AZ24: 0 | BA24: 0 | BB24: 0 | BC24: 0 | BD24: 0 | BE24: 0 | BF24: 0 | BG24: 0 | BH24: 0 | BI24: 0
C25: Spare | D25: % | J25: {=IF(_xlfn.ANCHORARRAY(J$11)=0,0,_xlfn.XLOOKUP(_xlfn.ANCHORARRAY(J$11),Inputs!$H$21:$S$21,Inputs!$H28:$S28))} -> 0 | K25: 0 | L25: 0 | M25: 0 | N25: 0 | O25: 0 | P25: 0 | Q25: 0 | R25: 0 | S25: 0 | T25: 0 | U25: 0 | V25: 0 | W25: 0 | X25: 0 | Y25: 0 | Z25: 0 | AA25: 0 | AB25: 0 | AC25: 0 | AD25: 0 | AE25: 0 | AF25: 0 | AG25: 0 | AH25: 0 | AI25: 0 | AJ25: 0 | AK25: 0 | AL25: 0 | AM25: 0 | AN25: 0 | AO25: 0 | AP25: 0 | AQ25: 0 | AR25: 0 | AS25: 0 | AT25: 0 | AU25: 0 | AV25: 0 | AW25: 0 | AX25: 0 | AY25: 0 | AZ25: 0 | BA25: 0 | BB25: 0 | BC25: 0 | BD25: 0 | BE25: 0 | BF25: 0 | BG25: 0 | BH25: 0 | BI25: 0
C27: Development costs
C28: {=_xlfn.ANCHORARRAY(C19)} -> Infrastructure | D28: {=Inputs!D22:D29} -> AUD M | E28: {=Inputs!E22:E28} -> 30 | I28: {=_xlfn.BYROW(_xlfn.ANCHORARRAY(J28),_xlfn.LAMBDA(_xlpm.A,SUM(_xlpm.A)))} -> 30 | J28: {=J19:BI25*_xlfn.ANCHORARRAY(E28)} -> 7.5 | K28: 7.5 | L28: 7.5 | M28: 7.5 | N28: 0 | O28: 0 | P28: 0 | Q28: 0 | R28: 0 | S28: 0 | T28: 0 | U28: 0 | V28: 0 | W28: 0 | X28: 0 | Y28: 0 | Z28: 0 | AA28: 0 | AB28: 0 | AC28: 0 | AD28: 0 | AE28: 0 | AF28: 0 | AG28: 0 | AH28: 0 | AI28: 0 | AJ28: 0 | AK28: 0 | AL28: 0 | AM28: 0 | AN28: 0 | AO28: 0 | AP28: 0 | AQ28: 0 | AR28: 0 | AS28: 0 | AT28: 0 | AU28: 0 | AV28: 0 | AW28: 0 | AX28: 0 | AY28: 0 | AZ28: 0 | BA28: 0 | BB28: 0 | BC28: 0 | BD28: 0 | BE28: 0 | BF28: 0 | BG28: 0 | BH28: 0 | BI28: 0
C29: Overburden | D29: AUD M | E29: 15 | I29: 15 | J29: 0 | K29: 3.75 | L29: 3.75 | M29: 7.5 | N29: 0 | O29: 0 | P29: 0 | Q29: 0 | R29: 0 | S29: 0 | T29: 0 | U29: 0 | V29: 0 | W29: 0 | X29: 0 | Y29: 0 | Z29: 0 | AA29: 0 | AB29: 0 | AC29: 0 | AD29: 0 | AE29: 0 | AF29: 0 | AG29: 0 | AH29: 0 | AI29: 0 | AJ29: 0 | AK29: 0 | AL29: 0 | AM29: 0 | AN29: 0 | AO29: 0 | AP29: 0 | AQ29: 0 | AR29: 0 | AS29: 0 | AT29: 0 | AU29: 0 | AV29: 0 | AW29: 0 | AX29: 0 | AY29: 0 | AZ29: 0 | BA29: 0 | BB29: 0 | BC29: 0 | BD29: 0 | BE29: 0 | BF29: 0 | BG29: 0 | BH29: 0 | BI29: 0
C30: Processing Plant | D30: AUD M | E30: 75 | I30: 75 | J30: 0 | K30: 0 | L30: 37.5 | M30: 37.5 | N30: 0 | O30: 0 | P30: 0 | Q30: 0 | R30: 0 | S30: 0 | T30: 0 | U30: 0 | V30: 0 | W30: 0 | X30: 0 | Y30: 0 | Z30: 0 | AA30: 0 | AB30: 0 | AC30: 0 | AD30: 0 | AE30: 0 | AF30: 0 | AG30: 0 | AH30: 0 | AI30: 0 | AJ30: 0 | AK30: 0 | AL30: 0 | AM30: 0 | AN30: 0 | AO30: 0 | AP30: 0 | AQ30: 0 | AR30: 0 | AS30: 0 | AT30: 0 | AU30: 0 | AV30: 0 | AW30: 0 | AX30: 0 | AY30: 0 | AZ30: 0 | BA30: 0 | BB30: 0 | BC30: 0 | BD30: 0 | BE30: 0 | BF30: 0 | BG30: 0 | BH30: 0 | BI30: 0
C31: Storage Dam | D31: AUD M | E31: 20 | I31: 20 | J31: 0 | K31: 0 | L31: 6 | M31: 14 | N31: 0 | O31: 0 | P31: 0 | Q31: 0 | R31: 0 | S31: 0 | T31: 0 | U31: 0 | V31: 0 | W31: 0 | X31: 0 | Y31: 0 | Z31: 0 | AA31: 0 | AB31: 0 | AC31: 0 | AD31: 0 | AE31: 0 | AF31: 0 | AG31: 0 | AH31: 0 | AI31: 0 | AJ31: 0 | AK31: 0 | AL31: 0 | AM31: 0 | AN31: 0 | AO31: 0 | AP31: 0 | AQ31: 0 | AR31: 0 | AS31: 0 | AT31: 0 | AU31: 0 | AV31: 0 | AW31: 0 | AX31: 0 | AY31: 0 | AZ31: 0 | BA31: 0 | BB31: 0 | BC31: 0 | BD31: 0 | BE31: 0 | BF31: 0 | BG31: 0 | BH31: 0 | BI31: 0
C32: Civil Works | D32: AUD M | E32: 15 | I32: 15 | J32: 0 | K32: 7.5 | L32: 3.75 | M32: 3.75 | N32: 0 | O32: 0 | P32: 0 | Q32: 0 | R32: 0 | S32: 0 | T32: 0 | U32: 0 | V32: 0 | W32: 0 | X32: 0 | Y32: 0 | Z32: 0 | AA32: 0 | AB32: 0 | AC32: 0 | AD32: 0 | AE32: 0 | AF32: 0 | AG32: 0 | AH32: 0 | AI32: 0 | AJ32: 0 | AK32: 0 | AL32: 0 | AM32: 0 | AN32: 0 | AO32: 0 | AP32: 0 | AQ32: 0 | AR32: 0 | AS32: 0 | AT32: 0 | AU32: 0 | AV32: 0 | AW32: 0 | AX32: 0 | AY32: 0 | AZ32: 0 | BA32: 0 | BB32: 0 | BC32: 0 | BD32: 0 | BE32: 0 | BF32: 0 | BG32: 0 | BH32: 0 | BI32: 0
C33: Spare | D33: AUD M | E33: 0 | I33: 0 | J33: 0 | K33: 0 | L33: 0 | M33: 0 | N33: 0 | O33: 0 | P33: 0 | Q33: 0 | R33: 0 | S33: 0 | T33: 0 | U33: 0 | V33: 0 | W33: 0 | X33: 0 | Y33: 0 | Z33: 0 | AA33: 0 | AB33: 0 | AC33: 0 | AD33: 0 | AE33: 0 | AF33: 0 | AG33: 0 | AH33: 0 | AI33: 0 | AJ33: 0 | AK33: 0 | AL33: 0 | AM33: 0 | AN33: 0 | AO33: 0 | AP33: 0 | AQ33: 0 | AR33: 0 | AS33: 0 | AT33: 0 | AU33: 0 | AV33: 0 | AW33: 0 | AX33: 0 | AY33: 0 | AZ33: 0 | BA33: 0 | BB33: 0 | BC33: 0 | BD33: 0 | BE33: 0 | BF33: 0 | BG33: 0 | BH33: 0 | BI33: 0
C34: Spare | D34: AUD M | E34: 0 | I34: 0 | J34: 0 | K34: 0 | L34: 0 | M34: 0 | N34: 0 | O34: 0 | P34: 0 | Q34: 0 | R34: 0 | S34: 0 | T34: 0 | U34: 0 | V34: 0 | W34: 0 | X34: 0 | Y34: 0 | Z34: 0 | AA34: 0 | AB34: 0 | AC34: 0 | AD34: 0 | AE34: 0 | AF34: 0 | AG34: 0 | AH34: 0 | AI34: 0 | AJ34: 0 | AK34: 0 | AL34: 0 | AM34: 0 | AN34: 0 | AO34: 0 | AP34: 0 | AQ34: 0 | AR34: 0 | AS34: 0 | AT34: 0 | AU34: 0 | AV34: 0 | AW34: 0 | AX34: 0 | AY34: 0 | AZ34: 0 | BA34: 0 | BB34: 0 | BC34: 0 | BD34: 0 | BE34: 0 | BF34: 0 | BG34: 0 | BH34: 0 | BI34: 0
C35: Total | D35: AUD M | I35: =SUM(_xlfn.ANCHORARRAY(J35)) -> 155 | J35: {=_xlfn.BYCOL(_xlfn.ANCHORARRAY(J28),_xlfn.LAMBDA(_xlpm.a,SUM(_xlpm.a)))} -> 7.5 | K35: 18.75 | L35: 58.5 | M35: 70.25 | N35: 0 | O35: 0 | P35: 0 | Q35: 0 | R35: 0 | S35: 0 | T35: 0 | U35: 0 | V35: 0 | W35: 0 | X35: 0 | Y35: 0 | Z35: 0 | AA35: 0 | AB35: 0 | AC35: 0 | AD35: 0 | AE35: 0 | AF35: 0 | AG35: 0 | AH35: 0 | AI35: 0 | AJ35: 0 | AK35: 0 | AL35: 0 | AM35: 0 | AN35: 0 | AO35: 0 | AP35: 0 | AQ35: 0 | AR35: 0 | AS35: 0 | AT35: 0 | AU35: 0 | AV35: 0 | AW35: 0 | AX35: 0 | AY35: 0 | AZ35: 0 | BA35: 0 | BB35: 0 | BC35: 0 | BD35: 0 | BE35: 0 | BF35: 0 | BG35: 0 | BH35: 0 | BI35: 0
C37: Development costs including contingency
C38: {=_xlfn.ANCHORARRAY(C19)} -> Infrastructure | D38: {=_xlfn.ANCHORARRAY(D28)} -> AUD M | E38: =Inputs!E31 -> 0.1 | I38: {=_xlfn.BYROW(_xlfn.ANCHORARRAY(J38),_xlfn.LAMBDA(_xlpm.A,SUM(_xlpm.A)))} -> 33 | J38: {=_xlfn.ANCHORARRAY(J28)*(1+E38)} -> 8.25 | K38: 8.25 | L38: 8.25 | M38: 8.25 | N38: 0 | O38: 0 | P38: 0 | Q38: 0 | R38: 0 | S38: 0 | T38: 0 | U38: 0 | V38: 0 | W38: 0 | X38: 0 | Y38: 0 | Z38: 0 | AA38: 0 | AB38: 0 | AC38: 0 | AD38: 0 | AE38: 0 | AF38: 0 | AG38: 0 | AH38: 0 | AI38: 0 | AJ38: 0 | AK38: 0 | AL38: 0 | AM38: 0 | AN38: 0 | AO38: 0 | AP38: 0 | AQ38: 0 | AR38: 0 | AS38: 0 | AT38: 0 | AU38: 0 | AV38: 0 | AW38: 0 | AX38: 0 | AY38: 0 | AZ38: 0 | BA38: 0 | BB38: 0 | BC38: 0 | BD38: 0 | BE38: 0 | BF38: 0 | BG38: 0 | BH38: 0 | BI38: 0
C39: Overburden | D39: AUD M | I39: 16.5 | J39: 0 | K39: 4.125 | L39: 4.125 | M39: 8.25 | N39: 0 | O39: 0 | P39: 0 | Q39: 0 | R39: 0 | S39: 0 | T39: 0 | U39: 0 | V39: 0 | W39: 0 | X39: 0 | Y39: 0 | Z39: 0 | AA39: 0 | AB39: 0 | AC39: 0 | AD39: 0 | AE39: 0 | AF39: 0 | AG39: 0 | AH39: 0 | AI39: 0 | AJ39: 0 | AK39: 0 | AL39: 0 | AM39: 0 | AN39: 0 | AO39: 0 | AP39: 0 | AQ39: 0 | AR39: 0 | AS39: 0 | AT39: 0 | AU39: 0 | AV39: 0 | AW39: 0 | AX39: 0 | AY39: 0 | AZ39: 0 | BA39: 0 | BB39: 0 | BC39: 0 | BD39: 0 | BE39: 0 | BF39: 0 | BG39: 0 | BH39: 0 | BI39: 0
C40: Processing Plant | D40: AUD M | I40: 82.5 | J40: 0 | K40: 0 | L40: 41.25 | M40: 41.25 | N40: 0 | O40: 0 | P40: 0 | Q40: 0 | R40: 0 | S40: 0 | T40: 0 | U40: 0 | V40: 0 | W40: 0 | X40: 0 | Y40: 0 | Z40: 0 | AA40: 0 | AB40: 0 | AC40: 0 | AD40: 0 | AE40: 0 | AF40: 0 | AG40: 0 | AH40: 0 | AI40: 0 | AJ40: 0 | AK40: 0 | AL40: 0 | AM40: 0 | AN40: 0 | AO40: 0 | AP40: 0 | AQ40: 0 | AR40: 0 | AS40: 0 | AT40: 0 | AU40: 0 | AV40: 0 | AW40: 0 | AX40: 0 | AY40: 0 | AZ40: 0 | BA40: 0 | BB40: 0 | BC40: 0 | BD40: 0 | BE40: 0 | BF40: 0 | BG40: 0 | BH40: 0 | BI40: 0
C41: Storage Dam | D41: AUD M | I41: 22 | J41: 0 | K41: 0 | L41: 6.6 | M41: 15.4 | N41: 0 | O41: 0 | P41: 0 | Q41: 0 | R41: 0 | S41: 0 | T41: 0 | U41: 0 | V41: 0 | W41: 0 | X41: 0 | Y41: 0 | Z41: 0 | AA41: 0 | AB41: 0 | AC41: 0 | AD41: 0 | AE41: 0 | AF41: 0 | AG41: 0 | AH41: 0 | AI41: 0 | AJ41: 0 | AK41: 0 | AL41: 0 | AM41: 0 | AN41: 0 | AO41: 0 | AP41: 0 | AQ41: 0 | AR41: 0 | AS41: 0 | AT41: 0 | AU41: 0 | AV41: 0 | AW41: 0 | AX41: 0 | AY41: 0 | AZ41: 0 | BA41: 0 | BB41: 0 | BC41: 0 | BD41: 0 | BE41: 0 | BF41: 0 | BG41: 0 | BH41: 0 | BI41: 0
C42: Civil Works | D42: AUD M | I42: 16.5 | J42: 0 | K42: 8.25 | L42: 4.125 | M42: 4.125 | N42: 0 | O42: 0 | P42: 0 | Q42: 0 | R42: 0 | S42: 0 | T42: 0 | U42: 0 | V42: 0 | W42: 0 | X42: 0 | Y42: 0 | Z42: 0 | AA42: 0 | AB42: 0 | AC42: 0 | AD42: 0 | AE42: 0 | AF42: 0 | AG42: 0 | AH42: 0 | AI42: 0 | AJ42: 0 | AK42: 0 | AL42: 0 | AM42: 0 | AN42: 0 | AO42: 0 | AP42: 0 | AQ42: 0 | AR42: 0 | AS42: 0 | AT42: 0 | AU42: 0 | AV42: 0 | AW42: 0 | AX42: 0 | AY42: 0 | AZ42: 0 | BA42: 0 | BB42: 0 | BC42: 0 | BD42: 0 | BE42: 0 | BF42: 0 | BG42: 0 | BH42: 0 | BI42: 0
C43: Spare | D43: AUD M | I43: 0 | J43: 0 | K43: 0 | L43: 0 | M43: 0 | N43: 0 | O43: 0 | P43: 0 | Q43: 0 | R43: 0 | S43: 0 | T43: 0 | U43: 0 | V43: 0 | W43: 0 | X43: 0 | Y43: 0 | Z43: 0 | AA43: 0 | AB43: 0 | AC43: 0 | AD43: 0 | AE43: 0 | AF43: 0 | AG43: 0 | AH43: 0 | AI43: 0 | AJ43: 0 | AK43: 0 | AL43: 0 | AM43: 0 | AN43: 0 | AO43: 0 | AP43: 0 | AQ43: 0 | AR43: 0 | AS43: 0 | AT43: 0 | AU43: 0 | AV43: 0 | AW43: 0 | AX43: 0 | AY43: 0 | AZ43: 0 | BA43: 0 | BB43: 0 | BC43: 0 | BD43: 0 | BE43: 0 | BF43: 0 | BG43: 0 | BH43: 0 | BI43: 0
C44: Spare | D44: AUD M | I44: 0 | J44: 0 | K44: 0 | L44: 0 | M44: 0 | N44: 0 | O44: 0 | P44: 0 | Q44: 0 | R44: 0 | S44: 0 | T44: 0 | U44: 0 | V44: 0 | W44: 0 | X44: 0 | Y44: 0 | Z44: 0 | AA44: 0 | AB44: 0 | AC44: 0 | AD44: 0 | AE44: 0 | AF44: 0 | AG44: 0 | AH44: 0 | AI44: 0 | AJ44: 0 | AK44: 0 | AL44: 0 | AM44: 0 | AN44: 0 | AO44: 0 | AP44: 0 | AQ44: 0 | AR44: 0 | AS44: 0 | AT44: 0 | AU44: 0 | AV44: 0 | AW44: 0 | AX44: 0 | AY44: 0 | AZ44: 0 | BA44: 0 | BB44: 0 | BC44: 0 | BD44: 0 | BE44: 0 | BF44: 0 | BG44: 0 | BH44: 0 | BI44: 0
C45: Total | D45: AUD M | I45: =SUM(_xlfn.ANCHORARRAY(J45)) -> 170.5 | J45: {=_xlfn.BYCOL(_xlfn.ANCHORARRAY(J38),_xlfn.LAMBDA(_xlpm.a,SUM(_xlpm.a)))} -> 8.25 | K45: 20.625 | L45: 64.35 | M45: 77.275 | N45: 0 | O45: 0 | P45: 0 | Q45: 0 | R45: 0 | S45: 0 | T45: 0 | U45: 0 | V45: 0 | W45: 0 | X45: 0 | Y45: 0 | Z45: 0 | AA45: 0 | AB45: 0 | AC45: 0 | AD45: 0 | AE45: 0 | AF45: 0 | AG45: 0 | AH45: 0 | AI45: 0 | AJ45: 0 | AK45: 0 | AL45: 0 | AM45: 0 | AN45: 0 | AO45: 0 | AP45: 0 | AQ45: 0 | AR45: 0 | AS45: 0 | AT45: 0 | AU45: 0 | AV45: 0 | AW45: 0 | AX45: 0 | AY45: 0 | AZ45: 0 | BA45: 0 | BB45: 0 | BC45: 0 | BD45: 0 | BE45: 0 | BF45: 0 | BG45: 0 | BH45: 0 | BI45: 0
C47: Funding
C48: Uses of funds
C49: Construction costs | D49: AUD M | I49: =SUM(_xlfn.ANCHORARRAY(J49)) -> 170.5 | J49: {=_xlfn.ANCHORARRAY(J45)} -> 8.25 | K49: 20.625 | L49: 64.35 | M49: 77.275 | N49: 0 | O49: 0 | P49: 0 | Q49: 0 | R49: 0 | S49: 0 | T49: 0 | U49: 0 | V49: 0 | W49: 0 | X49: 0 | Y49: 0 | Z49: 0 | AA49: 0 | AB49: 0 | AC49: 0 | AD49: 0 | AE49: 0 | AF49: 0 | AG49: 0 | AH49: 0 | AI49: 0 | AJ49: 0 | AK49: 0 | AL49: 0 | AM49: 0 | AN49: 0 | AO49: 0 | AP49: 0 | AQ49: 0 | AR49: 0 | AS49: 0 | AT49: 0 | AU49: 0 | AV49: 0 | AW49: 0 | AX49: 0 | AY49: 0 | AZ49: 0 | BA49: 0 | BB49: 0 | BC49: 0 | BD49: 0 | BE49: 0 | BF49: 0 | BG49: 0 | BH49: 0 | BI49: 0
C50: Interest during construction | D50: AUD M
D51: AUD M
D52: AUD M
C53: Total costs | D53: AUD M | I53: =SUM(_xlfn.ANCHORARRAY(J53)) -> 170.5 | J53: {=_xlfn.ANCHORARRAY(J49)} -> 8.25 | K53: 20.625 | L53: 64.35 | M53: 77.275 | N53: 0 | O53: 0 | P53: 0 | Q53: 0 | R53: 0 | S53: 0 | T53: 0 | U53: 0 | V53: 0 | W53: 0 | X53: 0 | Y53: 0 | Z53: 0 | AA53: 0 | AB53: 0 | AC53: 0 | AD53: 0 | AE53: 0 | AF53: 0 | AG53: 0 | AH53: 0 | AI53: 0 | AJ53: 0 | AK53: 0 | AL53: 0 | AM53: 0 | AN53: 0 | AO53: 0 | AP53: 0 | AQ53: 0 | AR53: 0 | AS53: 0 | AT53: 0 | AU53: 0 | AV53: 0 | AW53: 0 | AX53: 0 | AY53: 0 | AZ53: 0 | BA53: 0 | BB53: 0 | BC53: 0 | BD53: 0 | BE53: 0 | BF53: 0 | BG53: 0 | BH53: 0 | BI53: 0
J55: {=_xlfn.SCAN(0,I57,_xlfn.LAMBDA(_xlpm.a,_xlpm.a))} -> #VALUE!
C58: Sources of funds
C59: Equity | D59: AUD M | F59: =I59/(I59+I61) -> 1 | I59: =SUM(J59:L59) -> 38.88 | J59: 8.25 | K59: 20.63 | L59: 10
C60: Funding required after equity | D60: AUD M
C61: Debt | D61: AUD M | J61: 10 | K61: 10 | L61: 10 | M61: 10
C62: Funding required after debt | D62: AUD M
C65: Interest
C66: Construction interest
C67: Base rate | D67: % p.a. | E67: Margin | J67: {=_xlfn.XLOOKUP(_xlfn.ANCHORARRAY(J13),Inputs!$F$85:$I$85,Inputs!$F$86:$I$86,0,-1)} -> 0.03 | K67: 0.03 | L67: 0.03 | M67: 0.03 | N67: 0.029 | O67: 0.029 | P67: 0.029 | Q67: 0.029 | R67: 0.03 | S67: 0.03 | T67: 0.03 | U67: 0.03 | V67: 0.03 | W67: 0.03 | X67: 0.03 | Y67: 0.03 | Z67: 0.03 | AA67: 0.03 | AB67: 0.03 | AC67: 0.03 | AD67: 0.03 | AE67: 0.03 | AF67: 0.03 | AG67: 0.03 | AH67: 0.03 | AI67: 0.03 | AJ67: 0.03 | AK67: 0.03 | AL67: 0.03 | AM67: 0.03 | AN67: 0.03 | AO67: 0.03 | AP67: 0.03 | AQ67: 0.03 | AR67: 0.03 | AS67: 0.03 | AT67: 0.03 | AU67: 0.03 | AV67: 0.03 | AW67: 0.03 | AX67: 0.03 | AY67: 0.03 | AZ67: 0.03 | BA67: 0.03 | BB67: 0.03 | BC67: 0.03 | BD67: 0.03 | BE67: 0.03 | BF67: 0.03 | BG67: 0.03 | BH67: 0.03 | BI67: 0.03
C68: Margin | D68: % p.a. | E68: =Inputs!F74 -> 0.035 | J68: {=_xlfn.SEQUENCE(1,$D$6,E68,0)} -> 0.035 | K68: 0.035 | L68: 0.035 | M68: 0.035 | N68: 0.035 | O68: 0.035 | P68: 0.035 | Q68: 0.035 | R68: 0.035 | S68: 0.035 | T68: 0.035 | U68: 0.035 | V68: 0.035 | W68: 0.035 | X68: 0.035 | Y68: 0.035 | Z68: 0.035 | AA68: 0.035 | AB68: 0.035 | AC68: 0.035 | AD68: 0.035 | AE68: 0.035 | AF68: 0.035 | AG68: 0.035 | AH68: 0.035 | AI68: 0.035 | AJ68: 0.035 | AK68: 0.035 | AL68: 0.035 | AM68: 0.035 | AN68: 0.035 | AO68: 0.035 | AP68: 0.035 | AQ68: 0.035 | AR68: 0.035 | AS68: 0.035 | AT68: 0.035 | AU68: 0.035 | AV68: 0.035 | AW68: 0.035 | AX68: 0.035 | AY68: 0.035 | AZ68: 0.035 | BA68: 0.035 | BB68: 0.035 | BC68: 0.035 | BD68: 0.035 | BE68: 0.035 | BF68: 0.035 | BG68: 0.035 | BH68: 0.035 | BI68: 0.035
C69: All-in rate | D69: % p.a. | J69: {=_xlfn.ANCHORARRAY(J67)+_xlfn.ANCHORARRAY(J68)} -> 0.065 | K69: 0.065 | L69: 0.065 | M69: 0.065 | N69: 0.064 | O69: 0.064 | P69: 0.064 | Q69: 0.064 | R69: 0.065 | S69: 0.065 | T69: 0.065 | U69: 0.065 | V69: 0.065 | W69: 0.065 | X69: 0.065 | Y69: 0.065 | Z69: 0.065 | AA69: 0.065 | AB69: 0.065 | AC69: 0.065 | AD69: 0.065 | AE69: 0.065 | AF69: 0.065 | AG69: 0.065 | AH69: 0.065 | AI69: 0.065 | AJ69: 0.065 | AK69: 0.065 | AL69: 0.065 | AM69: 0.065 | AN69: 0.065 | AO69: 0.065 | AP69: 0.065 | AQ69: 0.065 | AR69: 0.065 | AS69: 0.065 | AT69: 0.065 | AU69: 0.065 | AV69: 0.065 | AW69: 0.065 | AX69: 0.065 | AY69: 0.065 | AZ69: 0.065 | BA69: 0.065 | BB69: 0.065 | BC69: 0.065 | BD69: 0.065 | BE69: 0.065 | BF69: 0.065 | BG69: 0.065 | BH69: 0.065 | BI69: 0.065
C70: All-in rate | D70: % p.q. | J70: {=_xlfn.ANCHORARRAY(J69)*_xlfn.ANCHORARRAY(J15)/Days_Yr} -> 0.016205479 | K70: 0.016205479 | L70: 0.016383562 | M70: 0.016383562 | N70: 0.015780822 | O70: 0.015956164 | P70: 0.016131507 | Q70: 0.016131507 | R70: 0.016027397 | S70: 0.016205479 | T70: 0.016383562 | U70: 0.016383562 | V70: 0.016027397 | W70: 0.016205479 | X70: 0.016383562 | Y70: 0.016383562 | Z70: 0.016205479 | AA70: 0.016205479 | AB70: 0.016383562 | AC70: 0.016383562 | AD70: 0.016027397 | AE70: 0.016205479 | AF70: 0.016383562 | AG70: 0.016383562 | AH70: 0.016027397 | AI70: 0.016205479 | AJ70: 0.016383562 | AK70: 0.016383562 | AL70: 0.016027397 | AM70: 0.016205479 | AN70: 0.016383562 | AO70: 0.016383562 | AP70: 0.016205479 | AQ70: 0.016205479 | AR70: 0.016383562 | AS70: 0.016383562 | AT70: 0.016027397 | AU70: 0.016205479 | AV70: 0.016383562 | AW70: 0.016383562 | AX70: 0.016027397 | AY70: 0.016205479 | AZ70: 0.016383562 | BA70: 0.016383562 | BB70: 0.016027397 | BC70: 0.016205479 | BD70: 0.016383562 | BE70: 0.016383562 | BF70: 0.016205479 | BG70: 0.016205479 | BH70: 0.016383562 | BI70: 0.016383562
C72: Discount multiple | D72: # | J72: {=1+_xlfn.ANCHORARRAY(J70)} -> 1.0162055 | K72: 1.0162055 | L72: 1.0163836 | M72: 1.0163836 | N72: 1.0157808 | O72: 1.0159562 | P72: 1.0161315 | Q72: 1.0161315 | R72: 1.0160274 | S72: 1.0162055 | T72: 1.0163836 | U72: 1.0163836 | V72: 1.0160274 | W72: 1.0162055 | X72: 1.0163836 | Y72: 1.0163836 | Z72: 1.0162055 | AA72: 1.0162055 | AB72: 1.0163836 | AC72: 1.0163836 | AD72: 1.0160274 | AE72: 1.0162055 | AF72: 1.0163836 | AG72: 1.0163836 | AH72: 1.0160274 | AI72: 1.0162055 | AJ72: 1.0163836 | AK72: 1.0163836 | AL72: 1.0160274 | AM72: 1.0162055 | AN72: 1.0163836 | AO72: 1.0163836 | AP72: 1.0162055 | AQ72: 1.0162055 | AR72: 1.0163836 | AS72: 1.0163836 | AT72: 1.0160274 | AU72: 1.0162055 | AV72: 1.0163836 | AW72: 1.0163836 | AX72: 1.0160274 | AY72: 1.0162055 | AZ72: 1.0163836 | BA72: 1.0163836 | BB72: 1.0160274 | BC72: 1.0162055 | BD72: 1.0163836 | BE72: 1.0163836 | BF72: 1.0162055 | BG72: 1.0162055 | BH72: 1.0163836 | BI72: 1.0163836
C74: Discount factor | D74: # | I74: 1 | J74: {=_xlfn.BYCOL(_xlfn.ANCHORARRAY(J72),_xlfn.LAMBDA(_xlpm.a,PRODUCT(J72:_xlpm.a)))} -> 1.0162055 | K74: 1.0326736 | L74: 1.0495924 | M74: 1.0667885 | N74: 1.0836233 | O74: 1.1009138 | P74: 1.1186732 | Q74: 1.1367191 | R74: 1.1549377 | S74: 1.173654 | T74: 1.1928827 | U74: 1.2124263 | V74: 1.2318584 | W74: 1.2518212 | X74: 1.2723305 | Y74: 1.2931758 | Z74: 1.3141324 | AA74: 1.3354285 | AB74: 1.3573076 | AC74: 1.3795451 | AD74: 1.4016556 | AE74: 1.4243701 | AF74: 1.4477064 | AG74: 1.471425 | AH74: 1.4950081 | AI74: 1.5192354 | AJ74: 1.5441259 | AK74: 1.5694242 | AL74: 1.594578 | AM74: 1.6204189 | AN74: 1.6469671 | AO74: 1.6739503 | AP74: 1.7010774 | AQ74: 1.7286442 | AR74: 1.7569656 | AS74: 1.7857509 | AT74: 1.8143719 | AU74: 1.8437746 | AV74: 1.8739822 | AW74: 1.9046847 | AX74: 1.9352119 | AY74: 1.9665729 | AZ74: 1.9987924 | BA74: 2.0315397 | BB74: 2.0641 | BC74: 2.0975497 | BD74: 2.1319151 | BE74: 2.1668434 | BF74: 2.2019582 | BG74: 2.237642 | BH74: 2.2743025 | BI74: 2.3115637
C76: Total costs | D76: AUD M | I76: =SUM(_xlfn.ANCHORARRAY(J76)) -> 170.5 | J76: {=_xlfn.ANCHORARRAY(J49)} -> 8.25 | K76: 20.625 | L76: 64.35 | M76: 77.275 | N76: 0 | O76: 0 | P76: 0 | Q76: 0 | R76: 0 | S76: 0 | T76: 0 | U76: 0 | V76: 0 | W76: 0 | X76: 0 | Y76: 0 | Z76: 0 | AA76: 0 | AB76: 0 | AC76: 0 | AD76: 0 | AE76: 0 | AF76: 0 | AG76: 0 | AH76: 0 | AI76: 0 | AJ76: 0 | AK76: 0 | AL76: 0 | AM76: 0 | AN76: 0 | AO76: 0 | AP76: 0 | AQ76: 0 | AR76: 0 | AS76: 0 | AT76: 0 | AU76: 0 | AV76: 0 | AW76: 0 | AX76: 0 | AY76: 0 | AZ76: 0 | BA76: 0 | BB76: 0 | BC76: 0 | BD76: 0 | BE76: 0 | BF76: 0 | BG76: 0 | BH76: 0 | BI76: 0
C77: Discounted costs | D77: AUD M | I77: =SUM(_xlfn.ANCHORARRAY(J77)) -> 161.83742 | J77: {=_xlfn.ANCHORARRAY(J76)/_xlfn.ANCHORARRAY(J74)} -> 8.1184368 | K77: 19.972429 | L77: 61.309511 | M77: 72.437038 | N77: 0 | O77: 0 | P77: 0 | Q77: 0 | R77: 0 | S77: 0 | T77: 0 | U77: 0 | V77: 0 | W77: 0 | X77: 0 | Y77: 0 | Z77: 0 | AA77: 0 | AB77: 0 | AC77: 0 | AD77: 0 | AE77: 0 | AF77: 0 | AG77: 0 | AH77: 0 | AI77: 0 | AJ77: 0 | AK77: 0 | AL77: 0 | AM77: 0 | AN77: 0 | AO77: 0 | AP77: 0 | AQ77: 0 | AR77: 0 | AS77: 0 | AT77: 0 | AU77: 0 | AV77: 0 | AW77: 0 | AX77: 0 | AY77: 0 | AZ77: 0 | BA77: 0 | BB77: 0 | BC77: 0 | BD77: 0 | BE77: 0 | BF77: 0 | BG77: 0 | BH77: 0 | BI77: 0
E78: Gearing | F78: Equity
C79: Equity component | D79: % | E79: =Inputs!F70 -> 0.7 | F79: =1-E79 -> 0.3 | I79: =I77*F79 -> 48.551225
C81: Cumulative construction costs | D81: AUD M | J81: {=_xlfn.BYCOL(_xlfn.ANCHORARRAY(J76),_xlfn.LAMBDA(_xlpm.a,SUM(J76:_xlpm.a)))*_xlfn.ANCHORARRAY(J7)} -> 8.25 | K81: 28.875 | L81: 93.225 | M81: 170.5 | N81: 0 | O81: 0 | P81: 0 | Q81: 0 | R81: 0 | S81: 0 | T81: 0 | U81: 0 | V81: 0 | W81: 0 | X81: 0 | Y81: 0 | Z81: 0 | AA81: 0 | AB81: 0 | AC81: 0 | AD81: 0 | AE81: 0 | AF81: 0 | AG81: 0 | AH81: 0 | AI81: 0 | AJ81: 0 | AK81: 0 | AL81: 0 | AM81: 0 | AN81: 0 | AO81: 0 | AP81: 0 | AQ81: 0 | AR81: 0 | AS81: 0 | AT81: 0 | AU81: 0 | AV81: 0 | AW81: 0 | AX81: 0 | AY81: 0 | AZ81: 0 | BA81: 0 | BB81: 0 | BC81: 0 | BD81: 0 | BE81: 0 | BF81: 0 | BG81: 0 | BH81: 0 | BI81: 0
C82: Cumulative equity drawdown | D82: AUD M | J82: {=IF(_xlfn.ANCHORARRAY(J7)=0,0,_xlfn.BYCOL(_xlfn.ANCHORARRAY(J81),_xlfn.LAMBDA(_xlpm.a,MIN(I79,_xlpm.a))))} -> 8.25 | K82: 28.875 | L82: 48.551225 | M82: 48.551225 | N82: 0 | O82: 0 | P82: 0 | Q82: 0 | R82: 0 | S82: 0 | T82: 0 | U82: 0 | V82: 0 | W82: 0 | X82: 0 | Y82: 0 | Z82: 0 | AA82: 0 | AB82: 0 | AC82: 0 | AD82: 0 | AE82: 0 | AF82: 0 | AG82: 0 | AH82: 0 | AI82: 0 | AJ82: 0 | AK82: 0 | AL82: 0 | AM82: 0 | AN82: 0 | AO82: 0 | AP82: 0 | AQ82: 0 | AR82: 0 | AS82: 0 | AT82: 0 | AU82: 0 | AV82: 0 | AW82: 0 | AX82: 0 | AY82: 0 | AZ82: 0 | BA82: 0 | BB82: 0 | BC82: 0 | BD82: 0 | BE82: 0 | BF82: 0 | BG82: 0 | BH82: 0 | BI82: 0
C83: Actual equity drawdown | D83: AUD M | I83: =SUM(_xlfn.ANCHORARRAY(J83)) -> 48.551225 | J83: {=IF(_xlfn.ANCHORARRAY(J6)=1,_xlfn.ANCHORARRAY(J82),_xlfn.ANCHORARRAY(J82)-INDEX(_xlfn.ANCHORARRAY(J82),1,_xlfn.ANCHORARRAY(J6)-1))*_xlfn.ANCHORARRAY(J7)} -> 8.25 | K83: 20.625 | L83: 19.676225 | M83: 0 | N83: 0 | O83: 0 | P83: 0 | Q83: 0 | R83: 0 | S83: 0 | T83: 0 | U83: 0 | V83: 0 | W83: 0 | X83: 0 | Y83: 0 | Z83: 0 | AA83: 0 | AB83: 0 | AC83: 0 | AD83: 0 | AE83: 0 | AF83: 0 | AG83: 0 | AH83: 0 | AI83: 0 | AJ83: 0 | AK83: 0 | AL83: 0 | AM83: 0 | AN83: 0 | AO83: 0 | AP83: 0 | AQ83: 0 | AR83: 0 | AS83: 0 | AT83: 0 | AU83: 0 | AV83: 0 | AW83: 0 | AX83: 0 | AY83: 0 | AZ83: 0 | BA83: 0 | BB83: 0 | BC83: 0 | BD83: 0 | BE83: 0 | BF83: 0 | BG83: 0 | BH83: 0 | BI83: 0
I84: =I83/(I83+I85) -> 0.28475792
C85: Debt drawdown required | D85: AUD M | I85: =SUM(_xlfn.ANCHORARRAY(J85)) -> 121.94878 | J85: {=_xlfn.ANCHORARRAY(J76)-_xlfn.ANCHORARRAY(J83)} -> 0 | K85: 0 | L85: 44.673775 | M85: 77.275 | N85: 0 | O85: 0 | P85: 0 | Q85: 0 | R85: 0 | S85: 0 | T85: 0 | U85: 0 | V85: 0 | W85: 0 | X85: 0 | Y85: 0 | Z85: 0 | AA85: 0 | AB85: 0 | AC85: 0 | AD85: 0 | AE85: 0 | AF85: 0 | AG85: 0 | AH85: 0 | AI85: 0 | AJ85: 0 | AK85: 0 | AL85: 0 | AM85: 0 | AN85: 0 | AO85: 0 | AP85: 0 | AQ85: 0 | AR85: 0 | AS85: 0 | AT85: 0 | AU85: 0 | AV85: 0 | AW85: 0 | AX85: 0 | AY85: 0 | AZ85: 0 | BA85: 0 | BB85: 0 | BC85: 0 | BD85: 0 | BE85: 0 | BF85: 0 | BG85: 0 | BH85: 0 | BI85: 0
C87: End of construction discount factor | D87: # | I87: {=_xlfn.XLOOKUP(Con_End,_xlfn.ANCHORARRAY(J5),_xlfn.ANCHORARRAY(J74))} -> 1.0667885
C88: FV of debt | D88: AUD M | J88: {=_xlfn.ANCHORARRAY(J85)*I87/_xlfn.ANCHORARRAY(J74)} -> 0 | K88: 0 | L88: 45.405691 | M88: 77.275 | N88: 0 | O88: 0 | P88: 0 | Q88: 0 | R88: 0 | S88: 0 | T88: 0 | U88: 0 | V88: 0 | W88: 0 | X88: 0 | Y88: 0 | Z88: 0 | AA88: 0 | AB88: 0 | AC88: 0 | AD88: 0 | AE88: 0 | AF88: 0 | AG88: 0 | AH88: 0 | AI88: 0 | AJ88: 0 | AK88: 0 | AL88: 0 | AM88: 0 | AN88: 0 | AO88: 0 | AP88: 0 | AQ88: 0 | AR88: 0 | AS88: 0 | AT88: 0 | AU88: 0 | AV88: 0 | AW88: 0 | AX88: 0 | AY88: 0 | AZ88: 0 | BA88: 0 | BB88: 0 | BC88: 0 | BD88: 0 | BE88: 0 | BF88: 0 | BG88: 0 | BH88: 0 | BI88: 0
C89: Total FV of debt funding | D89: AUD M | I89: =SUM(_xlfn.ANCHORARRAY(J88)) -> 122.68069
C91: FV of construction costs | D91: AUD M | J91: {=_xlfn.ANCHORARRAY(J76)*I87/_xlfn.ANCHORARRAY(J74)} -> 8.6606551 | K91: 21.306358 | L91: 65.404282 | M91: 77.275 | N91: 0 | O91: 0 | P91: 0 | Q91: 0 | R91: 0 | S91: 0 | T91: 0 | U91: 0 | V91: 0 | W91: 0 | X91: 0 | Y91: 0 | Z91: 0 | AA91: 0 | AB91: 0 | AC91: 0 | AD91: 0 | AE91: 0 | AF91: 0 | AG91: 0 | AH91: 0 | AI91: 0 | AJ91: 0 | AK91: 0 | AL91: 0 | AM91: 0 | AN91: 0 | AO91: 0 | AP91: 0 | AQ91: 0 | AR91: 0 | AS91: 0 | AT91: 0 | AU91: 0 | AV91: 0 | AW91: 0 | AX91: 0 | AY91: 0 | AZ91: 0 | BA91: 0 | BB91: 0 | BC91: 0 | BD91: 0 | BE91: 0 | BF91: 0 | BG91: 0 | BH91: 0 | BI91: 0
C92: Total FV of construction costs | D92: AUD M | I92: =SUM(_xlfn.ANCHORARRAY(J91)) -> 172.6463
C94: Equity funding + FV of debt funding | D94: AUD M | I94: =I79+I89 -> 171.23192
C96: FV construction = total construction + FV of equity - equity nominal
C97: Equity nominal = total construction - FV construction + FV equity
I101: =SUM(J101:M101) -> 400 | J101: 100 | K101: 100 | L101: 100 | M101: 100
E102: =100*(1-0.3)*E68/(0.3*((1+E68)^(4+1)-1)) -> 43.51232 | F102: =E102*I101 -> 17404.928 | J102: =J101 -> 100 | K102: =F102-J102 -> 17304.928
I103: =SUM(J103:M103) -> -17004.928 | K103: =K101-K102 -> -17204.928 | L103: 100 | M103: 100
C104: Equity = E | E104: =E * (1-t)*r/(t*((1+r)^(P+1)-1)) | I104: =SUM(J104:M104) -> -1859.8607 | K104: =K103*E68 -> -602.17249 | L104: =SUM(K103:K104,L103)*E68 -> -619.74852 | M104: =SUM(K103:L104,M103)*E68 -> -637.93972
C105: Periods = P | I105: =SUM(J105:M105) -> -18864.789 | J105: =SUM(J103:J104) -> 0 | K105: =SUM(K103:K104) -> -17807.101 | L105: =SUM(L103:L104) -> -519.74852 | M105: =SUM(M103:M104) -> -537.93972
C106: Rate = r
C107: Ratio = t | I107: =F102/I105 -> -0.92261452
C115: Construction costs | J115: 25 | K115: 25 | L115: 25 | M115: 25
C116: Interest rate | J116: 0.02 | K116: 0.02 | L116: 0.02 | M116: 0.02
C117: Equity
C118: Debt

Sheet L
A1: Style Legend
C6: Formatting of Headers / Dividers
C8: Header 1 | E8: Header 1 | G8: Header1
C9: Header 2 | E9: Header 2 | G9: Header2
C10: Header 3 | E10: Header 3 | G10: Header3
C12: Table Heading | E12: Table Heading | G12: Table_Heading
C14: Individual Cell Assumptions
C16: Standard Assumption | E16: 100 | G16: Assumptions
C18: Offsheet Reference | E18: 100 | G18: Offsheet
C20: Flex Cell | E20: 100 | G20: Assumption_Flex
C22: Technical Input | E22: 1000 | G22: Input
C24: Empty Cell | G24: Empty_Cell
C26: Check | E26: 0 | G26: Check
C28: Infrastructure
C30: Line Total | E30: 100 | G30: Line_Summary
C32: Units | E32: USD | G32: Unit
C34: Operation Line (Non-Addition) | E34: 100 | G34: Line_Operation
C36: Operation (Addition / Total) | E36: 100 | G36: Line_Total
C38: Closing Balance | E38: 100 | G38: Line_ClosingBal
C40: Key Line | E40: 100 | G40: Line_Key
C42: Development Styles
C44: WIP | E44: W | G44: WIP

Sheet N
A1: Names & Constants
C5: Entity Names
C6: Company Name | D6: Name | F6: Corality Financial Group
C7: Model Name | D7: Name | F7: New Modelling Standards
C8: Project Name | D8: Name | F8: Gold Mining Project
C10: Constants
C11: Days per Year | D11: Num# | F11: 365
C12: Months per Year | D12: Num# | F12: 12
C13: Quarters per Year | D13: Num# | F13: 4
C14: Months per Quarter | D14: Num# | F14: 3
C16: Thousand | D16: Num# | F16: 1000
C17: Million | D17: Num# | F17: 1000000
C18: Billion | D18: Num# | F18: 1000000000
C19: Very Small Number | D19: Num# | F19: 1e-07
C21: Gram to Oz (Troy) | D21: Num# | F21: 31.103477
