Workbook

Sheet Cover
B3: BREWERY FINANCIAL MODEL
B5: SkyBrew & AllDark Brewing Company
B7: 10-Year Monthly Projection Model
B9: Model Version: | C9: 1.0
B10: Last Updated: | C10: 2025-12-16
B12: Contents:
B13: 1. Control - Scenario selection and global settings
B14: 2. Timeline - 120-month date spine
B15: 3. SKU_Matrix - Product portfolio (24 SKUs)
B16: 4. Assumptions - Volume, Pricing, Costs, Capex, WC, Finance
B17: 5. Calculations - Volume, Revenue, COGS, Capacity, etc.
B18: 6. Financial Statements - IS, CF, BS
B19: 7. KPIs - Key performance indicators
B20: 8. Checks - Model integrity checks

Sheet Control
B2: SCENARIO & GLOBAL CONTROL
B4: SCENARIO SELECTION
B5: Active Scenario (1=Base, 2=Upside, 3=Downside) | D5: 1
B7: GLOBAL SETTINGS
B8: Model Start Date | D8: 45658
B9: Projection Years | D9: 10
B10: Periods per Year | D10: 12
B11: Total Periods | D11: =D9*D10 -> 120
B13: CURRENCY & TAX
B14: Reporting Currency | D14: AUD
B15: AUD/NZD Exchange Rate | D15: 1.1
B16: Corporate Tax Rate | D16: 0.3
B18: INFLATION ASSUMPTIONS
B19: General Inflation (Annual) | D19: 0.025
B20: Wage Inflation (Annual) | D20: 0.03

Sheet Timeline
A1: TIMELINE
A3: Period | B3: Date | C3: Month | D3: Year | E3: Quarter | F3: FY | G3: Period Label
A4: 1 | B4: 45658 | C4: 1 | D4: 2025 | E4: Q1 | F4: FY2025 | G4: Jan-25
A5: 2 | B5: 45689 | C5: 2 | D5: 2025 | E5: Q1 | F5: FY2025 | G5: Feb-25
A6: 3 | B6: 45717 | C6: 3 | D6: 2025 | E6: Q1 | F6: FY2025 | G6: Mar-25
A7: 4 | B7: 45748 | C7: 4 | D7: 2025 | E7: Q2 | F7: FY2025 | G7: Apr-25
A8: 5 | B8: 45778 | C8: 5 | D8: 2025 | E8: Q2 | F8: FY2025 | G8: May-25
A9: 6 | B9: 45809 | C9: 6 | D9: 2025 | E9: Q2 | F9: FY2025 | G9: Jun-25
A10: 7 | B10: 45839 | C10: 7 | D10: 2025 | E10: Q3 | F10: FY2026 | G10: Jul-25
A11: 8 | B11: 45870 | C11: 8 | D11: 2025 | E11: Q3 | F11: FY2026 | G11: Aug-25
A12: 9 | B12: 45901 | C12: 9 | D12: 2025 | E12: Q3 | F12: FY2026 | G12: Sep-25
A13: 10 | B13: 45931 | C13: 10 | D13: 2025 | E13: Q4 | F13: FY2026 | G13: Oct-25
A14: 11 | B14: 45962 | C14: 11 | D14: 2025 | E14: Q4 | F14: FY2026 | G14: Nov-25
A15: 12 | B15: 45992 | C15: 12 | D15: 2025 | E15: Q4 | F15: FY2026 | G15: Dec-25
... A123: 120 | B123: 49279 | C123: 12 | D123: 2034 | E123: Q4 | F123: FY2035 | G123: Dec-34

Sheet SKU_Matrix
A1: SKU MATRIX
A3: SKU_ID | B3: Brand | C3: Format | D3: Pack_Size | E3: Units_Per_Pack | F3: ML_Per_Unit | G3: HL_Per_Pack | H3: ABV | I3: On_Trade | J3: Off_Trade | K3: Active
A4: SKU01 | B4: SkyBrew | C4: Bottle | D4: 330ml Single | E4: 1 | F4: 330 | G4: =E4*F4/100000 -> 0.0033 | H4: 0.05 | I4: 1 | J4: 1 | K4: 1
A5: SKU02 | B5: SkyBrew | C5: Bottle | D5: 330ml 6-pack | E5: 6 | F5: 330 | G5: =E5*F5/100000 -> 0.0198 | H5: 0.05 | I5: 1 | J5: 1 | K5: 1
A6: SKU03 | B6: SkyBrew | C6: Bottle | D6: 330ml 24-pack | E6: 24 | F6: 330 | G6: =E6*F6/100000 -> 0.0792 | H6: 0.05 | I6: 0 | J6: 1 | K6: 1
A7: SKU04 | B7: SkyBrew | C7: Bottle | D7: 500ml Single | E7: 1 | F7: 500 | G7: =E7*F7/100000 -> 0.005 | H7: 0.05 | I7: 1 | J7: 1 | K7: 1
A8: SKU05 | B8: SkyBrew | C8: Bottle | D8: 750ml Single | E8: 1 | F8: 750 | G8: =E8*F8/100000 -> 0.0075 | H8: 0.05 | I8: 1 | J8: 1 | K8: 1
A9: SKU06 | B9: SkyBrew | C9: Can | D9: 330ml Single | E9: 1 | F9: 330 | G9: =E9*F9/100000 -> 0.0033 | H9: 0.05 | I9: 1 | J9: 1 | K9: 1
A10: SKU07 | B10: SkyBrew | C10: Can | D10: 330ml 4-pack | E10: 4 | F10: 330 | G10: =E10*F10/100000 -> 0.0132 | H10: 0.05 | I10: 0 | J10: 1 | K10: 1
A11: SKU08 | B11: SkyBrew | C11: Can | D11: 330ml 6-pack | E11: 6 | F11: 330 | G11: =E11*F11/100000 -> 0.0198 | H11: 0.05 | I11: 1 | J11: 1 | K11: 1
A12: SKU09 | B12: SkyBrew | C12: Can | D12: 330ml 24-pack | E12: 24 | F12: 330 | G12: =E12*F12/100000 -> 0.0792 | H12: 0.05 | I12: 0 | J12: 1 | K12: 1
A13: SKU10 | B13: SkyBrew | C13: Can | D13: 500ml Single | E13: 1 | F13: 500 | G13: =E13*F13/100000 -> 0.005 | H13: 0.05 | I13: 1 | J13: 1 | K13: 1
A14: SKU11 | B14: SkyBrew | C14: Keg | D14: 20L | E14: 1 | F14: 20000 | G14: =E14*F14/100000 -> 0.2 | H14: 0.05 | I14: 1 | J14: 0 | K14: 1
A15: SKU12 | B15: SkyBrew | C15: Keg | D15: 50L | E15: 1 | F15: 50000 | G15: =E15*F15/100000 -> 0.5 | H15: 0.05 | I15: 1 | J15: 0 | K15: 1
... A27: SKU24 | B27: AllDark | C27: Keg | D27: 50L | E27: 1 | F27: 50000 | G27: =E27*F27/100000 -> 0.5 | H27: 0.06 | I27: 1 | J27: 0 | K27: 1

Sheet Assum_Volume
A1: VOLUME ASSUMPTIONS
A3: BASE ANNUAL VOLUMES (HL) - YEAR 1
A5: Total Base Volume (HL) | C5: 800000
A7: BRAND MIX
A8: SkyBrew % | C8: 0.7
A9: AllDark % | C9: =1-C8 -> 0.3
A11: MARKET MIX
A12: Australia % | C12: 0.7
A13: New Zealand % | C13: =1-C12 -> 0.3
A15: CHANNEL MIX
A16: On-Trade % | C16: 0.35
A17: Off-Trade % | C17: =1-C16 -> 0.65
A19: FORMAT MIX (within channel)
A20: On-Trade:
A21: Kegs % | C21: 0.7
A22: Bottles % | C22: 0.2
A23: Cans % | C23: =1-C21-C22 -> 0.1
A25: Off-Trade:
A26: Bottles % | C26: 0.45
A27: Cans % | C27: 0.55
A30: ANNUAL VOLUME GROWTH RATES
B31: Base | C31: Upside | D31: Downside
A32: Year 1 | B32: 0 | C32: 0 | D32: 0
A33: Year 2 | B33: 0.08 | C33: 0.1 | D33: 0.05
A34: Year 3 | B34: 0.08 | C34: 0.1 | D34: 0.05
A35: Year 4 | B35: 0.06 | C35: 0.08 | D35: 0.03
A36: Year 5 | B36: 0.06 | C36: 0.08 | D36: 0.03
A37: Year 6 | B37: 0.04 | C37: 0.06 | D37: 0.02
A38: Year 7 | B38: 0.04 | C38: 0.06 | D38: 0.02
A39: Year 8 | B39: 0.04 | C39: 0.06 | D39: 0.02
A40: Year 9 | B40: 0.04 | C40: 0.06 | D40: 0.02
A41: Year 10 | B41: 0.04 | C41: 0.06 | D41: 0.02
A44: MONTHLY SEASONALITY INDEX
A45: (Sum = 12.00)
A46: Jan | B46: 1.15
A47: Feb | B47: 1.1
A48: Mar | B48: 1
A49: Apr | B49: 0.9
A50: May | B50: 0.85
A51: Jun | B51: 0.8
A52: Jul | B52: 0.8
A53: Aug | B53: 0.85
A54: Sep | B54: 0.95
A55: Oct | B55: 1.05
A56: Nov | B56: 1.15
A57: Dec | B57: 1.4
A58: Seasonality Check (should = 12) | B58: =SUM(B46:B57) -> 12

Sheet Assum_Pricing
A1: PRICING ASSUMPTIONS
A3: GROSS PRICE PER HL (AUD)
A5: Brand | B5: Format | C5: On-Trade | D5: Off-Trade
A6: SkyBrew | B6: Bottle | C6: 850 | D6: 550
A7: SkyBrew | B7: Can | C7: 800 | D7: 520
A8: SkyBrew | B8: Keg | C8: 650 | D8: 0
A9: AllDark | B9: Bottle | C9: 950 | D9: 620
A10: AllDark | B10: Can | C10: 900 | D10: 580
A11: AllDark | B11: Keg | C11: 720 | D11: 0
A14: DISCOUNTS & REBATES
A15: On-Trade Discount % | C15: 0.08
A16: Off-Trade Retail Discount % | C16: 0.12
A17: Off-Trade Wholesale Discount % | C17: 0.18
A18: Blended Off-Trade Discount | C18: =(C16+C17)/2 -> 0.15
A21: EXCISE DUTY
A22: Australia - Rate per Litre of Alcohol (LAL) | C22: 55
A23: Australia - Keg Rebate % | C23: 0.3
A24: New Zealand - Rate per LAL (AUD equivalent) | C24: 32
A26: CALCULATED EXCISE PER HL:
A27: AU SkyBrew (5% ABV) - Standard | C27: =$C$22*0.05*100 -> 275
A28: AU SkyBrew (5% ABV) - Keg | C28: =$C$22*0.05*100*(1-$C$23) -> 192.5
A29: AU AllDark (6% ABV) - Standard | C29: =$C$22*0.06*100 -> 330
A30: AU AllDark (6% ABV) - Keg | C30: =$C$22*0.06*100*(1-$C$23) -> 231
A31: NZ SkyBrew (5% ABV) | C31: =$C$24*0.05*100 -> 160
A32: NZ AllDark (6% ABV) | C32: =$C$24*0.06*100 -> 192
A35: ANNUAL PRICE INCREASE
A36: Base Scenario | C36: 0.025
A37: Upside Scenario | C37: 0.035
A38: Downside Scenario | C38: 0.015

Sheet Assum_Costs
A1: COST ASSUMPTIONS
A3: COGS PER HL (AUD)
A5: RAW MATERIALS (per HL)
A6: Malt & Adjuncts | C6: 12
A7: Hops | C7: 5
A8: Yeast | C8: 1.5
A9: Water & Treatment | C9: 1.5
A10: Total Raw Materials | C10: =SUM(C6:C9) -> 20
A12: PACKAGING MATERIALS (per HL)
A13: Bottles (glass, labels, caps, cartons) | C13: 35
A14: Cans (aluminum, labels, cartons) | C14: 30
A15: Kegs (depreciation, cleaning, fittings) | C15: 8
A17: DIRECT MANUFACTURING (per HL)
A18: Direct Labour | C18: 12
A19: Utilities (power, gas, water) | C19: 6
A20: Manufacturing Overhead | C20: 8
A21: Quality Control | C21: 2
A22: Total Direct Manufacturing | C22: =SUM(C18:C21) -> 28
A24: TOTAL COGS SUMMARY (per HL)
A25: Bottle Product | C25: =C10+C13+C22 -> 83
A26: Can Product | C26: =C10+C14+C22 -> 78
A27: Keg Product | C27: =C10+C15+C22 -> 56
A30: LOGISTICS & DISTRIBUTION (per HL)
A31: Domestic Freight - Australia | C31: 22
A32: Domestic Freight - New Zealand | C32: 18
A33: Export Freight (AU to NZ) | C33: 35
A34: Warehousing | C34: 8
A35: Cold Chain Premium (Kegs) | C35: 10
A38: SG&A (% of Revenue)
A39: Sales Team | C39: 0.04
A40: Marketing | C40: 0.06
A41: Trade Marketing | C41: 0.03
A42: General & Admin | C42: 0.04
A43: Total SG&A % | C43: =SUM(C39:C42) -> 0.17
A46: ANNUAL COST INFLATION
A47: Base Scenario | C47: 0.025
A48: Upside Scenario | C48: 0.02
A49: Downside Scenario | C49: 0.035

Sheet Assum_Capex
A1: CAPEX & CAPACITY ASSUMPTIONS
A3: OPENING BALANCE SHEET (Year 0)
A5: Asset Class | B5: Gross Value | C5: Accum Depr | D5: Net Value | E5: Useful Life | F5: Annual Depr
A6: Land | B6: 5000000 | C6: 0 | D6: =B6-C6 -> 5000000 | E6: N/A | F6: 0
A7: Buildings | B7: 15000000 | C7: 3000000 | D7: =B7-C7 -> 12000000 | E7: 40 | F7: =B7/E7 -> 375000
A8: Brewing Equipment | B8: 20000000 | C8: 8000000 | D8: =B8-C8 -> 12000000 | E8: 15 | F8: =B8/E8 -> 1333333.3
A9: Packaging Lines | B9: 12000000 | C9: 4800000 | D9: =B9-C9 -> 7200000 | E9: 10 | F9: =B9/E9 -> 1200000
A10: Kegs & Returnable Packaging | B10: 5000000 | C10: 2500000 | D10: =B10-C10 -> 2500000 | E10: 10 | F10: =B10/E10 -> 500000
A11: Vehicles & Logistics | B11: 3000000 | C11: 1500000 | D11: =B11-C11 -> 1500000 | E11: 5 | F11: =B11/E11 -> 600000
A12: IT & Systems | B12: 2000000 | C12: 1200000 | D12: =B12-C12 -> 800000 | E12: 4 | F12: =B12/E12 -> 500000
A13: TOTAL | B13: =SUM(B6:B12) -> 62000000 | C13: =SUM(C6:C12) -> 21000000 | D13: =SUM(D6:D12) -> 41000000 | F13: =SUM(F6:F12) -> 4508333.3
A16: PRODUCTION CAPACITY
A17: Fermentation Capacity (HL/year) | C17: 1000000
A18: Bottle Line Capacity (HL/year) | C18: 500000
A19: Can Line Capacity (HL/year) | C19: 400000
A20: Keg Line Capacity (HL/year) | C20: 200000
A23: EXPANSION CAPEX (per 20% capacity addition)
A24: Fermentation Expansion | C24: 15000000
A25: Bottle Line Expansion | C25: 8000000
A26: Can Line Expansion | C26: 6000000
A27: Keg Line Expansion | C27: 3000000
A30: MAINTENANCE CAPEX
A31: Annual Maintenance Capex (% of Gross PP&E) | C31: 0.02
A34: EXPANSION TRIGGER
A35: Utilization Trigger for Expansion | C35: 0.85

Sheet Assum_WC
A1: WORKING CAPITAL ASSUMPTIONS
A3: INVENTORY DAYS
A4: Raw Materials (days of COGS) | C4: 30
A5: Work in Progress (days of COGS) | C5: 14
A6: Finished Goods (days of COGS) | C6: 21
A7: Total Inventory Days | C7: =SUM(C4:C6) -> 65
A10: RECEIVABLE DAYS
A11: On-Trade (days of revenue) | C11: 55
A12: Off-Trade (days of revenue) | C12: 38
A13: Blended Average | C13: =C11*Assum_Volume!C16+C12*Assum_Volume!C17 -> 43.95
A16: PAYABLE DAYS
A17: Trade Payables (days of COGS + Opex) | C17: 35
A20: OTHER WORKING CAPITAL
A21: Prepayments (days of Opex) | C21: 15
A22: Accruals (days of Opex) | C22: 20
A23: Returnable Packaging Deposits (AUD) | C23: 2500000
A26: OPENING WORKING CAPITAL
A27: Opening Inventory ($000s) | C27: 12000
A28: Opening Receivables ($000s) | C28: 33000
A29: Opening Payables ($000s) | C29: 19000
A30: Opening Prepayments ($000s) | C30: 5500
A31: Opening Accruals ($000s) | C31: 7400
A32: Opening Net Working Capital | C32: =C27+C28+C30-C29-C31 -> 24100

Sheet Assum_Finance
A1: FINANCING ASSUMPTIONS
A3: EXISTING DEBT
A4: Term Loan - Principal Outstanding | C4: 25000000
A5: Term Loan - Interest Rate | C5: 0.065
A6: Term Loan - Remaining Term (years) | C6: 7
A7: Term Loan - Annual Principal Payment | C7: =C4/C6 -> 3571428.6
A10: REVOLVING FACILITY
A11: Facility Limit | C11: 10000000
A12: Current Drawn Amount | C12: 0
A13: Interest Rate | C13: 0.075
A14: Commitment Fee (on undrawn) | C14: 0.005
A17: EQUITY
A18: Opening Share Capital | C18: 30000000
A19: Opening Retained Earnings | C19: 18100000
A22: DIVIDEND POLICY
A23: Target Payout Ratio (% of Net Income) | C23: 0.4
A24: Minimum Cash Balance Before Dividends | C24: 5000000
A27: CASH
A28: Opening Cash Balance | C28: 8000000
A29: Minimum Operating Cash | C29: 3000000

Sheet Calc_Volume
A1: VOLUME CALCULATIONS
A3: Period | B3: 1 | C3: 2 | D3: 3 | E3: 4 | F3: 5 | G3: 6 | H3: 7 | I3: 8 | J3: 9 | K3: 10 | L3: 11 | M3: 12 | N3: 13 | O3: 14 | P3: 15 | Q3: 16 | R3: 17 | S3: 18 | T3: 19 | U3: 20 | V3: 21 | W3: 22 | X3: 23 | Y3: 24 | Z3: 25 | AA3: 26 | AB3: 27 | AC3: 28 | AD3: 29 | AE3: 30 | AF3: 31 | AG3: 32 | AH3: 33 | AI3: 34 | AJ3: 35 | AK3: 36 | AL3: 37 | AM3: 38 | AN3: 39 | AO3: 40 | AP3: 41 | AQ3: 42 | AR3: 43 | AS3: 44 | AT3: 45 | AU3: 46 | AV3: 47 | AW3: 48 | AX3: 49 | AY3: 50 | AZ3: 51 | BA3: 52 | BB3: 53 | BC3: 54 | BD3: 55 | BE3: 56 | BF3: 57 | BG3: 58 | BH3: 59 | BI3: 60 | BJ3: 61 | BK3: 62 | BL3: 63 | BM3: 64 | BN3: 65 | BO3: 66 | BP3: 67 | BQ3: 68 | BR3: 69 | BS3: 70 | BT3: 71 | BU3: 72 | BV3: 73 | BW3: 74 | BX3: 75 | BY3: 76 | BZ3: 77 | CA3: 78 | CB3: 79 | CC3: 80 | CD3: 81 | CE3: 82 | CF3: 83 | CG3: 84 | CH3: 85 | CI3: 86 | CJ3: 87 | CK3: 88 | CL3: 89 | CM3: 90 | CN3: 91 | CO3: 92 | CP3: 93 | CQ3: 94 | CR3: 95 | CS3: 96 | CT3: 97 | CU3: 98 | CV3: 99 | CW3: 100 | CX3: 101 | CY3: 102 | CZ3: 103 | DA3: 104 | DB3: 105 | DC3: 106 | DD3: 107 | DE3: 108 | DF3: 109 | DG3: 110 | DH3: 111 | DI3: 112 | DJ3: 113 | DK3: 114 | DL3: 115 | DM3: 116 | DN3: 117 | DO3: 118 | DP3: 119 | DQ3: 120
A4: Date | B4: 45658 | C4: 45689 | D4: 45717 | E4: 45748 | F4: 45778 | G4: 45809 | H4: 45839 | I4: 45870 | J4: 45901 | K4: 45931 | L4: 45962 | M4: 45992 | N4: 46023 | O4: 46054 | P4: 46082 | Q4: 46113 | R4: 46143 | S4: 46174 | T4: 46204 | U4: 46235 | V4: 46266 | W4: 46296 | X4: 46327 | Y4: 46357 | Z4: 46388 | AA4: 46419 | AB4: 46447 | AC4: 46478 | AD4: 46508 | AE4: 46539 | AF4: 46569 | AG4: 46600 | AH4: 46631 | AI4: 46661 | AJ4: 46692 | AK4: 46722 | AL4: 46753 | AM4: 46784 | AN4: 46813 | AO4: 46844 | AP4: 46874 | AQ4: 46905 | AR4: 46935 | AS4: 46966 | AT4: 46997 | AU4: 47027 | AV4: 47058 | AW4: 47088 | AX4: 47119 | AY4: 47150 | AZ4: 47178 | BA4: 47209 | BB4: 47239 | BC4: 47270 | BD4: 47300 | BE4: 47331 | BF4: 47362 | BG4: 47392 | BH4: 47423 | BI4: 47453 | BJ4: 47484 | BK4: 47515 | BL4: 47543 | BM4: 47574 | BN4: 47604 | BO4: 47635 | BP4: 47665 | BQ4: 47696 | BR4: 47727 | BS4: 47757 | BT4: 47788 | BU4: 47818 | BV4: 47849 | BW4: 47880 | BX4: 47908 | BY4: 47939 | BZ4: 47969 | CA4: 48000 | CB4: 48030 | CC4: 48061 | CD4: 48092 | CE4: 48122 | CF4: 48153 | CG4: 48183 | CH4: 48214 | CI4: 48245 | CJ4: 48274 | CK4: 48305 | CL4: 48335 | CM4: 48366 | CN4: 48396 | CO4: 48427 | CP4: 48458 | CQ4: 48488 | CR4: 48519 | CS4: 48549 | CT4: 48580 | CU4: 48611 | CV4: 48639 | CW4: 48670 | CX4: 48700 | CY4: 48731 | CZ4: 48761 | DA4: 48792 | DB4: 48823 | DC4: 48853 | DD4: 48884 | DE4: 48914 | DF4: 48945 | DG4: 48976 | DH4: 49004 | DI4: 49035 | DJ4: 49065 | DK4: 49096 | DL4: 49126 | DM4: 49157 | DN4: 49188 | DO4: 49218 | DP4: 49249 | DQ4: 49279
A5: Year | B5: 1 | C5: 1 | D5: 1 | E5: 1 | F5: 1 | G5: 1 | H5: 1 | I5: 1 | J5: 1 | K5: 1 | L5: 1 | M5: 1 | N5: 2 | O5: 2 | P5: 2 | Q5: 2 | R5: 2 | S5: 2 | T5: 2 | U5: 2 | V5: 2 | W5: 2 | X5: 2 | Y5: 2 | Z5: 3 | AA5: 3 | AB5: 3 | AC5: 3 | AD5: 3 | AE5: 3 | AF5: 3 | AG5: 3 | AH5: 3 | AI5: 3 | AJ5: 3 | AK5: 3 | AL5: 4 | AM5: 4 | AN5: 4 | AO5: 4 | AP5: 4 | AQ5: 4 | AR5: 4 | AS5: 4 | AT5: 4 | AU5: 4 | AV5: 4 | AW5: 4 | AX5: 5 | AY5: 5 | AZ5: 5 | BA5: 5 | BB5: 5 | BC5: 5 | BD5: 5 | BE5: 5 | BF5: 5 | BG5: 5 | BH5: 5 | BI5: 5 | BJ5: 6 | BK5: 6 | BL5: 6 | BM5: 6 | BN5: 6 | BO5: 6 | BP5: 6 | BQ5: 6 | BR5: 6 | BS5: 6 | BT5: 6 | BU5: 6 | BV5: 7 | BW5: 7 | BX5: 7 | BY5: 7 | BZ5: 7 | CA5: 7 | CB5: 7 | CC5: 7 | CD5: 7 | CE5: 7 | CF5: 7 | CG5: 7 | CH5: 8 | CI5: 8 | CJ5: 8 | CK5: 8 | CL5: 8 | CM5: 8 | CN5: 8 | CO5: 8 | CP5: 8 | CQ5: 8 | CR5: 8 | CS5: 8 | CT5: 9 | CU5: 9 | CV5: 9 | CW5: 9 | CX5: 9 | CY5: 9 | CZ5: 9 | DA5: 9 | DB5: 9 | DC5: 9 | DD5: 9 | DE5: 9 | DF5: 10 | DG5: 10 | DH5: 10 | DI5: 10 | DJ5: 10 | DK5: 10 | DL5: 10 | DM5: 10 | DN5: 10 | DO5: 10 | DP5: 10 | DQ5: 10
A6: Month | B6: 1 | C6: 2 | D6: 3 | E6: 4 | F6: 5 | G6: 6 | H6: 7 | I6: 8 | J6: 9 | K6: 10 | L6: 11 | M6: 12 | N6: 1 | O6: 2 | P6: 3 | Q6: 4 | R6: 5 | S6: 6 | T6: 7 | U6: 8 | V6: 9 | W6: 10 | X6: 11 | Y6: 12 | Z6: 1 | AA6: 2 | AB6: 3 | AC6: 4 | AD6: 5 | AE6: 6 | AF6: 7 | AG6: 8 | AH6: 9 | AI6: 10 | AJ6: 11 | AK6: 12 | AL6: 1 | AM6: 2 | AN6: 3 | AO6: 4 | AP6: 5 | AQ6: 6 | AR6: 7 | AS6: 8 | AT6: 9 | AU6: 10 | AV6: 11 | AW6: 12 | AX6: 1 | AY6: 2 | AZ6: 3 | BA6: 4 | BB6: 5 | BC6: 6 | BD6: 7 | BE6: 8 | BF6: 9 | BG6: 10 | BH6: 11 | BI6: 12 | BJ6: 1 | BK6: 2 | BL6: 3 | BM6: 4 | BN6: 5 | BO6: 6 | BP6: 7 | BQ6: 8 | BR6: 9 | BS6: 10 | BT6: 11 | BU6: 12 | BV6: 1 | BW6: 2 | BX6: 3 | BY6: 4 | BZ6: 5 | CA6: 6 | CB6: 7 | CC6: 8 | CD6: 9 | CE6: 10 | CF6: 11 | CG6: 12 | CH6: 1 | CI6: 2 | CJ6: 3 | CK6: 4 | CL6: 5 | CM6: 6 | CN6: 7 | CO6: 8 | CP6: 9 | CQ6: 10 | CR6: 11 | CS6: 12 | CT6: 1 | CU6: 2 | CV6: 3 | CW6: 4 | CX6: 5 | CY6: 6 | CZ6: 7 | DA6: 8 | DB6: 9 | DC6: 10 | DD6: 11 | DE6: 12 | DF6: 1 | DG6: 2 | DH6: 3 | DI6: 4 | DJ6: 5 | DK6: 6 | DL6: 7 | DM6: 8 | DN6: 9 | DO6: 10 | DP6: 11 | DQ6: 12
A7: Seasonality Index | B7: =Assum_Volume!$B$46 -> 1.15 | C7: =Assum_Volume!$B$47 -> 1.1 | D7: =Assum_Volume!$B$48 -> 1 | E7: =Assum_Volume!$B$49 -> 0.9 | F7: =Assum_Volume!$B$50 -> 0.85 | G7: =Assum_Volume!$B$51 -> 0.8 | H7: =Assum_Volume!$B$52 -> 0.8 | I7: =Assum_Volume!$B$53 -> 0.85 | J7: =Assum_Volume!$B$54 -> 0.95 | K7: =Assum_Volume!$B$55 -> 1.05 | L7: =Assum_Volume!$B$56 -> 1.15 | M7: =Assum_Volume!$B$57 -> 1.4 | N7: =Assum_Volume!$B$46 -> 1.15 | O7: =Assum_Volume!$B$47 -> 1.1 | P7: =Assum_Volume!$B$48 -> 1 | Q7: =Assum_Volume!$B$49 -> 0.9 | R7: =Assum_Volume!$B$50 -> 0.85 | S7: =Assum_Volume!$B$51 -> 0.8 | T7: =Assum_Volume!$B$52 -> 0.8 | U7: =Assum_Volume!$B$53 -> 0.85 | V7: =Assum_Volume!$B$54 -> 0.95 | W7: =Assum_Volume!$B$55 -> 1.05 | X7: =Assum_Volume!$B$56 -> 1.15 | Y7: =Assum_Volume!$B$57 -> 1.4 | Z7: =Assum_Volume!$B$46 -> 1.15 | AA7: =Assum_Volume!$B$47 -> 1.1 | AB7: =Assum_Volume!$B$48 -> 1 | AC7: =Assum_Volume!$B$49 -> 0.9 | AD7: =Assum_Volume!$B$50 -> 0.85 | AE7: =Assum_Volume!$B$51 -> 0.8 | AF7: =Assum_Volume!$B$52 -> 0.8 | AG7: =Assum_Volume!$B$53 -> 0.85 | AH7: =Assum_Volume!$B$54 -> 0.95 | AI7: =Assum_Volume!$B$55 -> 1.05 | AJ7: =Assum_Volume!$B$56 -> 1.15 | AK7: =Assum_Volume!$B$57 -> 1.4 | AL7: =Assum_Volume!$B$46 -> 1.15 | AM7: =Assum_Volume!$B$47 -> 1.1 | AN7: =Assum_Volume!$B$48 -> 1 | AO7: =Assum_Volume!$B$49 -> 0.9 | AP7: =Assum_Volume!$B$50 -> 0.85 | AQ7: =Assum_Volume!$B$51 -> 0.8 | AR7: =Assum_Volume!$B$52 -> 0.8 | AS7: =Assum_Volume!$B$53 -> 0.85 | AT7: =Assum_Volume!$B$54 -> 0.95 | AU7: =Assum_Volume!$B$55 -> 1.05 | AV7: =Assum_Volume!$B$56 -> 1.15 | AW7: =Assum_Volume!$B$57 -> 1.4 | AX7: =Assum_Volume!$B$46 -> 1.15 | AY7: =Assum_Volume!$B$47 -> 1.1 | AZ7: =Assum_Volume!$B$48 -> 1 | BA7: =Assum_Volume!$B$49 -> 0.9 | BB7: =Assum_Volume!$B$50 -> 0.85 | BC7: =Assum_Volume!$B$51 -> 0.8 | BD7: =Assum_Volume!$B$52 -> 0.8 | BE7: =Assum_Volume!$B$53 -> 0.85 | BF7: =Assum_Volume!$B$54 -> 0.95 | BG7: =Assum_Volume!$B$55 -> 1.05 | BH7: =Assum_Volume!$B$56 -> 1.15 | BI7: =Assum_Volume!$B$57 -> 1.4 | BJ7: =Assum_Volume!$B$46 -> 1.15 | BK7: =Assum_Volume!$B$47 -> 1.1 | BL7: =Assum_Volume!$B$48 -> 1 | BM7: =Assum_Volume!$B$49 -> 0.9 | BN7: =Assum_Volume!$B$50 -> 0.85 | BO7: =Assum_Volume!$B$51 -> 0.8 | BP7: =Assum_Volume!$B$52 -> 0.8 | BQ7: =Assum_Volume!$B$53 -> 0.85 | BR7: =Assum_Volume!$B$54 -> 0.95 | BS7: =Assum_Volume!$B$55 -> 1.05 | BT7: =Assum_Volume!$B$56 -> 1.15 | BU7: =Assum_Volume!$B$57 -> 1.4 | BV7: =Assum_Volume!$B$46 -> 1.15 | BW7: =Assum_Volume!$B$47 -> 1.1 | BX7: =Assum_Volume!$B$48 -> 1 | BY7: =Assum_Volume!$B$49 -> 0.9 | BZ7: =Assum_Volume!$B$50 -> 0.85 | CA7: =Assum_Volume!$B$51 -> 0.8 | CB7: =Assum_Volume!$B$52 -> 0.8 | CC7: =Assum_Volume!$B$53 -> 0.85 | CD7: =Assum_Volume!$B$54 -> 0.95 | CE7: =Assum_Volume!$B$55 -> 1.05 | CF7: =Assum_Volume!$B$56 -> 1.15 | CG7: =Assum_Volume!$B$57 -> 1.4 | CH7: =Assum_Volume!$B$46 -> 1.15 | CI7: =Assum_Volume!$B$47 -> 1.1 | CJ7: =Assum_Volume!$B$48 -> 1 | CK7: =Assum_Volume!$B$49 -> 0.9 | CL7: =Assum_Volume!$B$50 -> 0.85 | CM7: =Assum_Volume!$B$51 -> 0.8 | CN7: =Assum_Volume!$B$52 -> 0.8 | CO7: =Assum_Volume!$B$53 -> 0.85 | CP7: =Assum_Volume!$B$54 -> 0.95 | CQ7: =Assum_Volume!$B$55 -> 1.05 | CR7: =Assum_Volume!$B$56 -> 1.15 | CS7: =Assum_Volume!$B$57 -> 1.4 | CT7: =Assum_Volume!$B$46 -> 1.15 | CU7: =Assum_Volume!$B$47 -> 1.1 | CV7: =Assum_Volume!$B$48 -> 1 | CW7: =Assum_Volume!$B$49 -> 0.9 | CX7: =Assum_Volume!$B$50 -> 0.85 | CY7: =Assum_Volume!$B$51 -> 0.8 | CZ7: =Assum_Volume!$B$52 -> 0.8 | DA7: =Assum_Volume!$B$53 -> 0.85 | DB7: =Assum_Volume!$B$54 -> 0.95 | DC7: =Assum_Volume!$B$55 -> 1.05 | DD7: =Assum_Volume!$B$56 -> 1.15 | DE7: =Assum_Volume!$B$57 -> 1.4 | DF7: =Assum_Volume!$B$46 -> 1.15 | DG7: =Assum_Volume!$B$47 -> 1.1 | DH7: =Assum_Volume!$B$48 -> 1 | DI7: =Assum_Volume!$B$49 -> 0.9 | DJ7: =Assum_Volume!$B$50 -> 0.85 | DK7: =Assum_Volume!$B$51 -> 0.8 | DL7: =Assum_Volume!$B$52 -> 0.8 | DM7: =Assum_Volume!$B$53 -> 0.85 | DN7: =Assum_Volume!$B$54 -> 0.95 | DO7: =Assum_Volume!$B$55 -> 1.05 | DP7: =Assum_Volume!$B$56 -> 1.15 | DQ7: =Assum_Volume!$B$57 -> 1.4
A9: CUMULATIVE GROWTH INDEX | B9: 1 | C9: =B9 -> 1 | D9: =C9 -> 1 | E9: =D9 -> 1 | F9: =E9 -> 1 | G9: =F9 -> 1 | H9: =G9 -> 1 | I9: =H9 -> 1 | J9: =I9 -> 1 | ... M9: =L9 -> 1 | N9: =M9*(1+INDEX(Assum_Volume!$B$32:$D$41,2,Control!$D$5)) -> 1.08 | O9: =N9 -> 1.08 | P9: =O9 -> 1.08 | Q9: =P9 -> 1.08 | R9: =Q9 -> 1.08 | S9: =R9 -> 1.08 | T9: =S9 -> 1.08 | U9: =T9 -> 1.08 | V9: =U9 -> 1.08 | ... Y9: =X9 -> 1.08 | Z9: =Y9*(1+INDEX(Assum_Volume!$B$32:$D$41,3,Control!$D$5)) -> 1.1664 | AA9: =Z9 -> 1.1664 | AB9: =AA9 -> 1.1664 | AC9: =AB9 -> 1.1664 | AD9: =AC9 -> 1.1664 | AE9: =AD9 -> 1.1664 | AF9: =AE9 -> 1.1664 | AG9: =AF9 -> 1.1664 | AH9: =AG9 -> 1.1664 | ... AK9: =AJ9 -> 1.1664 | AL9: =AK9*(1+INDEX(Assum_Volume!$B$32:$D$41,4,Control!$D$5)) -> 1.236384 | AM9: =AL9 -> 1.236384 | AN9: =AM9 -> 1.236384 | AO9: =AN9 -> 1.236384 | AP9: =AO9 -> 1.236384 | AQ9: =AP9 -> 1.236384 | AR9: =AQ9 -> 1.236384 | AS9: =AR9 -> 1.236384 | AT9: =AS9 -> 1.236384 | ... AW9: =AV9 -> 1.236384 | AX9: =AW9*(1+INDEX(Assum_Volume!$B$32:$D$41,5,Control!$D$5)) -> 1.310567 | AY9: =AX9 -> 1.310567 | AZ9: =AY9 -> 1.310567 | BA9: =AZ9 -> 1.310567 | BB9: =BA9 -> 1.310567 | BC9: =BB9 -> 1.310567 | BD9: =BC9 -> 1.310567 | BE9: =BD9 -> 1.310567 | BF9: =BE9 -> 1.310567 | ... BI9: =BH9 -> 1.310567 | BJ9: =BI9*(1+INDEX(Assum_Volume!$B$32:$D$41,6,Control!$D$5)) -> 1.3629897 | BK9: =BJ9 -> 1.3629897 | BL9: =BK9 -> 1.3629897 | BM9: =BL9 -> 1.3629897 | BN9: =BM9 -> 1.3629897 | BO9: =BN9 -> 1.3629897 | BP9: =BO9 -> 1.3629897 | BQ9: =BP9 -> 1.3629897 | BR9: =BQ9 -> 1.3629897 | ... BU9: =BT9 -> 1.3629897 | BV9: =BU9*(1+INDEX(Assum_Volume!$B$32:$D$41,7,Control!$D$5)) -> 1.4175093 | BW9: =BV9 -> 1.4175093 | BX9: =BW9 -> 1.4175093 | BY9: =BX9 -> 1.4175093 | BZ9: =BY9 -> 1.4175093 | CA9: =BZ9 -> 1.4175093 | CB9: =CA9 -> 1.4175093 | CC9: =CB9 -> 1.4175093 | CD9: =CC9 -> 1.4175093 | ... CG9: =CF9 -> 1.4175093 | CH9: =CG9*(1+INDEX(Assum_Volume!$B$32:$D$41,8,Control!$D$5)) -> 1.4742097 | CI9: =CH9 -> 1.4742097 | CJ9: =CI9 -> 1.4742097 | CK9: =CJ9 -> 1.4742097 | CL9: =CK9 -> 1.4742097 | CM9: =CL9 -> 1.4742097 | CN9: =CM9 -> 1.4742097 | CO9: =CN9 -> 1.4742097 | CP9: =CO9 -> 1.4742097 | ... CS9: =CR9 -> 1.4742097 | CT9: =CS9*(1+INDEX(Assum_Volume!$B$32:$D$41,9,Control!$D$5)) -> 1.5331781 | CU9: =CT9 -> 1.5331781 | CV9: =CU9 -> 1.5331781 | CW9: =CV9 -> 1.5331781 | CX9: =CW9 -> 1.5331781 | CY9: =CX9 -> 1.5331781 | CZ9: =CY9 -> 1.5331781 | DA9: =CZ9 -> 1.5331781 | DB9: =DA9 -> 1.5331781 | ... DE9: =DD9 -> 1.5331781 | DF9: =DE9*(1+INDEX(Assum_Volume!$B$32:$D$41,10,Control!$D$5)) -> 1.5945052 | DG9: =DF9 -> 1.5945052 | DH9: =DG9 -> 1.5945052 | DI9: =DH9 -> 1.5945052 | DJ9: =DI9 -> 1.5945052 | DK9: =DJ9 -> 1.5945052 | DL9: =DK9 -> 1.5945052 | DM9: =DL9 -> 1.5945052 | DN9: =DM9 -> 1.5945052 | ... DQ9: =DP9 -> 1.5945052
A11: TOTAL VOLUME (HL)
A12: SkyBrew | B12: =Assum_Volume!$C$5*Assum_Volume!$C$8/12*B7*B9 -> 53666.667 | C12: =Assum_Volume!$C$5*Assum_Volume!$C$8/12*C7*C9 -> 51333.333 | D12: =Assum_Volume!$C$5*Assum_Volume!$C$8/12*D7*D9 -> 46666.667 | E12: =Assum_Volume!$C$5*Assum_Volume!$C$8/12*E7*E9 -> 42000 | F12: =Assum_Volume!$C$5*Assum_Volume!$C$8/12*F7*F9 -> 39666.667 | G12: =Assum_Volume!$C$5*Assum_Volume!$C$8/12*G7*G9 -> 37333.333 | H12: =Assum_Volume!$C$5*Assum_Volume!$C$8/12*H7*H9 -> 37333.333 | I12: =Assum_Volume!$C$5*Assum_Volume!$C$8/12*I7*I9 -> 39666.667 | ... DQ12: =Assum_Volume!$C$5*Assum_Volume!$C$8/12*DQ7*DQ9 -> 104174.34
A13: AllDark | B13: =Assum_Volume!$C$5*Assum_Volume!$C$9/12*B7*B9 -> 23000 | C13: =Assum_Volume!$C$5*Assum_Volume!$C$9/12*C7*C9 -> 22000 | D13: =Assum_Volume!$C$5*Assum_Volume!$C$9/12*D7*D9 -> 20000 | E13: =Assum_Volume!$C$5*Assum_Volume!$C$9/12*E7*E9 -> 18000 | F13: =Assum_Volume!$C$5*Assum_Volume!$C$9/12*F7*F9 -> 17000 | G13: =Assum_Volume!$C$5*Assum_Volume!$C$9/12*G7*G9 -> 16000 | H13: =Assum_Volume!$C$5*Assum_Volume!$C$9/12*H7*H9 -> 16000 | I13: =Assum_Volume!$C$5*Assum_Volume!$C$9/12*I7*I9 -> 17000 | ... DQ13: =Assum_Volume!$C$5*Assum_Volume!$C$9/12*DQ7*DQ9 -> 44646.145
A14: Total | B14: =B12+B13 -> 76666.667 | C14: =C12+C13 -> 73333.333 | D14: =D12+D13 -> 66666.667 | E14: =E12+E13 -> 60000 | F14: =F12+F13 -> 56666.667 | G14: =G12+G13 -> 53333.333 | H14: =H12+H13 -> 53333.333 | I14: =I12+I13 -> 56666.667 | ... DQ14: =DQ12+DQ13 -> 148820.48
A16: BY MARKET (HL)
A17: Australia | B17: =B14*Assum_Volume!$C$12 -> 53666.667 | C17: =C14*Assum_Volume!$C$12 -> 51333.333 | D17: =D14*Assum_Volume!$C$12 -> 46666.667 | E17: =E14*Assum_Volume!$C$12 -> 42000 | F17: =F14*Assum_Volume!$C$12 -> 39666.667 | G17: =G14*Assum_Volume!$C$12 -> 37333.333 | H17: =H14*Assum_Volume!$C$12 -> 37333.333 | I17: =I14*Assum_Volume!$C$12 -> 39666.667 | ... DQ17: =DQ14*Assum_Volume!$C$12 -> 104174.34
A18: New Zealand | B18: =B14*Assum_Volume!$C$13 -> 23000 | C18: =C14*Assum_Volume!$C$13 -> 22000 | D18: =D14*Assum_Volume!$C$13 -> 20000 | E18: =E14*Assum_Volume!$C$13 -> 18000 | F18: =F14*Assum_Volume!$C$13 -> 17000 | G18: =G14*Assum_Volume!$C$13 -> 16000 | H18: =H14*Assum_Volume!$C$13 -> 16000 | I18: =I14*Assum_Volume!$C$13 -> 17000 | ... DQ18: =DQ14*Assum_Volume!$C$13 -> 44646.145
A20: BY CHANNEL (HL)
A21: On-Trade | B21: =B14*Assum_Volume!$C$16 -> 26833.333 | C21: =C14*Assum_Volume!$C$16 -> 25666.667 | D21: =D14*Assum_Volume!$C$16 -> 23333.333 | E21: =E14*Assum_Volume!$C$16 -> 21000 | F21: =F14*Assum_Volume!$C$16 -> 19833.333 | G21: =G14*Assum_Volume!$C$16 -> 18666.667 | H21: =H14*Assum_Volume!$C$16 -> 18666.667 | I21: =I14*Assum_Volume!$C$16 -> 19833.333 | ... DQ21: =DQ14*Assum_Volume!$C$16 -> 52087.17
A22: Off-Trade | B22: =B14*Assum_Volume!$C$17 -> 49833.333 | C22: =C14*Assum_Volume!$C$17 -> 47666.667 | D22: =D14*Assum_Volume!$C$17 -> 43333.333 | E22: =E14*Assum_Volume!$C$17 -> 39000 | F22: =F14*Assum_Volume!$C$17 -> 36833.333 | G22: =G14*Assum_Volume!$C$17 -> 34666.667 | H22: =H14*Assum_Volume!$C$17 -> 34666.667 | I22: =I14*Assum_Volume!$C$17 -> 36833.333 | ... DQ22: =DQ14*Assum_Volume!$C$17 -> 96733.315
A24: BY FORMAT (HL)
A25: Bottles | B25: =B21*Assum_Volume!$C$22+B22*Assum_Volume!$C$26 -> 27791.667 | C25: =C21*Assum_Volume!$C$22+C22*Assum_Volume!$C$26 -> 26583.333 | D25: =D21*Assum_Volume!$C$22+D22*Assum_Volume!$C$26 -> 24166.667 | E25: =E21*Assum_Volume!$C$22+E22*Assum_Volume!$C$26 -> 21750 | F25: =F21*Assum_Volume!$C$22+F22*Assum_Volume!$C$26 -> 20541.667 | G25: =G21*Assum_Volume!$C$22+G22*Assum_Volume!$C$26 -> 19333.333 | H25: =H21*Assum_Volume!$C$22+H22*Assum_Volume!$C$26 -> 19333.333 | I25: =I21*Assum_Volume!$C$22+I22*Assum_Volume!$C$26 -> 20541.667 | ... DQ25: =DQ21*Assum_Volume!$C$22+DQ22*Assum_Volume!$C$26 -> 53947.426
A26: Cans | B26: =B21*Assum_Volume!$C$23+B22*Assum_Volume!$C$27 -> 30091.667 | C26: =C21*Assum_Volume!$C$23+C22*Assum_Volume!$C$27 -> 28783.333 | D26: =D21*Assum_Volume!$C$23+D22*Assum_Volume!$C$27 -> 26166.667 | E26: =E21*Assum_Volume!$C$23+E22*Assum_Volume!$C$27 -> 23550 | F26: =F21*Assum_Volume!$C$23+F22*Assum_Volume!$C$27 -> 22241.667 | G26: =G21*Assum_Volume!$C$23+G22*Assum_Volume!$C$27 -> 20933.333 | H26: =H21*Assum_Volume!$C$23+H22*Assum_Volume!$C$27 -> 20933.333 | I26: =I21*Assum_Volume!$C$23+I22*Assum_Volume!$C$27 -> 22241.667 | ... DQ26: =DQ21*Assum_Volume!$C$23+DQ22*Assum_Volume!$C$27 -> 58412.04
A27: Kegs | B27: =B21*Assum_Volume!$C$21 -> 18783.333 | C27: =C21*Assum_Volume!$C$21 -> 17966.667 | D27: =D21*Assum_Volume!$C$21 -> 16333.333 | E27: =E21*Assum_Volume!$C$21 -> 14700 | F27: =F21*Assum_Volume!$C$21 -> 13883.333 | G27: =G21*Assum_Volume!$C$21 -> 13066.667 | H27: =H21*Assum_Volume!$C$21 -> 13066.667 | I27: =I21*Assum_Volume!$C$21 -> 13883.333 | ... DQ27: =DQ21*Assum_Volume!$C$21 -> 36461.019

Sheet Calc_Revenue
A1: REVENUE CALCULATIONS
A3: Period | B3: =Calc_Volume!B3 -> 1 | C3: =Calc_Volume!C3 -> 2 | D3: =Calc_Volume!D3 -> 3 | E3: =Calc_Volume!E3 -> 4 | F3: =Calc_Volume!F3 -> 5 | G3: =Calc_Volume!G3 -> 6 | H3: =Calc_Volume!H3 -> 7 | I3: =Calc_Volume!I3 -> 8 | ... DQ3: =Calc_Volume!DQ3 -> 120
A4: Date | B4: =Calc_Volume!B4 -> 45658 | C4: =Calc_Volume!C4 -> 45689 | D4: =Calc_Volume!D4 -> 45717 | E4: =Calc_Volume!E4 -> 45748 | F4: =Calc_Volume!F4 -> 45778 | G4: =Calc_Volume!G4 -> 45809 | H4: =Calc_Volume!H4 -> 45839 | I4: =Calc_Volume!I4 -> 45870 | ... DQ4: =Calc_Volume!DQ4 -> 49279
A5: Price Index (cumulative) | B5: 1 | C5: =B5 -> 1 | D5: =C5 -> 1 | E5: =D5 -> 1 | F5: =E5 -> 1 | G5: =F5 -> 1 | H5: =G5 -> 1 | I5: =H5 -> 1 | J5: =I5 -> 1 | ... M5: =L5 -> 1 | N5: =M5*(1+INDEX(Assum_Pricing!$C$36:$C$38,Control!$D$5,1)) -> 1.025 | O5: =N5 -> 1.025 | P5: =O5 -> 1.025 | Q5: =P5 -> 1.025 | R5: =Q5 -> 1.025 | S5: =R5 -> 1.025 | T5: =S5 -> 1.025 | U5: =T5 -> 1.025 | V5: =U5 -> 1.025 | ... Y5: =X5 -> 1.025 | Z5: =Y5*(1+INDEX(Assum_Pricing!$C$36:$C$38,Control!$D$5,1)) -> 1.050625 | AA5: =Z5 -> 1.050625 | AB5: =AA5 -> 1.050625 | AC5: =AB5 -> 1.050625 | AD5: =AC5 -> 1.050625 | AE5: =AD5 -> 1.050625 | AF5: =AE5 -> 1.050625 | AG5: =AF5 -> 1.050625 | AH5: =AG5 -> 1.050625 | ... AK5: =AJ5 -> 1.050625 | AL5: =AK5*(1+INDEX(Assum_Pricing!$C$36:$C$38,Control!$D$5,1)) -> 1.0768906 | AM5: =AL5 -> 1.0768906 | AN5: =AM5 -> 1.0768906 | AO5: =AN5 -> 1.0768906 | AP5: =AO5 -> 1.0768906 | AQ5: =AP5 -> 1.0768906 | AR5: =AQ5 -> 1.0768906 | AS5: =AR5 -> 1.0768906 | AT5: =AS5 -> 1.0768906 | ... AW5: =AV5 -> 1.0768906 | AX5: =AW5*(1+INDEX(Assum_Pricing!$C$36:$C$38,Control!$D$5,1)) -> 1.1038129 | AY5: =AX5 -> 1.1038129 | AZ5: =AY5 -> 1.1038129 | BA5: =AZ5 -> 1.1038129 | BB5: =BA5 -> 1.1038129 | BC5: =BB5 -> 1.1038129 | BD5: =BC5 -> 1.1038129 | BE5: =BD5 -> 1.1038129 | BF5: =BE5 -> 1.1038129 | ... BI5: =BH5 -> 1.1038129 | BJ5: =BI5*(1+INDEX(Assum_Pricing!$C$36:$C$38,Control!$D$5,1)) -> 1.1314082 | BK5: =BJ5 -> 1.1314082 | BL5: =BK5 -> 1.1314082 | BM5: =BL5 -> 1.1314082 | BN5: =BM5 -> 1.1314082 | BO5: =BN5 -> 1.1314082 | BP5: =BO5 -> 1.1314082 | BQ5: =BP5 -> 1.1314082 | BR5: =BQ5 -> 1.1314082 | ... BU5: =BT5 -> 1.1314082 | BV5: =BU5*(1+INDEX(Assum_Pricing!$C$36:$C$38,Control!$D$5,1)) -> 1.1596934 | BW5: =BV5 -> 1.1596934 | BX5: =BW5 -> 1.1596934 | BY5: =BX5 -> 1.1596934 | BZ5: =BY5 -> 1.1596934 | CA5: =BZ5 -> 1.1596934 | CB5: =CA5 -> 1.1596934 | CC5: =CB5 -> 1.1596934 | CD5: =CC5 -> 1.1596934 | ... CG5: =CF5 -> 1.1596934 | CH5: =CG5*(1+INDEX(Assum_Pricing!$C$36:$C$38,Control!$D$5,1)) -> 1.1886858 | CI5: =CH5 -> 1.1886858 | CJ5: =CI5 -> 1.1886858 | CK5: =CJ5 -> 1.1886858 | CL5: =CK5 -> 1.1886858 | CM5: =CL5 -> 1.1886858 | CN5: =CM5 -> 1.1886858 | CO5: =CN5 -> 1.1886858 | CP5: =CO5 -> 1.1886858 | ... CS5: =CR5 -> 1.1886858 | CT5: =CS5*(1+INDEX(Assum_Pricing!$C$36:$C$38,Control!$D$5,1)) -> 1.2184029 | CU5: =CT5 -> 1.2184029 | CV5: =CU5 -> 1.2184029 | CW5: =CV5 -> 1.2184029 | CX5: =CW5 -> 1.2184029 | CY5: =CX5 -> 1.2184029 | CZ5: =CY5 -> 1.2184029 | DA5: =CZ5 -> 1.2184029 | DB5: =DA5 -> 1.2184029 | ... DE5: =DD5 -> 1.2184029 | DF5: =DE5*(1+INDEX(Assum_Pricing!$C$36:$C$38,Control!$D$5,1)) -> 1.248863 | DG5: =DF5 -> 1.248863 | DH5: =DG5 -> 1.248863 | DI5: =DH5 -> 1.248863 | DJ5: =DI5 -> 1.248863 | DK5: =DJ5 -> 1.248863 | DL5: =DK5 -> 1.248863 | DM5: =DL5 -> 1.248863 | DN5: =DM5 -> 1.248863 | ... DQ5: =DP5 -> 1.248863
A7: GROSS REVENUE ($000s)
A8: SkyBrew On-Trade | B8: =(Calc_Volume!B12*Assum_Volume!$C$16)*(Assum_Pricing!$C$6*Assum_Volume!$C$22+Assum_Pricing!$C$7*Assum_Volume!$C$23+Assum_Pricing!$C$8*Assum_Volume!$C$21)*B5/1000 -> 13242.25 | C8: =(Calc_Volume!C12*Assum_Volume!$C$16)*(Assum_Pricing!$C$6*Assum_Volume!$C$22+Assum_Pricing!$C$7*Assum_Volume!$C$23+Assum_Pricing!$C$8*Assum_Volume!$C$21)*C5/1000 -> 12666.5 | D8: =(Calc_Volume!D12*Assum_Volume!$C$16)*(Assum_Pricing!$C$6*Assum_Volume!$C$22+Assum_Pricing!$C$7*Assum_Volume!$C$23+Assum_Pricing!$C$8*Assum_Volume!$C$21)*D5/1000 -> 11515 | E8: =(Calc_Volume!E12*Assum_Volume!$C$16)*(Assum_Pricing!$C$6*Assum_Volume!$C$22+Assum_Pricing!$C$7*Assum_Volume!$C$23+Assum_Pricing!$C$8*Assum_Volume!$C$21)*E5/1000 -> 10363.5 | F8: =(Calc_Volume!F12*Assum_Volume!$C$16)*(Assum_Pricing!$C$6*Assum_Volume!$C$22+Assum_Pricing!$C$7*Assum_Volume!$C$23+Assum_Pricing!$C$8*Assum_Volume!$C$21)*F5/1000 -> 9787.75 | G8: =(Calc_Volume!G12*Assum_Volume!$C$16)*(Assum_Pricing!$C$6*Assum_Volume!$C$22+Assum_Pricing!$C$7*Assum_Volume!$C$23+Assum_Pricing!$C$8*Assum_Volume!$C$21)*G5/1000 -> 9212 | H8: =(Calc_Volume!H12*Assum_Volume!$C$16)*(Assum_Pricing!$C$6*Assum_Volume!$C$22+Assum_Pricing!$C$7*Assum_Volume!$C$23+Assum_Pricing!$C$8*Assum_Volume!$C$21)*H5/1000 -> 9212 | I8: =(Calc_Volume!I12*Assum_Volume!$C$16)*(Assum_Pricing!$C$6*Assum_Volume!$C$22+Assum_Pricing!$C$7*Assum_Volume!$C$23+Assum_Pricing!$C$8*Assum_Volume!$C$21)*I5/1000 -> 9787.75 | ... DQ8: =(Calc_Volume!DQ12*Assum_Volume!$C$16)*(Assum_Pricing!$C$6*Assum_Volume!$C$22+Assum_Pricing!$C$7*Assum_Volume!$C$23+Assum_Pricing!$C$8*Assum_Volume!$C$21)*DQ5/1000 -> 32102.045
A9: SkyBrew Off-Trade | B9: =(Calc_Volume!B12*Assum_Volume!$C$17)*(Assum_Pricing!$D$6*Assum_Volume!$C$26+Assum_Pricing!$D$7*Assum_Volume!$C$27)*B5/1000 -> 18610.258 | C9: =(Calc_Volume!C12*Assum_Volume!$C$17)*(Assum_Pricing!$D$6*Assum_Volume!$C$26+Assum_Pricing!$D$7*Assum_Volume!$C$27)*C5/1000 -> 17801.117 | D9: =(Calc_Volume!D12*Assum_Volume!$C$17)*(Assum_Pricing!$D$6*Assum_Volume!$C$26+Assum_Pricing!$D$7*Assum_Volume!$C$27)*D5/1000 -> 16182.833 | E9: =(Calc_Volume!E12*Assum_Volume!$C$17)*(Assum_Pricing!$D$6*Assum_Volume!$C$26+Assum_Pricing!$D$7*Assum_Volume!$C$27)*E5/1000 -> 14564.55 | F9: =(Calc_Volume!F12*Assum_Volume!$C$17)*(Assum_Pricing!$D$6*Assum_Volume!$C$26+Assum_Pricing!$D$7*Assum_Volume!$C$27)*F5/1000 -> 13755.408 | G9: =(Calc_Volume!G12*Assum_Volume!$C$17)*(Assum_Pricing!$D$6*Assum_Volume!$C$26+Assum_Pricing!$D$7*Assum_Volume!$C$27)*G5/1000 -> 12946.267 | H9: =(Calc_Volume!H12*Assum_Volume!$C$17)*(Assum_Pricing!$D$6*Assum_Volume!$C$26+Assum_Pricing!$D$7*Assum_Volume!$C$27)*H5/1000 -> 12946.267 | I9: =(Calc_Volume!I12*Assum_Volume!$C$17)*(Assum_Pricing!$D$6*Assum_Volume!$C$26+Assum_Pricing!$D$7*Assum_Volume!$C$27)*I5/1000 -> 13755.408 | ... DQ9: =(Calc_Volume!DQ12*Assum_Volume!$C$17)*(Assum_Pricing!$D$6*Assum_Volume!$C$26+Assum_Pricing!$D$7*Assum_Volume!$C$27)*DQ5/1000 -> 45115.245
A10: AllDark On-Trade | B10: =(Calc_Volume!B13*Assum_Volume!$C$16)*(Assum_Pricing!$C$9*Assum_Volume!$C$22+Assum_Pricing!$C$10*Assum_Volume!$C$23+Assum_Pricing!$C$11*Assum_Volume!$C$21)*B5/1000 -> 6311.2 | C10: =(Calc_Volume!C13*Assum_Volume!$C$16)*(Assum_Pricing!$C$9*Assum_Volume!$C$22+Assum_Pricing!$C$10*Assum_Volume!$C$23+Assum_Pricing!$C$11*Assum_Volume!$C$21)*C5/1000 -> 6036.8 | D10: =(Calc_Volume!D13*Assum_Volume!$C$16)*(Assum_Pricing!$C$9*Assum_Volume!$C$22+Assum_Pricing!$C$10*Assum_Volume!$C$23+Assum_Pricing!$C$11*Assum_Volume!$C$21)*D5/1000 -> 5488 | E10: =(Calc_Volume!E13*Assum_Volume!$C$16)*(Assum_Pricing!$C$9*Assum_Volume!$C$22+Assum_Pricing!$C$10*Assum_Volume!$C$23+Assum_Pricing!$C$11*Assum_Volume!$C$21)*E5/1000 -> 4939.2 | F10: =(Calc_Volume!F13*Assum_Volume!$C$16)*(Assum_Pricing!$C$9*Assum_Volume!$C$22+Assum_Pricing!$C$10*Assum_Volume!$C$23+Assum_Pricing!$C$11*Assum_Volume!$C$21)*F5/1000 -> 4664.8 | G10: =(Calc_Volume!G13*Assum_Volume!$C$16)*(Assum_Pricing!$C$9*Assum_Volume!$C$22+Assum_Pricing!$C$10*Assum_Volume!$C$23+Assum_Pricing!$C$11*Assum_Volume!$C$21)*G5/1000 -> 4390.4 | H10: =(Calc_Volume!H13*Assum_Volume!$C$16)*(Assum_Pricing!$C$9*Assum_Volume!$C$22+Assum_Pricing!$C$10*Assum_Volume!$C$23+Assum_Pricing!$C$11*Assum_Volume!$C$21)*H5/1000 -> 4390.4 | I10: =(Calc_Volume!I13*Assum_Volume!$C$16)*(Assum_Pricing!$C$9*Assum_Volume!$C$22+Assum_Pricing!$C$10*Assum_Volume!$C$23+Assum_Pricing!$C$11*Assum_Volume!$C$21)*I5/1000 -> 4664.8 | ... DQ10: =(Calc_Volume!DQ13*Assum_Volume!$C$16)*(Assum_Pricing!$C$9*Assum_Volume!$C$22+Assum_Pricing!$C$10*Assum_Volume!$C$23+Assum_Pricing!$C$11*Assum_Volume!$C$21)*DQ5/1000 -> 15299.698
A11: AllDark Off-Trade | B11: =(Calc_Volume!B13*Assum_Volume!$C$17)*(Assum_Pricing!$D$9*Assum_Volume!$C$26+Assum_Pricing!$D$10*Assum_Volume!$C$27)*B5/1000 -> 8940.1 | C11: =(Calc_Volume!C13*Assum_Volume!$C$17)*(Assum_Pricing!$D$9*Assum_Volume!$C$26+Assum_Pricing!$D$10*Assum_Volume!$C$27)*C5/1000 -> 8551.4 | D11: =(Calc_Volume!D13*Assum_Volume!$C$17)*(Assum_Pricing!$D$9*Assum_Volume!$C$26+Assum_Pricing!$D$10*Assum_Volume!$C$27)*D5/1000 -> 7774 | E11: =(Calc_Volume!E13*Assum_Volume!$C$17)*(Assum_Pricing!$D$9*Assum_Volume!$C$26+Assum_Pricing!$D$10*Assum_Volume!$C$27)*E5/1000 -> 6996.6 | F11: =(Calc_Volume!F13*Assum_Volume!$C$17)*(Assum_Pricing!$D$9*Assum_Volume!$C$26+Assum_Pricing!$D$10*Assum_Volume!$C$27)*F5/1000 -> 6607.9 | G11: =(Calc_Volume!G13*Assum_Volume!$C$17)*(Assum_Pricing!$D$9*Assum_Volume!$C$26+Assum_Pricing!$D$10*Assum_Volume!$C$27)*G5/1000 -> 6219.2 | H11: =(Calc_Volume!H13*Assum_Volume!$C$17)*(Assum_Pricing!$D$9*Assum_Volume!$C$26+Assum_Pricing!$D$10*Assum_Volume!$C$27)*H5/1000 -> 6219.2 | I11: =(Calc_Volume!I13*Assum_Volume!$C$17)*(Assum_Pricing!$D$9*Assum_Volume!$C$26+Assum_Pricing!$D$10*Assum_Volume!$C$27)*I5/1000 -> 6607.9 | ... DQ11: =(Calc_Volume!DQ13*Assum_Volume!$C$17)*(Assum_Pricing!$D$9*Assum_Volume!$C$26+Assum_Pricing!$D$10*Assum_Volume!$C$27)*DQ5/1000 -> 21672.714
A12: Total Gross Revenue | B12: =SUM(B8:B11) -> 47103.808 | C12: =SUM(C8:C11) -> 45055.817 | D12: =SUM(D8:D11) -> 40959.833 | E12: =SUM(E8:E11) -> 36863.85 | F12: =SUM(F8:F11) -> 34815.858 | G12: =SUM(G8:G11) -> 32767.867 | H12: =SUM(H8:H11) -> 32767.867 | I12: =SUM(I8:I11) -> 34815.858 | ... DQ12: =SUM(DQ8:DQ11) -> 114189.7
A14: DISCOUNTS ($000s)
A15: On-Trade Discounts | B15: =(B8+B10)*Assum_Pricing!$C$15 -> 1564.276 | C15: =(C8+C10)*Assum_Pricing!$C$15 -> 1496.264 | D15: =(D8+D10)*Assum_Pricing!$C$15 -> 1360.24 | E15: =(E8+E10)*Assum_Pricing!$C$15 -> 1224.216 | F15: =(F8+F10)*Assum_Pricing!$C$15 -> 1156.204 | G15: =(G8+G10)*Assum_Pricing!$C$15 -> 1088.192 | H15: =(H8+H10)*Assum_Pricing!$C$15 -> 1088.192 | I15: =(I8+I10)*Assum_Pricing!$C$15 -> 1156.204 | ... DQ15: =(DQ8+DQ10)*Assum_Pricing!$C$15 -> 3792.1395
A16: Off-Trade Discounts | B16: =(B9+B11)*Assum_Pricing!$C$18 -> 4132.5538 | C16: =(C9+C11)*Assum_Pricing!$C$18 -> 3952.8775 | D16: =(D9+D11)*Assum_Pricing!$C$18 -> 3593.525 | E16: =(E9+E11)*Assum_Pricing!$C$18 -> 3234.1725 | F16: =(F9+F11)*Assum_Pricing!$C$18 -> 3054.4963 | G16: =(G9+G11)*Assum_Pricing!$C$18 -> 2874.82 | H16: =(H9+H11)*Assum_Pricing!$C$18 -> 2874.82 | I16: =(I9+I11)*Assum_Pricing!$C$18 -> 3054.4963 | ... DQ16: =(DQ9+DQ11)*Assum_Pricing!$C$18 -> 10018.194
A17: Total Discounts | B17: =B15+B16 -> 5696.8297 | C17: =C15+C16 -> 5449.1415 | D17: =D15+D16 -> 4953.765 | E17: =E15+E16 -> 4458.3885 | F17: =F15+F16 -> 4210.7002 | G17: =G15+G16 -> 3963.012 | H17: =H15+H16 -> 3963.012 | I17: =I15+I16 -> 4210.7002 | ... DQ17: =DQ15+DQ16 -> 13810.333
A19: EXCISE DUTY ($000s)
A20: Australia Excise | B20: =Calc_Volume!B17*((Assum_Volume!$C$8*(1-Assum_Volume!$C$16*Assum_Volume!$C$21)*Assum_Pricing!$C$27+Assum_Volume!$C$8*Assum_Volume!$C$16*Assum_Volume!$C$21*Assum_Pricing!$C$28)+(Assum_Volume!$C$9*(1-Assum_Volume!$C$16*Assum_Volume!$C$21)*Assum_Pricing!$C$29+Assum_Volume!$C$9*Assum_Volume!$C$16*Assum_Volume!$C$21*Assum_Pricing!$C$30))/1000 -> 14494.012 | C20: =Calc_Volume!C17*((Assum_Volume!$C$8*(1-Assum_Volume!$C$16*Assum_Volume!$C$21)*Assum_Pricing!$C$27+Assum_Volume!$C$8*Assum_Volume!$C$16*Assum_Volume!$C$21*Assum_Pricing!$C$28)+(Assum_Volume!$C$9*(1-Assum_Volume!$C$16*Assum_Volume!$C$21)*Assum_Pricing!$C$29+Assum_Volume!$C$9*Assum_Volume!$C$16*Assum_Volume!$C$21*Assum_Pricing!$C$30))/1000 -> 13863.837 | D20: =Calc_Volume!D17*((Assum_Volume!$C$8*(1-Assum_Volume!$C$16*Assum_Volume!$C$21)*Assum_Pricing!$C$27+Assum_Volume!$C$8*Assum_Volume!$C$16*Assum_Volume!$C$21*Assum_Pricing!$C$28)+(Assum_Volume!$C$9*(1-Assum_Volume!$C$16*Assum_Volume!$C$21)*Assum_Pricing!$C$29+Assum_Volume!$C$9*Assum_Volume!$C$16*Assum_Volume!$C$21*Assum_Pricing!$C$30))/1000 -> 12603.488 | E20: =Calc_Volume!E17*((Assum_Volume!$C$8*(1-Assum_Volume!$C$16*Assum_Volume!$C$21)*Assum_Pricing!$C$27+Assum_Volume!$C$8*Assum_Volume!$C$16*Assum_Volume!$C$21*Assum_Pricing!$C$28)+(Assum_Volume!$C$9*(1-Assum_Volume!$C$16*Assum_Volume!$C$21)*Assum_Pricing!$C$29+Assum_Volume!$C$9*Assum_Volume!$C$16*Assum_Volume!$C$21*Assum_Pricing!$C$30))/1000 -> 11343.139 | F20: =Calc_Volume!F17*((Assum_Volume!$C$8*(1-Assum_Volume!$C$16*Assum_Volume!$C$21)*Assum_Pricing!$C$27+Assum_Volume!$C$8*Assum_Volume!$C$16*Assum_Volume!$C$21*Assum_Pricing!$C$28)+(Assum_Volume!$C$9*(1-Assum_Volume!$C$16*Assum_Volume!$C$21)*Assum_Pricing!$C$29+Assum_Volume!$C$9*Assum_Volume!$C$16*Assum_Volume!$C$21*Assum_Pricing!$C$30))/1000 -> 10712.965 | G20: =Calc_Volume!G17*((Assum_Volume!$C$8*(1-Assum_Volume!$C$16*Assum_Volume!$C$21)*Assum_Pricing!$C$27+Assum_Volume!$C$8*Assum_Volume!$C$16*Assum_Volume!$C$21*Assum_Pricing!$C$28)+(Assum_Volume!$C$9*(1-Assum_Volume!$C$16*Assum_Volume!$C$21)*Assum_Pricing!$C$29+Assum_Volume!$C$9*Assum_Volume!$C$16*Assum_Volume!$C$21*Assum_Pricing!$C$30))/1000 -> 10082.791 | H20: =Calc_Volume!H17*((Assum_Volume!$C$8*(1-Assum_Volume!$C$16*Assum_Volume!$C$21)*Assum_Pricing!$C$27+Assum_Volume!$C$8*Assum_Volume!$C$16*Assum_Volume!$C$21*Assum_Pricing!$C$28)+(Assum_Volume!$C$9*(1-Assum_Volume!$C$16*Assum_Volume!$C$21)*Assum_Pricing!$C$29+Assum_Volume!$C$9*Assum_Volume!$C$16*Assum_Volume!$C$21*Assum_Pricing!$C$30))/1000 -> 10082.791 | I20: =Calc_Volume!I17*((Assum_Volume!$C$8*(1-Assum_Volume!$C$16*Assum_Volume!$C$21)*Assum_Pricing!$C$27+Assum_Volume!$C$8*Assum_Volume!$C$16*Assum_Volume!$C$21*Assum_Pricing!$C$28)+(Assum_Volume!$C$9*(1-Assum_Volume!$C$16*Assum_Volume!$C$21)*Assum_Pricing!$C$29+Assum_Volume!$C$9*Assum_Volume!$C$16*Assum_Volume!$C$21*Assum_Pricing!$C$30))/1000 -> 10712.965 | ... DQ20: =Calc_Volume!DQ17*((Assum_Volume!$C$8*(1-Assum_Volume!$C$16*Assum_Volume!$C$21)*Assum_Pricing!$C$27+Assum_Volume!$C$8*Assum_Volume!$C$16*Assum_Volume!$C$21*Assum_Pricing!$C$28)+(Assum_Volume!$C$9*(1-Assum_Volume!$C$16*Assum_Volume!$C$21)*Assum_Pricing!$C$29+Assum_Volume!$C$9*Assum_Volume!$C$16*Assum_Volume!$C$21*Assum_Pricing!$C$30))/1000 -> 28134.859
A21: New Zealand Excise | B21: =Calc_Volume!B18*(Assum_Volume!$C$8*Assum_Pricing!$C$31+Assum_Volume!$C$9*Assum_Pricing!$C$32)/1000 -> 3900.8 | C21: =Calc_Volume!C18*(Assum_Volume!$C$8*Assum_Pricing!$C$31+Assum_Volume!$C$9*Assum_Pricing!$C$32)/1000 -> 3731.2 | D21: =Calc_Volume!D18*(Assum_Volume!$C$8*Assum_Pricing!$C$31+Assum_Volume!$C$9*Assum_Pricing!$C$32)/1000 -> 3392 | E21: =Calc_Volume!E18*(Assum_Volume!$C$8*Assum_Pricing!$C$31+Assum_Volume!$C$9*Assum_Pricing!$C$32)/1000 -> 3052.8 | F21: =Calc_Volume!F18*(Assum_Volume!$C$8*Assum_Pricing!$C$31+Assum_Volume!$C$9*Assum_Pricing!$C$32)/1000 -> 2883.2 | G21: =Calc_Volume!G18*(Assum_Volume!$C$8*Assum_Pricing!$C$31+Assum_Volume!$C$9*Assum_Pricing!$C$32)/1000 -> 2713.6 | H21: =Calc_Volume!H18*(Assum_Volume!$C$8*Assum_Pricing!$C$31+Assum_Volume!$C$9*Assum_Pricing!$C$32)/1000 -> 2713.6 | I21: =Calc_Volume!I18*(Assum_Volume!$C$8*Assum_Pricing!$C$31+Assum_Volume!$C$9*Assum_Pricing!$C$32)/1000 -> 2883.2 | ... DQ21: =Calc_Volume!DQ18*(Assum_Volume!$C$8*Assum_Pricing!$C$31+Assum_Volume!$C$9*Assum_Pricing!$C$32)/1000 -> 7571.9863
A22: Total Excise | B22: =B20+B21 -> 18394.812 | C22: =C20+C21 -> 17595.037 | D22: =D20+D21 -> 15995.488 | E22: =E20+E21 -> 14395.94 | F22: =F20+F21 -> 13596.165 | G22: =G20+G21 -> 12796.391 | H22: =H20+H21 -> 12796.391 | I22: =I20+I21 -> 13596.165 | ... DQ22: =DQ20+DQ21 -> 35706.845
A24: NET REVENUE ($000s)
A25: Net Revenue | B25: =B12-B17-B22 -> 23012.167 | C25: =C12-C17-C22 -> 22011.638 | D25: =D12-D17-D22 -> 20010.58 | E25: =E12-E17-E22 -> 18009.522 | F25: =F12-F17-F22 -> 17008.993 | G25: =G12-G17-G22 -> 16008.464 | H25: =H12-H17-H22 -> 16008.464 | I25: =I12-I17-I22 -> 17008.993 | ... DQ25: =DQ12-DQ17-DQ22 -> 64672.525
A27: KEY METRICS
A28: Gross Revenue per HL | B28: =IF(Calc_Volume!B14>0,B12*1000/Calc_Volume!B14,0) -> 614.3975 | C28: =IF(Calc_Volume!C14>0,C12*1000/Calc_Volume!C14,0) -> 614.3975 | D28: =IF(Calc_Volume!D14>0,D12*1000/Calc_Volume!D14,0) -> 614.3975 | E28: =IF(Calc_Volume!E14>0,E12*1000/Calc_Volume!E14,0) -> 614.3975 | F28: =IF(Calc_Volume!F14>0,F12*1000/Calc_Volume!F14,0) -> 614.3975 | G28: =IF(Calc_Volume!G14>0,G12*1000/Calc_Volume!G14,0) -> 614.3975 | H28: =IF(Calc_Volume!H14>0,H12*1000/Calc_Volume!H14,0) -> 614.3975 | I28: =IF(Calc_Volume!I14>0,I12*1000/Calc_Volume!I14,0) -> 614.3975 | ... DQ28: =IF(Calc_Volume!DQ14>0,DQ12*1000/Calc_Volume!DQ14,0) -> 767.29829
A29: Net Revenue per HL | B29: =IF(Calc_Volume!B14>0,B25*1000/Calc_Volume!B14,0) -> 300.1587 | C29: =IF(Calc_Volume!C14>0,C25*1000/Calc_Volume!C14,0) -> 300.1587 | D29: =IF(Calc_Volume!D14>0,D25*1000/Calc_Volume!D14,0) -> 300.1587 | E29: =IF(Calc_Volume!E14>0,E25*1000/Calc_Volume!E14,0) -> 300.1587 | F29: =IF(Calc_Volume!F14>0,F25*1000/Calc_Volume!F14,0) -> 300.1587 | G29: =IF(Calc_Volume!G14>0,G25*1000/Calc_Volume!G14,0) -> 300.1587 | H29: =IF(Calc_Volume!H14>0,H25*1000/Calc_Volume!H14,0) -> 300.1587 | I29: =IF(Calc_Volume!I14>0,I25*1000/Calc_Volume!I14,0) -> 300.1587 | ... DQ29: =IF(Calc_Volume!DQ14>0,DQ25*1000/Calc_Volume!DQ14,0) -> 434.56736
A30: Excise per HL | B30: =IF(Calc_Volume!B14>0,B22*1000/Calc_Volume!B14,0) -> 239.93232 | C30: =IF(Calc_Volume!C14>0,C22*1000/Calc_Volume!C14,0) -> 239.93232 | D30: =IF(Calc_Volume!D14>0,D22*1000/Calc_Volume!D14,0) -> 239.93232 | E30: =IF(Calc_Volume!E14>0,E22*1000/Calc_Volume!E14,0) -> 239.93232 | F30: =IF(Calc_Volume!F14>0,F22*1000/Calc_Volume!F14,0) -> 239.93232 | G30: =IF(Calc_Volume!G14>0,G22*1000/Calc_Volume!G14,0) -> 239.93233 | H30: =IF(Calc_Volume!H14>0,H22*1000/Calc_Volume!H14,0) -> 239.93233 | I30: =IF(Calc_Volume!I14>0,I22*1000/Calc_Volume!I14,0) -> 239.93232 | ... DQ30: =IF(Calc_Volume!DQ14>0,DQ22*1000/Calc_Volume!DQ14,0) -> 239.93233

Sheet Calc_COGS
A1: COST OF GOODS SOLD
A3: Period | B3: =Calc_Volume!B3 -> 1 | C3: =Calc_Volume!C3 -> 2 | D3: =Calc_Volume!D3 -> 3 | E3: =Calc_Volume!E3 -> 4 | F3: =Calc_Volume!F3 -> 5 | G3: =Calc_Volume!G3 -> 6 | H3: =Calc_Volume!H3 -> 7 | I3: =Calc_Volume!I3 -> 8 | ... DQ3: =Calc_Volume!DQ3 -> 120
A4: Date | B4: =Calc_Volume!B4 -> 45658 | C4: =Calc_Volume!C4 -> 45689 | D4: =Calc_Volume!D4 -> 45717 | E4: =Calc_Volume!E4 -> 45748 | F4: =Calc_Volume!F4 -> 45778 | G4: =Calc_Volume!G4 -> 45809 | H4: =Calc_Volume!H4 -> 45839 | I4: =Calc_Volume!I4 -> 45870 | ... DQ4: =Calc_Volume!DQ4 -> 49279
A5: Cost Index (cumulative) | B5: 1 | C5: =B5 -> 1 | D5: =C5 -> 1 | E5: =D5 -> 1 | F5: =E5 -> 1 | G5: =F5 -> 1 | H5: =G5 -> 1 | I5: =H5 -> 1 | J5: =I5 -> 1 | ... M5: =L5 -> 1 | N5: =M5*(1+INDEX(Assum_Costs!$C$47:$C$49,Control!$D$5,1)) -> 1.025 | O5: =N5 -> 1.025 | P5: =O5 -> 1.025 | Q5: =P5 -> 1.025 | R5: =Q5 -> 1.025 | S5: =R5 -> 1.025 | T5: =S5 -> 1.025 | U5: =T5 -> 1.025 | V5: =U5 -> 1.025 | ... Y5: =X5 -> 1.025 | Z5: =Y5*(1+INDEX(Assum_Costs!$C$47:$C$49,Control!$D$5,1)) -> 1.050625 | AA5: =Z5 -> 1.050625 | AB5: =AA5 -> 1.050625 | AC5: =AB5 -> 1.050625 | AD5: =AC5 -> 1.050625 | AE5: =AD5 -> 1.050625 | AF5: =AE5 -> 1.050625 | AG5: =AF5 -> 1.050625 | AH5: =AG5 -> 1.050625 | ... AK5: =AJ5 -> 1.050625 | AL5: =AK5*(1+INDEX(Assum_Costs!$C$47:$C$49,Control!$D$5,1)) -> 1.0768906 | AM5: =AL5 -> 1.0768906 | AN5: =AM5 -> 1.0768906 | AO5: =AN5 -> 1.0768906 | AP5: =AO5 -> 1.0768906 | AQ5: =AP5 -> 1.0768906 | AR5: =AQ5 -> 1.0768906 | AS5: =AR5 -> 1.0768906 | AT5: =AS5 -> 1.0768906 | ... AW5: =AV5 -> 1.0768906 | AX5: =AW5*(1+INDEX(Assum_Costs!$C$47:$C$49,Control!$D$5,1)) -> 1.1038129 | AY5: =AX5 -> 1.1038129 | AZ5: =AY5 -> 1.1038129 | BA5: =AZ5 -> 1.1038129 | BB5: =BA5 -> 1.1038129 | BC5: =BB5 -> 1.1038129 | BD5: =BC5 -> 1.1038129 | BE5: =BD5 -> 1.1038129 | BF5: =BE5 -> 1.1038129 | ... BI5: =BH5 -> 1.1038129 | BJ5: =BI5*(1+INDEX(Assum_Costs!$C$47:$C$49,Control!$D$5,1)) -> 1.1314082 | BK5: =BJ5 -> 1.1314082 | BL5: =BK5 -> 1.1314082 | BM5: =BL5 -> 1.1314082 | BN5: =BM5 -> 1.1314082 | BO5: =BN5 -> 1.1314082 | BP5: =BO5 -> 1.1314082 | BQ5: =BP5 -> 1.1314082 | BR5: =BQ5 -> 1.1314082 | ... BU5: =BT5 -> 1.1314082 | BV5: =BU5*(1+INDEX(Assum_Costs!$C$47:$C$49,Control!$D$5,1)) -> 1.1596934 | BW5: =BV5 -> 1.1596934 | BX5: =BW5 -> 1.1596934 | BY5: =BX5 -> 1.1596934 | BZ5: =BY5 -> 1.1596934 | CA5: =BZ5 -> 1.1596934 | CB5: =CA5 -> 1.1596934 | CC5: =CB5 -> 1.1596934 | CD5: =CC5 -> 1.1596934 | ... CG5: =CF5 -> 1.1596934 | CH5: =CG5*(1+INDEX(Assum_Costs!$C$47:$C$49,Control!$D$5,1)) -> 1.1886858 | CI5: =CH5 -> 1.1886858 | CJ5: =CI5 -> 1.1886858 | CK5: =CJ5 -> 1.1886858 | CL5: =CK5 -> 1.1886858 | CM5: =CL5 -> 1.1886858 | CN5: =CM5 -> 1.1886858 | CO5: =CN5 -> 1.1886858 | CP5: =CO5 -> 1.1886858 | ... CS5: =CR5 -> 1.1886858 | CT5: =CS5*(1+INDEX(Assum_Costs!$C$47:$C$49,Control!$D$5,1)) -> 1.2184029 | CU5: =CT5 -> 1.2184029 | CV5: =CU5 -> 1.2184029 | CW5: =CV5 -> 1.2184029 | CX5: =CW5 -> 1.2184029 | CY5: =CX5 -> 1.2184029 | CZ5: =CY5 -> 1.2184029 | DA5: =CZ5 -> 1.2184029 | DB5: =DA5 -> 1.2184029 | ... DE5: =DD5 -> 1.2184029 | DF5: =DE5*(1+INDEX(Assum_Costs!$C$47:$C$49,Control!$D$5,1)) -> 1.248863 | DG5: =DF5 -> 1.248863 | DH5: =DG5 -> 1.248863 | DI5: =DH5 -> 1.248863 | DJ5: =DI5 -> 1.248863 | DK5: =DJ5 -> 1.248863 | DL5: =DK5 -> 1.248863 | DM5: =DL5 -> 1.248863 | DN5: =DM5 -> 1.248863 | ... DQ5: =DP5 -> 1.248863
A7: RAW MATERIALS ($000s)
A8: Malt & Adjuncts | B8: =Calc_Volume!B14*Assum_Costs!$C$6*B5/1000 -> 920 | C8: =Calc_Volume!C14*Assum_Costs!$C$6*C5/1000 -> 880 | D8: =Calc_Volume!D14*Assum_Costs!$C$6*D5/1000 -> 800 | E8: =Calc_Volume!E14*Assum_Costs!$C$6*E5/1000 -> 720 | F8: =Calc_Volume!F14*Assum_Costs!$C$6*F5/1000 -> 680 | G8: =Calc_Volume!G14*Assum_Costs!$C$6*G5/1000 -> 640 | H8: =Calc_Volume!H14*Assum_Costs!$C$6*H5/1000 -> 640 | I8: =Calc_Volume!I14*Assum_Costs!$C$6*I5/1000 -> 680 | ... DQ8: =Calc_Volume!DQ14*Assum_Costs!$C$6*DQ5/1000 -> 2230.2767
A9: Hops | B9: =Calc_Volume!B14*Assum_Costs!$C$7*B5/1000 -> 383.33333 | C9: =Calc_Volume!C14*Assum_Costs!$C$7*C5/1000 -> 366.66667 | D9: =Calc_Volume!D14*Assum_Costs!$C$7*D5/1000 -> 333.33333 | E9: =Calc_Volume!E14*Assum_Costs!$C$7*E5/1000 -> 300 | F9: =Calc_Volume!F14*Assum_Costs!$C$7*F5/1000 -> 283.33333 | G9: =Calc_Volume!G14*Assum_Costs!$C$7*G5/1000 -> 266.66667 | H9: =Calc_Volume!H14*Assum_Costs!$C$7*H5/1000 -> 266.66667 | I9: =Calc_Volume!I14*Assum_Costs!$C$7*I5/1000 -> 283.33333 | ... DQ9: =Calc_Volume!DQ14*Assum_Costs!$C$7*DQ5/1000 -> 929.28196
A10: Yeast | B10: =Calc_Volume!B14*Assum_Costs!$C$8*B5/1000 -> 115 | C10: =Calc_Volume!C14*Assum_Costs!$C$8*C5/1000 -> 110 | D10: =Calc_Volume!D14*Assum_Costs!$C$8*D5/1000 -> 100 | E10: =Calc_Volume!E14*Assum_Costs!$C$8*E5/1000 -> 90 | F10: =Calc_Volume!F14*Assum_Costs!$C$8*F5/1000 -> 85 | G10: =Calc_Volume!G14*Assum_Costs!$C$8*G5/1000 -> 80 | H10: =Calc_Volume!H14*Assum_Costs!$C$8*H5/1000 -> 80 | I10: =Calc_Volume!I14*Assum_Costs!$C$8*I5/1000 -> 85 | ... DQ10: =Calc_Volume!DQ14*Assum_Costs!$C$8*DQ5/1000 -> 278.78459
A11: Water & Treatment | B11: =Calc_Volume!B14*Assum_Costs!$C$9*B5/1000 -> 115 | C11: =Calc_Volume!C14*Assum_Costs!$C$9*C5/1000 -> 110 | D11: =Calc_Volume!D14*Assum_Costs!$C$9*D5/1000 -> 100 | E11: =Calc_Volume!E14*Assum_Costs!$C$9*E5/1000 -> 90 | F11: =Calc_Volume!F14*Assum_Costs!$C$9*F5/1000 -> 85 | G11: =Calc_Volume!G14*Assum_Costs!$C$9*G5/1000 -> 80 | H11: =Calc_Volume!H14*Assum_Costs!$C$9*H5/1000 -> 80 | I11: =Calc_Volume!I14*Assum_Costs!$C$9*I5/1000 -> 85 | ... DQ11: =Calc_Volume!DQ14*Assum_Costs!$C$9*DQ5/1000 -> 278.78459
A12: Total Raw Materials | B12: =SUM(B8:B11) -> 1533.3333 | C12: =SUM(C8:C11) -> 1466.6667 | D12: =SUM(D8:D11) -> 1333.3333 | E12: =SUM(E8:E11) -> 1200 | F12: =SUM(F8:F11) -> 1133.3333 | G12: =SUM(G8:G11) -> 1066.6667 | H12: =SUM(H8:H11) -> 1066.6667 | I12: =SUM(I8:I11) -> 1133.3333 | ... DQ12: =SUM(DQ8:DQ11) -> 3717.1278
A14: PACKAGING ($000s)
A15: Bottles | B15: =Calc_Volume!B25*Assum_Costs!$C$13*B5/1000 -> 972.70833 | C15: =Calc_Volume!C25*Assum_Costs!$C$13*C5/1000 -> 930.41667 | D15: =Calc_Volume!D25*Assum_Costs!$C$13*D5/1000 -> 845.83333 | E15: =Calc_Volume!E25*Assum_Costs!$C$13*E5/1000 -> 761.25 | F15: =Calc_Volume!F25*Assum_Costs!$C$13*F5/1000 -> 718.95833 | G15: =Calc_Volume!G25*Assum_Costs!$C$13*G5/1000 -> 676.66667 | H15: =Calc_Volume!H25*Assum_Costs!$C$13*H5/1000 -> 676.66667 | I15: =Calc_Volume!I25*Assum_Costs!$C$13*I5/1000 -> 718.95833 | ... DQ15: =Calc_Volume!DQ25*Assum_Costs!$C$13*DQ5/1000 -> 2358.053
A16: Cans | B16: =Calc_Volume!B26*Assum_Costs!$C$14*B5/1000 -> 902.75 | C16: =Calc_Volume!C26*Assum_Costs!$C$14*C5/1000 -> 863.5 | D16: =Calc_Volume!D26*Assum_Costs!$C$14*D5/1000 -> 785 | E16: =Calc_Volume!E26*Assum_Costs!$C$14*E5/1000 -> 706.5 | F16: =Calc_Volume!F26*Assum_Costs!$C$14*F5/1000 -> 667.25 | G16: =Calc_Volume!G26*Assum_Costs!$C$14*G5/1000 -> 628 | H16: =Calc_Volume!H26*Assum_Costs!$C$14*H5/1000 -> 628 | I16: =Calc_Volume!I26*Assum_Costs!$C$14*I5/1000 -> 667.25 | ... DQ16: =Calc_Volume!DQ26*Assum_Costs!$C$14*DQ5/1000 -> 2188.459
A17: Kegs | B17: =Calc_Volume!B27*Assum_Costs!$C$15*B5/1000 -> 150.26667 | C17: =Calc_Volume!C27*Assum_Costs!$C$15*C5/1000 -> 143.73333 | D17: =Calc_Volume!D27*Assum_Costs!$C$15*D5/1000 -> 130.66667 | E17: =Calc_Volume!E27*Assum_Costs!$C$15*E5/1000 -> 117.6 | F17: =Calc_Volume!F27*Assum_Costs!$C$15*F5/1000 -> 111.06667 | G17: =Calc_Volume!G27*Assum_Costs!$C$15*G5/1000 -> 104.53333 | H17: =Calc_Volume!H27*Assum_Costs!$C$15*H5/1000 -> 104.53333 | I17: =Calc_Volume!I27*Assum_Costs!$C$15*I5/1000 -> 111.06667 | ... DQ17: =Calc_Volume!DQ27*Assum_Costs!$C$15*DQ5/1000 -> 364.27853
A18: Total Packaging | B18: =SUM(B15:B17) -> 2025.725 | C18: =SUM(C15:C17) -> 1937.65 | D18: =SUM(D15:D17) -> 1761.5 | E18: =SUM(E15:E17) -> 1585.35 | F18: =SUM(F15:F17) -> 1497.275 | G18: =SUM(G15:G17) -> 1409.2 | H18: =SUM(H15:H17) -> 1409.2 | I18: =SUM(I15:I17) -> 1497.275 | ... DQ18: =SUM(DQ15:DQ17) -> 4910.7905
A20: DIRECT MANUFACTURING ($000s)
A21: Direct Labour | B21: =Calc_Volume!B14*Assum_Costs!$C$18*B5/1000 -> 920 | C21: =Calc_Volume!C14*Assum_Costs!$C$18*C5/1000 -> 880 | D21: =Calc_Volume!D14*Assum_Costs!$C$18*D5/1000 -> 800 | E21: =Calc_Volume!E14*Assum_Costs!$C$18*E5/1000 -> 720 | F21: =Calc_Volume!F14*Assum_Costs!$C$18*F5/1000 -> 680 | G21: =Calc_Volume!G14*Assum_Costs!$C$18*G5/1000 -> 640 | H21: =Calc_Volume!H14*Assum_Costs!$C$18*H5/1000 -> 640 | I21: =Calc_Volume!I14*Assum_Costs!$C$18*I5/1000 -> 680 | ... DQ21: =Calc_Volume!DQ14*Assum_Costs!$C$18*DQ5/1000 -> 2230.2767
A22: Utilities | B22: =Calc_Volume!B14*Assum_Costs!$C$19*B5/1000 -> 460 | C22: =Calc_Volume!C14*Assum_Costs!$C$19*C5/1000 -> 440 | D22: =Calc_Volume!D14*Assum_Costs!$C$19*D5/1000 -> 400 | E22: =Calc_Volume!E14*Assum_Costs!$C$19*E5/1000 -> 360 | F22: =Calc_Volume!F14*Assum_Costs!$C$19*F5/1000 -> 340 | G22: =Calc_Volume!G14*Assum_Costs!$C$19*G5/1000 -> 320 | H22: =Calc_Volume!H14*Assum_Costs!$C$19*H5/1000 -> 320 | I22: =Calc_Volume!I14*Assum_Costs!$C$19*I5/1000 -> 340 | ... DQ22: =Calc_Volume!DQ14*Assum_Costs!$C$19*DQ5/1000 -> 1115.1384
A23: Manufacturing Overhead | B23: =Calc_Volume!B14*Assum_Costs!$C$20*B5/1000 -> 613.33333 | C23: =Calc_Volume!C14*Assum_Costs!$C$20*C5/1000 -> 586.66667 | D23: =Calc_Volume!D14*Assum_Costs!$C$20*D5/1000 -> 533.33333 | E23: =Calc_Volume!E14*Assum_Costs!$C$20*E5/1000 -> 480 | F23: =Calc_Volume!F14*Assum_Costs!$C$20*F5/1000 -> 453.33333 | G23: =Calc_Volume!G14*Assum_Costs!$C$20*G5/1000 -> 426.66667 | H23: =Calc_Volume!H14*Assum_Costs!$C$20*H5/1000 -> 426.66667 | I23: =Calc_Volume!I14*Assum_Costs!$C$20*I5/1000 -> 453.33333 | ... DQ23: =Calc_Volume!DQ14*Assum_Costs!$C$20*DQ5/1000 -> 1486.8511
A24: Quality Control | B24: =Calc_Volume!B14*Assum_Costs!$C$21*B5/1000 -> 153.33333 | C24: =Calc_Volume!C14*Assum_Costs!$C$21*C5/1000 -> 146.66667 | D24: =Calc_Volume!D14*Assum_Costs!$C$21*D5/1000 -> 133.33333 | E24: =Calc_Volume!E14*Assum_Costs!$C$21*E5/1000 -> 120 | F24: =Calc_Volume!F14*Assum_Costs!$C$21*F5/1000 -> 113.33333 | G24: =Calc_Volume!G14*Assum_Costs!$C$21*G5/1000 -> 106.66667 | H24: =Calc_Volume!H14*Assum_Costs!$C$21*H5/1000 -> 106.66667 | I24: =Calc_Volume!I14*Assum_Costs!$C$21*I5/1000 -> 113.33333 | ... DQ24: =Calc_Volume!DQ14*Assum_Costs!$C$21*DQ5/1000 -> 371.71278
A25: Total Direct Manufacturing | B25: =SUM(B21:B24) -> 2146.6667 | C25: =SUM(C21:C24) -> 2053.3333 | D25: =SUM(D21:D24) -> 1866.6667 | E25: =SUM(E21:E24) -> 1680 | F25: =SUM(F21:F24) -> 1586.6667 | G25: =SUM(G21:G24) -> 1493.3333 | H25: =SUM(H21:H24) -> 1493.3333 | I25: =SUM(I21:I24) -> 1586.6667 | ... DQ25: =SUM(DQ21:DQ24) -> 5203.979
A27: TOTAL COGS ($000s)
A28: Total COGS | B28: =B12+B18+B25 -> 5705.725 | C28: =C12+C18+C25 -> 5457.65 | D28: =D12+D18+D25 -> 4961.5 | E28: =E12+E18+E25 -> 4465.35 | F28: =F12+F18+F25 -> 4217.275 | G28: =G12+G18+G25 -> 3969.2 | H28: =H12+H18+H25 -> 3969.2 | I28: =I12+I18+I25 -> 4217.275 | ... DQ28: =DQ12+DQ18+DQ25 -> 13831.897
A30: KEY METRICS
A31: COGS per HL | B31: =IF(Calc_Volume!B14>0,B28*1000/Calc_Volume!B14,0) -> 74.4225 | C31: =IF(Calc_Volume!C14>0,C28*1000/Calc_Volume!C14,0) -> 74.4225 | D31: =IF(Calc_Volume!D14>0,D28*1000/Calc_Volume!D14,0) -> 74.4225 | E31: =IF(Calc_Volume!E14>0,E28*1000/Calc_Volume!E14,0) -> 74.4225 | F31: =IF(Calc_Volume!F14>0,F28*1000/Calc_Volume!F14,0) -> 74.4225 | G31: =IF(Calc_Volume!G14>0,G28*1000/Calc_Volume!G14,0) -> 74.4225 | H31: =IF(Calc_Volume!H14>0,H28*1000/Calc_Volume!H14,0) -> 74.4225 | I31: =IF(Calc_Volume!I14>0,I28*1000/Calc_Volume!I14,0) -> 74.4225 | ... DQ31: =IF(Calc_Volume!DQ14>0,DQ28*1000/Calc_Volume!DQ14,0) -> 92.943504
A32: Gross Margin % | B32: =IF(Calc_Revenue!B25>0,(Calc_Revenue!B25-B28)/Calc_Revenue!B25,0) -> 0.75205616 | C32: =IF(Calc_Revenue!C25>0,(Calc_Revenue!C25-C28)/Calc_Revenue!C25,0) -> 0.75205616 | D32: =IF(Calc_Revenue!D25>0,(Calc_Revenue!D25-D28)/Calc_Revenue!D25,0) -> 0.75205616 | E32: =IF(Calc_Revenue!E25>0,(Calc_Revenue!E25-E28)/Calc_Revenue!E25,0) -> 0.75205616 | F32: =IF(Calc_Revenue!F25>0,(Calc_Revenue!F25-F28)/Calc_Revenue!F25,0) -> 0.75205616 | G32: =IF(Calc_Revenue!G25>0,(Calc_Revenue!G25-G28)/Calc_Revenue!G25,0) -> 0.75205616 | H32: =IF(Calc_Revenue!H25>0,(Calc_Revenue!H25-H28)/Calc_Revenue!H25,0) -> 0.75205616 | I32: =IF(Calc_Revenue!I25>0,(Calc_Revenue!I25-I28)/Calc_Revenue!I25,0) -> 0.75205616 | ... DQ32: =IF(Calc_Revenue!DQ25>0,(Calc_Revenue!DQ25-DQ28)/Calc_Revenue!DQ25,0) -> 0.78612405

Sheet Calc_Opex
A1: OPERATING EXPENSES
A3: Period | B3: =Calc_Volume!B3 -> 1 | C3: =Calc_Volume!C3 -> 2 | D3: =Calc_Volume!D3 -> 3 | E3: =Calc_Volume!E3 -> 4 | F3: =Calc_Volume!F3 -> 5 | G3: =Calc_Volume!G3 -> 6 | H3: =Calc_Volume!H3 -> 7 | I3: =Calc_Volume!I3 -> 8 | ... DQ3: =Calc_Volume!DQ3 -> 120
A4: Date | B4: =Calc_Volume!B4 -> 45658 | C4: =Calc_Volume!C4 -> 45689 | D4: =Calc_Volume!D4 -> 45717 | E4: =Calc_Volume!E4 -> 45748 | F4: =Calc_Volume!F4 -> 45778 | G4: =Calc_Volume!G4 -> 45809 | H4: =Calc_Volume!H4 -> 45839 | I4: =Calc_Volume!I4 -> 45870 | ... DQ4: =Calc_Volume!DQ4 -> 49279
A6: LOGISTICS & DISTRIBUTION ($000s)
A7: Australia Freight | B7: =Calc_Volume!B17*Assum_Costs!$C$31*Calc_COGS!B5/1000 -> 1180.6667 | C7: =Calc_Volume!C17*Assum_Costs!$C$31*Calc_COGS!C5/1000 -> 1129.3333 | D7: =Calc_Volume!D17*Assum_Costs!$C$31*Calc_COGS!D5/1000 -> 1026.6667 | E7: =Calc_Volume!E17*Assum_Costs!$C$31*Calc_COGS!E5/1000 -> 924 | F7: =Calc_Volume!F17*Assum_Costs!$C$31*Calc_COGS!F5/1000 -> 872.66667 | G7: =Calc_Volume!G17*Assum_Costs!$C$31*Calc_COGS!G5/1000 -> 821.33333 | H7: =Calc_Volume!H17*Assum_Costs!$C$31*Calc_COGS!H5/1000 -> 821.33333 | I7: =Calc_Volume!I17*Assum_Costs!$C$31*Calc_COGS!I5/1000 -> 872.66667 | ... DQ7: =Calc_Volume!DQ17*Assum_Costs!$C$31*Calc_COGS!DQ5/1000 -> 2862.1884
A8: New Zealand Freight | B8: =Calc_Volume!B18*(Assum_Costs!$C$32+Assum_Costs!$C$33)*Calc_COGS!B5/1000 -> 1219 | C8: =Calc_Volume!C18*(Assum_Costs!$C$32+Assum_Costs!$C$33)*Calc_COGS!C5/1000 -> 1166 | D8: =Calc_Volume!D18*(Assum_Costs!$C$32+Assum_Costs!$C$33)*Calc_COGS!D5/1000 -> 1060 | E8: =Calc_Volume!E18*(Assum_Costs!$C$32+Assum_Costs!$C$33)*Calc_COGS!E5/1000 -> 954 | F8: =Calc_Volume!F18*(Assum_Costs!$C$32+Assum_Costs!$C$33)*Calc_COGS!F5/1000 -> 901 | G8: =Calc_Volume!G18*(Assum_Costs!$C$32+Assum_Costs!$C$33)*Calc_COGS!G5/1000 -> 848 | H8: =Calc_Volume!H18*(Assum_Costs!$C$32+Assum_Costs!$C$33)*Calc_COGS!H5/1000 -> 848 | I8: =Calc_Volume!I18*(Assum_Costs!$C$32+Assum_Costs!$C$33)*Calc_COGS!I5/1000 -> 901 | ... DQ8: =Calc_Volume!DQ18*(Assum_Costs!$C$32+Assum_Costs!$C$33)*Calc_COGS!DQ5/1000 -> 2955.1166
A9: Warehousing | B9: =Calc_Volume!B14*Assum_Costs!$C$34*Calc_COGS!B5/1000 -> 613.33333 | C9: =Calc_Volume!C14*Assum_Costs!$C$34*Calc_COGS!C5/1000 -> 586.66667 | D9: =Calc_Volume!D14*Assum_Costs!$C$34*Calc_COGS!D5/1000 -> 533.33333 | E9: =Calc_Volume!E14*Assum_Costs!$C$34*Calc_COGS!E5/1000 -> 480 | F9: =Calc_Volume!F14*Assum_Costs!$C$34*Calc_COGS!F5/1000 -> 453.33333 | G9: =Calc_Volume!G14*Assum_Costs!$C$34*Calc_COGS!G5/1000 -> 426.66667 | H9: =Calc_Volume!H14*Assum_Costs!$C$34*Calc_COGS!H5/1000 -> 426.66667 | I9: =Calc_Volume!I14*Assum_Costs!$C$34*Calc_COGS!I5/1000 -> 453.33333 | ... DQ9: =Calc_Volume!DQ14*Assum_Costs!$C$34*Calc_COGS!DQ5/1000 -> 1486.8511
A10: Cold Chain (Kegs) | B10: =Calc_Volume!B27*Assum_Costs!$C$35*Calc_COGS!B5/1000 -> 187.83333 | C10: =Calc_Volume!C27*Assum_Costs!$C$35*Calc_COGS!C5/1000 -> 179.66667 | D10: =Calc_Volume!D27*Assum_Costs!$C$35*Calc_COGS!D5/1000 -> 163.33333 | E10: =Calc_Volume!E27*Assum_Costs!$C$35*Calc_COGS!E5/1000 -> 147 | F10: =Calc_Volume!F27*Assum_Costs!$C$35*Calc_COGS!F5/1000 -> 138.83333 | G10: =Calc_Volume!G27*Assum_Costs!$C$35*Calc_COGS!G5/1000 -> 130.66667 | H10: =Calc_Volume!H27*Assum_Costs!$C$35*Calc_COGS!H5/1000 -> 130.66667 | I10: =Calc_Volume!I27*Assum_Costs!$C$35*Calc_COGS!I5/1000 -> 138.83333 | ... DQ10: =Calc_Volume!DQ27*Assum_Costs!$C$35*Calc_COGS!DQ5/1000 -> 455.34816
A11: Total Logistics | B11: =SUM(B7:B10) -> 3200.8333 | C11: =SUM(C7:C10) -> 3061.6667 | D11: =SUM(D7:D10) -> 2783.3333 | E11: =SUM(E7:E10) -> 2505 | F11: =SUM(F7:F10) -> 2365.8333 | G11: =SUM(G7:G10) -> 2226.6667 | H11: =SUM(H7:H10) -> 2226.6667 | I11: =SUM(I7:I10) -> 2365.8333 | ... DQ11: =SUM(DQ7:DQ10) -> 7759.5044
A13: SG&A ($000s)
A14: Sales Team | B14: =Calc_Revenue!B12*Assum_Costs!$C$39 -> 1884.1523 | C14: =Calc_Revenue!C12*Assum_Costs!$C$39 -> 1802.2327 | D14: =Calc_Revenue!D12*Assum_Costs!$C$39 -> 1638.3933 | E14: =Calc_Revenue!E12*Assum_Costs!$C$39 -> 1474.554 | F14: =Calc_Revenue!F12*Assum_Costs!$C$39 -> 1392.6343 | G14: =Calc_Revenue!G12*Assum_Costs!$C$39 -> 1310.7147 | H14: =Calc_Revenue!H12*Assum_Costs!$C$39 -> 1310.7147 | I14: =Calc_Revenue!I12*Assum_Costs!$C$39 -> 1392.6343 | ... DQ14: =Calc_Revenue!DQ12*Assum_Costs!$C$39 -> 4567.5881
A15: Marketing | B15: =Calc_Revenue!B12*Assum_Costs!$C$40 -> 2826.2285 | C15: =Calc_Revenue!C12*Assum_Costs!$C$40 -> 2703.349 | D15: =Calc_Revenue!D12*Assum_Costs!$C$40 -> 2457.59 | E15: =Calc_Revenue!E12*Assum_Costs!$C$40 -> 2211.831 | F15: =Calc_Revenue!F12*Assum_Costs!$C$40 -> 2088.9515 | G15: =Calc_Revenue!G12*Assum_Costs!$C$40 -> 1966.072 | H15: =Calc_Revenue!H12*Assum_Costs!$C$40 -> 1966.072 | I15: =Calc_Revenue!I12*Assum_Costs!$C$40 -> 2088.9515 | ... DQ15: =Calc_Revenue!DQ12*Assum_Costs!$C$40 -> 6851.3822
A16: Trade Marketing | B16: =Calc_Revenue!B12*Assum_Costs!$C$41 -> 1413.1143 | C16: =Calc_Revenue!C12*Assum_Costs!$C$41 -> 1351.6745 | D16: =Calc_Revenue!D12*Assum_Costs!$C$41 -> 1228.795 | E16: =Calc_Revenue!E12*Assum_Costs!$C$41 -> 1105.9155 | F16: =Calc_Revenue!F12*Assum_Costs!$C$41 -> 1044.4758 | G16: =Calc_Revenue!G12*Assum_Costs!$C$41 -> 983.036 | H16: =Calc_Revenue!H12*Assum_Costs!$C$41 -> 983.036 | I16: =Calc_Revenue!I12*Assum_Costs!$C$41 -> 1044.4758 | ... DQ16: =Calc_Revenue!DQ12*Assum_Costs!$C$41 -> 3425.6911
A17: General & Admin | B17: =Calc_Revenue!B12*Assum_Costs!$C$42 -> 1884.1523 | C17: =Calc_Revenue!C12*Assum_Costs!$C$42 -> 1802.2327 | D17: =Calc_Revenue!D12*Assum_Costs!$C$42 -> 1638.3933 | E17: =Calc_Revenue!E12*Assum_Costs!$C$42 -> 1474.554 | F17: =Calc_Revenue!F12*Assum_Costs!$C$42 -> 1392.6343 | G17: =Calc_Revenue!G12*Assum_Costs!$C$42 -> 1310.7147 | H17: =Calc_Revenue!H12*Assum_Costs!$C$42 -> 1310.7147 | I17: =Calc_Revenue!I12*Assum_Costs!$C$42 -> 1392.6343 | ... DQ17: =Calc_Revenue!DQ12*Assum_Costs!$C$42 -> 4567.5881
A18: Total SG&A | B18: =SUM(B14:B17) -> 8007.6474 | C18: =SUM(C14:C17) -> 7659.4888 | D18: =SUM(D14:D17) -> 6963.1717 | E18: =SUM(E14:E17) -> 6266.8545 | F18: =SUM(F14:F17) -> 5918.6959 | G18: =SUM(G14:G17) -> 5570.5373 | H18: =SUM(H14:H17) -> 5570.5373 | I18: =SUM(I14:I17) -> 5918.6959 | ... DQ18: =SUM(DQ14:DQ17) -> 19412.249
A20: TOTAL OPEX ($000s)
A21: Total Operating Expenses | B21: =B11+B18 -> 11208.481 | C21: =C11+C18 -> 10721.156 | D21: =D11+D18 -> 9746.505 | E21: =E11+E18 -> 8771.8545 | F21: =F11+F18 -> 8284.5293 | G21: =G11+G18 -> 7797.204 | H21: =H11+H18 -> 7797.204 | I21: =I11+I18 -> 8284.5293 | ... DQ21: =DQ11+DQ18 -> 27171.754

Sheet Calc_Capex
A1: CAPEX & DEPRECIATION
A3: Period | B3: =Calc_Volume!B3 -> 1 | C3: =Calc_Volume!C3 -> 2 | D3: =Calc_Volume!D3 -> 3 | E3: =Calc_Volume!E3 -> 4 | F3: =Calc_Volume!F3 -> 5 | G3: =Calc_Volume!G3 -> 6 | H3: =Calc_Volume!H3 -> 7 | I3: =Calc_Volume!I3 -> 8 | ... DQ3: =Calc_Volume!DQ3 -> 120
A4: Date | B4: =Calc_Volume!B4 -> 45658 | C4: =Calc_Volume!C4 -> 45689 | D4: =Calc_Volume!D4 -> 45717 | E4: =Calc_Volume!E4 -> 45748 | F4: =Calc_Volume!F4 -> 45778 | G4: =Calc_Volume!G4 -> 45809 | H4: =Calc_Volume!H4 -> 45839 | I4: =Calc_Volume!I4 -> 45870 | ... DQ4: =Calc_Volume!DQ4 -> 49279
A6: OPENING PP&E ($000s)
A7: Gross PP&E - Opening | B7: =Assum_Capex!$B$13/1000 -> 62000 | C7: =B18 -> 62103.333 | D7: =C18 -> 62206.839 | E7: =D18 -> 62310.517 | F7: =E18 -> 62414.368 | G7: =F18 -> 62518.392 | H7: =G18 -> 62622.589 | I7: =H18 -> 62726.96 | J7: =I18 -> 62831.505 | ... DQ7: =DP18 -> 75588.384
A8: Accumulated Depreciation - Opening | B8: =Assum_Capex!$C$13/1000 -> 21000 | C8: =B19 -> 21375.694 | D8: =C19 -> 21751.389 | E8: =D19 -> 22127.083 | F8: =E19 -> 22502.778 | G8: =F19 -> 22878.472 | H8: =G19 -> 23254.167 | I8: =H19 -> 23629.861 | J8: =I19 -> 24005.556 | ... DQ8: =DP19 -> 65707.639
A9: Net PP&E - Opening | B9: =B7-B8 -> 41000 | C9: =C7-C8 -> 40727.639 | D9: =D7-D8 -> 40455.45 | E9: =E7-E8 -> 40183.434 | F9: =F7-F8 -> 39911.59 | G9: =G7-G8 -> 39639.92 | H9: =H7-H8 -> 39368.422 | I9: =I7-I8 -> 39097.099 | ... DQ9: =DQ7-DQ8 -> 9880.7454
A11: MOVEMENTS ($000s)
A12: Maintenance Capex | B12: =B7*Assum_Capex!$C$31/12 -> 103.33333 | C12: =C7*Assum_Capex!$C$31/12 -> 103.50556 | D12: =D7*Assum_Capex!$C$31/12 -> 103.67806 | E12: =E7*Assum_Capex!$C$31/12 -> 103.85086 | F12: =F7*Assum_Capex!$C$31/12 -> 104.02395 | G12: =G7*Assum_Capex!$C$31/12 -> 104.19732 | H12: =H7*Assum_Capex!$C$31/12 -> 104.37098 | I12: =I7*Assum_Capex!$C$31/12 -> 104.54493 | ... DQ12: =DQ7*Assum_Capex!$C$31/12 -> 125.98064
A13: Expansion Capex | B13: 0 | C13: 0 | D13: 0 | E13: 0 | F13: 0 | G13: 0 | H13: 0 | I13: 0 | J13: 0 | K13: 0 | L13: 0 | M13: 0 | N13: 0 | O13: 0 | P13: 0 | Q13: 0 | R13: 0 | S13: 0 | T13: 0 | U13: 0 | V13: 0 | W13: 0 | X13: 0 | Y13: 0 | Z13: 0 | AA13: 0 | AB13: 0 | AC13: 0 | AD13: 0 | AE13: 0 | AF13: 0 | AG13: 0 | AH13: 0 | AI13: 0 | AJ13: 0 | AK13: 0 | AL13: 0 | AM13: 0 | AN13: 0 | AO13: 0 | AP13: 0 | AQ13: 0 | AR13: 0 | AS13: 0 | AT13: 0 | AU13: 0 | AV13: 0 | AW13: 0 | AX13: 0 | AY13: 0 | AZ13: 0 | BA13: 0 | BB13: 0 | BC13: 0 | BD13: 0 | BE13: 0 | BF13: 0 | BG13: 0 | BH13: 0 | BI13: 0 | BJ13: 0 | BK13: 0 | BL13: 0 | BM13: 0 | BN13: 0 | BO13: 0 | BP13: 0 | BQ13: 0 | BR13: 0 | BS13: 0 | BT13: 0 | BU13: 0 | BV13: 0 | BW13: 0 | BX13: 0 | BY13: 0 | BZ13: 0 | CA13: 0 | CB13: 0 | CC13: 0 | CD13: 0 | CE13: 0 | CF13: 0 | CG13: 0 | CH13: 0 | CI13: 0 | CJ13: 0 | CK13: 0 | CL13: 0 | CM13: 0 | CN13: 0 | CO13: 0 | CP13: 0 | CQ13: 0 | CR13: 0 | CS13: 0 | CT13: 0 | CU13: 0 | CV13: 0 | CW13: 0 | CX13: 0 | CY13: 0 | CZ13: 0 | DA13: 0 | DB13: 0 | DC13: 0 | DD13: 0 | DE13: 0 | DF13: 0 | DG13: 0 | DH13: 0 | DI13: 0 | DJ13: 0 | DK13: 0 | DL13: 0 | DM13: 0 | DN13: 0 | DO13: 0 | DP13: 0 | DQ13: 0
A14: Total Capex | B14: =B12+B13 -> 103.33333 | C14: =C12+C13 -> 103.50556 | D14: =D12+D13 -> 103.67806 | E14: =E12+E13 -> 103.85086 | F14: =F12+F13 -> 104.02395 | G14: =G12+G13 -> 104.19732 | H14: =H12+H13 -> 104.37098 | I14: =I12+I13 -> 104.54493 | ... DQ14: =DQ12+DQ13 -> 125.98064
A15: Depreciation | B15: =Assum_Capex!$F$13/12/1000 -> 375.69444 | C15: =Assum_Capex!$F$13/12/1000 -> 375.69444 | D15: =Assum_Capex!$F$13/12/1000 -> 375.69444 | E15: =Assum_Capex!$F$13/12/1000 -> 375.69444 | F15: =Assum_Capex!$F$13/12/1000 -> 375.69444 | G15: =Assum_Capex!$F$13/12/1000 -> 375.69444 | H15: =Assum_Capex!$F$13/12/1000 -> 375.69444 | I15: =Assum_Capex!$F$13/12/1000 -> 375.69444 | ... DQ15: =Assum_Capex!$F$13/12/1000 -> 375.69444
A17: CLOSING PP&E ($000s)
A18: Gross PP&E - Closing | B18: =B7+B14 -> 62103.333 | C18: =C7+C14 -> 62206.839 | D18: =D7+D14 -> 62310.517 | E18: =E7+E14 -> 62414.368 | F18: =F7+F14 -> 62518.392 | G18: =G7+G14 -> 62622.589 | H18: =H7+H14 -> 62726.96 | I18: =I7+I14 -> 62831.505 | ... DQ18: =DQ7+DQ14 -> 75714.365
A19: Accumulated Depreciation - Closing | B19: =B8+B15 -> 21375.694 | C19: =C8+C15 -> 21751.389 | D19: =D8+D15 -> 22127.083 | E19: =E8+E15 -> 22502.778 | F19: =F8+F15 -> 22878.472 | G19: =G8+G15 -> 23254.167 | H19: =H8+H15 -> 23629.861 | I19: =I8+I15 -> 24005.556 | ... DQ19: =DQ8+DQ15 -> 66083.333
A20: Net PP&E - Closing | B20: =B18-B19 -> 40727.639 | C20: =C18-C19 -> 40455.45 | D20: =D18-D19 -> 40183.434 | E20: =E18-E19 -> 39911.59 | F20: =F18-F19 -> 39639.92 | G20: =G18-G19 -> 39368.422 | H20: =H18-H19 -> 39097.099 | I20: =I18-I19 -> 38825.949 | ... DQ20: =DQ18-DQ19 -> 9631.0316
A22: CAPACITY UTILIZATION
A23: Fermentation Capacity (HL/month) | B23: =Assum_Capex!$C$17/12 -> 83333.333 | C23: =Assum_Capex!$C$17/12 -> 83333.333 | D23: =Assum_Capex!$C$17/12 -> 83333.333 | E23: =Assum_Capex!$C$17/12 -> 83333.333 | F23: =Assum_Capex!$C$17/12 -> 83333.333 | G23: =Assum_Capex!$C$17/12 -> 83333.333 | H23: =Assum_Capex!$C$17/12 -> 83333.333 | I23: =Assum_Capex!$C$17/12 -> 83333.333 | ... DQ23: =Assum_Capex!$C$17/12 -> 83333.333
A24: Volume Produced (HL) | B24: =Calc_Volume!B14 -> 76666.667 | C24: =Calc_Volume!C14 -> 73333.333 | D24: =Calc_Volume!D14 -> 66666.667 | E24: =Calc_Volume!E14 -> 60000 | F24: =Calc_Volume!F14 -> 56666.667 | G24: =Calc_Volume!G14 -> 53333.333 | H24: =Calc_Volume!H14 -> 53333.333 | I24: =Calc_Volume!I14 -> 56666.667 | ... DQ24: =Calc_Volume!DQ14 -> 148820.48
A25: Utilization % | B25: =IF(B23>0,B24/B23,0) -> 0.92 | C25: =IF(C23>0,C24/C23,0) -> 0.88 | D25: =IF(D23>0,D24/D23,0) -> 0.8 | E25: =IF(E23>0,E24/E23,0) -> 0.72 | F25: =IF(F23>0,F24/F23,0) -> 0.68 | G25: =IF(G23>0,G24/G23,0) -> 0.64 | H25: =IF(H23>0,H24/H23,0) -> 0.64 | I25: =IF(I23>0,I24/I23,0) -> 0.68 | ... DQ25: =IF(DQ23>0,DQ24/DQ23,0) -> 1.7858458

Sheet Calc_WC
A1: WORKING CAPITAL
A3: Period | B3: =Calc_Volume!B3 -> 1 | C3: =Calc_Volume!C3 -> 2 | D3: =Calc_Volume!D3 -> 3 | E3: =Calc_Volume!E3 -> 4 | F3: =Calc_Volume!F3 -> 5 | G3: =Calc_Volume!G3 -> 6 | H3: =Calc_Volume!H3 -> 7 | I3: =Calc_Volume!I3 -> 8 | ... DQ3: =Calc_Volume!DQ3 -> 120
A4: Date | B4: =Calc_Volume!B4 -> 45658 | C4: =Calc_Volume!C4 -> 45689 | D4: =Calc_Volume!D4 -> 45717 | E4: =Calc_Volume!E4 -> 45748 | F4: =Calc_Volume!F4 -> 45778 | G4: =Calc_Volume!G4 -> 45809 | H4: =Calc_Volume!H4 -> 45839 | I4: =Calc_Volume!I4 -> 45870 | ... DQ4: =Calc_Volume!DQ4 -> 49279
A6: INVENTORY ($000s)
A7: Raw Materials | B7: =Assum_WC!$C$4*Calc_COGS!B28*12/365 -> 5627.5644 | C7: =Assum_WC!$C$4*Calc_COGS!C28*12/365 -> 5382.8877 | D7: =Assum_WC!$C$4*Calc_COGS!D28*12/365 -> 4893.5342 | E7: =Assum_WC!$C$4*Calc_COGS!E28*12/365 -> 4404.1808 | F7: =Assum_WC!$C$4*Calc_COGS!F28*12/365 -> 4159.5041 | G7: =Assum_WC!$C$4*Calc_COGS!G28*12/365 -> 3914.8274 | H7: =Assum_WC!$C$4*Calc_COGS!H28*12/365 -> 3914.8274 | I7: =Assum_WC!$C$4*Calc_COGS!I28*12/365 -> 4159.5041 | ... DQ7: =Assum_WC!$C$4*Calc_COGS!DQ28*12/365 -> 13642.419
A8: Work in Progress | B8: =Assum_WC!$C$5*Calc_COGS!B28*12/365 -> 2626.1967 | C8: =Assum_WC!$C$5*Calc_COGS!C28*12/365 -> 2512.0142 | D8: =Assum_WC!$C$5*Calc_COGS!D28*12/365 -> 2283.6493 | E8: =Assum_WC!$C$5*Calc_COGS!E28*12/365 -> 2055.2844 | F8: =Assum_WC!$C$5*Calc_COGS!F28*12/365 -> 1941.1019 | G8: =Assum_WC!$C$5*Calc_COGS!G28*12/365 -> 1826.9195 | H8: =Assum_WC!$C$5*Calc_COGS!H28*12/365 -> 1826.9195 | I8: =Assum_WC!$C$5*Calc_COGS!I28*12/365 -> 1941.1019 | ... DQ8: =Assum_WC!$C$5*Calc_COGS!DQ28*12/365 -> 6366.4624
A9: Finished Goods | B9: =Assum_WC!$C$6*Calc_COGS!B28*12/365 -> 3939.2951 | C9: =Assum_WC!$C$6*Calc_COGS!C28*12/365 -> 3768.0214 | D9: =Assum_WC!$C$6*Calc_COGS!D28*12/365 -> 3425.474 | E9: =Assum_WC!$C$6*Calc_COGS!E28*12/365 -> 3082.9266 | F9: =Assum_WC!$C$6*Calc_COGS!F28*12/365 -> 2911.6529 | G9: =Assum_WC!$C$6*Calc_COGS!G28*12/365 -> 2740.3792 | H9: =Assum_WC!$C$6*Calc_COGS!H28*12/365 -> 2740.3792 | I9: =Assum_WC!$C$6*Calc_COGS!I28*12/365 -> 2911.6529 | ... DQ9: =Assum_WC!$C$6*Calc_COGS!DQ28*12/365 -> 9549.6935
A10: Total Inventory | B10: =SUM(B7:B9) -> 12193.056 | C10: =SUM(C7:C9) -> 11662.923 | D10: =SUM(D7:D9) -> 10602.658 | E10: =SUM(E7:E9) -> 9542.3918 | F10: =SUM(F7:F9) -> 9012.2589 | G10: =SUM(G7:G9) -> 8482.126 | H10: =SUM(H7:H9) -> 8482.126 | I10: =SUM(I7:I9) -> 9012.2589 | ... DQ10: =SUM(DQ7:DQ9) -> 29558.575
A12: RECEIVABLES ($000s)
A13: Trade Receivables | B13: =Assum_WC!$C$13*Calc_Revenue!B25*12/365 -> 33251.005 | C13: =Assum_WC!$C$13*Calc_Revenue!C25*12/365 -> 31805.309 | D13: =Assum_WC!$C$13*Calc_Revenue!D25*12/365 -> 28913.918 | E13: =Assum_WC!$C$13*Calc_Revenue!E25*12/365 -> 26022.526 | F13: =Assum_WC!$C$13*Calc_Revenue!F25*12/365 -> 24576.83 | G13: =Assum_WC!$C$13*Calc_Revenue!G25*12/365 -> 23131.134 | H13: =Assum_WC!$C$13*Calc_Revenue!H25*12/365 -> 23131.134 | I13: =Assum_WC!$C$13*Calc_Revenue!I25*12/365 -> 24576.83 | ... DQ13: =Assum_WC!$C$13*Calc_Revenue!DQ25*12/365 -> 93447.368
A15: PAYABLES ($000s)
A16: Trade Payables | B16: =Assum_WC!$C$17*(Calc_COGS!B28+Calc_Opex!B21)*12/365 -> 19462.922 | C16: =Assum_WC!$C$17*(Calc_COGS!C28+Calc_Opex!C21)*12/365 -> 18616.708 | D16: =Assum_WC!$C$17*(Calc_COGS!D28+Calc_Opex!D21)*12/365 -> 16924.28 | E16: =Assum_WC!$C$17*(Calc_COGS!E28+Calc_Opex!E21)*12/365 -> 15231.852 | F16: =Assum_WC!$C$17*(Calc_COGS!F28+Calc_Opex!F21)*12/365 -> 14385.638 | G16: =Assum_WC!$C$17*(Calc_COGS!G28+Calc_Opex!G21)*12/365 -> 13539.424 | H16: =Assum_WC!$C$17*(Calc_COGS!H28+Calc_Opex!H21)*12/365 -> 13539.424 | I16: =Assum_WC!$C$17*(Calc_COGS!I28+Calc_Opex!I21)*12/365 -> 14385.638 | ... DQ16: =Assum_WC!$C$17*(Calc_COGS!DQ28+Calc_Opex!DQ21)*12/365 -> 47182.284
A18: OTHER ($000s)
A19: Prepayments | B19: =Assum_WC!$C$21*Calc_Opex!B21*12/365 -> 5527.47 | C19: =Assum_WC!$C$21*Calc_Opex!C21*12/365 -> 5287.1452 | D19: =Assum_WC!$C$21*Calc_Opex!D21*12/365 -> 4806.4956 | E19: =Assum_WC!$C$21*Calc_Opex!E21*12/365 -> 4325.8461 | F19: =Assum_WC!$C$21*Calc_Opex!F21*12/365 -> 4085.5213 | G19: =Assum_WC!$C$21*Calc_Opex!G21*12/365 -> 3845.1965 | H19: =Assum_WC!$C$21*Calc_Opex!H21*12/365 -> 3845.1965 | I19: =Assum_WC!$C$21*Calc_Opex!I21*12/365 -> 4085.5213 | ... DQ19: =Assum_WC!$C$21*Calc_Opex!DQ21*12/365 -> 13399.769
A20: Accruals | B20: =Assum_WC!$C$22*Calc_Opex!B21*12/365 -> 7369.9599 | C20: =Assum_WC!$C$22*Calc_Opex!C21*12/365 -> 7049.5269 | D20: =Assum_WC!$C$22*Calc_Opex!D21*12/365 -> 6408.6608 | E20: =Assum_WC!$C$22*Calc_Opex!E21*12/365 -> 5767.7947 | F20: =Assum_WC!$C$22*Calc_Opex!F21*12/365 -> 5447.3617 | G20: =Assum_WC!$C$22*Calc_Opex!G21*12/365 -> 5126.9287 | H20: =Assum_WC!$C$22*Calc_Opex!H21*12/365 -> 5126.9287 | I20: =Assum_WC!$C$22*Calc_Opex!I21*12/365 -> 5447.3617 | ... DQ20: =Assum_WC!$C$22*Calc_Opex!DQ21*12/365 -> 17866.359
A22: NET WORKING CAPITAL ($000s)
A23: Net Working Capital | B23: =B10+B13+B19-B16-B20 -> 24138.65 | C23: =C10+C13+C19-C16-C20 -> 23089.143 | D23: =D10+D13+D19-D16-D20 -> 20990.13 | E23: =E10+E13+E19-E16-E20 -> 18891.117 | F23: =F10+F13+F19-F16-F20 -> 17841.611 | G23: =G10+G13+G19-G16-G20 -> 16792.104 | H23: =H10+H13+H19-H16-H20 -> 16792.104 | I23: =I10+I13+I19-I16-I20 -> 17841.611 | ... DQ23: =DQ10+DQ13+DQ19-DQ16-DQ20 -> 71357.07
A24: Change in NWC | B24: =B23-Assum_WC!$C$32 -> 38.649632 | C24: =C23-B23 -> -1049.5065 | D24: =D23-C23 -> -2099.013 | E24: =E23-D23 -> -2099.013 | F24: =F23-E23 -> -1049.5065 | G24: =G23-F23 -> -1049.5065 | H24: =H23-G23 -> 0 | I24: =I23-H23 -> 1049.5065 | J24: =J23-I23 -> 2099.013 | ... DQ24: =DQ23-DP23 -> 12742.334

Sheet Calc_Debt
A1: DEBT SCHEDULE
A3: Period | B3: =Calc_Volume!B3 -> 1 | C3: =Calc_Volume!C3 -> 2 | D3: =Calc_Volume!D3 -> 3 | E3: =Calc_Volume!E3 -> 4 | F3: =Calc_Volume!F3 -> 5 | G3: =Calc_Volume!G3 -> 6 | H3: =Calc_Volume!H3 -> 7 | I3: =Calc_Volume!I3 -> 8 | ... DQ3: =Calc_Volume!DQ3 -> 120
A4: Date | B4: =Calc_Volume!B4 -> 45658 | C4: =Calc_Volume!C4 -> 45689 | D4: =Calc_Volume!D4 -> 45717 | E4: =Calc_Volume!E4 -> 45748 | F4: =Calc_Volume!F4 -> 45778 | G4: =Calc_Volume!G4 -> 45809 | H4: =Calc_Volume!H4 -> 45839 | I4: =Calc_Volume!I4 -> 45870 | ... DQ4: =Calc_Volume!DQ4 -> 49279
A6: TERM LOAN ($000s)
A7: Opening Balance | B7: =Assum_Finance!$C$4/1000 -> 25000 | C7: =B9 -> 24702.381 | D7: =C9 -> 24404.762 | E7: =D9 -> 24107.143 | F7: =E9 -> 23809.524 | G7: =F9 -> 23511.905 | H7: =G9 -> 23214.286 | I7: =H9 -> 22916.667 | J7: =I9 -> 22619.048 | ... DQ7: =DP9 -> 0
A8: Principal Payment | B8: =MIN(B7,Assum_Finance!$C$7/12/1000) -> 297.61905 | C8: =MIN(C7,Assum_Finance!$C$7/12/1000) -> 297.61905 | D8: =MIN(D7,Assum_Finance!$C$7/12/1000) -> 297.61905 | E8: =MIN(E7,Assum_Finance!$C$7/12/1000) -> 297.61905 | F8: =MIN(F7,Assum_Finance!$C$7/12/1000) -> 297.61905 | G8: =MIN(G7,Assum_Finance!$C$7/12/1000) -> 297.61905 | H8: =MIN(H7,Assum_Finance!$C$7/12/1000) -> 297.61905 | I8: =MIN(I7,Assum_Finance!$C$7/12/1000) -> 297.61905 | ... DQ8: =MIN(DQ7,Assum_Finance!$C$7/12/1000) -> 0
A9: Closing Balance | B9: =B7-B8 -> 24702.381 | C9: =C7-C8 -> 24404.762 | D9: =D7-D8 -> 24107.143 | E9: =E7-E8 -> 23809.524 | F9: =F7-F8 -> 23511.905 | G9: =G7-G8 -> 23214.286 | H9: =H7-H8 -> 22916.667 | I9: =I7-I8 -> 22619.048 | ... DQ9: =DQ7-DQ8 -> 0
A10: Interest Expense | B10: =B7*Assum_Finance!$C$5/12 -> 135.41667 | C10: =C7*Assum_Finance!$C$5/12 -> 133.80456 | D10: =D7*Assum_Finance!$C$5/12 -> 132.19246 | E10: =E7*Assum_Finance!$C$5/12 -> 130.58036 | F10: =F7*Assum_Finance!$C$5/12 -> 128.96825 | G10: =G7*Assum_Finance!$C$5/12 -> 127.35615 | H10: =H7*Assum_Finance!$C$5/12 -> 125.74405 | I10: =I7*Assum_Finance!$C$5/12 -> 124.13194 | ... DQ10: =DQ7*Assum_Finance!$C$5/12 -> 0
A12: REVOLVER ($000s)
A13: Opening Balance | B13: =Assum_Finance!$C$12/1000 -> 0 | C13: =B15 -> 0 | D13: =C15 -> 0 | E13: =D15 -> 0 | F13: =E15 -> 0 | G13: =F15 -> 0 | H13: =G15 -> 0 | I13: =H15 -> 0 | J13: =I15 -> 0 | ... DQ13: =DP15 -> 0
A14: Draw / (Repay) | B14: 0 | C14: 0 | D14: 0 | E14: 0 | F14: 0 | G14: 0 | H14: 0 | I14: 0 | J14: 0 | K14: 0 | L14: 0 | M14: 0 | N14: 0 | O14: 0 | P14: 0 | Q14: 0 | R14: 0 | S14: 0 | T14: 0 | U14: 0 | V14: 0 | W14: 0 | X14: 0 | Y14: 0 | Z14: 0 | AA14: 0 | AB14: 0 | AC14: 0 | AD14: 0 | AE14: 0 | AF14: 0 | AG14: 0 | AH14: 0 | AI14: 0 | AJ14: 0 | AK14: 0 | AL14: 0 | AM14: 0 | AN14: 0 | AO14: 0 | AP14: 0 | AQ14: 0 | AR14: 0 | AS14: 0 | AT14: 0 | AU14: 0 | AV14: 0 | AW14: 0 | AX14: 0 | AY14: 0 | AZ14: 0 | BA14: 0 | BB14: 0 | BC14: 0 | BD14: 0 | BE14: 0 | BF14: 0 | BG14: 0 | BH14: 0 | BI14: 0 | BJ14: 0 | BK14: 0 | BL14: 0 | BM14: 0 | BN14: 0 | BO14: 0 | BP14: 0 | BQ14: 0 | BR14: 0 | BS14: 0 | BT14: 0 | BU14: 0 | BV14: 0 | BW14: 0 | BX14: 0 | BY14: 0 | BZ14: 0 | CA14: 0 | CB14: 0 | CC14: 0 | CD14: 0 | CE14: 0 | CF14: 0 | CG14: 0 | CH14: 0 | CI14: 0 | CJ14: 0 | CK14: 0 | CL14: 0 | CM14: 0 | CN14: 0 | CO14: 0 | CP14: 0 | CQ14: 0 | CR14: 0 | CS14: 0 | CT14: 0 | CU14: 0 | CV14: 0 | CW14: 0 | CX14: 0 | CY14: 0 | CZ14: 0 | DA14: 0 | DB14: 0 | DC14: 0 | DD14: 0 | DE14: 0 | DF14: 0 | DG14: 0 | DH14: 0 | DI14: 0 | DJ14: 0 | DK14: 0 | DL14: 0 | DM14: 0 | DN14: 0 | DO14: 0 | DP14: 0 | DQ14: 0
A15: Closing Balance | B15: =B13+B14 -> 0 | C15: =C13+C14 -> 0 | D15: =D13+D14 -> 0 | E15: =E13+E14 -> 0 | F15: =F13+F14 -> 0 | G15: =G13+G14 -> 0 | H15: =H13+H14 -> 0 | I15: =I13+I14 -> 0 | ... DQ15: =DQ13+DQ14 -> 0
A16: Interest Expense | B16: =B13*Assum_Finance!$C$13/12 -> 0 | C16: =C13*Assum_Finance!$C$13/12 -> 0 | D16: =D13*Assum_Finance!$C$13/12 -> 0 | E16: =E13*Assum_Finance!$C$13/12 -> 0 | F16: =F13*Assum_Finance!$C$13/12 -> 0 | G16: =G13*Assum_Finance!$C$13/12 -> 0 | H16: =H13*Assum_Finance!$C$13/12 -> 0 | I16: =I13*Assum_Finance!$C$13/12 -> 0 | ... DQ16: =DQ13*Assum_Finance!$C$13/12 -> 0
A17: Commitment Fee | B17: =(Assum_Finance!$C$11/1000-B13)*Assum_Finance!$C$14/12 -> 4.1666667 | C17: =(Assum_Finance!$C$11/1000-C13)*Assum_Finance!$C$14/12 -> 4.1666667 | D17: =(Assum_Finance!$C$11/1000-D13)*Assum_Finance!$C$14/12 -> 4.1666667 | E17: =(Assum_Finance!$C$11/1000-E13)*Assum_Finance!$C$14/12 -> 4.1666667 | F17: =(Assum_Finance!$C$11/1000-F13)*Assum_Finance!$C$14/12 -> 4.1666667 | G17: =(Assum_Finance!$C$11/1000-G13)*Assum_Finance!$C$14/12 -> 4.1666667 | H17: =(Assum_Finance!$C$11/1000-H13)*Assum_Finance!$C$14/12 -> 4.1666667 | I17: =(Assum_Finance!$C$11/1000-I13)*Assum_Finance!$C$14/12 -> 4.1666667 | ... DQ17: =(Assum_Finance!$C$11/1000-DQ13)*Assum_Finance!$C$14/12 -> 4.1666667
A19: TOTAL DEBT ($000s)
A20: Total Debt | B20: =B9+B15 -> 24702.381 | C20: =C9+C15 -> 24404.762 | D20: =D9+D15 -> 24107.143 | E20: =E9+E15 -> 23809.524 | F20: =F9+F15 -> 23511.905 | G20: =G9+G15 -> 23214.286 | H20: =H9+H15 -> 22916.667 | I20: =I9+I15 -> 22619.048 | ... DQ20: =DQ9+DQ15 -> 0
A21: Total Interest Expense | B21: =B10+B16+B17 -> 139.58333 | C21: =C10+C16+C17 -> 137.97123 | D21: =D10+D16+D17 -> 136.35913 | E21: =E10+E16+E17 -> 134.74702 | F21: =F10+F16+F17 -> 133.13492 | G21: =G10+G16+G17 -> 131.52282 | H21: =H10+H16+H17 -> 129.91071 | I21: =I10+I16+I17 -> 128.29861 | ... DQ21: =DQ10+DQ16+DQ17 -> 4.1666667

Sheet IS
A1: INCOME STATEMENT
A3: Period | B3: =Calc_Volume!B3 -> 1 | C3: =Calc_Volume!C3 -> 2 | D3: =Calc_Volume!D3 -> 3 | E3: =Calc_Volume!E3 -> 4 | F3: =Calc_Volume!F3 -> 5 | G3: =Calc_Volume!G3 -> 6 | H3: =Calc_Volume!H3 -> 7 | I3: =Calc_Volume!I3 -> 8 | ... DQ3: =Calc_Volume!DQ3 -> 120
A4: Date | B4: =Calc_Volume!B4 -> 45658 | C4: =Calc_Volume!C4 -> 45689 | D4: =Calc_Volume!D4 -> 45717 | E4: =Calc_Volume!E4 -> 45748 | F4: =Calc_Volume!F4 -> 45778 | G4: =Calc_Volume!G4 -> 45809 | H4: =Calc_Volume!H4 -> 45839 | I4: =Calc_Volume!I4 -> 45870 | ... DQ4: =Calc_Volume!DQ4 -> 49279
A6: REVENUE ($000s)
A7: Gross Revenue | B7: =Calc_Revenue!B12 -> 47103.808 | C7: =Calc_Revenue!C12 -> 45055.817 | D7: =Calc_Revenue!D12 -> 40959.833 | E7: =Calc_Revenue!E12 -> 36863.85 | F7: =Calc_Revenue!F12 -> 34815.858 | G7: =Calc_Revenue!G12 -> 32767.867 | H7: =Calc_Revenue!H12 -> 32767.867 | I7: =Calc_Revenue!I12 -> 34815.858 | ... DQ7: =Calc_Revenue!DQ12 -> 114189.7
A8: Less: Discounts | B8: =-Calc_Revenue!B17 -> -5696.8297 | C8: =-Calc_Revenue!C17 -> -5449.1415 | D8: =-Calc_Revenue!D17 -> -4953.765 | E8: =-Calc_Revenue!E17 -> -4458.3885 | F8: =-Calc_Revenue!F17 -> -4210.7002 | G8: =-Calc_Revenue!G17 -> -3963.012 | H8: =-Calc_Revenue!H17 -> -3963.012 | I8: =-Calc_Revenue!I17 -> -4210.7002 | ... DQ8: =-Calc_Revenue!DQ17 -> -13810.333
A9: Less: Excise Duty | B9: =-Calc_Revenue!B22 -> -18394.812 | C9: =-Calc_Revenue!C22 -> -17595.037 | D9: =-Calc_Revenue!D22 -> -15995.488 | E9: =-Calc_Revenue!E22 -> -14395.94 | F9: =-Calc_Revenue!F22 -> -13596.165 | G9: =-Calc_Revenue!G22 -> -12796.391 | H9: =-Calc_Revenue!H22 -> -12796.391 | I9: =-Calc_Revenue!I22 -> -13596.165 | ... DQ9: =-Calc_Revenue!DQ22 -> -35706.845
A10: Net Revenue | B10: =Calc_Revenue!B25 -> 23012.167 | C10: =Calc_Revenue!C25 -> 22011.638 | D10: =Calc_Revenue!D25 -> 20010.58 | E10: =Calc_Revenue!E25 -> 18009.522 | F10: =Calc_Revenue!F25 -> 17008.993 | G10: =Calc_Revenue!G25 -> 16008.464 | H10: =Calc_Revenue!H25 -> 16008.464 | I10: =Calc_Revenue!I25 -> 17008.993 | ... DQ10: =Calc_Revenue!DQ25 -> 64672.525
A12: COST OF GOODS SOLD ($000s)
A13: Raw Materials | B13: =-Calc_COGS!B12 -> -1533.3333 | C13: =-Calc_COGS!C12 -> -1466.6667 | D13: =-Calc_COGS!D12 -> -1333.3333 | E13: =-Calc_COGS!E12 -> -1200 | F13: =-Calc_COGS!F12 -> -1133.3333 | G13: =-Calc_COGS!G12 -> -1066.6667 | H13: =-Calc_COGS!H12 -> -1066.6667 | I13: =-Calc_COGS!I12 -> -1133.3333 | ... DQ13: =-Calc_COGS!DQ12 -> -3717.1278
A14: Packaging | B14: =-Calc_COGS!B18 -> -2025.725 | C14: =-Calc_COGS!C18 -> -1937.65 | D14: =-Calc_COGS!D18 -> -1761.5 | E14: =-Calc_COGS!E18 -> -1585.35 | F14: =-Calc_COGS!F18 -> -1497.275 | G14: =-Calc_COGS!G18 -> -1409.2 | H14: =-Calc_COGS!H18 -> -1409.2 | I14: =-Calc_COGS!I18 -> -1497.275 | ... DQ14: =-Calc_COGS!DQ18 -> -4910.7905
A15: Direct Manufacturing | B15: =-Calc_COGS!B25 -> -2146.6667 | C15: =-Calc_COGS!C25 -> -2053.3333 | D15: =-Calc_COGS!D25 -> -1866.6667 | E15: =-Calc_COGS!E25 -> -1680 | F15: =-Calc_COGS!F25 -> -1586.6667 | G15: =-Calc_COGS!G25 -> -1493.3333 | H15: =-Calc_COGS!H25 -> -1493.3333 | I15: =-Calc_COGS!I25 -> -1586.6667 | ... DQ15: =-Calc_COGS!DQ25 -> -5203.979
A16: Total COGS | B16: =-Calc_COGS!B28 -> -5705.725 | C16: =-Calc_COGS!C28 -> -5457.65 | D16: =-Calc_COGS!D28 -> -4961.5 | E16: =-Calc_COGS!E28 -> -4465.35 | F16: =-Calc_COGS!F28 -> -4217.275 | G16: =-Calc_COGS!G28 -> -3969.2 | H16: =-Calc_COGS!H28 -> -3969.2 | I16: =-Calc_COGS!I28 -> -4217.275 | ... DQ16: =-Calc_COGS!DQ28 -> -13831.897
A18: GROSS PROFIT
A19: Gross Profit | B19: =B10+B16 -> 17306.442 | C19: =C10+C16 -> 16553.988 | D19: =D10+D16 -> 15049.08 | E19: =E10+E16 -> 13544.172 | F19: =F10+F16 -> 12791.718 | G19: =G10+G16 -> 12039.264 | H19: =H10+H16 -> 12039.264 | I19: =I10+I16 -> 12791.718 | ... DQ19: =DQ10+DQ16 -> 50840.627
A20: Gross Margin % | B20: =IF(B10>0,B19/B10,0) -> 0.75205616 | C20: =IF(C10>0,C19/C10,0) -> 0.75205616 | D20: =IF(D10>0,D19/D10,0) -> 0.75205616 | E20: =IF(E10>0,E19/E10,0) -> 0.75205616 | F20: =IF(F10>0,F19/F10,0) -> 0.75205616 | G20: =IF(G10>0,G19/G10,0) -> 0.75205616 | H20: =IF(H10>0,H19/H10,0) -> 0.75205616 | I20: =IF(I10>0,I19/I10,0) -> 0.75205616 | ... DQ20: =IF(DQ10>0,DQ19/DQ10,0) -> 0.78612405
A22: OPERATING EXPENSES ($000s)
A23: Logistics & Distribution | B23: =-Calc_Opex!B11 -> -3200.8333 | C23: =-Calc_Opex!C11 -> -3061.6667 | D23: =-Calc_Opex!D11 -> -2783.3333 | E23: =-Calc_Opex!E11 -> -2505 | F23: =-Calc_Opex!F11 -> -2365.8333 | G23: =-Calc_Opex!G11 -> -2226.6667 | H23: =-Calc_Opex!H11 -> -2226.6667 | I23: =-Calc_Opex!I11 -> -2365.8333 | ... DQ23: =-Calc_Opex!DQ11 -> -7759.5044
A24: Sales & Marketing | B24: =-(Calc_Opex!B14+Calc_Opex!B15+Calc_Opex!B16) -> -6123.4951 | C24: =-(Calc_Opex!C14+Calc_Opex!C15+Calc_Opex!C16) -> -5857.2562 | D24: =-(Calc_Opex!D14+Calc_Opex!D15+Calc_Opex!D16) -> -5324.7783 | E24: =-(Calc_Opex!E14+Calc_Opex!E15+Calc_Opex!E16) -> -4792.3005 | F24: =-(Calc_Opex!F14+Calc_Opex!F15+Calc_Opex!F16) -> -4526.0616 | G24: =-(Calc_Opex!G14+Calc_Opex!G15+Calc_Opex!G16) -> -4259.8227 | H24: =-(Calc_Opex!H14+Calc_Opex!H15+Calc_Opex!H16) -> -4259.8227 | I24: =-(Calc_Opex!I14+Calc_Opex!I15+Calc_Opex!I16) -> -4526.0616 | ... DQ24: =-(Calc_Opex!DQ14+Calc_Opex!DQ15+Calc_Opex!DQ16) -> -14844.661
A25: General & Admin | B25: =-Calc_Opex!B17 -> -1884.1523 | C25: =-Calc_Opex!C17 -> -1802.2327 | D25: =-Calc_Opex!D17 -> -1638.3933 | E25: =-Calc_Opex!E17 -> -1474.554 | F25: =-Calc_Opex!F17 -> -1392.6343 | G25: =-Calc_Opex!G17 -> -1310.7147 | H25: =-Calc_Opex!H17 -> -1310.7147 | I25: =-Calc_Opex!I17 -> -1392.6343 | ... DQ25: =-Calc_Opex!DQ17 -> -4567.5881
A26: Total Opex | B26: =-Calc_Opex!B21 -> -11208.481 | C26: =-Calc_Opex!C21 -> -10721.156 | D26: =-Calc_Opex!D21 -> -9746.505 | E26: =-Calc_Opex!E21 -> -8771.8545 | F26: =-Calc_Opex!F21 -> -8284.5293 | G26: =-Calc_Opex!G21 -> -7797.204 | H26: =-Calc_Opex!H21 -> -7797.204 | I26: =-Calc_Opex!I21 -> -8284.5293 | ... DQ26: =-Calc_Opex!DQ21 -> -27171.754
A28: EBITDA
A29: EBITDA | B29: =B19+B26 -> 6097.9613 | C29: =C19+C26 -> 5832.8325 | D29: =D19+D26 -> 5302.575 | E29: =E19+E26 -> 4772.3175 | F29: =F19+F26 -> 4507.1887 | G29: =G19+G26 -> 4242.06 | H29: =H19+H26 -> 4242.06 | I29: =I19+I26 -> 4507.1887 | ... DQ29: =DQ19+DQ26 -> 23668.873
A30: EBITDA Margin % | B30: =IF(B10>0,B29/B10,0) -> 0.26498857 | C30: =IF(C10>0,C29/C10,0) -> 0.26498857 | D30: =IF(D10>0,D29/D10,0) -> 0.26498857 | E30: =IF(E10>0,E29/E10,0) -> 0.26498857 | F30: =IF(F10>0,F29/F10,0) -> 0.26498857 | G30: =IF(G10>0,G29/G10,0) -> 0.26498857 | H30: =IF(H10>0,H29/H10,0) -> 0.26498857 | I30: =IF(I10>0,I29/I10,0) -> 0.26498857 | ... DQ30: =IF(DQ10>0,DQ29/DQ10,0) -> 0.36598035
A32: Depreciation | B32: =-Calc_Capex!B15 -> -375.69444 | C32: =-Calc_Capex!C15 -> -375.69444 | D32: =-Calc_Capex!D15 -> -375.69444 | E32: =-Calc_Capex!E15 -> -375.69444 | F32: =-Calc_Capex!F15 -> -375.69444 | G32: =-Calc_Capex!G15 -> -375.69444 | H32: =-Calc_Capex!H15 -> -375.69444 | I32: =-Calc_Capex!I15 -> -375.69444 | ... DQ32: =-Calc_Capex!DQ15 -> -375.69444
A33: EBIT | B33: =B29+B32 -> 5722.2668 | C33: =C29+C32 -> 5457.1381 | D33: =D29+D32 -> 4926.8806 | E33: =E29+E32 -> 4396.6231 | F33: =F29+F32 -> 4131.4943 | G33: =G29+G32 -> 3866.3656 | H33: =H29+H32 -> 3866.3656 | I33: =I29+I32 -> 4131.4943 | ... DQ33: =DQ29+DQ32 -> 23293.179
A34: EBIT Margin % | B34: =IF(B10>0,B33/B10,0) -> 0.24866267 | C34: =IF(C10>0,C33/C10,0) -> 0.24792058 | D34: =IF(D10>0,D33/D10,0) -> 0.24621378 | E34: =IF(E10>0,E33/E10,0) -> 0.24412769 | F34: =IF(F10>0,F33/F10,0) -> 0.24290058 | G34: =IF(G10>0,G33/G10,0) -> 0.24152008 | H34: =IF(H10>0,H33/H10,0) -> 0.24152008 | I34: =IF(I10>0,I33/I10,0) -> 0.24290058 | ... DQ34: =IF(DQ10>0,DQ33/DQ10,0) -> 0.36017117
A36: Interest Expense | B36: =-Calc_Debt!B21 -> -139.58333 | C36: =-Calc_Debt!C21 -> -137.97123 | D36: =-Calc_Debt!D21 -> -136.35913 | E36: =-Calc_Debt!E21 -> -134.74702 | F36: =-Calc_Debt!F21 -> -133.13492 | G36: =-Calc_Debt!G21 -> -131.52282 | H36: =-Calc_Debt!H21 -> -129.91071 | I36: =-Calc_Debt!I21 -> -128.29861 | ... DQ36: =-Calc_Debt!DQ21 -> -4.1666667
A37: EBT | B37: =B33+B36 -> 5582.6835 | C37: =C33+C36 -> 5319.1668 | D37: =D33+D36 -> 4790.5214 | E37: =E33+E36 -> 4261.876 | F37: =F33+F36 -> 3998.3594 | G37: =G33+G36 -> 3734.8427 | H37: =H33+H36 -> 3736.4548 | I37: =I33+I36 -> 4003.1957 | ... DQ37: =DQ33+DQ36 -> 23289.012
A39: Income Tax | B39: =-MAX(0,B37)*Control!$D$16 -> -1674.805 | C39: =-MAX(0,C37)*Control!$D$16 -> -1595.75 | D39: =-MAX(0,D37)*Control!$D$16 -> -1437.1564 | E39: =-MAX(0,E37)*Control!$D$16 -> -1278.5628 | F39: =-MAX(0,F37)*Control!$D$16 -> -1199.5078 | G39: =-MAX(0,G37)*Control!$D$16 -> -1120.4528 | H39: =-MAX(0,H37)*Control!$D$16 -> -1120.9365 | I39: =-MAX(0,I37)*Control!$D$16 -> -1200.9587 | ... DQ39: =-MAX(0,DQ37)*Control!$D$16 -> -6986.7037
A40: NET INCOME | B40: =B37+B39 -> 3907.8784 | C40: =C37+C39 -> 3723.4168 | D40: =D37+D39 -> 3353.365 | E40: =E37+E39 -> 2983.3132 | F40: =F37+F39 -> 2798.8516 | G40: =G37+G39 -> 2614.3899 | H40: =H37+H39 -> 2615.5184 | I40: =I37+I39 -> 2802.237 | ... DQ40: =DQ37+DQ39 -> 16302.309
A41: Net Margin % | B41: =IF(B10>0,B40/B10,0) -> 0.16981792 | C41: =IF(C10>0,C40/C10,0) -> 0.16915673 | D41: =IF(D10>0,D40/D10,0) -> 0.1675796 | E41: =IF(E10>0,E40/E10,0) -> 0.16565199 | F41: =IF(F10>0,F40/F10,0) -> 0.16455128 | G41: =IF(G10>0,G40/G10,0) -> 0.16331298 | H41: =IF(H10>0,H40/H10,0) -> 0.16338347 | I41: =IF(I10>0,I40/I10,0) -> 0.16475032 | ... DQ41: =IF(DQ10>0,DQ40/DQ10,0) -> 0.25207472

Sheet CF
A1: CASH FLOW STATEMENT
A3: Period | B3: =Calc_Volume!B3 -> 1 | C3: =Calc_Volume!C3 -> 2 | D3: =Calc_Volume!D3 -> 3 | E3: =Calc_Volume!E3 -> 4 | F3: =Calc_Volume!F3 -> 5 | G3: =Calc_Volume!G3 -> 6 | H3: =Calc_Volume!H3 -> 7 | I3: =Calc_Volume!I3 -> 8 | ... DQ3: =Calc_Volume!DQ3 -> 120
A4: Date | B4: =Calc_Volume!B4 -> 45658 | C4: =Calc_Volume!C4 -> 45689 | D4: =Calc_Volume!D4 -> 45717 | E4: =Calc_Volume!E4 -> 45748 | F4: =Calc_Volume!F4 -> 45778 | G4: =Calc_Volume!G4 -> 45809 | H4: =Calc_Volume!H4 -> 45839 | I4: =Calc_Volume!I4 -> 45870 | ... DQ4: =Calc_Volume!DQ4 -> 49279
A6: OPERATING ACTIVITIES ($000s)
A7: Net Income | B7: =IS!B40 -> 3907.8784 | C7: =IS!C40 -> 3723.4168 | D7: =IS!D40 -> 3353.365 | E7: =IS!E40 -> 2983.3132 | F7: =IS!F40 -> 2798.8516 | G7: =IS!G40 -> 2614.3899 | H7: =IS!H40 -> 2615.5184 | I7: =IS!I40 -> 2802.237 | ... DQ7: =IS!DQ40 -> 16302.309
A8: Add: Depreciation | B8: =Calc_Capex!B15 -> 375.69444 | C8: =Calc_Capex!C15 -> 375.69444 | D8: =Calc_Capex!D15 -> 375.69444 | E8: =Calc_Capex!E15 -> 375.69444 | F8: =Calc_Capex!F15 -> 375.69444 | G8: =Calc_Capex!G15 -> 375.69444 | H8: =Calc_Capex!H15 -> 375.69444 | I8: =Calc_Capex!I15 -> 375.69444 | ... DQ8: =Calc_Capex!DQ15 -> 375.69444
A9: Change in Working Capital | B9: =-Calc_WC!B24 -> -38.649632 | C9: =-Calc_WC!C24 -> 1049.5065 | D9: =-Calc_WC!D24 -> 2099.013 | E9: =-Calc_WC!E24 -> 2099.013 | F9: =-Calc_WC!F24 -> 1049.5065 | G9: =-Calc_WC!G24 -> 1049.5065 | H9: =-Calc_WC!H24 -> 0 | I9: =-Calc_WC!I24 -> -1049.5065 | ... DQ9: =-Calc_WC!DQ24 -> -12742.334
A10: Cash from Operations | B10: =SUM(B7:B9) -> 4244.9232 | C10: =SUM(C7:C9) -> 5148.6177 | D10: =SUM(D7:D9) -> 5828.0725 | E10: =SUM(E7:E9) -> 5458.0207 | F10: =SUM(F7:F9) -> 4224.0525 | G10: =SUM(G7:G9) -> 4039.5909 | H10: =SUM(H7:H9) -> 2991.2128 | I10: =SUM(I7:I9) -> 2128.4249 | ... DQ10: =SUM(DQ7:DQ9) -> 3935.669
A12: INVESTING ACTIVITIES ($000s)
A13: Capital Expenditure | B13: =-Calc_Capex!B14 -> -103.33333 | C13: =-Calc_Capex!C14 -> -103.50556 | D13: =-Calc_Capex!D14 -> -103.67806 | E13: =-Calc_Capex!E14 -> -103.85086 | F13: =-Calc_Capex!F14 -> -104.02395 | G13: =-Calc_Capex!G14 -> -104.19732 | H13: =-Calc_Capex!H14 -> -104.37098 | I13: =-Calc_Capex!I14 -> -104.54493 | ... DQ13: =-Calc_Capex!DQ14 -> -125.98064
A14: Cash from Investing | B14: =B13 -> -103.33333 | C14: =C13 -> -103.50556 | D14: =D13 -> -103.67806 | E14: =E13 -> -103.85086 | F14: =F13 -> -104.02395 | G14: =G13 -> -104.19732 | H14: =H13 -> -104.37098 | I14: =I13 -> -104.54493 | ... DQ14: =DQ13 -> -125.98064
A16: FINANCING ACTIVITIES ($000s)
A17: Term Loan Principal Payments | B17: =-Calc_Debt!B8 -> -297.61905 | C17: =-Calc_Debt!C8 -> -297.61905 | D17: =-Calc_Debt!D8 -> -297.61905 | E17: =-Calc_Debt!E8 -> -297.61905 | F17: =-Calc_Debt!F8 -> -297.61905 | G17: =-Calc_Debt!G8 -> -297.61905 | H17: =-Calc_Debt!H8 -> -297.61905 | I17: =-Calc_Debt!I8 -> -297.61905 | ... DQ17: =-Calc_Debt!DQ8 -> 0
A18: Revolver Draw / (Repay) | B18: =Calc_Debt!B14 -> 0 | C18: =Calc_Debt!C14 -> 0 | D18: =Calc_Debt!D14 -> 0 | E18: =Calc_Debt!E14 -> 0 | F18: =Calc_Debt!F14 -> 0 | G18: =Calc_Debt!G14 -> 0 | H18: =Calc_Debt!H14 -> 0 | I18: =Calc_Debt!I14 -> 0 | ... DQ18: =Calc_Debt!DQ14 -> 0
A19: Dividends Paid | B19: =-MAX(0,IS!B40)*Assum_Finance!$C$23 -> -1563.1514 | C19: =-MAX(0,IS!C40)*Assum_Finance!$C$23 -> -1489.3667 | D19: =-MAX(0,IS!D40)*Assum_Finance!$C$23 -> -1341.346 | E19: =-MAX(0,IS!E40)*Assum_Finance!$C$23 -> -1193.3253 | F19: =-MAX(0,IS!F40)*Assum_Finance!$C$23 -> -1119.5406 | G19: =-MAX(0,IS!G40)*Assum_Finance!$C$23 -> -1045.756 | H19: =-MAX(0,IS!H40)*Assum_Finance!$C$23 -> -1046.2074 | I19: =-MAX(0,IS!I40)*Assum_Finance!$C$23 -> -1120.8948 | ... DQ19: =-MAX(0,IS!DQ40)*Assum_Finance!$C$23 -> -6520.9234
A20: Cash from Financing | B20: =SUM(B17:B19) -> -1860.7704 | C20: =SUM(C17:C19) -> -1786.9858 | D20: =SUM(D17:D19) -> -1638.965 | E20: =SUM(E17:E19) -> -1490.9443 | F20: =SUM(F17:F19) -> -1417.1597 | G20: =SUM(G17:G19) -> -1343.375 | H20: =SUM(H17:H19) -> -1343.8264 | I20: =SUM(I17:I19) -> -1418.5138 | ... DQ20: =SUM(DQ17:DQ19) -> -6520.9234
A22: CASH MOVEMENT ($000s)
A23: Net Cash Flow | B23: =B10+B14+B20 -> 2280.8195 | C23: =C10+C14+C20 -> 3258.1264 | D23: =D10+D14+D20 -> 4085.4293 | E23: =E10+E14+E20 -> 3863.2255 | F23: =F10+F14+F20 -> 2702.8689 | G23: =G10+G14+G20 -> 2592.0185 | H23: =H10+H14+H20 -> 1543.0154 | I23: =I10+I14+I20 -> 605.36615 | ... DQ23: =DQ10+DQ14+DQ20 -> -2711.235
A24: Opening Cash | B24: =Assum_Finance!$C$28/1000 -> 8000 | C24: =B25 -> 10280.819 | D24: =C25 -> 13538.946 | E24: =D25 -> 17624.375 | F24: =E25 -> 21487.601 | G24: =F25 -> 24190.47 | H24: =G25 -> 26782.488 | I24: =H25 -> 28325.504 | J24: =I25 -> 28930.87 | ... DQ24: =DP25 -> 486349.62
A25: Closing Cash | B25: =B24+B23 -> 10280.819 | C25: =C24+C23 -> 13538.946 | D25: =D24+D23 -> 17624.375 | E25: =E24+E23 -> 21487.601 | F25: =F24+F23 -> 24190.47 | G25: =G24+G23 -> 26782.488 | H25: =H24+H23 -> 28325.504 | I25: =I24+I23 -> 28930.87 | ... DQ25: =DQ24+DQ23 -> 483638.39

Sheet BS
A1: BALANCE SHEET
A3: Period | B3: =Calc_Volume!B3 -> 1 | C3: =Calc_Volume!C3 -> 2 | D3: =Calc_Volume!D3 -> 3 | E3: =Calc_Volume!E3 -> 4 | F3: =Calc_Volume!F3 -> 5 | G3: =Calc_Volume!G3 -> 6 | H3: =Calc_Volume!H3 -> 7 | I3: =Calc_Volume!I3 -> 8 | ... DQ3: =Calc_Volume!DQ3 -> 120
A4: Date | B4: =Calc_Volume!B4 -> 45658 | C4: =Calc_Volume!C4 -> 45689 | D4: =Calc_Volume!D4 -> 45717 | E4: =Calc_Volume!E4 -> 45748 | F4: =Calc_Volume!F4 -> 45778 | G4: =Calc_Volume!G4 -> 45809 | H4: =Calc_Volume!H4 -> 45839 | I4: =Calc_Volume!I4 -> 45870 | ... DQ4: =Calc_Volume!DQ4 -> 49279
A6: ASSETS ($000s)
A7: Current Assets:
A8: Cash | B8: =CF!B25 -> 10280.819 | C8: =CF!C25 -> 13538.946 | D8: =CF!D25 -> 17624.375 | E8: =CF!E25 -> 21487.601 | F8: =CF!F25 -> 24190.47 | G8: =CF!G25 -> 26782.488 | H8: =CF!H25 -> 28325.504 | I8: =CF!I25 -> 28930.87 | ... DQ8: =CF!DQ25 -> 483638.39
A9: Trade Receivables | B9: =Calc_WC!B13 -> 33251.005 | C9: =Calc_WC!C13 -> 31805.309 | D9: =Calc_WC!D13 -> 28913.918 | E9: =Calc_WC!E13 -> 26022.526 | F9: =Calc_WC!F13 -> 24576.83 | G9: =Calc_WC!G13 -> 23131.134 | H9: =Calc_WC!H13 -> 23131.134 | I9: =Calc_WC!I13 -> 24576.83 | ... DQ9: =Calc_WC!DQ13 -> 93447.368
A10: Inventory | B10: =Calc_WC!B10 -> 12193.056 | C10: =Calc_WC!C10 -> 11662.923 | D10: =Calc_WC!D10 -> 10602.658 | E10: =Calc_WC!E10 -> 9542.3918 | F10: =Calc_WC!F10 -> 9012.2589 | G10: =Calc_WC!G10 -> 8482.126 | H10: =Calc_WC!H10 -> 8482.126 | I10: =Calc_WC!I10 -> 9012.2589 | ... DQ10: =Calc_WC!DQ10 -> 29558.575
A11: Prepayments | B11: =Calc_WC!B19 -> 5527.47 | C11: =Calc_WC!C19 -> 5287.1452 | D11: =Calc_WC!D19 -> 4806.4956 | E11: =Calc_WC!E19 -> 4325.8461 | F11: =Calc_WC!F19 -> 4085.5213 | G11: =Calc_WC!G19 -> 3845.1965 | H11: =Calc_WC!H19 -> 3845.1965 | I11: =Calc_WC!I19 -> 4085.5213 | ... DQ11: =Calc_WC!DQ19 -> 13399.769
A12: Total Current Assets | B12: =SUM(B8:B11) -> 61252.351 | C12: =SUM(C8:C11) -> 62294.324 | D12: =SUM(D8:D11) -> 61947.446 | E12: =SUM(E8:E11) -> 61378.364 | F12: =SUM(F8:F11) -> 61865.08 | G12: =SUM(G8:G11) -> 62240.945 | H12: =SUM(H8:H11) -> 63783.96 | I12: =SUM(I8:I11) -> 66605.48 | ... DQ12: =SUM(DQ8:DQ11) -> 620044.1
A14: Non-Current Assets:
A15: Property, Plant & Equipment | B15: =Calc_Capex!B20 -> 40727.639 | C15: =Calc_Capex!C20 -> 40455.45 | D15: =Calc_Capex!D20 -> 40183.434 | E15: =Calc_Capex!E20 -> 39911.59 | F15: =Calc_Capex!F20 -> 39639.92 | G15: =Calc_Capex!G20 -> 39368.422 | H15: =Calc_Capex!H20 -> 39097.099 | I15: =Calc_Capex!I20 -> 38825.949 | ... DQ15: =Calc_Capex!DQ20 -> 9631.0316
A16: Total Non-Current Assets | B16: =B15 -> 40727.639 | C16: =C15 -> 40455.45 | D16: =D15 -> 40183.434 | E16: =E15 -> 39911.59 | F16: =F15 -> 39639.92 | G16: =G15 -> 39368.422 | H16: =H15 -> 39097.099 | I16: =I15 -> 38825.949 | ... DQ16: =DQ15 -> 9631.0316
A18: TOTAL ASSETS | B18: =B12+B16 -> 101979.99 | C18: =C12+C16 -> 102749.77 | D18: =D12+D16 -> 102130.88 | E18: =E12+E16 -> 101289.95 | F18: =F12+F16 -> 101505 | G18: =G12+G16 -> 101609.37 | H18: =H12+H16 -> 102881.06 | I18: =I12+I16 -> 105431.43 | ... DQ18: =DQ12+DQ16 -> 629675.13
A20: LIABILITIES ($000s)
A21: Current Liabilities:
A22: Trade Payables | B22: =Calc_WC!B16 -> 19462.922 | C22: =Calc_WC!C16 -> 18616.708 | D22: =Calc_WC!D16 -> 16924.28 | E22: =Calc_WC!E16 -> 15231.852 | F22: =Calc_WC!F16 -> 14385.638 | G22: =Calc_WC!G16 -> 13539.424 | H22: =Calc_WC!H16 -> 13539.424 | I22: =Calc_WC!I16 -> 14385.638 | ... DQ22: =Calc_WC!DQ16 -> 47182.284
A23: Accruals | B23: =Calc_WC!B20 -> 7369.9599 | C23: =Calc_WC!C20 -> 7049.5269 | D23: =Calc_WC!D20 -> 6408.6608 | E23: =Calc_WC!E20 -> 5767.7947 | F23: =Calc_WC!F20 -> 5447.3617 | G23: =Calc_WC!G20 -> 5126.9287 | H23: =Calc_WC!H20 -> 5126.9287 | I23: =Calc_WC!I20 -> 5447.3617 | ... DQ23: =Calc_WC!DQ20 -> 17866.359
A24: Current Debt | B24: =MIN(Calc_Debt!B9,Assum_Finance!$C$7/1000) -> 3571.4286 | C24: =MIN(Calc_Debt!C9,Assum_Finance!$C$7/1000) -> 3571.4286 | D24: =MIN(Calc_Debt!D9,Assum_Finance!$C$7/1000) -> 3571.4286 | E24: =MIN(Calc_Debt!E9,Assum_Finance!$C$7/1000) -> 3571.4286 | F24: =MIN(Calc_Debt!F9,Assum_Finance!$C$7/1000) -> 3571.4286 | G24: =MIN(Calc_Debt!G9,Assum_Finance!$C$7/1000) -> 3571.4286 | H24: =MIN(Calc_Debt!H9,Assum_Finance!$C$7/1000) -> 3571.4286 | I24: =MIN(Calc_Debt!I9,Assum_Finance!$C$7/1000) -> 3571.4286 | ... DQ24: =MIN(Calc_Debt!DQ9,Assum_Finance!$C$7/1000) -> 0
A25: Total Current Liabilities | B25: =SUM(B22:B24) -> 30404.31 | C25: =SUM(C22:C24) -> 29237.663 | D25: =SUM(D22:D24) -> 26904.369 | E25: =SUM(E22:E24) -> 24571.075 | F25: =SUM(F22:F24) -> 23404.428 | G25: =SUM(G22:G24) -> 22237.781 | H25: =SUM(H22:H24) -> 22237.781 | I25: =SUM(I22:I24) -> 23404.428 | ... DQ25: =SUM(DQ22:DQ24) -> 65048.642
A27: Non-Current Liabilities:
A28: Long-term Debt | B28: =MAX(0,Calc_Debt!B20-B24) -> 21130.952 | C28: =MAX(0,Calc_Debt!C20-C24) -> 20833.333 | D28: =MAX(0,Calc_Debt!D20-D24) -> 20535.714 | E28: =MAX(0,Calc_Debt!E20-E24) -> 20238.095 | F28: =MAX(0,Calc_Debt!F20-F24) -> 19940.476 | G28: =MAX(0,Calc_Debt!G20-G24) -> 19642.857 | H28: =MAX(0,Calc_Debt!H20-H24) -> 19345.238 | I28: =MAX(0,Calc_Debt!I20-I24) -> 19047.619 | ... DQ28: =MAX(0,Calc_Debt!DQ20-DQ24) -> 0
A29: Total Non-Current Liabilities | B29: =B28 -> 21130.952 | C29: =C28 -> 20833.333 | D29: =D28 -> 20535.714 | E29: =E28 -> 20238.095 | F29: =F28 -> 19940.476 | G29: =G28 -> 19642.857 | H29: =H28 -> 19345.238 | I29: =I28 -> 19047.619 | ... DQ29: =DQ28 -> 0
A31: TOTAL LIABILITIES | B31: =B25+B29 -> 51535.263 | C31: =C25+C29 -> 50070.997 | D31: =D25+D29 -> 47440.083 | E31: =E25+E29 -> 44809.17 | F31: =F25+F29 -> 43344.904 | G31: =G25+G29 -> 41880.638 | H31: =H25+H29 -> 41583.019 | I31: =I25+I29 -> 42452.047 | ... DQ31: =DQ25+DQ29 -> 65048.642
A33: EQUITY ($000s)
A34: Share Capital | B34: =Assum_Finance!$C$18/1000 -> 30000 | C34: =Assum_Finance!$C$18/1000 -> 30000 | D34: =Assum_Finance!$C$18/1000 -> 30000 | E34: =Assum_Finance!$C$18/1000 -> 30000 | F34: =Assum_Finance!$C$18/1000 -> 30000 | G34: =Assum_Finance!$C$18/1000 -> 30000 | H34: =Assum_Finance!$C$18/1000 -> 30000 | I34: =Assum_Finance!$C$18/1000 -> 30000 | ... DQ34: =Assum_Finance!$C$18/1000 -> 30000
A35: Retained Earnings | B35: =Assum_Finance!$C$19/1000+IS!B40+CF!B19 -> 20444.727 | C35: =B35+IS!C40+CF!C19 -> 22678.777 | D35: =C35+IS!D40+CF!D19 -> 24690.796 | E35: =D35+IS!E40+CF!E19 -> 26480.784 | F35: =E35+IS!F40+CF!F19 -> 28160.095 | G35: =F35+IS!G40+CF!G19 -> 29728.729 | H35: =G35+IS!H40+CF!H19 -> 31298.04 | I35: =H35+IS!I40+CF!I19 -> 32979.382 | J35: =I35+IS!J40+CF!J19 -> 34884.11 | ... DQ35: =DP35+IS!DQ40+CF!DQ19 -> 534626.49
A36: TOTAL EQUITY | B36: =B34+B35 -> 50444.727 | C36: =C34+C35 -> 52678.777 | D36: =D34+D35 -> 54690.796 | E36: =E34+E35 -> 56480.784 | F36: =F34+F35 -> 58160.095 | G36: =G34+G35 -> 59728.729 | H36: =H34+H35 -> 61298.04 | I36: =I34+I35 -> 62979.382 | ... DQ36: =DQ34+DQ35 -> 564626.49
A38: TOTAL LIABILITIES & EQUITY | B38: =B31+B36 -> 101979.99 | C38: =C31+C36 -> 102749.77 | D38: =D31+D36 -> 102130.88 | E38: =E31+E36 -> 101289.95 | F38: =F31+F36 -> 101505 | G38: =G31+G36 -> 101609.37 | H38: =H31+H36 -> 102881.06 | I38: =I31+I36 -> 105431.43 | ... DQ38: =DQ31+DQ36 -> 629675.13
A40: BALANCE CHECK
A41: Assets - Liabilities - Equity | B41: =ROUND(B18-B38,0) -> 0 | C41: =ROUND(C18-C38,0) -> 0 | D41: =ROUND(D18-D38,0) -> 0 | E41: =ROUND(E18-E38,0) -> 0 | F41: =ROUND(F18-F38,0) -> 0 | G41: =ROUND(G18-G38,0) -> 0 | H41: =ROUND(H18-H38,0) -> 0 | I41: =ROUND(I18-I38,0) -> 0 | ... DQ41: =ROUND(DQ18-DQ38,0) -> 0

Sheet KPIs
A1: KEY PERFORMANCE INDICATORS
A3: Period | B3: =Calc_Volume!B3 -> 1 | C3: =Calc_Volume!C3 -> 2 | D3: =Calc_Volume!D3 -> 3 | E3: =Calc_Volume!E3 -> 4 | F3: =Calc_Volume!F3 -> 5 | G3: =Calc_Volume!G3 -> 6 | H3: =Calc_Volume!H3 -> 7 | I3: =Calc_Volume!I3 -> 8 | ... DQ3: =Calc_Volume!DQ3 -> 120
A4: Date | B4: =Calc_Volume!B4 -> 45658 | C4: =Calc_Volume!C4 -> 45689 | D4: =Calc_Volume!D4 -> 45717 | E4: =Calc_Volume!E4 -> 45748 | F4: =Calc_Volume!F4 -> 45778 | G4: =Calc_Volume!G4 -> 45809 | H4: =Calc_Volume!H4 -> 45839 | I4: =Calc_Volume!I4 -> 45870 | ... DQ4: =Calc_Volume!DQ4 -> 49279
A6: VOLUME METRICS
A7: Total Volume (HL) | B7: =Calc_Volume!B14 -> 76666.667 | C7: =Calc_Volume!C14 -> 73333.333 | D7: =Calc_Volume!D14 -> 66666.667 | E7: =Calc_Volume!E14 -> 60000 | F7: =Calc_Volume!F14 -> 56666.667 | G7: =Calc_Volume!G14 -> 53333.333 | H7: =Calc_Volume!H14 -> 53333.333 | I7: =Calc_Volume!I14 -> 56666.667 | ... DQ7: =Calc_Volume!DQ14 -> 148820.48
A8: Volume Growth (YoY %) | B8: 0 | C8: 0 | D8: 0 | E8: 0 | F8: 0 | G8: 0 | H8: 0 | I8: 0 | J8: 0 | K8: 0 | L8: 0 | M8: 0 | N8: =IF(B7>0,(N7-B7)/B7,0) -> 0.08 | O8: =IF(C7>0,(O7-C7)/C7,0) -> 0.08 | P8: =IF(D7>0,(P7-D7)/D7,0) -> 0.08 | Q8: =IF(E7>0,(Q7-E7)/E7,0) -> 0.08 | R8: =IF(F7>0,(R7-F7)/F7,0) -> 0.08 | S8: =IF(G7>0,(S7-G7)/G7,0) -> 0.08 | T8: =IF(H7>0,(T7-H7)/H7,0) -> 0.08 | U8: =IF(I7>0,(U7-I7)/I7,0) -> 0.08 | ... DQ8: =IF(DE7>0,(DQ7-DE7)/DE7,0) -> 0.04
A9: Capacity Utilization % | B9: =Calc_Capex!B25 -> 0.92 | C9: =Calc_Capex!C25 -> 0.88 | D9: =Calc_Capex!D25 -> 0.8 | E9: =Calc_Capex!E25 -> 0.72 | F9: =Calc_Capex!F25 -> 0.68 | G9: =Calc_Capex!G25 -> 0.64 | H9: =Calc_Capex!H25 -> 0.64 | I9: =Calc_Capex!I25 -> 0.68 | ... DQ9: =Calc_Capex!DQ25 -> 1.7858458
A11: REVENUE METRICS
A12: Gross Revenue ($000s) | B12: =Calc_Revenue!B12 -> 47103.808 | C12: =Calc_Revenue!C12 -> 45055.817 | D12: =Calc_Revenue!D12 -> 40959.833 | E12: =Calc_Revenue!E12 -> 36863.85 | F12: =Calc_Revenue!F12 -> 34815.858 | G12: =Calc_Revenue!G12 -> 32767.867 | H12: =Calc_Revenue!H12 -> 32767.867 | I12: =Calc_Revenue!I12 -> 34815.858 | ... DQ12: =Calc_Revenue!DQ12 -> 114189.7
A13: Net Revenue ($000s) | B13: =Calc_Revenue!B25 -> 23012.167 | C13: =Calc_Revenue!C25 -> 22011.638 | D13: =Calc_Revenue!D25 -> 20010.58 | E13: =Calc_Revenue!E25 -> 18009.522 | F13: =Calc_Revenue!F25 -> 17008.993 | G13: =Calc_Revenue!G25 -> 16008.464 | H13: =Calc_Revenue!H25 -> 16008.464 | I13: =Calc_Revenue!I25 -> 17008.993 | ... DQ13: =Calc_Revenue!DQ25 -> 64672.525
A14: Revenue per HL ($) | B14: =IF(B7>0,B13*1000/B7,0) -> 300.1587 | C14: =IF(C7>0,C13*1000/C7,0) -> 300.1587 | D14: =IF(D7>0,D13*1000/D7,0) -> 300.1587 | E14: =IF(E7>0,E13*1000/E7,0) -> 300.1587 | F14: =IF(F7>0,F13*1000/F7,0) -> 300.1587 | G14: =IF(G7>0,G13*1000/G7,0) -> 300.1587 | H14: =IF(H7>0,H13*1000/H7,0) -> 300.1587 | I14: =IF(I7>0,I13*1000/I7,0) -> 300.1587 | ... DQ14: =IF(DQ7>0,DQ13*1000/DQ7,0) -> 434.56736
A15: Revenue Growth (YoY %) | B15: 0 | C15: 0 | D15: 0 | E15: 0 | F15: 0 | G15: 0 | H15: 0 | I15: 0 | J15: 0 | K15: 0 | L15: 0 | M15: 0 | N15: =IF(B13>0,(N13-B13)/B13,0) -> 0.12858249 | O15: =IF(C13>0,(O13-C13)/C13,0) -> 0.12858249 | P15: =IF(D13>0,(P13-D13)/D13,0) -> 0.12858249 | Q15: =IF(E13>0,(Q13-E13)/E13,0) -> 0.12858249 | R15: =IF(F13>0,(R13-F13)/F13,0) -> 0.12858249 | S15: =IF(G13>0,(S13-G13)/G13,0) -> 0.12858249 | T15: =IF(H13>0,(T13-H13)/H13,0) -> 0.12858249 | U15: =IF(I13>0,(U13-I13)/I13,0) -> 0.12858249 | ... DQ15: =IF(DE13>0,(DQ13-DE13)/DE13,0) -> 0.080919875
A17: PROFITABILITY METRICS
A18: Gross Margin % | B18: =IS!B20 -> 0.75205616 | C18: =IS!C20 -> 0.75205616 | D18: =IS!D20 -> 0.75205616 | E18: =IS!E20 -> 0.75205616 | F18: =IS!F20 -> 0.75205616 | G18: =IS!G20 -> 0.75205616 | H18: =IS!H20 -> 0.75205616 | I18: =IS!I20 -> 0.75205616 | ... DQ18: =IS!DQ20 -> 0.78612405
A19: EBITDA ($000s) | B19: =IS!B29 -> 6097.9613 | C19: =IS!C29 -> 5832.8325 | D19: =IS!D29 -> 5302.575 | E19: =IS!E29 -> 4772.3175 | F19: =IS!F29 -> 4507.1887 | G19: =IS!G29 -> 4242.06 | H19: =IS!H29 -> 4242.06 | I19: =IS!I29 -> 4507.1887 | ... DQ19: =IS!DQ29 -> 23668.873
A20: EBITDA Margin % | B20: =IS!B30 -> 0.26498857 | C20: =IS!C30 -> 0.26498857 | D20: =IS!D30 -> 0.26498857 | E20: =IS!E30 -> 0.26498857 | F20: =IS!F30 -> 0.26498857 | G20: =IS!G30 -> 0.26498857 | H20: =IS!H30 -> 0.26498857 | I20: =IS!I30 -> 0.26498857 | ... DQ20: =IS!DQ30 -> 0.36598035
A21: EBIT Margin % | B21: =IS!B34 -> 0.24866267 | C21: =IS!C34 -> 0.24792058 | D21: =IS!D34 -> 0.24621378 | E21: =IS!E34 -> 0.24412769 | F21: =IS!F34 -> 0.24290058 | G21: =IS!G34 -> 0.24152008 | H21: =IS!H34 -> 0.24152008 | I21: =IS!I34 -> 0.24290058 | ... DQ21: =IS!DQ34 -> 0.36017117
A22: Net Income ($000s) | B22: =IS!B40 -> 3907.8784 | C22: =IS!C40 -> 3723.4168 | D22: =IS!D40 -> 3353.365 | E22: =IS!E40 -> 2983.3132 | F22: =IS!F40 -> 2798.8516 | G22: =IS!G40 -> 2614.3899 | H22: =IS!H40 -> 2615.5184 | I22: =IS!I40 -> 2802.237 | ... DQ22: =IS!DQ40 -> 16302.309
A23: Net Margin % | B23: =IS!B41 -> 0.16981792 | C23: =IS!C41 -> 0.16915673 | D23: =IS!D41 -> 0.1675796 | E23: =IS!E41 -> 0.16565199 | F23: =IS!F41 -> 0.16455128 | G23: =IS!G41 -> 0.16331298 | H23: =IS!H41 -> 0.16338347 | I23: =IS!I41 -> 0.16475032 | ... DQ23: =IS!DQ41 -> 0.25207472
A25: CASH & LEVERAGE
A26: Cash Balance ($000s) | B26: =CF!B25 -> 10280.819 | C26: =CF!C25 -> 13538.946 | D26: =CF!D25 -> 17624.375 | E26: =CF!E25 -> 21487.601 | F26: =CF!F25 -> 24190.47 | G26: =CF!G25 -> 26782.488 | H26: =CF!H25 -> 28325.504 | I26: =CF!I25 -> 28930.87 | ... DQ26: =CF!DQ25 -> 483638.39
A27: Total Debt ($000s) | B27: =Calc_Debt!B20 -> 24702.381 | C27: =Calc_Debt!C20 -> 24404.762 | D27: =Calc_Debt!D20 -> 24107.143 | E27: =Calc_Debt!E20 -> 23809.524 | F27: =Calc_Debt!F20 -> 23511.905 | G27: =Calc_Debt!G20 -> 23214.286 | H27: =Calc_Debt!H20 -> 22916.667 | I27: =Calc_Debt!I20 -> 22619.048 | ... DQ27: =Calc_Debt!DQ20 -> 0
A28: Net Debt ($000s) | B28: =B27-B26 -> 14421.561 | C28: =C27-C26 -> 10865.816 | D28: =D27-D26 -> 6482.7676 | E28: =E27-E26 -> 2321.9231 | F28: =F27-F26 -> -678.56486 | G28: =G27-G26 -> -3568.2024 | H28: =H27-H26 -> -5408.8369 | I28: =I27-I26 -> -6311.8221 | ... DQ28: =DQ27-DQ26 -> -483638.39
A29: Net Debt / EBITDA (LTM) | B29: 0 | C29: 0 | D29: 0 | E29: 0 | F29: 0 | G29: 0 | H29: 0 | I29: 0 | J29: 0 | K29: 0 | L29: 0 | M29: =IF(SUM(IS!B29:M29)>0,M28/SUM(IS!B29:M29),0) -> -0.080831587 | N29: =IF(SUM(IS!C29:N29)>0,N28/SUM(IS!C29:N29),0) -> -0.15739741 | O29: =IF(SUM(IS!D29:O29)>0,O28/SUM(IS!D29:O29),0) -> -0.21802241 | P29: =IF(SUM(IS!E29:P29)>0,P28/SUM(IS!E29:P29),0) -> -0.29095926 | Q29: =IF(SUM(IS!F29:Q29)>0,Q28/SUM(IS!F29:Q29),0) -> -0.3583843 | R29: =IF(SUM(IS!G29:R29)>0,R28/SUM(IS!G29:R29),0) -> -0.40504726 | S29: =IF(SUM(IS!H29:S29)>0,S28/SUM(IS!H29:S29),0) -> -0.44899458 | T29: =IF(SUM(IS!I29:T29)>0,T28/SUM(IS!I29:T29),0) -> -0.47496039 | ... DQ29: =IF(SUM(IS!DF29:DQ29)>0,DQ28/SUM(IS!DF29:DQ29),0) -> -2.3839106
A30: Interest Coverage (EBITDA/Interest) | B30: =IF(Calc_Debt!B21>0,IS!B29/Calc_Debt!B21,0) -> 43.686887 | C30: =IF(Calc_Debt!C21>0,IS!C29/Calc_Debt!C21,0) -> 42.275716 | D30: =IF(Calc_Debt!D21>0,IS!D29/Calc_Debt!D21,0) -> 38.886836 | E30: =IF(Calc_Debt!E21>0,IS!E29/Calc_Debt!E21,0) -> 35.416868 | F30: =IF(Calc_Debt!F21>0,IS!F29/Calc_Debt!F21,0) -> 33.854294 | G30: =IF(Calc_Debt!G21>0,IS!G29/Calc_Debt!G21,0) -> 32.253415 | H30: =IF(Calc_Debt!H21>0,IS!H29/Calc_Debt!H21,0) -> 32.653658 | I30: =IF(Calc_Debt!I21>0,IS!I29/Calc_Debt!I21,0) -> 35.130456 | ... DQ30: =IF(Calc_Debt!DQ21>0,IS!DQ29/Calc_Debt!DQ21,0) -> 5680.5296
A32: RETURNS
A33: ROE % | B33: =IF(BS!B36>0,B22*12/BS!B36,0) -> 0.92962226 | C33: =IF(BS!C36>0,C22*12/BS!C36,0) -> 0.84817841 | D33: =IF(BS!D36>0,D22*12/BS!D36,0) -> 0.73577974 | E33: =IF(BS!E36>0,E22*12/BS!E36,0) -> 0.63383962 | F33: =IF(BS!F36>0,F22*12/BS!F36,0) -> 0.57747875 | G33: =IF(BS!G36>0,G22*12/BS!G36,0) -> 0.52525275 | H33: =IF(BS!H36>0,H22*12/BS!H36,0) -> 0.5120265 | I33: =IF(BS!I36>0,I22*12/BS!I36,0) -> 0.53393416 | ... DQ33: =IF(BS!DQ36>0,DQ22*12/BS!DQ36,0) -> 0.34647277
A34: ROA % | B34: =IF(BS!B18>0,B22*12/BS!B18,0) -> 0.45984062 | C34: =IF(BS!C18>0,C22*12/BS!C18,0) -> 0.43485255 | D34: =IF(BS!D18>0,D22*12/BS!D18,0) -> 0.39400796 | E34: =IF(BS!E18>0,E22*12/BS!E18,0) -> 0.35343839 | F34: =IF(BS!F18>0,F22*12/BS!F18,0) -> 0.33088241 | G34: =IF(BS!G18>0,G22*12/BS!G18,0) -> 0.30875774 | H34: =IF(BS!H18>0,H22*12/BS!H18,0) -> 0.30507288 | I34: =IF(BS!I18>0,I22*12/BS!I18,0) -> 0.31894516 | ... DQ34: =IF(BS!DQ18>0,DQ22*12/BS!DQ18,0) -> 0.31068037
A35: ROCE % | B35: =IF((BS!B36+B27)>0,IS!B33*12/(BS!B36+B27),0) -> 0.91377038 | C35: =IF((BS!C36+C27)>0,IS!C33*12/(BS!C36+C27),0) -> 0.84954139 | D35: =IF((BS!D36+D27)>0,IS!D33*12/(BS!D36+D27),0) -> 0.750306 | E35: =IF((BS!E36+E27)>0,IS!E33*12/(BS!E36+E27),0) -> 0.65710891 | F35: =IF((BS!F36+F27)>0,IS!F33*12/(BS!F36+F27),0) -> 0.60703707 | G35: =IF((BS!G36+G27)>0,IS!G33*12/(BS!G36+G27),0) -> 0.55937666 | H35: =IF((BS!H36+H27)>0,IS!H33*12/(BS!H36+H27),0) -> 0.55092974 | I35: =IF((BS!I36+I27)>0,IS!I33*12/(BS!I36+I27),0) -> 0.57919207 | ... DQ35: =IF((BS!DQ36+DQ27)>0,IS!DQ33*12/(BS!DQ36+DQ27),0) -> 0.49504965
A37: WORKING CAPITAL
A38: Net Working Capital ($000s) | B38: =Calc_WC!B23 -> 24138.65 | C38: =Calc_WC!C23 -> 23089.143 | D38: =Calc_WC!D23 -> 20990.13 | E38: =Calc_WC!E23 -> 18891.117 | F38: =Calc_WC!F23 -> 17841.611 | G38: =Calc_WC!G23 -> 16792.104 | H38: =Calc_WC!H23 -> 16792.104 | I38: =Calc_WC!I23 -> 17841.611 | ... DQ38: =Calc_WC!DQ23 -> 71357.07
A39: NWC as % of Revenue | B39: =IF(B13>0,B38/B13,0) -> 1.0489516 | C39: =IF(C13>0,C38/C13,0) -> 1.0489516 | D39: =IF(D13>0,D38/D13,0) -> 1.0489516 | E39: =IF(E13>0,E38/E13,0) -> 1.0489516 | F39: =IF(F13>0,F38/F13,0) -> 1.0489516 | G39: =IF(G13>0,G38/G13,0) -> 1.0489516 | H39: =IF(H13>0,H38/H13,0) -> 1.0489516 | I39: =IF(I13>0,I38/I13,0) -> 1.0489516 | ... DQ39: =IF(DQ13>0,DQ38/DQ13,0) -> 1.1033599
A40: Cash Conversion Cycle (days) | B40: =Assum_WC!$C$7+Assum_WC!$C$13-Assum_WC!$C$17 -> 73.95 | C40: =Assum_WC!$C$7+Assum_WC!$C$13-Assum_WC!$C$17 -> 73.95 | D40: =Assum_WC!$C$7+Assum_WC!$C$13-Assum_WC!$C$17 -> 73.95 | E40: =Assum_WC!$C$7+Assum_WC!$C$13-Assum_WC!$C$17 -> 73.95 | F40: =Assum_WC!$C$7+Assum_WC!$C$13-Assum_WC!$C$17 -> 73.95 | G40: =Assum_WC!$C$7+Assum_WC!$C$13-Assum_WC!$C$17 -> 73.95 | H40: =Assum_WC!$C$7+Assum_WC!$C$13-Assum_WC!$C$17 -> 73.95 | I40: =Assum_WC!$C$7+Assum_WC!$C$13-Assum_WC!$C$17 -> 73.95 | ... DQ40: =Assum_WC!$C$7+Assum_WC!$C$13-Assum_WC!$C$17 -> 73.95

Sheet Checks
A1: MODEL INTEGRITY CHECKS
A3: CHECK DESCRIPTION | B3: FORMULA | C3: RESULT | D3: STATUS
A4: Balance Sheet Balances (all periods) | B4: =SUMPRODUCT(ABS(BS!B41:DQ41)) -> 0 | C4: =IF(B4<1,"PASS","FAIL") -> PASS
A5: Seasonality Sums to 12 | B5: =Assum_Volume!B58 -> 12 | C5: =IF(ABS(B5-12)<0.01,"PASS","FAIL") -> PASS
A6: Brand Mix Sums to 100% | B6: =Assum_Volume!C8+Assum_Volume!C9 -> 1 | C6: =IF(ABS(B6-1)<0.001,"PASS","FAIL") -> PASS
A7: Market Mix Sums to 100% | B7: =Assum_Volume!C12+Assum_Volume!C13 -> 1 | C7: =IF(ABS(B7-1)<0.001,"PASS","FAIL") -> PASS
A8: Channel Mix Sums to 100% | B8: =Assum_Volume!C16+Assum_Volume!C17 -> 1 | C8: =IF(ABS(B8-1)<0.001,"PASS","FAIL") -> PASS
A9: Cash Never Negative | B9: =MIN(CF!B25:DT25) -> 10280.819 | C9: =IF(B9>=0,"PASS","FAIL") -> PASS
A10: Debt Never Negative | B10: =MIN(Calc_Debt!B20:DT20) -> 0 | C10: =IF(B10>=0,"PASS","FAIL") -> PASS
A11: Volume Never Negative | B11: =MIN(Calc_Volume!B14:DT14) -> 53333.333 | C11: =IF(B11>=0,"PASS","FAIL") -> PASS
A12: Gross Margin Always Positive | B12: =MIN(IS!B20:DT20) -> 0.75205616 | C12: =IF(B12>0,"PASS","FAIL") -> PASS
A13: Total Assets = Total L&E (Period 1) | B13: =BS!B18-BS!B38 -> 0 | C13: =IF(ABS(B13)<1,"PASS","FAIL") -> PASS
A14: Total Assets = Total L&E (Period 60) | B14: =BS!BI18-BS!BI38 -> 0 | C14: =IF(ABS(B14)<1,"PASS","FAIL") -> PASS
A15: Total Assets = Total L&E (Period 120) | B15: =BS!DQ18-BS!DQ38 -> 0 | C15: =IF(ABS(B15)<1,"PASS","FAIL") -> PASS
A16: Net Income Flows to RE | B16: =SUM(IS!B40:DQ40)+SUM(CF!B19:DQ19)-(BS!DQ35-Assum_Finance!C19/1000) -> 1.1059456e-09 | C16: =IF(ABS(B16)<1,"PASS","FAIL") -> PASS
A20: OVERALL STATUS | B20: =COUNTIF(C4:C16,"FAIL") -> 0 | C20: =IF(B20=0,"ALL CHECKS PASS",B20&" CHECK(S) FAILED") -> ALL CHECKS PASS

Sheet Annual_Summary
A1: ANNUAL SUMMARY
A3: METRIC | B3: Year 1 | C3: Year 2 | D3: Year 3 | E3: Year 4 | F3: Year 5 | G3: Year 6 | H3: Year 7 | I3: Year 8 | J3: Year 9 | K3: Year 10
A4: Volume (HL) | B4: =SUM(Calc_Volume!B14:M14) -> 800000 | C4: =SUM(Calc_Volume!N14:Y14) -> 864000 | D4: =SUM(Calc_Volume!Z14:AK14) -> 933120 | E4: =SUM(Calc_Volume!AL14:AW14) -> 989107.2 | F4: =SUM(Calc_Volume!AX14:BI14) -> 1048453.6 | G4: =SUM(Calc_Volume!BJ14:BU14) -> 1090391.8 | H4: =SUM(Calc_Volume!BV14:CG14) -> 1134007.4 | I4: =SUM(Calc_Volume!CH14:CS14) -> 1179367.7 | J4: =SUM(Calc_Volume!CT14:DE14) -> 1226542.5 | K4: =SUM(Calc_Volume!DF14:DQ14) -> 1275604.2
A5: Gross Revenue ($000s) | B5: =SUM(Calc_Revenue!B12:M12) -> 491518 | C5: =SUM(Calc_Revenue!N12:Y12) -> 544110.43 | D5: =SUM(Calc_Revenue!Z12:AK12) -> 602330.24 | E5: =SUM(Calc_Revenue!AL12:AW12) -> 654431.81 | F5: =SUM(Calc_Revenue!AX12:BI12) -> 711040.16 | G5: =SUM(Calc_Revenue!BJ12:BU12) -> 757968.81 | H5: =SUM(Calc_Revenue!BV12:CG12) -> 807994.75 | I5: =SUM(Calc_Revenue!CH12:CS12) -> 861322.4 | J5: =SUM(Calc_Revenue!CT12:DE12) -> 918169.68 | K5: =SUM(Calc_Revenue!DF12:DQ12) -> 978768.88
A6: Net Revenue ($000s) | B6: =SUM(Calc_Revenue!B25:M25) -> 240126.96 | C6: =SUM(Calc_Revenue!N25:Y25) -> 271003.08 | D6: =SUM(Calc_Revenue!Z25:AK25) -> 305597.55 | E6: =SUM(Calc_Revenue!AL25:AW25) -> 337964.71 | F6: =SUM(Calc_Revenue!AX25:BI25) -> 373487.61 | G6: =SUM(Calc_Revenue!BJ25:BU25) -> 404678.3 | H6: =SUM(Calc_Revenue!BV25:CG25) -> 438189.19 | I6: =SUM(Calc_Revenue!CH25:CS25) -> 474183.89 | J6: =SUM(Calc_Revenue!CT25:DE25) -> 512837.2 | K6: =SUM(Calc_Revenue!DF25:DQ25) -> 554335.93
A7: COGS ($000s) | B7: =SUM(Calc_COGS!B28:M28) -> 59538 | C7: =SUM(Calc_COGS!N28:Y28) -> 65908.566 | D7: =SUM(Calc_COGS!Z28:AK28) -> 72960.783 | E7: =SUM(Calc_COGS!AL28:AW28) -> 79271.89 | F7: =SUM(Calc_COGS!AX28:BI28) -> 86128.909 | G7: =SUM(Calc_COGS!BJ28:BU28) -> 91813.417 | H7: =SUM(Calc_COGS!BV28:CG28) -> 97873.102 | I7: =SUM(Calc_COGS!CH28:CS28) -> 104332.73 | J7: =SUM(Calc_COGS!CT28:DE28) -> 111218.69 | K7: =SUM(Calc_COGS!DF28:DQ28) -> 118559.12
A8: Gross Profit ($000s) | B8: =SUM(IS!B19:M19) -> 180588.96 | C8: =SUM(IS!N19:Y19) -> 205094.52 | D8: =SUM(IS!Z19:AK19) -> 232636.77 | E8: =SUM(IS!AL19:AW19) -> 258692.82 | F8: =SUM(IS!AX19:BI19) -> 287358.7 | G8: =SUM(IS!BJ19:BU19) -> 312864.88 | H8: =SUM(IS!BV19:CG19) -> 340316.09 | I8: =SUM(IS!CH19:CS19) -> 369851.16 | J8: =SUM(IS!CT19:DE19) -> 401618.52 | K8: =SUM(IS!DF19:DQ19) -> 435776.81
A9: EBITDA ($000s) | B9: =SUM(IS!B29:M29) -> 63630.9 | C9: =SUM(IS!N29:Y29) -> 75621.945 | D9: =SUM(IS!Z29:AK29) -> 89310.634 | E9: =SUM(IS!AL29:AW29) -> 102968.97 | F9: =SUM(IS!AX29:BI29) -> 118164.74 | G9: =SUM(IS!BJ29:BU29) -> 132504.12 | H9: =SUM(IS!BV29:CG29) -> 148051.51 | I9: =SUM(IS!CH29:CS29) -> 164897.12 | J9: =SUM(IS!CT29:DE29) -> 183137.51 | K9: =SUM(IS!DF29:DQ29) -> 202876.06
A10: EBIT ($000s) | B10: =SUM(IS!B33:M33) -> 59122.567 | C10: =SUM(IS!N33:Y33) -> 71113.611 | D10: =SUM(IS!Z33:AK33) -> 84802.301 | E10: =SUM(IS!AL33:AW33) -> 98460.64 | F10: =SUM(IS!AX33:BI33) -> 113656.4 | G10: =SUM(IS!BJ33:BU33) -> 127995.78 | H10: =SUM(IS!BV33:CG33) -> 143543.18 | I10: =SUM(IS!CH33:CS33) -> 160388.79 | J10: =SUM(IS!CT33:DE33) -> 178629.18 | K10: =SUM(IS!DF33:DQ33) -> 198367.72
A11: Net Income ($000s) | B11: =SUM(IS!B40:M40) -> 40287.776 | C11: =SUM(IS!N40:Y40) -> 48844.007 | D11: =SUM(IS!Z40:AK40) -> 58588.59 | E11: =SUM(IS!AL40:AW40) -> 68311.927 | F11: =SUM(IS!AX40:BI40) -> 79111.462 | G11: =SUM(IS!BJ40:BU40) -> 89311.527 | H11: =SUM(IS!BV40:CG40) -> 100357.21 | I11: =SUM(IS!CH40:CS40) -> 112237.15 | J11: =SUM(IS!CT40:DE40) -> 125005.43 | K11: =SUM(IS!DF40:DQ40) -> 138822.41
A12: Capex ($000s) | B12: =SUM(Calc_Capex!B14:M14) -> 1251.4301 | C12: =SUM(Calc_Capex!N14:Y14) -> 1276.6894 | D12: =SUM(Calc_Capex!Z14:AK14) -> 1302.4585 | E12: =SUM(Calc_Capex!AL14:AW14) -> 1328.7478 | F12: =SUM(Calc_Capex!AX14:BI14) -> 1355.5677 | G12: =SUM(Calc_Capex!BJ14:BU14) -> 1382.929 | H12: =SUM(Calc_Capex!BV14:CG14) -> 1410.8425 | I12: =SUM(Calc_Capex!CH14:CS14) -> 1439.3195 | J12: =SUM(Calc_Capex!CT14:DE14) -> 1468.3712 | K12: =SUM(Calc_Capex!DF14:DQ14) -> 1498.0093
A13: Cash from Ops ($000s) | B13: =SUM(CF!B10:M10) -> 39509.927 | C13: =SUM(CF!N10:Y10) -> 49334.371 | D13: =SUM(CF!Z10:AK10) -> 58579.139 | E13: =SUM(CF!AL10:AW10) -> 68539.861 | F13: =SUM(CF!AX10:BI10) -> 78909.132 | G13: =SUM(CF!BJ10:BU10) -> 89621.034 | H13: =SUM(CF!BV10:CG10) -> 100345.49 | I13: =SUM(CF!CH10:CS10) -> 111881.25 | J13: =SUM(CF!CT10:DE10) -> 124280.78 | K13: =SUM(CF!DF10:DQ10) -> 137702.77
A14: Closing Cash ($000s) | B14: =CF!M25 -> 26571.958 | C14: =CF!Y25 -> 51520.608 | D14: =CF!AK25 -> 81790.424 | E14: =CF!AW25 -> 118105.34 | F14: =CF!BI25 -> 160442.89 | G14: =CF!BU25 -> 209384.95 | H14: =CF!CG25 -> 264605.29 | I14: =CF!CS25 -> 330152.35 | J14: =CF!DE25 -> 402962.59 | K14: =CF!DQ25 -> 483638.39
A15: Total Debt ($000s) | B15: =Calc_Debt!M20 -> 21428.571 | C15: =Calc_Debt!Y20 -> 17857.143 | D15: =Calc_Debt!AK20 -> 14285.714 | E15: =Calc_Debt!AW20 -> 10714.286 | F15: =Calc_Debt!BI20 -> 7142.8571 | G15: =Calc_Debt!BU20 -> 3571.4286 | H15: =Calc_Debt!CG20 -> 4.3769433e-11 | I15: =Calc_Debt!CS20 -> 0 | J15: =Calc_Debt!DE20 -> 0 | K15: =Calc_Debt!DQ20 -> 0
A16: Total Equity ($000s) | B16: =BS!M36 -> 72272.666 | C16: =BS!Y36 -> 101579.07 | D16: =BS!AK36 -> 136732.22 | E16: =BS!AW36 -> 177719.38 | F16: =BS!BI36 -> 225186.26 | G16: =BS!BU36 -> 278773.17 | H16: =BS!CG36 -> 338987.5 | I16: =BS!CS36 -> 406329.79 | J16: =BS!DE36 -> 481333.05 | K16: =BS!DQ36 -> 564626.49
A18: Gross Margin % | B18: =IF(B5>0,B7/B5,0) -> 0.12113086 | C18: =IF(C5>0,C7/C5,0) -> 0.12113086 | D18: =IF(D5>0,D7/D5,0) -> 0.12113086 | E18: =IF(E5>0,E7/E5,0) -> 0.12113086 | F18: =IF(F5>0,F7/F5,0) -> 0.12113086 | G18: =IF(G5>0,G7/G5,0) -> 0.12113086 | H18: =IF(H5>0,H7/H5,0) -> 0.12113086 | I18: =IF(I5>0,I7/I5,0) -> 0.12113086 | ... K18: =IF(K5>0,K7/K5,0) -> 0.12113086
A19: EBITDA Margin % | B19: =IF(B5>0,B8/B5,0) -> 0.36741067 | C19: =IF(C5>0,C8/C5,0) -> 0.37693547 | D19: =IF(D5>0,D8/D5,0) -> 0.38622795 | E19: =IF(E5>0,E8/E5,0) -> 0.39529378 | F19: =IF(F5>0,F8/F5,0) -> 0.40413849 | G19: =IF(G5>0,G8/G5,0) -> 0.41276748 | H19: =IF(H5>0,H8/H5,0) -> 0.42118601 | I19: =IF(I5>0,I8/I5,0) -> 0.42939921 | ... K19: =IF(K5>0,K8/K5,0) -> 0.44522953
A20: Net Margin % | B20: =IF(B5>0,B10/B5,0) -> 0.12028566 | C20: =IF(C5>0,C10/C5,0) -> 0.13069702 | D20: =IF(D5>0,D10/D5,0) -> 0.14079037 | E20: =IF(E5>0,E10/E5,0) -> 0.1504521 | F20: =IF(F5>0,F10/F5,0) -> 0.15984527 | G20: =IF(G5>0,G10/G5,0) -> 0.16886682 | H20: =IF(H5>0,H10/H5,0) -> 0.17765361 | I20: =IF(I5>0,I10/I5,0) -> 0.18621226 | ... K20: =IF(K5>0,K10/K5,0) -> 0.20267065
