Workbook

Sheet 01_Control
A1: MODEL CONTROL PANEL
A3: Scenario Selector (1=Base, 2=Spike) | B3: 1
A5: Scenario Assumptions
A6: Malt Price Spike (%) | B6: 0.25
A7: Hops Price Spike (%) | B7: 0.5

Sheet 02_Inputs
A1: OPERATIONAL INPUTS
A3: Base Malt Price ($/kg) | B3: 1.25
A4: Base Hops Price ($/kg) | B4: 48
A6: Live Malt Price | B6: =IF('01_Control'!$B$3=2, $B$3*(1+'01_Control'!$B$6), $B$3) -> 0
A7: Live Hops Price | B7: =IF('01_Control'!$B$3=2, $B$4*(1+'01_Control'!$B$7), $B$4) -> 0
A9: Seasonality
A11: 1.2 | B11: 1.1 | C11: 0.9 | D11: 0.8 | E11: 0.7 | F11: 0.8 | G11: 0.9 | H11: 1 | I11: 1.1 | J11: 1.2 | K11: 1.3 | L11: 1.4
A12: Loss Rate | B12: 0.07
A13: Channel Split On-Trade % | B13: 0.35
A15: Labor
A17: Brewing | B17: 4 | C17: 85000
A18: Packaging | B18: 3 | C18: 65000
A19: Sales | B19: 3 | C19: 95000
A20: Admin | B20: 2 | C20: 80000

Sheet 03_Calcs
B3: M1 | C3: M2 | D3: M3 | E3: M4 | F3: M5 | G3: M6 | H3: M7 | I3: M8 | J3: M9 | K3: M10 | L3: M11 | M3: M12 | N3: M13 | O3: M14 | P3: M15 | Q3: M16 | R3: M17 | S3: M18 | T3: M19 | U3: M20 | V3: M21 | W3: M22 | X3: M23 | Y3: M24 | Z3: M25 | AA3: M26 | AB3: M27 | AC3: M28 | AD3: M29 | AE3: M30 | AF3: M31 | AG3: M32 | AH3: M33 | AI3: M34 | AJ3: M35 | AK3: M36 | AL3: M37 | AM3: M38 | AN3: M39 | AO3: M40 | AP3: M41 | AQ3: M42 | AR3: M43 | AS3: M44 | AT3: M45 | AU3: M46 | AV3: M47 | AW3: M48 | AX3: M49 | AY3: M50 | AZ3: M51 | BA3: M52 | BB3: M53 | BC3: M54 | BD3: M55 | BE3: M56 | BF3: M57 | BG3: M58 | BH3: M59 | BI3: M60
A5: Crisp Lager | B5: =800 * '02_Inputs'!A11 * (1.005^0) -> 0 | C5: =800 * '02_Inputs'!B11 * (1.005^1) -> 0 | D5: =800 * '02_Inputs'!C11 * (1.005^2) -> 0 | E5: =800 * '02_Inputs'!D11 * (1.005^3) -> 0 | F5: =800 * '02_Inputs'!E11 * (1.005^4) -> 0 | G5: =800 * '02_Inputs'!F11 * (1.005^5) -> 0 | H5: =800 * '02_Inputs'!G11 * (1.005^6) -> 0 | I5: =800 * '02_Inputs'!H11 * (1.005^7) -> 0 | J5: =800 * '02_Inputs'!I11 * (1.005^8) -> 0 | K5: =800 * '02_Inputs'!J11 * (1.005^9) -> 0 | L5: =800 * '02_Inputs'!K11 * (1.005^10) -> 0 | M5: =800 * '02_Inputs'!L11 * (1.005^11) -> 0 | N5: =800 * '02_Inputs'!A11 * (1.005^12) -> 0 | O5: =800 * '02_Inputs'!B11 * (1.005^13) -> 0 | P5: =800 * '02_Inputs'!C11 * (1.005^14) -> 0 | Q5: =800 * '02_Inputs'!D11 * (1.005^15) -> 0 | R5: =800 * '02_Inputs'!E11 * (1.005^16) -> 0 | S5: =800 * '02_Inputs'!F11 * (1.005^17) -> 0 | T5: =800 * '02_Inputs'!G11 * (1.005^18) -> 0 | U5: =800 * '02_Inputs'!H11 * (1.005^19) -> 0 | V5: =800 * '02_Inputs'!I11 * (1.005^20) -> 0 | W5: =800 * '02_Inputs'!J11 * (1.005^21) -> 0 | X5: =800 * '02_Inputs'!K11 * (1.005^22) -> 0 | Y5: =800 * '02_Inputs'!L11 * (1.005^23) -> 0 | Z5: =800 * '02_Inputs'!A11 * (1.005^24) -> 0 | AA5: =800 * '02_Inputs'!B11 * (1.005^25) -> 0 | AB5: =800 * '02_Inputs'!C11 * (1.005^26) -> 0 | AC5: =800 * '02_Inputs'!D11 * (1.005^27) -> 0 | AD5: =800 * '02_Inputs'!E11 * (1.005^28) -> 0 | AE5: =800 * '02_Inputs'!F11 * (1.005^29) -> 0 | AF5: =800 * '02_Inputs'!G11 * (1.005^30) -> 0 | AG5: =800 * '02_Inputs'!H11 * (1.005^31) -> 0 | AH5: =800 * '02_Inputs'!I11 * (1.005^32) -> 0 | AI5: =800 * '02_Inputs'!J11 * (1.005^33) -> 0 | AJ5: =800 * '02_Inputs'!K11 * (1.005^34) -> 0 | AK5: =800 * '02_Inputs'!L11 * (1.005^35) -> 0 | AL5: =800 * '02_Inputs'!A11 * (1.005^36) -> 0 | AM5: =800 * '02_Inputs'!B11 * (1.005^37) -> 0 | AN5: =800 * '02_Inputs'!C11 * (1.005^38) -> 0 | AO5: =800 * '02_Inputs'!D11 * (1.005^39) -> 0 | AP5: =800 * '02_Inputs'!E11 * (1.005^40) -> 0 | AQ5: =800 * '02_Inputs'!F11 * (1.005^41) -> 0 | AR5: =800 * '02_Inputs'!G11 * (1.005^42) -> 0 | AS5: =800 * '02_Inputs'!H11 * (1.005^43) -> 0 | AT5: =800 * '02_Inputs'!I11 * (1.005^44) -> 0 | AU5: =800 * '02_Inputs'!J11 * (1.005^45) -> 0 | AV5: =800 * '02_Inputs'!K11 * (1.005^46) -> 0 | AW5: =800 * '02_Inputs'!L11 * (1.005^47) -> 0 | AX5: =800 * '02_Inputs'!A11 * (1.005^48) -> 0 | AY5: =800 * '02_Inputs'!B11 * (1.005^49) -> 0 | AZ5: =800 * '02_Inputs'!C11 * (1.005^50) -> 0 | BA5: =800 * '02_Inputs'!D11 * (1.005^51) -> 0 | BB5: =800 * '02_Inputs'!E11 * (1.005^52) -> 0 | BC5: =800 * '02_Inputs'!F11 * (1.005^53) -> 0 | BD5: =800 * '02_Inputs'!G11 * (1.005^54) -> 0 | BE5: =800 * '02_Inputs'!H11 * (1.005^55) -> 0 | BF5: =800 * '02_Inputs'!I11 * (1.005^56) -> 0 | BG5: =800 * '02_Inputs'!J11 * (1.005^57) -> 0 | BH5: =800 * '02_Inputs'!K11 * (1.005^58) -> 0 | BI5: =800 * '02_Inputs'!L11 * (1.005^59) -> 0
A6: Pacific Pale | B6: =600 * '02_Inputs'!A11 * (1.005^0) -> 0 | C6: =600 * '02_Inputs'!B11 * (1.005^1) -> 0 | D6: =600 * '02_Inputs'!C11 * (1.005^2) -> 0 | E6: =600 * '02_Inputs'!D11 * (1.005^3) -> 0 | F6: =600 * '02_Inputs'!E11 * (1.005^4) -> 0 | G6: =600 * '02_Inputs'!F11 * (1.005^5) -> 0 | H6: =600 * '02_Inputs'!G11 * (1.005^6) -> 0 | I6: =600 * '02_Inputs'!H11 * (1.005^7) -> 0 | J6: =600 * '02_Inputs'!I11 * (1.005^8) -> 0 | K6: =600 * '02_Inputs'!J11 * (1.005^9) -> 0 | L6: =600 * '02_Inputs'!K11 * (1.005^10) -> 0 | M6: =600 * '02_Inputs'!L11 * (1.005^11) -> 0 | N6: =600 * '02_Inputs'!A11 * (1.005^12) -> 0 | O6: =600 * '02_Inputs'!B11 * (1.005^13) -> 0 | P6: =600 * '02_Inputs'!C11 * (1.005^14) -> 0 | Q6: =600 * '02_Inputs'!D11 * (1.005^15) -> 0 | R6: =600 * '02_Inputs'!E11 * (1.005^16) -> 0 | S6: =600 * '02_Inputs'!F11 * (1.005^17) -> 0 | T6: =600 * '02_Inputs'!G11 * (1.005^18) -> 0 | U6: =600 * '02_Inputs'!H11 * (1.005^19) -> 0 | V6: =600 * '02_Inputs'!I11 * (1.005^20) -> 0 | W6: =600 * '02_Inputs'!J11 * (1.005^21) -> 0 | X6: =600 * '02_Inputs'!K11 * (1.005^22) -> 0 | Y6: =600 * '02_Inputs'!L11 * (1.005^23) -> 0 | Z6: =600 * '02_Inputs'!A11 * (1.005^24) -> 0 | AA6: =600 * '02_Inputs'!B11 * (1.005^25) -> 0 | AB6: =600 * '02_Inputs'!C11 * (1.005^26) -> 0 | AC6: =600 * '02_Inputs'!D11 * (1.005^27) -> 0 | AD6: =600 * '02_Inputs'!E11 * (1.005^28) -> 0 | AE6: =600 * '02_Inputs'!F11 * (1.005^29) -> 0 | AF6: =600 * '02_Inputs'!G11 * (1.005^30) -> 0 | AG6: =600 * '02_Inputs'!H11 * (1.005^31) -> 0 | AH6: =600 * '02_Inputs'!I11 * (1.005^32) -> 0 | AI6: =600 * '02_Inputs'!J11 * (1.005^33) -> 0 | AJ6: =600 * '02_Inputs'!K11 * (1.005^34) -> 0 | AK6: =600 * '02_Inputs'!L11 * (1.005^35) -> 0 | AL6: =600 * '02_Inputs'!A11 * (1.005^36) -> 0 | AM6: =600 * '02_Inputs'!B11 * (1.005^37) -> 0 | AN6: =600 * '02_Inputs'!C11 * (1.005^38) -> 0 | AO6: =600 * '02_Inputs'!D11 * (1.005^39) -> 0 | AP6: =600 * '02_Inputs'!E11 * (1.005^40) -> 0 | AQ6: =600 * '02_Inputs'!F11 * (1.005^41) -> 0 | AR6: =600 * '02_Inputs'!G11 * (1.005^42) -> 0 | AS6: =600 * '02_Inputs'!H11 * (1.005^43) -> 0 | AT6: =600 * '02_Inputs'!I11 * (1.005^44) -> 0 | AU6: =600 * '02_Inputs'!J11 * (1.005^45) -> 0 | AV6: =600 * '02_Inputs'!K11 * (1.005^46) -> 0 | AW6: =600 * '02_Inputs'!L11 * (1.005^47) -> 0 | AX6: =600 * '02_Inputs'!A11 * (1.005^48) -> 0 | AY6: =600 * '02_Inputs'!B11 * (1.005^49) -> 0 | AZ6: =600 * '02_Inputs'!C11 * (1.005^50) -> 0 | BA6: =600 * '02_Inputs'!D11 * (1.005^51) -> 0 | BB6: =600 * '02_Inputs'!E11 * (1.005^52) -> 0 | BC6: =600 * '02_Inputs'!F11 * (1.005^53) -> 0 | BD6: =600 * '02_Inputs'!G11 * (1.005^54) -> 0 | BE6: =600 * '02_Inputs'!H11 * (1.005^55) -> 0 | BF6: =600 * '02_Inputs'!I11 * (1.005^56) -> 0 | BG6: =600 * '02_Inputs'!J11 * (1.005^57) -> 0 | BH6: =600 * '02_Inputs'!K11 * (1.005^58) -> 0 | BI6: =600 * '02_Inputs'!L11 * (1.005^59) -> 0
A7: Hops Smash IPA | B7: =300 * '02_Inputs'!A11 * (1.005^0) -> 0 | C7: =300 * '02_Inputs'!B11 * (1.005^1) -> 0 | D7: =300 * '02_Inputs'!C11 * (1.005^2) -> 0 | E7: =300 * '02_Inputs'!D11 * (1.005^3) -> 0 | F7: =300 * '02_Inputs'!E11 * (1.005^4) -> 0 | G7: =300 * '02_Inputs'!F11 * (1.005^5) -> 0 | H7: =300 * '02_Inputs'!G11 * (1.005^6) -> 0 | I7: =300 * '02_Inputs'!H11 * (1.005^7) -> 0 | J7: =300 * '02_Inputs'!I11 * (1.005^8) -> 0 | K7: =300 * '02_Inputs'!J11 * (1.005^9) -> 0 | L7: =300 * '02_Inputs'!K11 * (1.005^10) -> 0 | M7: =300 * '02_Inputs'!L11 * (1.005^11) -> 0 | N7: =300 * '02_Inputs'!A11 * (1.005^12) -> 0 | O7: =300 * '02_Inputs'!B11 * (1.005^13) -> 0 | P7: =300 * '02_Inputs'!C11 * (1.005^14) -> 0 | Q7: =300 * '02_Inputs'!D11 * (1.005^15) -> 0 | R7: =300 * '02_Inputs'!E11 * (1.005^16) -> 0 | S7: =300 * '02_Inputs'!F11 * (1.005^17) -> 0 | T7: =300 * '02_Inputs'!G11 * (1.005^18) -> 0 | U7: =300 * '02_Inputs'!H11 * (1.005^19) -> 0 | V7: =300 * '02_Inputs'!I11 * (1.005^20) -> 0 | W7: =300 * '02_Inputs'!J11 * (1.005^21) -> 0 | X7: =300 * '02_Inputs'!K11 * (1.005^22) -> 0 | Y7: =300 * '02_Inputs'!L11 * (1.005^23) -> 0 | Z7: =300 * '02_Inputs'!A11 * (1.005^24) -> 0 | AA7: =300 * '02_Inputs'!B11 * (1.005^25) -> 0 | AB7: =300 * '02_Inputs'!C11 * (1.005^26) -> 0 | AC7: =300 * '02_Inputs'!D11 * (1.005^27) -> 0 | AD7: =300 * '02_Inputs'!E11 * (1.005^28) -> 0 | AE7: =300 * '02_Inputs'!F11 * (1.005^29) -> 0 | AF7: =300 * '02_Inputs'!G11 * (1.005^30) -> 0 | AG7: =300 * '02_Inputs'!H11 * (1.005^31) -> 0 | AH7: =300 * '02_Inputs'!I11 * (1.005^32) -> 0 | AI7: =300 * '02_Inputs'!J11 * (1.005^33) -> 0 | AJ7: =300 * '02_Inputs'!K11 * (1.005^34) -> 0 | AK7: =300 * '02_Inputs'!L11 * (1.005^35) -> 0 | AL7: =300 * '02_Inputs'!A11 * (1.005^36) -> 0 | AM7: =300 * '02_Inputs'!B11 * (1.005^37) -> 0 | AN7: =300 * '02_Inputs'!C11 * (1.005^38) -> 0 | AO7: =300 * '02_Inputs'!D11 * (1.005^39) -> 0 | AP7: =300 * '02_Inputs'!E11 * (1.005^40) -> 0 | AQ7: =300 * '02_Inputs'!F11 * (1.005^41) -> 0 | AR7: =300 * '02_Inputs'!G11 * (1.005^42) -> 0 | AS7: =300 * '02_Inputs'!H11 * (1.005^43) -> 0 | AT7: =300 * '02_Inputs'!I11 * (1.005^44) -> 0 | AU7: =300 * '02_Inputs'!J11 * (1.005^45) -> 0 | AV7: =300 * '02_Inputs'!K11 * (1.005^46) -> 0 | AW7: =300 * '02_Inputs'!L11 * (1.005^47) -> 0 | AX7: =300 * '02_Inputs'!A11 * (1.005^48) -> 0 | AY7: =300 * '02_Inputs'!B11 * (1.005^49) -> 0 | AZ7: =300 * '02_Inputs'!C11 * (1.005^50) -> 0 | BA7: =300 * '02_Inputs'!D11 * (1.005^51) -> 0 | BB7: =300 * '02_Inputs'!E11 * (1.005^52) -> 0 | BC7: =300 * '02_Inputs'!F11 * (1.005^53) -> 0 | BD7: =300 * '02_Inputs'!G11 * (1.005^54) -> 0 | BE7: =300 * '02_Inputs'!H11 * (1.005^55) -> 0 | BF7: =300 * '02_Inputs'!I11 * (1.005^56) -> 0 | BG7: =300 * '02_Inputs'!J11 * (1.005^57) -> 0 | BH7: =300 * '02_Inputs'!K11 * (1.005^58) -> 0 | BI7: =300 * '02_Inputs'!L11 * (1.005^59) -> 0
A8: Night Owl Stout | B8: =150 * '02_Inputs'!A11 * (1.005^0) -> 0 | C8: =150 * '02_Inputs'!B11 * (1.005^1) -> 0 | D8: =150 * '02_Inputs'!C11 * (1.005^2) -> 0 | E8: =150 * '02_Inputs'!D11 * (1.005^3) -> 0 | F8: =150 * '02_Inputs'!E11 * (1.005^4) -> 0 | G8: =150 * '02_Inputs'!F11 * (1.005^5) -> 0 | H8: =150 * '02_Inputs'!G11 * (1.005^6) -> 0 | I8: =150 * '02_Inputs'!H11 * (1.005^7) -> 0 | J8: =150 * '02_Inputs'!I11 * (1.005^8) -> 0 | K8: =150 * '02_Inputs'!J11 * (1.005^9) -> 0 | L8: =150 * '02_Inputs'!K11 * (1.005^10) -> 0 | M8: =150 * '02_Inputs'!L11 * (1.005^11) -> 0 | N8: =150 * '02_Inputs'!A11 * (1.005^12) -> 0 | O8: =150 * '02_Inputs'!B11 * (1.005^13) -> 0 | P8: =150 * '02_Inputs'!C11 * (1.005^14) -> 0 | Q8: =150 * '02_Inputs'!D11 * (1.005^15) -> 0 | R8: =150 * '02_Inputs'!E11 * (1.005^16) -> 0 | S8: =150 * '02_Inputs'!F11 * (1.005^17) -> 0 | T8: =150 * '02_Inputs'!G11 * (1.005^18) -> 0 | U8: =150 * '02_Inputs'!H11 * (1.005^19) -> 0 | V8: =150 * '02_Inputs'!I11 * (1.005^20) -> 0 | W8: =150 * '02_Inputs'!J11 * (1.005^21) -> 0 | X8: =150 * '02_Inputs'!K11 * (1.005^22) -> 0 | Y8: =150 * '02_Inputs'!L11 * (1.005^23) -> 0 | Z8: =150 * '02_Inputs'!A11 * (1.005^24) -> 0 | AA8: =150 * '02_Inputs'!B11 * (1.005^25) -> 0 | AB8: =150 * '02_Inputs'!C11 * (1.005^26) -> 0 | AC8: =150 * '02_Inputs'!D11 * (1.005^27) -> 0 | AD8: =150 * '02_Inputs'!E11 * (1.005^28) -> 0 | AE8: =150 * '02_Inputs'!F11 * (1.005^29) -> 0 | AF8: =150 * '02_Inputs'!G11 * (1.005^30) -> 0 | AG8: =150 * '02_Inputs'!H11 * (1.005^31) -> 0 | AH8: =150 * '02_Inputs'!I11 * (1.005^32) -> 0 | AI8: =150 * '02_Inputs'!J11 * (1.005^33) -> 0 | AJ8: =150 * '02_Inputs'!K11 * (1.005^34) -> 0 | AK8: =150 * '02_Inputs'!L11 * (1.005^35) -> 0 | AL8: =150 * '02_Inputs'!A11 * (1.005^36) -> 0 | AM8: =150 * '02_Inputs'!B11 * (1.005^37) -> 0 | AN8: =150 * '02_Inputs'!C11 * (1.005^38) -> 0 | AO8: =150 * '02_Inputs'!D11 * (1.005^39) -> 0 | AP8: =150 * '02_Inputs'!E11 * (1.005^40) -> 0 | AQ8: =150 * '02_Inputs'!F11 * (1.005^41) -> 0 | AR8: =150 * '02_Inputs'!G11 * (1.005^42) -> 0 | AS8: =150 * '02_Inputs'!H11 * (1.005^43) -> 0 | AT8: =150 * '02_Inputs'!I11 * (1.005^44) -> 0 | AU8: =150 * '02_Inputs'!J11 * (1.005^45) -> 0 | AV8: =150 * '02_Inputs'!K11 * (1.005^46) -> 0 | AW8: =150 * '02_Inputs'!L11 * (1.005^47) -> 0 | AX8: =150 * '02_Inputs'!A11 * (1.005^48) -> 0 | AY8: =150 * '02_Inputs'!B11 * (1.005^49) -> 0 | AZ8: =150 * '02_Inputs'!C11 * (1.005^50) -> 0 | BA8: =150 * '02_Inputs'!D11 * (1.005^51) -> 0 | BB8: =150 * '02_Inputs'!E11 * (1.005^52) -> 0 | BC8: =150 * '02_Inputs'!F11 * (1.005^53) -> 0 | BD8: =150 * '02_Inputs'!G11 * (1.005^54) -> 0 | BE8: =150 * '02_Inputs'!H11 * (1.005^55) -> 0 | BF8: =150 * '02_Inputs'!I11 * (1.005^56) -> 0 | BG8: =150 * '02_Inputs'!J11 * (1.005^57) -> 0 | BH8: =150 * '02_Inputs'!K11 * (1.005^58) -> 0 | BI8: =150 * '02_Inputs'!L11 * (1.005^59) -> 0
A9: Summer Ale | B9: =400 * '02_Inputs'!A11 * (1.005^0) -> 0 | C9: =400 * '02_Inputs'!B11 * (1.005^1) -> 0 | D9: =400 * '02_Inputs'!C11 * (1.005^2) -> 0 | E9: =400 * '02_Inputs'!D11 * (1.005^3) -> 0 | F9: =400 * '02_Inputs'!E11 * (1.005^4) -> 0 | G9: =400 * '02_Inputs'!F11 * (1.005^5) -> 0 | H9: =400 * '02_Inputs'!G11 * (1.005^6) -> 0 | I9: =400 * '02_Inputs'!H11 * (1.005^7) -> 0 | J9: =400 * '02_Inputs'!I11 * (1.005^8) -> 0 | K9: =400 * '02_Inputs'!J11 * (1.005^9) -> 0 | L9: =400 * '02_Inputs'!K11 * (1.005^10) -> 0 | M9: =400 * '02_Inputs'!L11 * (1.005^11) -> 0 | N9: =400 * '02_Inputs'!A11 * (1.005^12) -> 0 | O9: =400 * '02_Inputs'!B11 * (1.005^13) -> 0 | P9: =400 * '02_Inputs'!C11 * (1.005^14) -> 0 | Q9: =400 * '02_Inputs'!D11 * (1.005^15) -> 0 | R9: =400 * '02_Inputs'!E11 * (1.005^16) -> 0 | S9: =400 * '02_Inputs'!F11 * (1.005^17) -> 0 | T9: =400 * '02_Inputs'!G11 * (1.005^18) -> 0 | U9: =400 * '02_Inputs'!H11 * (1.005^19) -> 0 | V9: =400 * '02_Inputs'!I11 * (1.005^20) -> 0 | W9: =400 * '02_Inputs'!J11 * (1.005^21) -> 0 | X9: =400 * '02_Inputs'!K11 * (1.005^22) -> 0 | Y9: =400 * '02_Inputs'!L11 * (1.005^23) -> 0 | Z9: =400 * '02_Inputs'!A11 * (1.005^24) -> 0 | AA9: =400 * '02_Inputs'!B11 * (1.005^25) -> 0 | AB9: =400 * '02_Inputs'!C11 * (1.005^26) -> 0 | AC9: =400 * '02_Inputs'!D11 * (1.005^27) -> 0 | AD9: =400 * '02_Inputs'!E11 * (1.005^28) -> 0 | AE9: =400 * '02_Inputs'!F11 * (1.005^29) -> 0 | AF9: =400 * '02_Inputs'!G11 * (1.005^30) -> 0 | AG9: =400 * '02_Inputs'!H11 * (1.005^31) -> 0 | AH9: =400 * '02_Inputs'!I11 * (1.005^32) -> 0 | AI9: =400 * '02_Inputs'!J11 * (1.005^33) -> 0 | AJ9: =400 * '02_Inputs'!K11 * (1.005^34) -> 0 | AK9: =400 * '02_Inputs'!L11 * (1.005^35) -> 0 | AL9: =400 * '02_Inputs'!A11 * (1.005^36) -> 0 | AM9: =400 * '02_Inputs'!B11 * (1.005^37) -> 0 | AN9: =400 * '02_Inputs'!C11 * (1.005^38) -> 0 | AO9: =400 * '02_Inputs'!D11 * (1.005^39) -> 0 | AP9: =400 * '02_Inputs'!E11 * (1.005^40) -> 0 | AQ9: =400 * '02_Inputs'!F11 * (1.005^41) -> 0 | AR9: =400 * '02_Inputs'!G11 * (1.005^42) -> 0 | AS9: =400 * '02_Inputs'!H11 * (1.005^43) -> 0 | AT9: =400 * '02_Inputs'!I11 * (1.005^44) -> 0 | AU9: =400 * '02_Inputs'!J11 * (1.005^45) -> 0 | AV9: =400 * '02_Inputs'!K11 * (1.005^46) -> 0 | AW9: =400 * '02_Inputs'!L11 * (1.005^47) -> 0 | AX9: =400 * '02_Inputs'!A11 * (1.005^48) -> 0 | AY9: =400 * '02_Inputs'!B11 * (1.005^49) -> 0 | AZ9: =400 * '02_Inputs'!C11 * (1.005^50) -> 0 | BA9: =400 * '02_Inputs'!D11 * (1.005^51) -> 0 | BB9: =400 * '02_Inputs'!E11 * (1.005^52) -> 0 | BC9: =400 * '02_Inputs'!F11 * (1.005^53) -> 0 | BD9: =400 * '02_Inputs'!G11 * (1.005^54) -> 0 | BE9: =400 * '02_Inputs'!H11 * (1.005^55) -> 0 | BF9: =400 * '02_Inputs'!I11 * (1.005^56) -> 0 | BG9: =400 * '02_Inputs'!J11 * (1.005^57) -> 0 | BH9: =400 * '02_Inputs'!K11 * (1.005^58) -> 0 | BI9: =400 * '02_Inputs'!L11 * (1.005^59) -> 0
A10: Barrel Aged Ltd | B10: =80 * '02_Inputs'!A11 * (1.005^0) -> 0 | C10: =80 * '02_Inputs'!B11 * (1.005^1) -> 0 | D10: =80 * '02_Inputs'!C11 * (1.005^2) -> 0 | E10: =80 * '02_Inputs'!D11 * (1.005^3) -> 0 | F10: =80 * '02_Inputs'!E11 * (1.005^4) -> 0 | G10: =80 * '02_Inputs'!F11 * (1.005^5) -> 0 | H10: =80 * '02_Inputs'!G11 * (1.005^6) -> 0 | I10: =80 * '02_Inputs'!H11 * (1.005^7) -> 0 | J10: =80 * '02_Inputs'!I11 * (1.005^8) -> 0 | K10: =80 * '02_Inputs'!J11 * (1.005^9) -> 0 | L10: =80 * '02_Inputs'!K11 * (1.005^10) -> 0 | M10: =80 * '02_Inputs'!L11 * (1.005^11) -> 0 | N10: =80 * '02_Inputs'!A11 * (1.005^12) -> 0 | O10: =80 * '02_Inputs'!B11 * (1.005^13) -> 0 | P10: =80 * '02_Inputs'!C11 * (1.005^14) -> 0 | Q10: =80 * '02_Inputs'!D11 * (1.005^15) -> 0 | R10: =80 * '02_Inputs'!E11 * (1.005^16) -> 0 | S10: =80 * '02_Inputs'!F11 * (1.005^17) -> 0 | T10: =80 * '02_Inputs'!G11 * (1.005^18) -> 0 | U10: =80 * '02_Inputs'!H11 * (1.005^19) -> 0 | V10: =80 * '02_Inputs'!I11 * (1.005^20) -> 0 | W10: =80 * '02_Inputs'!J11 * (1.005^21) -> 0 | X10: =80 * '02_Inputs'!K11 * (1.005^22) -> 0 | Y10: =80 * '02_Inputs'!L11 * (1.005^23) -> 0 | Z10: =80 * '02_Inputs'!A11 * (1.005^24) -> 0 | AA10: =80 * '02_Inputs'!B11 * (1.005^25) -> 0 | AB10: =80 * '02_Inputs'!C11 * (1.005^26) -> 0 | AC10: =80 * '02_Inputs'!D11 * (1.005^27) -> 0 | AD10: =80 * '02_Inputs'!E11 * (1.005^28) -> 0 | AE10: =80 * '02_Inputs'!F11 * (1.005^29) -> 0 | AF10: =80 * '02_Inputs'!G11 * (1.005^30) -> 0 | AG10: =80 * '02_Inputs'!H11 * (1.005^31) -> 0 | AH10: =80 * '02_Inputs'!I11 * (1.005^32) -> 0 | AI10: =80 * '02_Inputs'!J11 * (1.005^33) -> 0 | AJ10: =80 * '02_Inputs'!K11 * (1.005^34) -> 0 | AK10: =80 * '02_Inputs'!L11 * (1.005^35) -> 0 | AL10: =80 * '02_Inputs'!A11 * (1.005^36) -> 0 | AM10: =80 * '02_Inputs'!B11 * (1.005^37) -> 0 | AN10: =80 * '02_Inputs'!C11 * (1.005^38) -> 0 | AO10: =80 * '02_Inputs'!D11 * (1.005^39) -> 0 | AP10: =80 * '02_Inputs'!E11 * (1.005^40) -> 0 | AQ10: =80 * '02_Inputs'!F11 * (1.005^41) -> 0 | AR10: =80 * '02_Inputs'!G11 * (1.005^42) -> 0 | AS10: =80 * '02_Inputs'!H11 * (1.005^43) -> 0 | AT10: =80 * '02_Inputs'!I11 * (1.005^44) -> 0 | AU10: =80 * '02_Inputs'!J11 * (1.005^45) -> 0 | AV10: =80 * '02_Inputs'!K11 * (1.005^46) -> 0 | AW10: =80 * '02_Inputs'!L11 * (1.005^47) -> 0 | AX10: =80 * '02_Inputs'!A11 * (1.005^48) -> 0 | AY10: =80 * '02_Inputs'!B11 * (1.005^49) -> 0 | AZ10: =80 * '02_Inputs'!C11 * (1.005^50) -> 0 | BA10: =80 * '02_Inputs'!D11 * (1.005^51) -> 0 | BB10: =80 * '02_Inputs'!E11 * (1.005^52) -> 0 | BC10: =80 * '02_Inputs'!F11 * (1.005^53) -> 0 | BD10: =80 * '02_Inputs'!G11 * (1.005^54) -> 0 | BE10: =80 * '02_Inputs'!H11 * (1.005^55) -> 0 | BF10: =80 * '02_Inputs'!I11 * (1.005^56) -> 0 | BG10: =80 * '02_Inputs'!J11 * (1.005^57) -> 0 | BH10: =80 * '02_Inputs'!K11 * (1.005^58) -> 0 | BI10: =80 * '02_Inputs'!L11 * (1.005^59) -> 0
A11: Total Volume HL | B11: =SUM(B5:B10) -> 0 | C11: =SUM(C5:C10) -> 0 | D11: =SUM(D5:D10) -> 0 | E11: =SUM(E5:E10) -> 0 | F11: =SUM(F5:F10) -> 0 | G11: =SUM(G5:G10) -> 0 | H11: =SUM(H5:H10) -> 0 | I11: =SUM(I5:I10) -> 0 | ... BI11: =SUM(BI5:BI10) -> 0
A13: Net Revenue | B13: =B5*('02_Inputs'!$B$13*420+(1-'02_Inputs'!$B$13)*380)*0.85 + B6*('02_Inputs'!$B$13*550+(1-'02_Inputs'!$B$13)*480)*0.85 + B7*('02_Inputs'!$B$13*680+(1-'02_Inputs'!$B$13)*600)*0.85 + B8*('02_Inputs'!$B$13*620+(1-'02_Inputs'!$B$13)*540)*0.85 + B9*('02_Inputs'!$B$13*480+(1-'02_Inputs'!$B$13)*420)*0.85 + B10*('02_Inputs'!$B$13*980+(1-'02_Inputs'!$B$13)*880)*0.85 -> 0 | C13: =C5*('02_Inputs'!$B$13*420+(1-'02_Inputs'!$B$13)*380)*0.85 + C6*('02_Inputs'!$B$13*550+(1-'02_Inputs'!$B$13)*480)*0.85 + C7*('02_Inputs'!$B$13*680+(1-'02_Inputs'!$B$13)*600)*0.85 + C8*('02_Inputs'!$B$13*620+(1-'02_Inputs'!$B$13)*540)*0.85 + C9*('02_Inputs'!$B$13*480+(1-'02_Inputs'!$B$13)*420)*0.85 + C10*('02_Inputs'!$B$13*980+(1-'02_Inputs'!$B$13)*880)*0.85 -> 0 | D13: =D5*('02_Inputs'!$B$13*420+(1-'02_Inputs'!$B$13)*380)*0.85 + D6*('02_Inputs'!$B$13*550+(1-'02_Inputs'!$B$13)*480)*0.85 + D7*('02_Inputs'!$B$13*680+(1-'02_Inputs'!$B$13)*600)*0.85 + D8*('02_Inputs'!$B$13*620+(1-'02_Inputs'!$B$13)*540)*0.85 + D9*('02_Inputs'!$B$13*480+(1-'02_Inputs'!$B$13)*420)*0.85 + D10*('02_Inputs'!$B$13*980+(1-'02_Inputs'!$B$13)*880)*0.85 -> 0 | E13: =E5*('02_Inputs'!$B$13*420+(1-'02_Inputs'!$B$13)*380)*0.85 + E6*('02_Inputs'!$B$13*550+(1-'02_Inputs'!$B$13)*480)*0.85 + E7*('02_Inputs'!$B$13*680+(1-'02_Inputs'!$B$13)*600)*0.85 + E8*('02_Inputs'!$B$13*620+(1-'02_Inputs'!$B$13)*540)*0.85 + E9*('02_Inputs'!$B$13*480+(1-'02_Inputs'!$B$13)*420)*0.85 + E10*('02_Inputs'!$B$13*980+(1-'02_Inputs'!$B$13)*880)*0.85 -> 0 | F13: =F5*('02_Inputs'!$B$13*420+(1-'02_Inputs'!$B$13)*380)*0.85 + F6*('02_Inputs'!$B$13*550+(1-'02_Inputs'!$B$13)*480)*0.85 + F7*('02_Inputs'!$B$13*680+(1-'02_Inputs'!$B$13)*600)*0.85 + F8*('02_Inputs'!$B$13*620+(1-'02_Inputs'!$B$13)*540)*0.85 + F9*('02_Inputs'!$B$13*480+(1-'02_Inputs'!$B$13)*420)*0.85 + F10*('02_Inputs'!$B$13*980+(1-'02_Inputs'!$B$13)*880)*0.85 -> 0 | G13: =G5*('02_Inputs'!$B$13*420+(1-'02_Inputs'!$B$13)*380)*0.85 + G6*('02_Inputs'!$B$13*550+(1-'02_Inputs'!$B$13)*480)*0.85 + G7*('02_Inputs'!$B$13*680+(1-'02_Inputs'!$B$13)*600)*0.85 + G8*('02_Inputs'!$B$13*620+(1-'02_Inputs'!$B$13)*540)*0.85 + G9*('02_Inputs'!$B$13*480+(1-'02_Inputs'!$B$13)*420)*0.85 + G10*('02_Inputs'!$B$13*980+(1-'02_Inputs'!$B$13)*880)*0.85 -> 0 | H13: =H5*('02_Inputs'!$B$13*420+(1-'02_Inputs'!$B$13)*380)*0.85 + H6*('02_Inputs'!$B$13*550+(1-'02_Inputs'!$B$13)*480)*0.85 + H7*('02_Inputs'!$B$13*680+(1-'02_Inputs'!$B$13)*600)*0.85 + H8*('02_Inputs'!$B$13*620+(1-'02_Inputs'!$B$13)*540)*0.85 + H9*('02_Inputs'!$B$13*480+(1-'02_Inputs'!$B$13)*420)*0.85 + H10*('02_Inputs'!$B$13*980+(1-'02_Inputs'!$B$13)*880)*0.85 -> 0 | I13: =I5*('02_Inputs'!$B$13*420+(1-'02_Inputs'!$B$13)*380)*0.85 + I6*('02_Inputs'!$B$13*550+(1-'02_Inputs'!$B$13)*480)*0.85 + I7*('02_Inputs'!$B$13*680+(1-'02_Inputs'!$B$13)*600)*0.85 + I8*('02_Inputs'!$B$13*620+(1-'02_Inputs'!$B$13)*540)*0.85 + I9*('02_Inputs'!$B$13*480+(1-'02_Inputs'!$B$13)*420)*0.85 + I10*('02_Inputs'!$B$13*980+(1-'02_Inputs'!$B$13)*880)*0.85 -> 0 | ... BI13: =BI5*('02_Inputs'!$B$13*420+(1-'02_Inputs'!$B$13)*380)*0.85 + BI6*('02_Inputs'!$B$13*550+(1-'02_Inputs'!$B$13)*480)*0.85 + BI7*('02_Inputs'!$B$13*680+(1-'02_Inputs'!$B$13)*600)*0.85 + BI8*('02_Inputs'!$B$13*620+(1-'02_Inputs'!$B$13)*540)*0.85 + BI9*('02_Inputs'!$B$13*480+(1-'02_Inputs'!$B$13)*420)*0.85 + BI10*('02_Inputs'!$B$13*980+(1-'02_Inputs'!$B$13)*880)*0.85 -> 0
A15: Total COGS | B15: =(B5*17*(1/(1-'02_Inputs'!$B$12))*'02_Inputs'!$B$6 + B5*0.15*(1/(1-'02_Inputs'!$B$12))*'02_Inputs'!$B$7) + (B6*20*(1/(1-'02_Inputs'!$B$12))*'02_Inputs'!$B$6 + B6*0.5*(1/(1-'02_Inputs'!$B$12))*'02_Inputs'!$B$7) + (B7*23*(1/(1-'02_Inputs'!$B$12))*'02_Inputs'!$B$6 + B7*1.1*(1/(1-'02_Inputs'!$B$12))*'02_Inputs'!$B$7) + (B8*25*(1/(1-'02_Inputs'!$B$12))*'02_Inputs'!$B$6 + B8*0.4*(1/(1-'02_Inputs'!$B$12))*'02_Inputs'!$B$7) + (B9*16*(1/(1-'02_Inputs'!$B$12))*'02_Inputs'!$B$6 + B9*0.35*(1/(1-'02_Inputs'!$B$12))*'02_Inputs'!$B$7) + (B10*30*(1/(1-'02_Inputs'!$B$12))*'02_Inputs'!$B$6 + B10*0.7*(1/(1-'02_Inputs'!$B$12))*'02_Inputs'!$B$7) + B11*75 -> 0 | C15: =(C5*17*(1/(1-'02_Inputs'!$B$12))*'02_Inputs'!$B$6 + C5*0.15*(1/(1-'02_Inputs'!$B$12))*'02_Inputs'!$B$7) + (C6*20*(1/(1-'02_Inputs'!$B$12))*'02_Inputs'!$B$6 + C6*0.5*(1/(1-'02_Inputs'!$B$12))*'02_Inputs'!$B$7) + (C7*23*(1/(1-'02_Inputs'!$B$12))*'02_Inputs'!$B$6 + C7*1.1*(1/(1-'02_Inputs'!$B$12))*'02_Inputs'!$B$7) + (C8*25*(1/(1-'02_Inputs'!$B$12))*'02_Inputs'!$B$6 + C8*0.4*(1/(1-'02_Inputs'!$B$12))*'02_Inputs'!$B$7) + (C9*16*(1/(1-'02_Inputs'!$B$12))*'02_Inputs'!$B$6 + C9*0.35*(1/(1-'02_Inputs'!$B$12))*'02_Inputs'!$B$7) + (C10*30*(1/(1-'02_Inputs'!$B$12))*'02_Inputs'!$B$6 + C10*0.7*(1/(1-'02_Inputs'!$B$12))*'02_Inputs'!$B$7) + C11*75 -> 0 | D15: =(D5*17*(1/(1-'02_Inputs'!$B$12))*'02_Inputs'!$B$6 + D5*0.15*(1/(1-'02_Inputs'!$B$12))*'02_Inputs'!$B$7) + (D6*20*(1/(1-'02_Inputs'!$B$12))*'02_Inputs'!$B$6 + D6*0.5*(1/(1-'02_Inputs'!$B$12))*'02_Inputs'!$B$7) + (D7*23*(1/(1-'02_Inputs'!$B$12))*'02_Inputs'!$B$6 + D7*1.1*(1/(1-'02_Inputs'!$B$12))*'02_Inputs'!$B$7) + (D8*25*(1/(1-'02_Inputs'!$B$12))*'02_Inputs'!$B$6 + D8*0.4*(1/(1-'02_Inputs'!$B$12))*'02_Inputs'!$B$7) + (D9*16*(1/(1-'02_Inputs'!$B$12))*'02_Inputs'!$B$6 + D9*0.35*(1/(1-'02_Inputs'!$B$12))*'02_Inputs'!$B$7) + (D10*30*(1/(1-'02_Inputs'!$B$12))*'02_Inputs'!$B$6 + D10*0.7*(1/(1-'02_Inputs'!$B$12))*'02_Inputs'!$B$7) + D11*75 -> 0 | E15: =(E5*17*(1/(1-'02_Inputs'!$B$12))*'02_Inputs'!$B$6 + E5*0.15*(1/(1-'02_Inputs'!$B$12))*'02_Inputs'!$B$7) + (E6*20*(1/(1-'02_Inputs'!$B$12))*'02_Inputs'!$B$6 + E6*0.5*(1/(1-'02_Inputs'!$B$12))*'02_Inputs'!$B$7) + (E7*23*(1/(1-'02_Inputs'!$B$12))*'02_Inputs'!$B$6 + E7*1.1*(1/(1-'02_Inputs'!$B$12))*'02_Inputs'!$B$7) + (E8*25*(1/(1-'02_Inputs'!$B$12))*'02_Inputs'!$B$6 + E8*0.4*(1/(1-'02_Inputs'!$B$12))*'02_Inputs'!$B$7) + (E9*16*(1/(1-'02_Inputs'!$B$12))*'02_Inputs'!$B$6 + E9*0.35*(1/(1-'02_Inputs'!$B$12))*'02_Inputs'!$B$7) + (E10*30*(1/(1-'02_Inputs'!$B$12))*'02_Inputs'!$B$6 + E10*0.7*(1/(1-'02_Inputs'!$B$12))*'02_Inputs'!$B$7) + E11*75 -> 0 | F15: =(F5*17*(1/(1-'02_Inputs'!$B$12))*'02_Inputs'!$B$6 + F5*0.15*(1/(1-'02_Inputs'!$B$12))*'02_Inputs'!$B$7) + (F6*20*(1/(1-'02_Inputs'!$B$12))*'02_Inputs'!$B$6 + F6*0.5*(1/(1-'02_Inputs'!$B$12))*'02_Inputs'!$B$7) + (F7*23*(1/(1-'02_Inputs'!$B$12))*'02_Inputs'!$B$6 + F7*1.1*(1/(1-'02_Inputs'!$B$12))*'02_Inputs'!$B$7) + (F8*25*(1/(1-'02_Inputs'!$B$12))*'02_Inputs'!$B$6 + F8*0.4*(1/(1-'02_Inputs'!$B$12))*'02_Inputs'!$B$7) + (F9*16*(1/(1-'02_Inputs'!$B$12))*'02_Inputs'!$B$6 + F9*0.35*(1/(1-'02_Inputs'!$B$12))*'02_Inputs'!$B$7) + (F10*30*(1/(1-'02_Inputs'!$B$12))*'02_Inputs'!$B$6 + F10*0.7*(1/(1-'02_Inputs'!$B$12))*'02_Inputs'!$B$7) + F11*75 -> 0 | G15: =(G5*17*(1/(1-'02_Inputs'!$B$12))*'02_Inputs'!$B$6 + G5*0.15*(1/(1-'02_Inputs'!$B$12))*'02_Inputs'!$B$7) + (G6*20*(1/(1-'02_Inputs'!$B$12))*'02_Inputs'!$B$6 + G6*0.5*(1/(1-'02_Inputs'!$B$12))*'02_Inputs'!$B$7) + (G7*23*(1/(1-'02_Inputs'!$B$12))*'02_Inputs'!$B$6 + G7*1.1*(1/(1-'02_Inputs'!$B$12))*'02_Inputs'!$B$7) + (G8*25*(1/(1-'02_Inputs'!$B$12))*'02_Inputs'!$B$6 + G8*0.4*(1/(1-'02_Inputs'!$B$12))*'02_Inputs'!$B$7) + (G9*16*(1/(1-'02_Inputs'!$B$12))*'02_Inputs'!$B$6 + G9*0.35*(1/(1-'02_Inputs'!$B$12))*'02_Inputs'!$B$7) + (G10*30*(1/(1-'02_Inputs'!$B$12))*'02_Inputs'!$B$6 + G10*0.7*(1/(1-'02_Inputs'!$B$12))*'02_Inputs'!$B$7) + G11*75 -> 0 | H15: =(H5*17*(1/(1-'02_Inputs'!$B$12))*'02_Inputs'!$B$6 + H5*0.15*(1/(1-'02_Inputs'!$B$12))*'02_Inputs'!$B$7) + (H6*20*(1/(1-'02_Inputs'!$B$12))*'02_Inputs'!$B$6 + H6*0.5*(1/(1-'02_Inputs'!$B$12))*'02_Inputs'!$B$7) + (H7*23*(1/(1-'02_Inputs'!$B$12))*'02_Inputs'!$B$6 + H7*1.1*(1/(1-'02_Inputs'!$B$12))*'02_Inputs'!$B$7) + (H8*25*(1/(1-'02_Inputs'!$B$12))*'02_Inputs'!$B$6 + H8*0.4*(1/(1-'02_Inputs'!$B$12))*'02_Inputs'!$B$7) + (H9*16*(1/(1-'02_Inputs'!$B$12))*'02_Inputs'!$B$6 + H9*0.35*(1/(1-'02_Inputs'!$B$12))*'02_Inputs'!$B$7) + (H10*30*(1/(1-'02_Inputs'!$B$12))*'02_Inputs'!$B$6 + H10*0.7*(1/(1-'02_Inputs'!$B$12))*'02_Inputs'!$B$7) + H11*75 -> 0 | I15: =(I5*17*(1/(1-'02_Inputs'!$B$12))*'02_Inputs'!$B$6 + I5*0.15*(1/(1-'02_Inputs'!$B$12))*'02_Inputs'!$B$7) + (I6*20*(1/(1-'02_Inputs'!$B$12))*'02_Inputs'!$B$6 + I6*0.5*(1/(1-'02_Inputs'!$B$12))*'02_Inputs'!$B$7) + (I7*23*(1/(1-'02_Inputs'!$B$12))*'02_Inputs'!$B$6 + I7*1.1*(1/(1-'02_Inputs'!$B$12))*'02_Inputs'!$B$7) + (I8*25*(1/(1-'02_Inputs'!$B$12))*'02_Inputs'!$B$6 + I8*0.4*(1/(1-'02_Inputs'!$B$12))*'02_Inputs'!$B$7) + (I9*16*(1/(1-'02_Inputs'!$B$12))*'02_Inputs'!$B$6 + I9*0.35*(1/(1-'02_Inputs'!$B$12))*'02_Inputs'!$B$7) + (I10*30*(1/(1-'02_Inputs'!$B$12))*'02_Inputs'!$B$6 + I10*0.7*(1/(1-'02_Inputs'!$B$12))*'02_Inputs'!$B$7) + I11*75 -> 0 | ... BI15: =(BI5*17*(1/(1-'02_Inputs'!$B$12))*'02_Inputs'!$B$6 + BI5*0.15*(1/(1-'02_Inputs'!$B$12))*'02_Inputs'!$B$7) + (BI6*20*(1/(1-'02_Inputs'!$B$12))*'02_Inputs'!$B$6 + BI6*0.5*(1/(1-'02_Inputs'!$B$12))*'02_Inputs'!$B$7) + (BI7*23*(1/(1-'02_Inputs'!$B$12))*'02_Inputs'!$B$6 + BI7*1.1*(1/(1-'02_Inputs'!$B$12))*'02_Inputs'!$B$7) + (BI8*25*(1/(1-'02_Inputs'!$B$12))*'02_Inputs'!$B$6 + BI8*0.4*(1/(1-'02_Inputs'!$B$12))*'02_Inputs'!$B$7) + (BI9*16*(1/(1-'02_Inputs'!$B$12))*'02_Inputs'!$B$6 + BI9*0.35*(1/(1-'02_Inputs'!$B$12))*'02_Inputs'!$B$7) + (BI10*30*(1/(1-'02_Inputs'!$B$12))*'02_Inputs'!$B$6 + BI10*0.7*(1/(1-'02_Inputs'!$B$12))*'02_Inputs'!$B$7) + BI11*75 -> 0
A17: Total OpEx | B17: =(SUMPRODUCT('02_Inputs'!$B$16:$B$19, '02_Inputs'!$C$16:$C$19)/12) + B13*0.1 -> 0 | C17: =(SUMPRODUCT('02_Inputs'!$B$16:$B$19, '02_Inputs'!$C$16:$C$19)/12) + C13*0.1 -> 0 | D17: =(SUMPRODUCT('02_Inputs'!$B$16:$B$19, '02_Inputs'!$C$16:$C$19)/12) + D13*0.1 -> 0 | E17: =(SUMPRODUCT('02_Inputs'!$B$16:$B$19, '02_Inputs'!$C$16:$C$19)/12) + E13*0.1 -> 0 | F17: =(SUMPRODUCT('02_Inputs'!$B$16:$B$19, '02_Inputs'!$C$16:$C$19)/12) + F13*0.1 -> 0 | G17: =(SUMPRODUCT('02_Inputs'!$B$16:$B$19, '02_Inputs'!$C$16:$C$19)/12) + G13*0.1 -> 0 | H17: =(SUMPRODUCT('02_Inputs'!$B$16:$B$19, '02_Inputs'!$C$16:$C$19)/12) + H13*0.1 -> 0 | I17: =(SUMPRODUCT('02_Inputs'!$B$16:$B$19, '02_Inputs'!$C$16:$C$19)/12) + I13*0.1 -> 0 | ... BI17: =(SUMPRODUCT('02_Inputs'!$B$16:$B$19, '02_Inputs'!$C$16:$C$19)/12) + BI13*0.1 -> 0

Sheet 04_Outputs
B3: M1 | C3: M2 | D3: M3 | E3: M4 | F3: M5 | G3: M6 | H3: M7 | I3: M8 | J3: M9 | K3: M10 | L3: M11 | M3: M12 | N3: Y2 | O3: Y3 | P3: Y4 | Q3: Y5
A5: INCOME STATEMENT
A6: Net Revenue | B6: =1*'03_Calcs'!B13 -> 0 | C6: =1*'03_Calcs'!C13 -> 0 | D6: =1*'03_Calcs'!D13 -> 0 | E6: =1*'03_Calcs'!E13 -> 0 | F6: =1*'03_Calcs'!F13 -> 0 | G6: =1*'03_Calcs'!G13 -> 0 | H6: =1*'03_Calcs'!H13 -> 0 | I6: =1*'03_Calcs'!I13 -> 0 | ... M6: =1*'03_Calcs'!M13 -> 0 | N6: =1*SUM('03_Calcs'!N13:Y13) -> 0 | O6: =1*SUM('03_Calcs'!Z13:AK13) -> 0 | P6: =1*SUM('03_Calcs'!AL13:AW13) -> 0 | Q6: =1*SUM('03_Calcs'!AX13:BI13) -> 0
A7: COGS | B7: =-1*'03_Calcs'!B15 -> 0 | C7: =-1*'03_Calcs'!C15 -> 0 | D7: =-1*'03_Calcs'!D15 -> 0 | E7: =-1*'03_Calcs'!E15 -> 0 | F7: =-1*'03_Calcs'!F15 -> 0 | G7: =-1*'03_Calcs'!G15 -> 0 | H7: =-1*'03_Calcs'!H15 -> 0 | I7: =-1*'03_Calcs'!I15 -> 0 | ... M7: =-1*'03_Calcs'!M15 -> 0 | N7: =-1*SUM('03_Calcs'!N15:Y15) -> 0 | O7: =-1*SUM('03_Calcs'!Z15:AK15) -> 0 | P7: =-1*SUM('03_Calcs'!AL15:AW15) -> 0 | Q7: =-1*SUM('03_Calcs'!AX15:BI15) -> 0
A8: OpEx | B8: =-1*'03_Calcs'!B17 -> 0 | C8: =-1*'03_Calcs'!C17 -> 0 | D8: =-1*'03_Calcs'!D17 -> 0 | E8: =-1*'03_Calcs'!E17 -> 0 | F8: =-1*'03_Calcs'!F17 -> 0 | G8: =-1*'03_Calcs'!G17 -> 0 | H8: =-1*'03_Calcs'!H17 -> 0 | I8: =-1*'03_Calcs'!I17 -> 0 | ... M8: =-1*'03_Calcs'!M17 -> 0 | N8: =-1*SUM('03_Calcs'!N17:Y17) -> 0 | O8: =-1*SUM('03_Calcs'!Z17:AK17) -> 0 | P8: =-1*SUM('03_Calcs'!AL17:AW17) -> 0 | Q8: =-1*SUM('03_Calcs'!AX17:BI17) -> 0
A9: EBITDA | B9: =SUM(B6:B8) -> 0 | C9: =SUM(C6:C8) -> 0 | D9: =SUM(D6:D8) -> 0 | E9: =SUM(E6:E8) -> 0 | F9: =SUM(F6:F8) -> 0 | G9: =SUM(G6:G8) -> 0 | H9: =SUM(H6:H8) -> 0 | I9: =SUM(I6:I8) -> 0 | ... Q9: =SUM(Q6:Q8) -> 0
A12: BALANCE SHEET
A13: Cash Asset | B13: =B20 -> 0 | C13: =C20 -> 0 | D13: =D20 -> 0 | E13: =E20 -> 0 | F13: =F20 -> 0 | G13: =G20 -> 0 | H13: =H20 -> 0 | I13: =I20 -> 0 | ... Q13: =Q20 -> 0
A17: CASH FLOW
A18: Net Cash Flow | B18: =B9*0.7 -> 0 | C18: =C9*0.7 -> 0 | D18: =D9*0.7 -> 0 | E18: =E9*0.7 -> 0 | F18: =F9*0.7 -> 0 | G18: =G9*0.7 -> 0 | H18: =H9*0.7 -> 0 | I18: =I9*0.7 -> 0 | ... Q18: =Q9*0.7 -> 0
A19: Opening Cash | B19: 500000 | C19: =B20 -> 0 | D19: =C20 -> 0 | E19: =D20 -> 0 | F19: =E20 -> 0 | G19: =F20 -> 0 | H19: =G20 -> 0 | I19: =H20 -> 0 | J19: =I20 -> 0 | ... Q19: =P20 -> 0
A20: Closing Cash | B20: =SUM(B18:B19) -> 0 | C20: =SUM(C18:C19) -> 0 | D20: =SUM(D18:D19) -> 0 | E20: =SUM(E18:E19) -> 0 | F20: =SUM(F18:F19) -> 0 | G20: =SUM(G18:G19) -> 0 | H20: =SUM(H18:H19) -> 0 | I20: =SUM(I18:I19) -> 0 | ... Q20: =SUM(Q18:Q19) -> 0

Sheet 05_Dashboard
A1: BREWERY KPI DASHBOARD
A4: Year 1 EBITDA | B4: =SUM('04_Outputs'!B9:M9) -> 0
