Workbook

Sheet 01_Control
A1: MODEL CONTROL PANEL
A3: Scenario Selector | B3: 1
A5: Global Rates
A6: GST Rate | B6: 0.1
A7: Corp Tax Rate | B7: 0.3
A8: Excise Packaged / LAL | B8: 60.22
A9: Excise Draught / LAL | B9: 40.5

Sheet 02_Inputs
A1: INPUTS
A5: SKU Name | B5: ABV % | C5: Price On-Trade | D5: Price Off-Trade | E5: Promo On % | F5: Promo Off % | G5: Base Vol
A6: Lager | B6: 0.042 | C6: 520 | D6: 450 | E6: 0.05 | F6: 0.12 | G6: 1000
A7: Pale Ale | B7: 0.05 | C7: 580 | D7: 500 | E7: 0.06 | F7: 0.14 | G7: 800
A8: IPA | B8: 0.065 | C8: 650 | D8: 580 | E8: 0.08 | F8: 0.15 | G8: 400
A9: Stout | B9: 0.055 | C9: 600 | D9: 530 | E9: 0.05 | F9: 0.1 | G9: 200
A10: Seasonal | B10: 0.045 | C10: 540 | D10: 470 | E10: 0.1 | F10: 0.2 | G10: 300
A11: On-Trade Split % | B11: 0.4
A12: Brewing Loss % | B12: 0.05
A13: Pack Loss % | B13: 0.02
A15: Labor Count
A17: Production | B17: 8 | C17: 80
A18: S&M | B18: 6 | C18: 105
A19: G&A | B19: 3 | C19: 115

Sheet 03_Calcs
B3: M1 | C3: M2 | D3: M3 | E3: M4 | F3: M5 | G3: M6 | H3: M7 | I3: M8 | J3: M9 | K3: M10 | L3: M11 | M3: M12 | N3: M13 | O3: M14 | P3: M15 | Q3: M16 | R3: M17 | S3: M18 | T3: M19 | U3: M20 | V3: M21 | W3: M22 | X3: M23 | Y3: M24 | Z3: M25 | AA3: M26 | AB3: M27 | AC3: M28 | AD3: M29 | AE3: M30 | AF3: M31 | AG3: M32 | AH3: M33 | AI3: M34 | AJ3: M35 | AK3: M36 | AL3: M37 | AM3: M38 | AN3: M39 | AO3: M40 | AP3: M41 | AQ3: M42 | AR3: M43 | AS3: M44 | AT3: M45 | AU3: M46 | AV3: M47 | AW3: M48 | AX3: M49 | AY3: M50 | AZ3: M51 | BA3: M52 | BB3: M53 | BC3: M54 | BD3: M55 | BE3: M56 | BF3: M57 | BG3: M58 | BH3: M59 | BI3: M60
A5: Lager | B5: ='02_Inputs'!G6 * (1.005^0) -> 0 | C5: ='02_Inputs'!G6 * (1.005^1) -> 0 | D5: ='02_Inputs'!G6 * (1.005^2) -> 0 | E5: ='02_Inputs'!G6 * (1.005^3) -> 0 | F5: ='02_Inputs'!G6 * (1.005^4) -> 0 | G5: ='02_Inputs'!G6 * (1.005^5) -> 0 | H5: ='02_Inputs'!G6 * (1.005^6) -> 0 | I5: ='02_Inputs'!G6 * (1.005^7) -> 0 | J5: ='02_Inputs'!G6 * (1.005^8) -> 0 | K5: ='02_Inputs'!G6 * (1.005^9) -> 0 | L5: ='02_Inputs'!G6 * (1.005^10) -> 0 | M5: ='02_Inputs'!G6 * (1.005^11) -> 0 | N5: ='02_Inputs'!G6 * (1.005^12) -> 0 | O5: ='02_Inputs'!G6 * (1.005^13) -> 0 | P5: ='02_Inputs'!G6 * (1.005^14) -> 0 | Q5: ='02_Inputs'!G6 * (1.005^15) -> 0 | R5: ='02_Inputs'!G6 * (1.005^16) -> 0 | S5: ='02_Inputs'!G6 * (1.005^17) -> 0 | T5: ='02_Inputs'!G6 * (1.005^18) -> 0 | U5: ='02_Inputs'!G6 * (1.005^19) -> 0 | V5: ='02_Inputs'!G6 * (1.005^20) -> 0 | W5: ='02_Inputs'!G6 * (1.005^21) -> 0 | X5: ='02_Inputs'!G6 * (1.005^22) -> 0 | Y5: ='02_Inputs'!G6 * (1.005^23) -> 0 | Z5: ='02_Inputs'!G6 * (1.005^24) -> 0 | AA5: ='02_Inputs'!G6 * (1.005^25) -> 0 | AB5: ='02_Inputs'!G6 * (1.005^26) -> 0 | AC5: ='02_Inputs'!G6 * (1.005^27) -> 0 | AD5: ='02_Inputs'!G6 * (1.005^28) -> 0 | AE5: ='02_Inputs'!G6 * (1.005^29) -> 0 | AF5: ='02_Inputs'!G6 * (1.005^30) -> 0 | AG5: ='02_Inputs'!G6 * (1.005^31) -> 0 | AH5: ='02_Inputs'!G6 * (1.005^32) -> 0 | AI5: ='02_Inputs'!G6 * (1.005^33) -> 0 | AJ5: ='02_Inputs'!G6 * (1.005^34) -> 0 | AK5: ='02_Inputs'!G6 * (1.005^35) -> 0 | AL5: ='02_Inputs'!G6 * (1.005^36) -> 0 | AM5: ='02_Inputs'!G6 * (1.005^37) -> 0 | AN5: ='02_Inputs'!G6 * (1.005^38) -> 0 | AO5: ='02_Inputs'!G6 * (1.005^39) -> 0 | AP5: ='02_Inputs'!G6 * (1.005^40) -> 0 | AQ5: ='02_Inputs'!G6 * (1.005^41) -> 0 | AR5: ='02_Inputs'!G6 * (1.005^42) -> 0 | AS5: ='02_Inputs'!G6 * (1.005^43) -> 0 | AT5: ='02_Inputs'!G6 * (1.005^44) -> 0 | AU5: ='02_Inputs'!G6 * (1.005^45) -> 0 | AV5: ='02_Inputs'!G6 * (1.005^46) -> 0 | AW5: ='02_Inputs'!G6 * (1.005^47) -> 0 | AX5: ='02_Inputs'!G6 * (1.005^48) -> 0 | AY5: ='02_Inputs'!G6 * (1.005^49) -> 0 | AZ5: ='02_Inputs'!G6 * (1.005^50) -> 0 | BA5: ='02_Inputs'!G6 * (1.005^51) -> 0 | BB5: ='02_Inputs'!G6 * (1.005^52) -> 0 | BC5: ='02_Inputs'!G6 * (1.005^53) -> 0 | BD5: ='02_Inputs'!G6 * (1.005^54) -> 0 | BE5: ='02_Inputs'!G6 * (1.005^55) -> 0 | BF5: ='02_Inputs'!G6 * (1.005^56) -> 0 | BG5: ='02_Inputs'!G6 * (1.005^57) -> 0 | BH5: ='02_Inputs'!G6 * (1.005^58) -> 0 | BI5: ='02_Inputs'!G6 * (1.005^59) -> 0
A6: Pale Ale | B6: ='02_Inputs'!G7 * (1.005^0) -> 0 | C6: ='02_Inputs'!G7 * (1.005^1) -> 0 | D6: ='02_Inputs'!G7 * (1.005^2) -> 0 | E6: ='02_Inputs'!G7 * (1.005^3) -> 0 | F6: ='02_Inputs'!G7 * (1.005^4) -> 0 | G6: ='02_Inputs'!G7 * (1.005^5) -> 0 | H6: ='02_Inputs'!G7 * (1.005^6) -> 0 | I6: ='02_Inputs'!G7 * (1.005^7) -> 0 | J6: ='02_Inputs'!G7 * (1.005^8) -> 0 | K6: ='02_Inputs'!G7 * (1.005^9) -> 0 | L6: ='02_Inputs'!G7 * (1.005^10) -> 0 | M6: ='02_Inputs'!G7 * (1.005^11) -> 0 | N6: ='02_Inputs'!G7 * (1.005^12) -> 0 | O6: ='02_Inputs'!G7 * (1.005^13) -> 0 | P6: ='02_Inputs'!G7 * (1.005^14) -> 0 | Q6: ='02_Inputs'!G7 * (1.005^15) -> 0 | R6: ='02_Inputs'!G7 * (1.005^16) -> 0 | S6: ='02_Inputs'!G7 * (1.005^17) -> 0 | T6: ='02_Inputs'!G7 * (1.005^18) -> 0 | U6: ='02_Inputs'!G7 * (1.005^19) -> 0 | V6: ='02_Inputs'!G7 * (1.005^20) -> 0 | W6: ='02_Inputs'!G7 * (1.005^21) -> 0 | X6: ='02_Inputs'!G7 * (1.005^22) -> 0 | Y6: ='02_Inputs'!G7 * (1.005^23) -> 0 | Z6: ='02_Inputs'!G7 * (1.005^24) -> 0 | AA6: ='02_Inputs'!G7 * (1.005^25) -> 0 | AB6: ='02_Inputs'!G7 * (1.005^26) -> 0 | AC6: ='02_Inputs'!G7 * (1.005^27) -> 0 | AD6: ='02_Inputs'!G7 * (1.005^28) -> 0 | AE6: ='02_Inputs'!G7 * (1.005^29) -> 0 | AF6: ='02_Inputs'!G7 * (1.005^30) -> 0 | AG6: ='02_Inputs'!G7 * (1.005^31) -> 0 | AH6: ='02_Inputs'!G7 * (1.005^32) -> 0 | AI6: ='02_Inputs'!G7 * (1.005^33) -> 0 | AJ6: ='02_Inputs'!G7 * (1.005^34) -> 0 | AK6: ='02_Inputs'!G7 * (1.005^35) -> 0 | AL6: ='02_Inputs'!G7 * (1.005^36) -> 0 | AM6: ='02_Inputs'!G7 * (1.005^37) -> 0 | AN6: ='02_Inputs'!G7 * (1.005^38) -> 0 | AO6: ='02_Inputs'!G7 * (1.005^39) -> 0 | AP6: ='02_Inputs'!G7 * (1.005^40) -> 0 | AQ6: ='02_Inputs'!G7 * (1.005^41) -> 0 | AR6: ='02_Inputs'!G7 * (1.005^42) -> 0 | AS6: ='02_Inputs'!G7 * (1.005^43) -> 0 | AT6: ='02_Inputs'!G7 * (1.005^44) -> 0 | AU6: ='02_Inputs'!G7 * (1.005^45) -> 0 | AV6: ='02_Inputs'!G7 * (1.005^46) -> 0 | AW6: ='02_Inputs'!G7 * (1.005^47) -> 0 | AX6: ='02_Inputs'!G7 * (1.005^48) -> 0 | AY6: ='02_Inputs'!G7 * (1.005^49) -> 0 | AZ6: ='02_Inputs'!G7 * (1.005^50) -> 0 | BA6: ='02_Inputs'!G7 * (1.005^51) -> 0 | BB6: ='02_Inputs'!G7 * (1.005^52) -> 0 | BC6: ='02_Inputs'!G7 * (1.005^53) -> 0 | BD6: ='02_Inputs'!G7 * (1.005^54) -> 0 | BE6: ='02_Inputs'!G7 * (1.005^55) -> 0 | BF6: ='02_Inputs'!G7 * (1.005^56) -> 0 | BG6: ='02_Inputs'!G7 * (1.005^57) -> 0 | BH6: ='02_Inputs'!G7 * (1.005^58) -> 0 | BI6: ='02_Inputs'!G7 * (1.005^59) -> 0
A7: IPA | B7: ='02_Inputs'!G8 * (1.005^0) -> 0 | C7: ='02_Inputs'!G8 * (1.005^1) -> 0 | D7: ='02_Inputs'!G8 * (1.005^2) -> 0 | E7: ='02_Inputs'!G8 * (1.005^3) -> 0 | F7: ='02_Inputs'!G8 * (1.005^4) -> 0 | G7: ='02_Inputs'!G8 * (1.005^5) -> 0 | H7: ='02_Inputs'!G8 * (1.005^6) -> 0 | I7: ='02_Inputs'!G8 * (1.005^7) -> 0 | J7: ='02_Inputs'!G8 * (1.005^8) -> 0 | K7: ='02_Inputs'!G8 * (1.005^9) -> 0 | L7: ='02_Inputs'!G8 * (1.005^10) -> 0 | M7: ='02_Inputs'!G8 * (1.005^11) -> 0 | N7: ='02_Inputs'!G8 * (1.005^12) -> 0 | O7: ='02_Inputs'!G8 * (1.005^13) -> 0 | P7: ='02_Inputs'!G8 * (1.005^14) -> 0 | Q7: ='02_Inputs'!G8 * (1.005^15) -> 0 | R7: ='02_Inputs'!G8 * (1.005^16) -> 0 | S7: ='02_Inputs'!G8 * (1.005^17) -> 0 | T7: ='02_Inputs'!G8 * (1.005^18) -> 0 | U7: ='02_Inputs'!G8 * (1.005^19) -> 0 | V7: ='02_Inputs'!G8 * (1.005^20) -> 0 | W7: ='02_Inputs'!G8 * (1.005^21) -> 0 | X7: ='02_Inputs'!G8 * (1.005^22) -> 0 | Y7: ='02_Inputs'!G8 * (1.005^23) -> 0 | Z7: ='02_Inputs'!G8 * (1.005^24) -> 0 | AA7: ='02_Inputs'!G8 * (1.005^25) -> 0 | AB7: ='02_Inputs'!G8 * (1.005^26) -> 0 | AC7: ='02_Inputs'!G8 * (1.005^27) -> 0 | AD7: ='02_Inputs'!G8 * (1.005^28) -> 0 | AE7: ='02_Inputs'!G8 * (1.005^29) -> 0 | AF7: ='02_Inputs'!G8 * (1.005^30) -> 0 | AG7: ='02_Inputs'!G8 * (1.005^31) -> 0 | AH7: ='02_Inputs'!G8 * (1.005^32) -> 0 | AI7: ='02_Inputs'!G8 * (1.005^33) -> 0 | AJ7: ='02_Inputs'!G8 * (1.005^34) -> 0 | AK7: ='02_Inputs'!G8 * (1.005^35) -> 0 | AL7: ='02_Inputs'!G8 * (1.005^36) -> 0 | AM7: ='02_Inputs'!G8 * (1.005^37) -> 0 | AN7: ='02_Inputs'!G8 * (1.005^38) -> 0 | AO7: ='02_Inputs'!G8 * (1.005^39) -> 0 | AP7: ='02_Inputs'!G8 * (1.005^40) -> 0 | AQ7: ='02_Inputs'!G8 * (1.005^41) -> 0 | AR7: ='02_Inputs'!G8 * (1.005^42) -> 0 | AS7: ='02_Inputs'!G8 * (1.005^43) -> 0 | AT7: ='02_Inputs'!G8 * (1.005^44) -> 0 | AU7: ='02_Inputs'!G8 * (1.005^45) -> 0 | AV7: ='02_Inputs'!G8 * (1.005^46) -> 0 | AW7: ='02_Inputs'!G8 * (1.005^47) -> 0 | AX7: ='02_Inputs'!G8 * (1.005^48) -> 0 | AY7: ='02_Inputs'!G8 * (1.005^49) -> 0 | AZ7: ='02_Inputs'!G8 * (1.005^50) -> 0 | BA7: ='02_Inputs'!G8 * (1.005^51) -> 0 | BB7: ='02_Inputs'!G8 * (1.005^52) -> 0 | BC7: ='02_Inputs'!G8 * (1.005^53) -> 0 | BD7: ='02_Inputs'!G8 * (1.005^54) -> 0 | BE7: ='02_Inputs'!G8 * (1.005^55) -> 0 | BF7: ='02_Inputs'!G8 * (1.005^56) -> 0 | BG7: ='02_Inputs'!G8 * (1.005^57) -> 0 | BH7: ='02_Inputs'!G8 * (1.005^58) -> 0 | BI7: ='02_Inputs'!G8 * (1.005^59) -> 0
A8: Stout | B8: ='02_Inputs'!G9 * (1.005^0) -> 0 | C8: ='02_Inputs'!G9 * (1.005^1) -> 0 | D8: ='02_Inputs'!G9 * (1.005^2) -> 0 | E8: ='02_Inputs'!G9 * (1.005^3) -> 0 | F8: ='02_Inputs'!G9 * (1.005^4) -> 0 | G8: ='02_Inputs'!G9 * (1.005^5) -> 0 | H8: ='02_Inputs'!G9 * (1.005^6) -> 0 | I8: ='02_Inputs'!G9 * (1.005^7) -> 0 | J8: ='02_Inputs'!G9 * (1.005^8) -> 0 | K8: ='02_Inputs'!G9 * (1.005^9) -> 0 | L8: ='02_Inputs'!G9 * (1.005^10) -> 0 | M8: ='02_Inputs'!G9 * (1.005^11) -> 0 | N8: ='02_Inputs'!G9 * (1.005^12) -> 0 | O8: ='02_Inputs'!G9 * (1.005^13) -> 0 | P8: ='02_Inputs'!G9 * (1.005^14) -> 0 | Q8: ='02_Inputs'!G9 * (1.005^15) -> 0 | R8: ='02_Inputs'!G9 * (1.005^16) -> 0 | S8: ='02_Inputs'!G9 * (1.005^17) -> 0 | T8: ='02_Inputs'!G9 * (1.005^18) -> 0 | U8: ='02_Inputs'!G9 * (1.005^19) -> 0 | V8: ='02_Inputs'!G9 * (1.005^20) -> 0 | W8: ='02_Inputs'!G9 * (1.005^21) -> 0 | X8: ='02_Inputs'!G9 * (1.005^22) -> 0 | Y8: ='02_Inputs'!G9 * (1.005^23) -> 0 | Z8: ='02_Inputs'!G9 * (1.005^24) -> 0 | AA8: ='02_Inputs'!G9 * (1.005^25) -> 0 | AB8: ='02_Inputs'!G9 * (1.005^26) -> 0 | AC8: ='02_Inputs'!G9 * (1.005^27) -> 0 | AD8: ='02_Inputs'!G9 * (1.005^28) -> 0 | AE8: ='02_Inputs'!G9 * (1.005^29) -> 0 | AF8: ='02_Inputs'!G9 * (1.005^30) -> 0 | AG8: ='02_Inputs'!G9 * (1.005^31) -> 0 | AH8: ='02_Inputs'!G9 * (1.005^32) -> 0 | AI8: ='02_Inputs'!G9 * (1.005^33) -> 0 | AJ8: ='02_Inputs'!G9 * (1.005^34) -> 0 | AK8: ='02_Inputs'!G9 * (1.005^35) -> 0 | AL8: ='02_Inputs'!G9 * (1.005^36) -> 0 | AM8: ='02_Inputs'!G9 * (1.005^37) -> 0 | AN8: ='02_Inputs'!G9 * (1.005^38) -> 0 | AO8: ='02_Inputs'!G9 * (1.005^39) -> 0 | AP8: ='02_Inputs'!G9 * (1.005^40) -> 0 | AQ8: ='02_Inputs'!G9 * (1.005^41) -> 0 | AR8: ='02_Inputs'!G9 * (1.005^42) -> 0 | AS8: ='02_Inputs'!G9 * (1.005^43) -> 0 | AT8: ='02_Inputs'!G9 * (1.005^44) -> 0 | AU8: ='02_Inputs'!G9 * (1.005^45) -> 0 | AV8: ='02_Inputs'!G9 * (1.005^46) -> 0 | AW8: ='02_Inputs'!G9 * (1.005^47) -> 0 | AX8: ='02_Inputs'!G9 * (1.005^48) -> 0 | AY8: ='02_Inputs'!G9 * (1.005^49) -> 0 | AZ8: ='02_Inputs'!G9 * (1.005^50) -> 0 | BA8: ='02_Inputs'!G9 * (1.005^51) -> 0 | BB8: ='02_Inputs'!G9 * (1.005^52) -> 0 | BC8: ='02_Inputs'!G9 * (1.005^53) -> 0 | BD8: ='02_Inputs'!G9 * (1.005^54) -> 0 | BE8: ='02_Inputs'!G9 * (1.005^55) -> 0 | BF8: ='02_Inputs'!G9 * (1.005^56) -> 0 | BG8: ='02_Inputs'!G9 * (1.005^57) -> 0 | BH8: ='02_Inputs'!G9 * (1.005^58) -> 0 | BI8: ='02_Inputs'!G9 * (1.005^59) -> 0
A9: Seasonal | B9: ='02_Inputs'!G10 * (1.005^0) -> 0 | C9: ='02_Inputs'!G10 * (1.005^1) -> 0 | D9: ='02_Inputs'!G10 * (1.005^2) -> 0 | E9: ='02_Inputs'!G10 * (1.005^3) -> 0 | F9: ='02_Inputs'!G10 * (1.005^4) -> 0 | G9: ='02_Inputs'!G10 * (1.005^5) -> 0 | H9: ='02_Inputs'!G10 * (1.005^6) -> 0 | I9: ='02_Inputs'!G10 * (1.005^7) -> 0 | J9: ='02_Inputs'!G10 * (1.005^8) -> 0 | K9: ='02_Inputs'!G10 * (1.005^9) -> 0 | L9: ='02_Inputs'!G10 * (1.005^10) -> 0 | M9: ='02_Inputs'!G10 * (1.005^11) -> 0 | N9: ='02_Inputs'!G10 * (1.005^12) -> 0 | O9: ='02_Inputs'!G10 * (1.005^13) -> 0 | P9: ='02_Inputs'!G10 * (1.005^14) -> 0 | Q9: ='02_Inputs'!G10 * (1.005^15) -> 0 | R9: ='02_Inputs'!G10 * (1.005^16) -> 0 | S9: ='02_Inputs'!G10 * (1.005^17) -> 0 | T9: ='02_Inputs'!G10 * (1.005^18) -> 0 | U9: ='02_Inputs'!G10 * (1.005^19) -> 0 | V9: ='02_Inputs'!G10 * (1.005^20) -> 0 | W9: ='02_Inputs'!G10 * (1.005^21) -> 0 | X9: ='02_Inputs'!G10 * (1.005^22) -> 0 | Y9: ='02_Inputs'!G10 * (1.005^23) -> 0 | Z9: ='02_Inputs'!G10 * (1.005^24) -> 0 | AA9: ='02_Inputs'!G10 * (1.005^25) -> 0 | AB9: ='02_Inputs'!G10 * (1.005^26) -> 0 | AC9: ='02_Inputs'!G10 * (1.005^27) -> 0 | AD9: ='02_Inputs'!G10 * (1.005^28) -> 0 | AE9: ='02_Inputs'!G10 * (1.005^29) -> 0 | AF9: ='02_Inputs'!G10 * (1.005^30) -> 0 | AG9: ='02_Inputs'!G10 * (1.005^31) -> 0 | AH9: ='02_Inputs'!G10 * (1.005^32) -> 0 | AI9: ='02_Inputs'!G10 * (1.005^33) -> 0 | AJ9: ='02_Inputs'!G10 * (1.005^34) -> 0 | AK9: ='02_Inputs'!G10 * (1.005^35) -> 0 | AL9: ='02_Inputs'!G10 * (1.005^36) -> 0 | AM9: ='02_Inputs'!G10 * (1.005^37) -> 0 | AN9: ='02_Inputs'!G10 * (1.005^38) -> 0 | AO9: ='02_Inputs'!G10 * (1.005^39) -> 0 | AP9: ='02_Inputs'!G10 * (1.005^40) -> 0 | AQ9: ='02_Inputs'!G10 * (1.005^41) -> 0 | AR9: ='02_Inputs'!G10 * (1.005^42) -> 0 | AS9: ='02_Inputs'!G10 * (1.005^43) -> 0 | AT9: ='02_Inputs'!G10 * (1.005^44) -> 0 | AU9: ='02_Inputs'!G10 * (1.005^45) -> 0 | AV9: ='02_Inputs'!G10 * (1.005^46) -> 0 | AW9: ='02_Inputs'!G10 * (1.005^47) -> 0 | AX9: ='02_Inputs'!G10 * (1.005^48) -> 0 | AY9: ='02_Inputs'!G10 * (1.005^49) -> 0 | AZ9: ='02_Inputs'!G10 * (1.005^50) -> 0 | BA9: ='02_Inputs'!G10 * (1.005^51) -> 0 | BB9: ='02_Inputs'!G10 * (1.005^52) -> 0 | BC9: ='02_Inputs'!G10 * (1.005^53) -> 0 | BD9: ='02_Inputs'!G10 * (1.005^54) -> 0 | BE9: ='02_Inputs'!G10 * (1.005^55) -> 0 | BF9: ='02_Inputs'!G10 * (1.005^56) -> 0 | BG9: ='02_Inputs'!G10 * (1.005^57) -> 0 | BH9: ='02_Inputs'!G10 * (1.005^58) -> 0 | BI9: ='02_Inputs'!G10 * (1.005^59) -> 0
B10: =SUM(B5:B9) -> 0 | C10: =SUM(C5:C9) -> 0 | D10: =SUM(D5:D9) -> 0 | E10: =SUM(E5:E9) -> 0 | F10: =SUM(F5:F9) -> 0 | G10: =SUM(G5:G9) -> 0 | H10: =SUM(H5:H9) -> 0 | I10: =SUM(I5:I9) -> 0 | ... BI10: =SUM(BI5:BI9) -> 0
B11: =B10 / (1-0.07) -> 0 | C11: =C10 / (1-0.07) -> 0 | D11: =D10 / (1-0.07) -> 0 | E11: =E10 / (1-0.07) -> 0 | F11: =F10 / (1-0.07) -> 0 | G11: =G10 / (1-0.07) -> 0 | H11: =H10 / (1-0.07) -> 0 | I11: =I10 / (1-0.07) -> 0 | ... BI11: =BI10 / (1-0.07) -> 0
B13: =(B5 * ('02_Inputs'!$B$11 * '02_Inputs'!C6 + (1-'02_Inputs'!$B$11) * '02_Inputs'!D6)) + (B6 * ('02_Inputs'!$B$11 * '02_Inputs'!C7 + (1-'02_Inputs'!$B$11) * '02_Inputs'!D7)) + (B7 * ('02_Inputs'!$B$11 * '02_Inputs'!C8 + (1-'02_Inputs'!$B$11) * '02_Inputs'!D8)) + (B8 * ('02_Inputs'!$B$11 * '02_Inputs'!C9 + (1-'02_Inputs'!$B$11) * '02_Inputs'!D9)) + (B9 * ('02_Inputs'!$B$11 * '02_Inputs'!C10 + (1-'02_Inputs'!$B$11) * '02_Inputs'!D10)) -> 0 | C13: =(C5 * ('02_Inputs'!$B$11 * '02_Inputs'!C6 + (1-'02_Inputs'!$B$11) * '02_Inputs'!D6)) + (C6 * ('02_Inputs'!$B$11 * '02_Inputs'!C7 + (1-'02_Inputs'!$B$11) * '02_Inputs'!D7)) + (C7 * ('02_Inputs'!$B$11 * '02_Inputs'!C8 + (1-'02_Inputs'!$B$11) * '02_Inputs'!D8)) + (C8 * ('02_Inputs'!$B$11 * '02_Inputs'!C9 + (1-'02_Inputs'!$B$11) * '02_Inputs'!D9)) + (C9 * ('02_Inputs'!$B$11 * '02_Inputs'!C10 + (1-'02_Inputs'!$B$11) * '02_Inputs'!D10)) -> 0 | D13: =(D5 * ('02_Inputs'!$B$11 * '02_Inputs'!C6 + (1-'02_Inputs'!$B$11) * '02_Inputs'!D6)) + (D6 * ('02_Inputs'!$B$11 * '02_Inputs'!C7 + (1-'02_Inputs'!$B$11) * '02_Inputs'!D7)) + (D7 * ('02_Inputs'!$B$11 * '02_Inputs'!C8 + (1-'02_Inputs'!$B$11) * '02_Inputs'!D8)) + (D8 * ('02_Inputs'!$B$11 * '02_Inputs'!C9 + (1-'02_Inputs'!$B$11) * '02_Inputs'!D9)) + (D9 * ('02_Inputs'!$B$11 * '02_Inputs'!C10 + (1-'02_Inputs'!$B$11) * '02_Inputs'!D10)) -> 0 | E13: =(E5 * ('02_Inputs'!$B$11 * '02_Inputs'!C6 + (1-'02_Inputs'!$B$11) * '02_Inputs'!D6)) + (E6 * ('02_Inputs'!$B$11 * '02_Inputs'!C7 + (1-'02_Inputs'!$B$11) * '02_Inputs'!D7)) + (E7 * ('02_Inputs'!$B$11 * '02_Inputs'!C8 + (1-'02_Inputs'!$B$11) * '02_Inputs'!D8)) + (E8 * ('02_Inputs'!$B$11 * '02_Inputs'!C9 + (1-'02_Inputs'!$B$11) * '02_Inputs'!D9)) + (E9 * ('02_Inputs'!$B$11 * '02_Inputs'!C10 + (1-'02_Inputs'!$B$11) * '02_Inputs'!D10)) -> 0 | F13: =(F5 * ('02_Inputs'!$B$11 * '02_Inputs'!C6 + (1-'02_Inputs'!$B$11) * '02_Inputs'!D6)) + (F6 * ('02_Inputs'!$B$11 * '02_Inputs'!C7 + (1-'02_Inputs'!$B$11) * '02_Inputs'!D7)) + (F7 * ('02_Inputs'!$B$11 * '02_Inputs'!C8 + (1-'02_Inputs'!$B$11) * '02_Inputs'!D8)) + (F8 * ('02_Inputs'!$B$11 * '02_Inputs'!C9 + (1-'02_Inputs'!$B$11) * '02_Inputs'!D9)) + (F9 * ('02_Inputs'!$B$11 * '02_Inputs'!C10 + (1-'02_Inputs'!$B$11) * '02_Inputs'!D10)) -> 0 | G13: =(G5 * ('02_Inputs'!$B$11 * '02_Inputs'!C6 + (1-'02_Inputs'!$B$11) * '02_Inputs'!D6)) + (G6 * ('02_Inputs'!$B$11 * '02_Inputs'!C7 + (1-'02_Inputs'!$B$11) * '02_Inputs'!D7)) + (G7 * ('02_Inputs'!$B$11 * '02_Inputs'!C8 + (1-'02_Inputs'!$B$11) * '02_Inputs'!D8)) + (G8 * ('02_Inputs'!$B$11 * '02_Inputs'!C9 + (1-'02_Inputs'!$B$11) * '02_Inputs'!D9)) + (G9 * ('02_Inputs'!$B$11 * '02_Inputs'!C10 + (1-'02_Inputs'!$B$11) * '02_Inputs'!D10)) -> 0 | H13: =(H5 * ('02_Inputs'!$B$11 * '02_Inputs'!C6 + (1-'02_Inputs'!$B$11) * '02_Inputs'!D6)) + (H6 * ('02_Inputs'!$B$11 * '02_Inputs'!C7 + (1-'02_Inputs'!$B$11) * '02_Inputs'!D7)) + (H7 * ('02_Inputs'!$B$11 * '02_Inputs'!C8 + (1-'02_Inputs'!$B$11) * '02_Inputs'!D8)) + (H8 * ('02_Inputs'!$B$11 * '02_Inputs'!C9 + (1-'02_Inputs'!$B$11) * '02_Inputs'!D9)) + (H9 * ('02_Inputs'!$B$11 * '02_Inputs'!C10 + (1-'02_Inputs'!$B$11) * '02_Inputs'!D10)) -> 0 | I13: =(I5 * ('02_Inputs'!$B$11 * '02_Inputs'!C6 + (1-'02_Inputs'!$B$11) * '02_Inputs'!D6)) + (I6 * ('02_Inputs'!$B$11 * '02_Inputs'!C7 + (1-'02_Inputs'!$B$11) * '02_Inputs'!D7)) + (I7 * ('02_Inputs'!$B$11 * '02_Inputs'!C8 + (1-'02_Inputs'!$B$11) * '02_Inputs'!D8)) + (I8 * ('02_Inputs'!$B$11 * '02_Inputs'!C9 + (1-'02_Inputs'!$B$11) * '02_Inputs'!D9)) + (I9 * ('02_Inputs'!$B$11 * '02_Inputs'!C10 + (1-'02_Inputs'!$B$11) * '02_Inputs'!D10)) -> 0 | J13: =(J5 * ('02_Inputs'!$B$11 * '02_Inputs'!C6 + (1-'02_Inputs'!$B$11) * '02_Inputs'!D6)) + (J6 * ('02_Inputs'!$B$11 * '02_Inputs'!C7 + (1-'02_Inputs'!$B$11) * '02_Inputs'!D7)) + (J7 * ('02_Inputs'!$B$11 * '02_Inputs'!C8 + (1-'02_Inputs'!$B$11) * '02_Inputs'!D8)) + (J8 * ('02_Inputs'!$B$11 * '02_Inputs'!C9 + (1-'02_Inputs'!$B$11) * '02_Inputs'!D9)) + (J9 * ('02_Inputs'!$B$11 * '02_Inputs'!C10 + (1-'02_Inputs'!$B$11) * '02_Inputs'!D10)) -> 0 | K13: =(K5 * ('02_Inputs'!$B$11 * '02_Inputs'!C6 + (1-'02_Inputs'!$B$11) * '02_Inputs'!D6)) + (K6 * ('02_Inputs'!$B$11 * '02_Inputs'!C7 + (1-'02_Inputs'!$B$11) * '02_Inputs'!D7)) + (K7 * ('02_Inputs'!$B$11 * '02_Inputs'!C8 + (1-'02_Inputs'!$B$11) * '02_Inputs'!D8)) + (K8 * ('02_Inputs'!$B$11 * '02_Inputs'!C9 + (1-'02_Inputs'!$B$11) * '02_Inputs'!D9)) + (K9 * ('02_Inputs'!$B$11 * '02_Inputs'!C10 + (1-'02_Inputs'!$B$11) * '02_Inputs'!D10)) -> 0 | L13: =(L5 * ('02_Inputs'!$B$11 * '02_Inputs'!C6 + (1-'02_Inputs'!$B$11) * '02_Inputs'!D6)) + (L6 * ('02_Inputs'!$B$11 * '02_Inputs'!C7 + (1-'02_Inputs'!$B$11) * '02_Inputs'!D7)) + (L7 * ('02_Inputs'!$B$11 * '02_Inputs'!C8 + (1-'02_Inputs'!$B$11) * '02_Inputs'!D8)) + (L8 * ('02_Inputs'!$B$11 * '02_Inputs'!C9 + (1-'02_Inputs'!$B$11) * '02_Inputs'!D9)) + (L9 * ('02_Inputs'!$B$11 * '02_Inputs'!C10 + (1-'02_Inputs'!$B$11) * '02_Inputs'!D10)) -> 0 | M13: =(M5 * ('02_Inputs'!$B$11 * '02_Inputs'!C6 + (1-'02_Inputs'!$B$11) * '02_Inputs'!D6)) + (M6 * ('02_Inputs'!$B$11 * '02_Inputs'!C7 + (1-'02_Inputs'!$B$11) * '02_Inputs'!D7)) + (M7 * ('02_Inputs'!$B$11 * '02_Inputs'!C8 + (1-'02_Inputs'!$B$11) * '02_Inputs'!D8)) + (M8 * ('02_Inputs'!$B$11 * '02_Inputs'!C9 + (1-'02_Inputs'!$B$11) * '02_Inputs'!D9)) + (M9 * ('02_Inputs'!$B$11 * '02_Inputs'!C10 + (1-'02_Inputs'!$B$11) * '02_Inputs'!D10)) -> 0 | N13: =(N5 * ('02_Inputs'!$B$11 * '02_Inputs'!C6 + (1-'02_Inputs'!$B$11) * '02_Inputs'!D6)) + (N6 * ('02_Inputs'!$B$11 * '02_Inputs'!C7 + (1-'02_Inputs'!$B$11) * '02_Inputs'!D7)) + (N7 * ('02_Inputs'!$B$11 * '02_Inputs'!C8 + (1-'02_Inputs'!$B$11) * '02_Inputs'!D8)) + (N8 * ('02_Inputs'!$B$11 * '02_Inputs'!C9 + (1-'02_Inputs'!$B$11) * '02_Inputs'!D9)) + (N9 * ('02_Inputs'!$B$11 * '02_Inputs'!C10 + (1-'02_Inputs'!$B$11) * '02_Inputs'!D10)) -> 0 | O13: =(O5 * ('02_Inputs'!$B$11 * '02_Inputs'!C6 + (1-'02_Inputs'!$B$11) * '02_Inputs'!D6)) + (O6 * ('02_Inputs'!$B$11 * '02_Inputs'!C7 + (1-'02_Inputs'!$B$11) * '02_Inputs'!D7)) + (O7 * ('02_Inputs'!$B$11 * '02_Inputs'!C8 + (1-'02_Inputs'!$B$11) * '02_Inputs'!D8)) + (O8 * ('02_Inputs'!$B$11 * '02_Inputs'!C9 + (1-'02_Inputs'!$B$11) * '02_Inputs'!D9)) + (O9 * ('02_Inputs'!$B$11 * '02_Inputs'!C10 + (1-'02_Inputs'!$B$11) * '02_Inputs'!D10)) -> 0 | P13: =(P5 * ('02_Inputs'!$B$11 * '02_Inputs'!C6 + (1-'02_Inputs'!$B$11) * '02_Inputs'!D6)) + (P6 * ('02_Inputs'!$B$11 * '02_Inputs'!C7 + (1-'02_Inputs'!$B$11) * '02_Inputs'!D7)) + (P7 * ('02_Inputs'!$B$11 * '02_Inputs'!C8 + (1-'02_Inputs'!$B$11) * '02_Inputs'!D8)) + (P8 * ('02_Inputs'!$B$11 * '02_Inputs'!C9 + (1-'02_Inputs'!$B$11) * '02_Inputs'!D9)) + (P9 * ('02_Inputs'!$B$11 * '02_Inputs'!C10 + (1-'02_Inputs'!$B$11) * '02_Inputs'!D10)) -> 0 | Q13: =(Q5 * ('02_Inputs'!$B$11 * '02_Inputs'!C6 + (1-'02_Inputs'!$B$11) * '02_Inputs'!D6)) + (Q6 * ('02_Inputs'!$B$11 * '02_Inputs'!C7 + (1-'02_Inputs'!$B$11) * '02_Inputs'!D7)) + (Q7 * ('02_Inputs'!$B$11 * '02_Inputs'!C8 + (1-'02_Inputs'!$B$11) * '02_Inputs'!D8)) + (Q8 * ('02_Inputs'!$B$11 * '02_Inputs'!C9 + (1-'02_Inputs'!$B$11) * '02_Inputs'!D9)) + (Q9 * ('02_Inputs'!$B$11 * '02_Inputs'!C10 + (1-'02_Inputs'!$B$11) * '02_Inputs'!D10)) -> 0 | R13: =(R5 * ('02_Inputs'!$B$11 * '02_Inputs'!C6 + (1-'02_Inputs'!$B$11) * '02_Inputs'!D6)) + (R6 * ('02_Inputs'!$B$11 * '02_Inputs'!C7 + (1-'02_Inputs'!$B$11) * '02_Inputs'!D7)) + (R7 * ('02_Inputs'!$B$11 * '02_Inputs'!C8 + (1-'02_Inputs'!$B$11) * '02_Inputs'!D8)) + (R8 * ('02_Inputs'!$B$11 * '02_Inputs'!C9 + (1-'02_Inputs'!$B$11) * '02_Inputs'!D9)) + (R9 * ('02_Inputs'!$B$11 * '02_Inputs'!C10 + (1-'02_Inputs'!$B$11) * '02_Inputs'!D10)) -> 0 | S13: =(S5 * ('02_Inputs'!$B$11 * '02_Inputs'!C6 + (1-'02_Inputs'!$B$11) * '02_Inputs'!D6)) + (S6 * ('02_Inputs'!$B$11 * '02_Inputs'!C7 + (1-'02_Inputs'!$B$11) * '02_Inputs'!D7)) + (S7 * ('02_Inputs'!$B$11 * '02_Inputs'!C8 + (1-'02_Inputs'!$B$11) * '02_Inputs'!D8)) + (S8 * ('02_Inputs'!$B$11 * '02_Inputs'!C9 + (1-'02_Inputs'!$B$11) * '02_Inputs'!D9)) + (S9 * ('02_Inputs'!$B$11 * '02_Inputs'!C10 + (1-'02_Inputs'!$B$11) * '02_Inputs'!D10)) -> 0 | T13: =(T5 * ('02_Inputs'!$B$11 * '02_Inputs'!C6 + (1-'02_Inputs'!$B$11) * '02_Inputs'!D6)) + (T6 * ('02_Inputs'!$B$11 * '02_Inputs'!C7 + (1-'02_Inputs'!$B$11) * '02_Inputs'!D7)) + (T7 * ('02_Inputs'!$B$11 * '02_Inputs'!C8 + (1-'02_Inputs'!$B$11) * '02_Inputs'!D8)) + (T8 * ('02_Inputs'!$B$11 * '02_Inputs'!C9 + (1-'02_Inputs'!$B$11) * '02_Inputs'!D9)) + (T9 * ('02_Inputs'!$B$11 * '02_Inputs'!C10 + (1-'02_Inputs'!$B$11) * '02_Inputs'!D10)) -> 0 | U13: =(U5 * ('02_Inputs'!$B$11 * '02_Inputs'!C6 + (1-'02_Inputs'!$B$11) * '02_Inputs'!D6)) + (U6 * ('02_Inputs'!$B$11 * '02_Inputs'!C7 + (1-'02_Inputs'!$B$11) * '02_Inputs'!D7)) + (U7 * ('02_Inputs'!$B$11 * '02_Inputs'!C8 + (1-'02_Inputs'!$B$11) * '02_Inputs'!D8)) + (U8 * ('02_Inputs'!$B$11 * '02_Inputs'!C9 + (1-'02_Inputs'!$B$11) * '02_Inputs'!D9)) + (U9 * ('02_Inputs'!$B$11 * '02_Inputs'!C10 + (1-'02_Inputs'!$B$11) * '02_Inputs'!D10)) -> 0 | V13: =(V5 * ('02_Inputs'!$B$11 * '02_Inputs'!C6 + (1-'02_Inputs'!$B$11) * '02_Inputs'!D6)) + (V6 * ('02_Inputs'!$B$11 * '02_Inputs'!C7 + (1-'02_Inputs'!$B$11) * '02_Inputs'!D7)) + (V7 * ('02_Inputs'!$B$11 * '02_Inputs'!C8 + (1-'02_Inputs'!$B$11) * '02_Inputs'!D8)) + (V8 * ('02_Inputs'!$B$11 * '02_Inputs'!C9 + (1-'02_Inputs'!$B$11) * '02_Inputs'!D9)) + (V9 * ('02_Inputs'!$B$11 * '02_Inputs'!C10 + (1-'02_Inputs'!$B$11) * '02_Inputs'!D10)) -> 0 | W13: =(W5 * ('02_Inputs'!$B$11 * '02_Inputs'!C6 + (1-'02_Inputs'!$B$11) * '02_Inputs'!D6)) + (W6 * ('02_Inputs'!$B$11 * '02_Inputs'!C7 + (1-'02_Inputs'!$B$11) * '02_Inputs'!D7)) + (W7 * ('02_Inputs'!$B$11 * '02_Inputs'!C8 + (1-'02_Inputs'!$B$11) * '02_Inputs'!D8)) + (W8 * ('02_Inputs'!$B$11 * '02_Inputs'!C9 + (1-'02_Inputs'!$B$11) * '02_Inputs'!D9)) + (W9 * ('02_Inputs'!$B$11 * '02_Inputs'!C10 + (1-'02_Inputs'!$B$11) * '02_Inputs'!D10)) -> 0 | X13: =(X5 * ('02_Inputs'!$B$11 * '02_Inputs'!C6 + (1-'02_Inputs'!$B$11) * '02_Inputs'!D6)) + (X6 * ('02_Inputs'!$B$11 * '02_Inputs'!C7 + (1-'02_Inputs'!$B$11) * '02_Inputs'!D7)) + (X7 * ('02_Inputs'!$B$11 * '02_Inputs'!C8 + (1-'02_Inputs'!$B$11) * '02_Inputs'!D8)) + (X8 * ('02_Inputs'!$B$11 * '02_Inputs'!C9 + (1-'02_Inputs'!$B$11) * '02_Inputs'!D9)) + (X9 * ('02_Inputs'!$B$11 * '02_Inputs'!C10 + (1-'02_Inputs'!$B$11) * '02_Inputs'!D10)) -> 0 | Y13: =(Y5 * ('02_Inputs'!$B$11 * '02_Inputs'!C6 + (1-'02_Inputs'!$B$11) * '02_Inputs'!D6)) + (Y6 * ('02_Inputs'!$B$11 * '02_Inputs'!C7 + (1-'02_Inputs'!$B$11) * '02_Inputs'!D7)) + (Y7 * ('02_Inputs'!$B$11 * '02_Inputs'!C8 + (1-'02_Inputs'!$B$11) * '02_Inputs'!D8)) + (Y8 * ('02_Inputs'!$B$11 * '02_Inputs'!C9 + (1-'02_Inputs'!$B$11) * '02_Inputs'!D9)) + (Y9 * ('02_Inputs'!$B$11 * '02_Inputs'!C10 + (1-'02_Inputs'!$B$11) * '02_Inputs'!D10)) -> 0 | Z13: =(Z5 * ('02_Inputs'!$B$11 * '02_Inputs'!C6 + (1-'02_Inputs'!$B$11) * '02_Inputs'!D6)) + (Z6 * ('02_Inputs'!$B$11 * '02_Inputs'!C7 + (1-'02_Inputs'!$B$11) * '02_Inputs'!D7)) + (Z7 * ('02_Inputs'!$B$11 * '02_Inputs'!C8 + (1-'02_Inputs'!$B$11) * '02_Inputs'!D8)) + (Z8 * ('02_Inputs'!$B$11 * '02_Inputs'!C9 + (1-'02_Inputs'!$B$11) * '02_Inputs'!D9)) + (Z9 * ('02_Inputs'!$B$11 * '02_Inputs'!C10 + (1-'02_Inputs'!$B$11) * '02_Inputs'!D10)) -> 0 | AA13: =(AA5 * ('02_Inputs'!$B$11 * '02_Inputs'!C6 + (1-'02_Inputs'!$B$11) * '02_Inputs'!D6)) + (AA6 * ('02_Inputs'!$B$11 * '02_Inputs'!C7 + (1-'02_Inputs'!$B$11) * '02_Inputs'!D7)) + (AA7 * ('02_Inputs'!$B$11 * '02_Inputs'!C8 + (1-'02_Inputs'!$B$11) * '02_Inputs'!D8)) + (AA8 * ('02_Inputs'!$B$11 * '02_Inputs'!C9 + (1-'02_Inputs'!$B$11) * '02_Inputs'!D9)) + (AA9 * ('02_Inputs'!$B$11 * '02_Inputs'!C10 + (1-'02_Inputs'!$B$11) * '02_Inputs'!D10)) -> 0 | AB13: =(AB5 * ('02_Inputs'!$B$11 * '02_Inputs'!C6 + (1-'02_Inputs'!$B$11) * '02_Inputs'!D6)) + (AB6 * ('02_Inputs'!$B$11 * '02_Inputs'!C7 + (1-'02_Inputs'!$B$11) * '02_Inputs'!D7)) + (AB7 * ('02_Inputs'!$B$11 * '02_Inputs'!C8 + (1-'02_Inputs'!$B$11) * '02_Inputs'!D8)) + (AB8 * ('02_Inputs'!$B$11 * '02_Inputs'!C9 + (1-'02_Inputs'!$B$11) * '02_Inputs'!D9)) + (AB9 * ('02_Inputs'!$B$11 * '02_Inputs'!C10 + (1-'02_Inputs'!$B$11) * '02_Inputs'!D10)) -> 0 | AC13: =(AC5 * ('02_Inputs'!$B$11 * '02_Inputs'!C6 + (1-'02_Inputs'!$B$11) * '02_Inputs'!D6)) + (AC6 * ('02_Inputs'!$B$11 * '02_Inputs'!C7 + (1-'02_Inputs'!$B$11) * '02_Inputs'!D7)) + (AC7 * ('02_Inputs'!$B$11 * '02_Inputs'!C8 + (1-'02_Inputs'!$B$11) * '02_Inputs'!D8)) + (AC8 * ('02_Inputs'!$B$11 * '02_Inputs'!C9 + (1-'02_Inputs'!$B$11) * '02_Inputs'!D9)) + (AC9 * ('02_Inputs'!$B$11 * '02_Inputs'!C10 + (1-'02_Inputs'!$B$11) * '02_Inputs'!D10)) -> 0 | AD13: =(AD5 * ('02_Inputs'!$B$11 * '02_Inputs'!C6 + (1-'02_Inputs'!$B$11) * '02_Inputs'!D6)) + (AD6 * ('02_Inputs'!$B$11 * '02_Inputs'!C7 + (1-'02_Inputs'!$B$11) * '02_Inputs'!D7)) + (AD7 * ('02_Inputs'!$B$11 * '02_Inputs'!C8 + (1-'02_Inputs'!$B$11) * '02_Inputs'!D8)) + (AD8 * ('02_Inputs'!$B$11 * '02_Inputs'!C9 + (1-'02_Inputs'!$B$11) * '02_Inputs'!D9)) + (AD9 * ('02_Inputs'!$B$11 * '02_Inputs'!C10 + (1-'02_Inputs'!$B$11) * '02_Inputs'!D10)) -> 0 | AE13: =(AE5 * ('02_Inputs'!$B$11 * '02_Inputs'!C6 + (1-'02_Inputs'!$B$11) * '02_Inputs'!D6)) + (AE6 * ('02_Inputs'!$B$11 * '02_Inputs'!C7 + (1-'02_Inputs'!$B$11) * '02_Inputs'!D7)) + (AE7 * ('02_Inputs'!$B$11 * '02_Inputs'!C8 + (1-'02_Inputs'!$B$11) * '02_Inputs'!D8)) + (AE8 * ('02_Inputs'!$B$11 * '02_Inputs'!C9 + (1-'02_Inputs'!$B$11) * '02_Inputs'!D9)) + (AE9 * ('02_Inputs'!$B$11 * '02_Inputs'!C10 + (1-'02_Inputs'!$B$11) * '02_Inputs'!D10)) -> 0 | AF13: =(AF5 * ('02_Inputs'!$B$11 * '02_Inputs'!C6 + (1-'02_Inputs'!$B$11) * '02_Inputs'!D6)) + (AF6 * ('02_Inputs'!$B$11 * '02_Inputs'!C7 + (1-'02_Inputs'!$B$11) * '02_Inputs'!D7)) + (AF7 * ('02_Inputs'!$B$11 * '02_Inputs'!C8 + (1-'02_Inputs'!$B$11) * '02_Inputs'!D8)) + (AF8 * ('02_Inputs'!$B$11 * '02_Inputs'!C9 + (1-'02_Inputs'!$B$11) * '02_Inputs'!D9)) + (AF9 * ('02_Inputs'!$B$11 * '02_Inputs'!C10 + (1-'02_Inputs'!$B$11) * '02_Inputs'!D10)) -> 0 | AG13: =(AG5 * ('02_Inputs'!$B$11 * '02_Inputs'!C6 + (1-'02_Inputs'!$B$11) * '02_Inputs'!D6)) + (AG6 * ('02_Inputs'!$B$11 * '02_Inputs'!C7 + (1-'02_Inputs'!$B$11) * '02_Inputs'!D7)) + (AG7 * ('02_Inputs'!$B$11 * '02_Inputs'!C8 + (1-'02_Inputs'!$B$11) * '02_Inputs'!D8)) + (AG8 * ('02_Inputs'!$B$11 * '02_Inputs'!C9 + (1-'02_Inputs'!$B$11) * '02_Inputs'!D9)) + (AG9 * ('02_Inputs'!$B$11 * '02_Inputs'!C10 + (1-'02_Inputs'!$B$11) * '02_Inputs'!D10)) -> 0 | AH13: =(AH5 * ('02_Inputs'!$B$11 * '02_Inputs'!C6 + (1-'02_Inputs'!$B$11) * '02_Inputs'!D6)) + (AH6 * ('02_Inputs'!$B$11 * '02_Inputs'!C7 + (1-'02_Inputs'!$B$11) * '02_Inputs'!D7)) + (AH7 * ('02_Inputs'!$B$11 * '02_Inputs'!C8 + (1-'02_Inputs'!$B$11) * '02_Inputs'!D8)) + (AH8 * ('02_Inputs'!$B$11 * '02_Inputs'!C9 + (1-'02_Inputs'!$B$11) * '02_Inputs'!D9)) + (AH9 * ('02_Inputs'!$B$11 * '02_Inputs'!C10 + (1-'02_Inputs'!$B$11) * '02_Inputs'!D10)) -> 0 | AI13: =(AI5 * ('02_Inputs'!$B$11 * '02_Inputs'!C6 + (1-'02_Inputs'!$B$11) * '02_Inputs'!D6)) + (AI6 * ('02_Inputs'!$B$11 * '02_Inputs'!C7 + (1-'02_Inputs'!$B$11) * '02_Inputs'!D7)) + (AI7 * ('02_Inputs'!$B$11 * '02_Inputs'!C8 + (1-'02_Inputs'!$B$11) * '02_Inputs'!D8)) + (AI8 * ('02_Inputs'!$B$11 * '02_Inputs'!C9 + (1-'02_Inputs'!$B$11) * '02_Inputs'!D9)) + (AI9 * ('02_Inputs'!$B$11 * '02_Inputs'!C10 + (1-'02_Inputs'!$B$11) * '02_Inputs'!D10)) -> 0 | AJ13: =(AJ5 * ('02_Inputs'!$B$11 * '02_Inputs'!C6 + (1-'02_Inputs'!$B$11) * '02_Inputs'!D6)) + (AJ6 * ('02_Inputs'!$B$11 * '02_Inputs'!C7 + (1-'02_Inputs'!$B$11) * '02_Inputs'!D7)) + (AJ7 * ('02_Inputs'!$B$11 * '02_Inputs'!C8 + (1-'02_Inputs'!$B$11) * '02_Inputs'!D8)) + (AJ8 * ('02_Inputs'!$B$11 * '02_Inputs'!C9 + (1-'02_Inputs'!$B$11) * '02_Inputs'!D9)) + (AJ9 * ('02_Inputs'!$B$11 * '02_Inputs'!C10 + (1-'02_Inputs'!$B$11) * '02_Inputs'!D10)) -> 0 | AK13: =(AK5 * ('02_Inputs'!$B$11 * '02_Inputs'!C6 + (1-'02_Inputs'!$B$11) * '02_Inputs'!D6)) + (AK6 * ('02_Inputs'!$B$11 * '02_Inputs'!C7 + (1-'02_Inputs'!$B$11) * '02_Inputs'!D7)) + (AK7 * ('02_Inputs'!$B$11 * '02_Inputs'!C8 + (1-'02_Inputs'!$B$11) * '02_Inputs'!D8)) + (AK8 * ('02_Inputs'!$B$11 * '02_Inputs'!C9 + (1-'02_Inputs'!$B$11) * '02_Inputs'!D9)) + (AK9 * ('02_Inputs'!$B$11 * '02_Inputs'!C10 + (1-'02_Inputs'!$B$11) * '02_Inputs'!D10)) -> 0 | AL13: =(AL5 * ('02_Inputs'!$B$11 * '02_Inputs'!C6 + (1-'02_Inputs'!$B$11) * '02_Inputs'!D6)) + (AL6 * ('02_Inputs'!$B$11 * '02_Inputs'!C7 + (1-'02_Inputs'!$B$11) * '02_Inputs'!D7)) + (AL7 * ('02_Inputs'!$B$11 * '02_Inputs'!C8 + (1-'02_Inputs'!$B$11) * '02_Inputs'!D8)) + (AL8 * ('02_Inputs'!$B$11 * '02_Inputs'!C9 + (1-'02_Inputs'!$B$11) * '02_Inputs'!D9)) + (AL9 * ('02_Inputs'!$B$11 * '02_Inputs'!C10 + (1-'02_Inputs'!$B$11) * '02_Inputs'!D10)) -> 0 | AM13: =(AM5 * ('02_Inputs'!$B$11 * '02_Inputs'!C6 + (1-'02_Inputs'!$B$11) * '02_Inputs'!D6)) + (AM6 * ('02_Inputs'!$B$11 * '02_Inputs'!C7 + (1-'02_Inputs'!$B$11) * '02_Inputs'!D7)) + (AM7 * ('02_Inputs'!$B$11 * '02_Inputs'!C8 + (1-'02_Inputs'!$B$11) * '02_Inputs'!D8)) + (AM8 * ('02_Inputs'!$B$11 * '02_Inputs'!C9 + (1-'02_Inputs'!$B$11) * '02_Inputs'!D9)) + (AM9 * ('02_Inputs'!$B$11 * '02_Inputs'!C10 + (1-'02_Inputs'!$B$11) * '02_Inputs'!D10)) -> 0 | AN13: =(AN5 * ('02_Inputs'!$B$11 * '02_Inputs'!C6 + (1-'02_Inputs'!$B$11) * '02_Inputs'!D6)) + (AN6 * ('02_Inputs'!$B$11 * '02_Inputs'!C7 + (1-'02_Inputs'!$B$11) * '02_Inputs'!D7)) + (AN7 * ('02_Inputs'!$B$11 * '02_Inputs'!C8 + (1-'02_Inputs'!$B$11) * '02_Inputs'!D8)) + (AN8 * ('02_Inputs'!$B$11 * '02_Inputs'!C9 + (1-'02_Inputs'!$B$11) * '02_Inputs'!D9)) + (AN9 * ('02_Inputs'!$B$11 * '02_Inputs'!C10 + (1-'02_Inputs'!$B$11) * '02_Inputs'!D10)) -> 0 | AO13: =(AO5 * ('02_Inputs'!$B$11 * '02_Inputs'!C6 + (1-'02_Inputs'!$B$11) * '02_Inputs'!D6)) + (AO6 * ('02_Inputs'!$B$11 * '02_Inputs'!C7 + (1-'02_Inputs'!$B$11) * '02_Inputs'!D7)) + (AO7 * ('02_Inputs'!$B$11 * '02_Inputs'!C8 + (1-'02_Inputs'!$B$11) * '02_Inputs'!D8)) + (AO8 * ('02_Inputs'!$B$11 * '02_Inputs'!C9 + (1-'02_Inputs'!$B$11) * '02_Inputs'!D9)) + (AO9 * ('02_Inputs'!$B$11 * '02_Inputs'!C10 + (1-'02_Inputs'!$B$11) * '02_Inputs'!D10)) -> 0 | AP13: =(AP5 * ('02_Inputs'!$B$11 * '02_Inputs'!C6 + (1-'02_Inputs'!$B$11) * '02_Inputs'!D6)) + (AP6 * ('02_Inputs'!$B$11 * '02_Inputs'!C7 + (1-'02_Inputs'!$B$11) * '02_Inputs'!D7)) + (AP7 * ('02_Inputs'!$B$11 * '02_Inputs'!C8 + (1-'02_Inputs'!$B$11) * '02_Inputs'!D8)) + (AP8 * ('02_Inputs'!$B$11 * '02_Inputs'!C9 + (1-'02_Inputs'!$B$11) * '02_Inputs'!D9)) + (AP9 * ('02_Inputs'!$B$11 * '02_Inputs'!C10 + (1-'02_Inputs'!$B$11) * '02_Inputs'!D10)) -> 0 | AQ13: =(AQ5 * ('02_Inputs'!$B$11 * '02_Inputs'!C6 + (1-'02_Inputs'!$B$11) * '02_Inputs'!D6)) + (AQ6 * ('02_Inputs'!$B$11 * '02_Inputs'!C7 + (1-'02_Inputs'!$B$11) * '02_Inputs'!D7)) + (AQ7 * ('02_Inputs'!$B$11 * '02_Inputs'!C8 + (1-'02_Inputs'!$B$11) * '02_Inputs'!D8)) + (AQ8 * ('02_Inputs'!$B$11 * '02_Inputs'!C9 + (1-'02_Inputs'!$B$11) * '02_Inputs'!D9)) + (AQ9 * ('02_Inputs'!$B$11 * '02_Inputs'!C10 + (1-'02_Inputs'!$B$11) * '02_Inputs'!D10)) -> 0 | AR13: =(AR5 * ('02_Inputs'!$B$11 * '02_Inputs'!C6 + (1-'02_Inputs'!$B$11) * '02_Inputs'!D6)) + (AR6 * ('02_Inputs'!$B$11 * '02_Inputs'!C7 + (1-'02_Inputs'!$B$11) * '02_Inputs'!D7)) + (AR7 * ('02_Inputs'!$B$11 * '02_Inputs'!C8 + (1-'02_Inputs'!$B$11) * '02_Inputs'!D8)) + (AR8 * ('02_Inputs'!$B$11 * '02_Inputs'!C9 + (1-'02_Inputs'!$B$11) * '02_Inputs'!D9)) + (AR9 * ('02_Inputs'!$B$11 * '02_Inputs'!C10 + (1-'02_Inputs'!$B$11) * '02_Inputs'!D10)) -> 0 | AS13: =(AS5 * ('02_Inputs'!$B$11 * '02_Inputs'!C6 + (1-'02_Inputs'!$B$11) * '02_Inputs'!D6)) + (AS6 * ('02_Inputs'!$B$11 * '02_Inputs'!C7 + (1-'02_Inputs'!$B$11) * '02_Inputs'!D7)) + (AS7 * ('02_Inputs'!$B$11 * '02_Inputs'!C8 + (1-'02_Inputs'!$B$11) * '02_Inputs'!D8)) + (AS8 * ('02_Inputs'!$B$11 * '02_Inputs'!C9 + (1-'02_Inputs'!$B$11) * '02_Inputs'!D9)) + (AS9 * ('02_Inputs'!$B$11 * '02_Inputs'!C10 + (1-'02_Inputs'!$B$11) * '02_Inputs'!D10)) -> 0 | AT13: =(AT5 * ('02_Inputs'!$B$11 * '02_Inputs'!C6 + (1-'02_Inputs'!$B$11) * '02_Inputs'!D6)) + (AT6 * ('02_Inputs'!$B$11 * '02_Inputs'!C7 + (1-'02_Inputs'!$B$11) * '02_Inputs'!D7)) + (AT7 * ('02_Inputs'!$B$11 * '02_Inputs'!C8 + (1-'02_Inputs'!$B$11) * '02_Inputs'!D8)) + (AT8 * ('02_Inputs'!$B$11 * '02_Inputs'!C9 + (1-'02_Inputs'!$B$11) * '02_Inputs'!D9)) + (AT9 * ('02_Inputs'!$B$11 * '02_Inputs'!C10 + (1-'02_Inputs'!$B$11) * '02_Inputs'!D10)) -> 0 | AU13: =(AU5 * ('02_Inputs'!$B$11 * '02_Inputs'!C6 + (1-'02_Inputs'!$B$11) * '02_Inputs'!D6)) + (AU6 * ('02_Inputs'!$B$11 * '02_Inputs'!C7 + (1-'02_Inputs'!$B$11) * '02_Inputs'!D7)) + (AU7 * ('02_Inputs'!$B$11 * '02_Inputs'!C8 + (1-'02_Inputs'!$B$11) * '02_Inputs'!D8)) + (AU8 * ('02_Inputs'!$B$11 * '02_Inputs'!C9 + (1-'02_Inputs'!$B$11) * '02_Inputs'!D9)) + (AU9 * ('02_Inputs'!$B$11 * '02_Inputs'!C10 + (1-'02_Inputs'!$B$11) * '02_Inputs'!D10)) -> 0 | AV13: =(AV5 * ('02_Inputs'!$B$11 * '02_Inputs'!C6 + (1-'02_Inputs'!$B$11) * '02_Inputs'!D6)) + (AV6 * ('02_Inputs'!$B$11 * '02_Inputs'!C7 + (1-'02_Inputs'!$B$11) * '02_Inputs'!D7)) + (AV7 * ('02_Inputs'!$B$11 * '02_Inputs'!C8 + (1-'02_Inputs'!$B$11) * '02_Inputs'!D8)) + (AV8 * ('02_Inputs'!$B$11 * '02_Inputs'!C9 + (1-'02_Inputs'!$B$11) * '02_Inputs'!D9)) + (AV9 * ('02_Inputs'!$B$11 * '02_Inputs'!C10 + (1-'02_Inputs'!$B$11) * '02_Inputs'!D10)) -> 0 | AW13: =(AW5 * ('02_Inputs'!$B$11 * '02_Inputs'!C6 + (1-'02_Inputs'!$B$11) * '02_Inputs'!D6)) + (AW6 * ('02_Inputs'!$B$11 * '02_Inputs'!C7 + (1-'02_Inputs'!$B$11) * '02_Inputs'!D7)) + (AW7 * ('02_Inputs'!$B$11 * '02_Inputs'!C8 + (1-'02_Inputs'!$B$11) * '02_Inputs'!D8)) + (AW8 * ('02_Inputs'!$B$11 * '02_Inputs'!C9 + (1-'02_Inputs'!$B$11) * '02_Inputs'!D9)) + (AW9 * ('02_Inputs'!$B$11 * '02_Inputs'!C10 + (1-'02_Inputs'!$B$11) * '02_Inputs'!D10)) -> 0 | AX13: =(AX5 * ('02_Inputs'!$B$11 * '02_Inputs'!C6 + (1-'02_Inputs'!$B$11) * '02_Inputs'!D6)) + (AX6 * ('02_Inputs'!$B$11 * '02_Inputs'!C7 + (1-'02_Inputs'!$B$11) * '02_Inputs'!D7)) + (AX7 * ('02_Inputs'!$B$11 * '02_Inputs'!C8 + (1-'02_Inputs'!$B$11) * '02_Inputs'!D8)) + (AX8 * ('02_Inputs'!$B$11 * '02_Inputs'!C9 + (1-'02_Inputs'!$B$11) * '02_Inputs'!D9)) + (AX9 * ('02_Inputs'!$B$11 * '02_Inputs'!C10 + (1-'02_Inputs'!$B$11) * '02_Inputs'!D10)) -> 0 | AY13: =(AY5 * ('02_Inputs'!$B$11 * '02_Inputs'!C6 + (1-'02_Inputs'!$B$11) * '02_Inputs'!D6)) + (AY6 * ('02_Inputs'!$B$11 * '02_Inputs'!C7 + (1-'02_Inputs'!$B$11) * '02_Inputs'!D7)) + (AY7 * ('02_Inputs'!$B$11 * '02_Inputs'!C8 + (1-'02_Inputs'!$B$11) * '02_Inputs'!D8)) + (AY8 * ('02_Inputs'!$B$11 * '02_Inputs'!C9 + (1-'02_Inputs'!$B$11) * '02_Inputs'!D9)) + (AY9 * ('02_Inputs'!$B$11 * '02_Inputs'!C10 + (1-'02_Inputs'!$B$11) * '02_Inputs'!D10)) -> 0 | AZ13: =(AZ5 * ('02_Inputs'!$B$11 * '02_Inputs'!C6 + (1-'02_Inputs'!$B$11) * '02_Inputs'!D6)) + (AZ6 * ('02_Inputs'!$B$11 * '02_Inputs'!C7 + (1-'02_Inputs'!$B$11) * '02_Inputs'!D7)) + (AZ7 * ('02_Inputs'!$B$11 * '02_Inputs'!C8 + (1-'02_Inputs'!$B$11) * '02_Inputs'!D8)) + (AZ8 * ('02_Inputs'!$B$11 * '02_Inputs'!C9 + (1-'02_Inputs'!$B$11) * '02_Inputs'!D9)) + (AZ9 * ('02_Inputs'!$B$11 * '02_Inputs'!C10 + (1-'02_Inputs'!$B$11) * '02_Inputs'!D10)) -> 0 | BA13: =(BA5 * ('02_Inputs'!$B$11 * '02_Inputs'!C6 + (1-'02_Inputs'!$B$11) * '02_Inputs'!D6)) + (BA6 * ('02_Inputs'!$B$11 * '02_Inputs'!C7 + (1-'02_Inputs'!$B$11) * '02_Inputs'!D7)) + (BA7 * ('02_Inputs'!$B$11 * '02_Inputs'!C8 + (1-'02_Inputs'!$B$11) * '02_Inputs'!D8)) + (BA8 * ('02_Inputs'!$B$11 * '02_Inputs'!C9 + (1-'02_Inputs'!$B$11) * '02_Inputs'!D9)) + (BA9 * ('02_Inputs'!$B$11 * '02_Inputs'!C10 + (1-'02_Inputs'!$B$11) * '02_Inputs'!D10)) -> 0 | BB13: =(BB5 * ('02_Inputs'!$B$11 * '02_Inputs'!C6 + (1-'02_Inputs'!$B$11) * '02_Inputs'!D6)) + (BB6 * ('02_Inputs'!$B$11 * '02_Inputs'!C7 + (1-'02_Inputs'!$B$11) * '02_Inputs'!D7)) + (BB7 * ('02_Inputs'!$B$11 * '02_Inputs'!C8 + (1-'02_Inputs'!$B$11) * '02_Inputs'!D8)) + (BB8 * ('02_Inputs'!$B$11 * '02_Inputs'!C9 + (1-'02_Inputs'!$B$11) * '02_Inputs'!D9)) + (BB9 * ('02_Inputs'!$B$11 * '02_Inputs'!C10 + (1-'02_Inputs'!$B$11) * '02_Inputs'!D10)) -> 0 | BC13: =(BC5 * ('02_Inputs'!$B$11 * '02_Inputs'!C6 + (1-'02_Inputs'!$B$11) * '02_Inputs'!D6)) + (BC6 * ('02_Inputs'!$B$11 * '02_Inputs'!C7 + (1-'02_Inputs'!$B$11) * '02_Inputs'!D7)) + (BC7 * ('02_Inputs'!$B$11 * '02_Inputs'!C8 + (1-'02_Inputs'!$B$11) * '02_Inputs'!D8)) + (BC8 * ('02_Inputs'!$B$11 * '02_Inputs'!C9 + (1-'02_Inputs'!$B$11) * '02_Inputs'!D9)) + (BC9 * ('02_Inputs'!$B$11 * '02_Inputs'!C10 + (1-'02_Inputs'!$B$11) * '02_Inputs'!D10)) -> 0 | BD13: =(BD5 * ('02_Inputs'!$B$11 * '02_Inputs'!C6 + (1-'02_Inputs'!$B$11) * '02_Inputs'!D6)) + (BD6 * ('02_Inputs'!$B$11 * '02_Inputs'!C7 + (1-'02_Inputs'!$B$11) * '02_Inputs'!D7)) + (BD7 * ('02_Inputs'!$B$11 * '02_Inputs'!C8 + (1-'02_Inputs'!$B$11) * '02_Inputs'!D8)) + (BD8 * ('02_Inputs'!$B$11 * '02_Inputs'!C9 + (1-'02_Inputs'!$B$11) * '02_Inputs'!D9)) + (BD9 * ('02_Inputs'!$B$11 * '02_Inputs'!C10 + (1-'02_Inputs'!$B$11) * '02_Inputs'!D10)) -> 0 | BE13: =(BE5 * ('02_Inputs'!$B$11 * '02_Inputs'!C6 + (1-'02_Inputs'!$B$11) * '02_Inputs'!D6)) + (BE6 * ('02_Inputs'!$B$11 * '02_Inputs'!C7 + (1-'02_Inputs'!$B$11) * '02_Inputs'!D7)) + (BE7 * ('02_Inputs'!$B$11 * '02_Inputs'!C8 + (1-'02_Inputs'!$B$11) * '02_Inputs'!D8)) + (BE8 * ('02_Inputs'!$B$11 * '02_Inputs'!C9 + (1-'02_Inputs'!$B$11) * '02_Inputs'!D9)) + (BE9 * ('02_Inputs'!$B$11 * '02_Inputs'!C10 + (1-'02_Inputs'!$B$11) * '02_Inputs'!D10)) -> 0 | BF13: =(BF5 * ('02_Inputs'!$B$11 * '02_Inputs'!C6 + (1-'02_Inputs'!$B$11) * '02_Inputs'!D6)) + (BF6 * ('02_Inputs'!$B$11 * '02_Inputs'!C7 + (1-'02_Inputs'!$B$11) * '02_Inputs'!D7)) + (BF7 * ('02_Inputs'!$B$11 * '02_Inputs'!C8 + (1-'02_Inputs'!$B$11) * '02_Inputs'!D8)) + (BF8 * ('02_Inputs'!$B$11 * '02_Inputs'!C9 + (1-'02_Inputs'!$B$11) * '02_Inputs'!D9)) + (BF9 * ('02_Inputs'!$B$11 * '02_Inputs'!C10 + (1-'02_Inputs'!$B$11) * '02_Inputs'!D10)) -> 0 | BG13: =(BG5 * ('02_Inputs'!$B$11 * '02_Inputs'!C6 + (1-'02_Inputs'!$B$11) * '02_Inputs'!D6)) + (BG6 * ('02_Inputs'!$B$11 * '02_Inputs'!C7 + (1-'02_Inputs'!$B$11) * '02_Inputs'!D7)) + (BG7 * ('02_Inputs'!$B$11 * '02_Inputs'!C8 + (1-'02_Inputs'!$B$11) * '02_Inputs'!D8)) + (BG8 * ('02_Inputs'!$B$11 * '02_Inputs'!C9 + (1-'02_Inputs'!$B$11) * '02_Inputs'!D9)) + (BG9 * ('02_Inputs'!$B$11 * '02_Inputs'!C10 + (1-'02_Inputs'!$B$11) * '02_Inputs'!D10)) -> 0 | BH13: =(BH5 * ('02_Inputs'!$B$11 * '02_Inputs'!C6 + (1-'02_Inputs'!$B$11) * '02_Inputs'!D6)) + (BH6 * ('02_Inputs'!$B$11 * '02_Inputs'!C7 + (1-'02_Inputs'!$B$11) * '02_Inputs'!D7)) + (BH7 * ('02_Inputs'!$B$11 * '02_Inputs'!C8 + (1-'02_Inputs'!$B$11) * '02_Inputs'!D8)) + (BH8 * ('02_Inputs'!$B$11 * '02_Inputs'!C9 + (1-'02_Inputs'!$B$11) * '02_Inputs'!D9)) + (BH9 * ('02_Inputs'!$B$11 * '02_Inputs'!C10 + (1-'02_Inputs'!$B$11) * '02_Inputs'!D10)) -> 0 | BI13: =(BI5 * ('02_Inputs'!$B$11 * '02_Inputs'!C6 + (1-'02_Inputs'!$B$11) * '02_Inputs'!D6)) + (BI6 * ('02_Inputs'!$B$11 * '02_Inputs'!C7 + (1-'02_Inputs'!$B$11) * '02_Inputs'!D7)) + (BI7 * ('02_Inputs'!$B$11 * '02_Inputs'!C8 + (1-'02_Inputs'!$B$11) * '02_Inputs'!D8)) + (BI8 * ('02_Inputs'!$B$11 * '02_Inputs'!C9 + (1-'02_Inputs'!$B$11) * '02_Inputs'!D9)) + (BI9 * ('02_Inputs'!$B$11 * '02_Inputs'!C10 + (1-'02_Inputs'!$B$11) * '02_Inputs'!D10)) -> 0
B14: =-(B5 * 100 * (0.042-0.0115) * ('02_Inputs'!$B$11 * '01_Control'!$B$9 + (1-'02_Inputs'!$B$11) * '01_Control'!$B$8)) + (B6 * 100 * (0.05-0.0115) * ('02_Inputs'!$B$11 * '01_Control'!$B$9 + (1-'02_Inputs'!$B$11) * '01_Control'!$B$8)) + (B7 * 100 * (0.065-0.0115) * ('02_Inputs'!$B$11 * '01_Control'!$B$9 + (1-'02_Inputs'!$B$11) * '01_Control'!$B$8)) + (B8 * 100 * (0.055-0.0115) * ('02_Inputs'!$B$11 * '01_Control'!$B$9 + (1-'02_Inputs'!$B$11) * '01_Control'!$B$8)) + (B9 * 100 * (0.045-0.0115) * ('02_Inputs'!$B$11 * '01_Control'!$B$9 + (1-'02_Inputs'!$B$11) * '01_Control'!$B$8)) -> 0 | C14: =-(C5 * 100 * (0.042-0.0115) * ('02_Inputs'!$B$11 * '01_Control'!$B$9 + (1-'02_Inputs'!$B$11) * '01_Control'!$B$8)) + (C6 * 100 * (0.05-0.0115) * ('02_Inputs'!$B$11 * '01_Control'!$B$9 + (1-'02_Inputs'!$B$11) * '01_Control'!$B$8)) + (C7 * 100 * (0.065-0.0115) * ('02_Inputs'!$B$11 * '01_Control'!$B$9 + (1-'02_Inputs'!$B$11) * '01_Control'!$B$8)) + (C8 * 100 * (0.055-0.0115) * ('02_Inputs'!$B$11 * '01_Control'!$B$9 + (1-'02_Inputs'!$B$11) * '01_Control'!$B$8)) + (C9 * 100 * (0.045-0.0115) * ('02_Inputs'!$B$11 * '01_Control'!$B$9 + (1-'02_Inputs'!$B$11) * '01_Control'!$B$8)) -> 0 | D14: =-(D5 * 100 * (0.042-0.0115) * ('02_Inputs'!$B$11 * '01_Control'!$B$9 + (1-'02_Inputs'!$B$11) * '01_Control'!$B$8)) + (D6 * 100 * (0.05-0.0115) * ('02_Inputs'!$B$11 * '01_Control'!$B$9 + (1-'02_Inputs'!$B$11) * '01_Control'!$B$8)) + (D7 * 100 * (0.065-0.0115) * ('02_Inputs'!$B$11 * '01_Control'!$B$9 + (1-'02_Inputs'!$B$11) * '01_Control'!$B$8)) + (D8 * 100 * (0.055-0.0115) * ('02_Inputs'!$B$11 * '01_Control'!$B$9 + (1-'02_Inputs'!$B$11) * '01_Control'!$B$8)) + (D9 * 100 * (0.045-0.0115) * ('02_Inputs'!$B$11 * '01_Control'!$B$9 + (1-'02_Inputs'!$B$11) * '01_Control'!$B$8)) -> 0 | E14: =-(E5 * 100 * (0.042-0.0115) * ('02_Inputs'!$B$11 * '01_Control'!$B$9 + (1-'02_Inputs'!$B$11) * '01_Control'!$B$8)) + (E6 * 100 * (0.05-0.0115) * ('02_Inputs'!$B$11 * '01_Control'!$B$9 + (1-'02_Inputs'!$B$11) * '01_Control'!$B$8)) + (E7 * 100 * (0.065-0.0115) * ('02_Inputs'!$B$11 * '01_Control'!$B$9 + (1-'02_Inputs'!$B$11) * '01_Control'!$B$8)) + (E8 * 100 * (0.055-0.0115) * ('02_Inputs'!$B$11 * '01_Control'!$B$9 + (1-'02_Inputs'!$B$11) * '01_Control'!$B$8)) + (E9 * 100 * (0.045-0.0115) * ('02_Inputs'!$B$11 * '01_Control'!$B$9 + (1-'02_Inputs'!$B$11) * '01_Control'!$B$8)) -> 0 | F14: =-(F5 * 100 * (0.042-0.0115) * ('02_Inputs'!$B$11 * '01_Control'!$B$9 + (1-'02_Inputs'!$B$11) * '01_Control'!$B$8)) + (F6 * 100 * (0.05-0.0115) * ('02_Inputs'!$B$11 * '01_Control'!$B$9 + (1-'02_Inputs'!$B$11) * '01_Control'!$B$8)) + (F7 * 100 * (0.065-0.0115) * ('02_Inputs'!$B$11 * '01_Control'!$B$9 + (1-'02_Inputs'!$B$11) * '01_Control'!$B$8)) + (F8 * 100 * (0.055-0.0115) * ('02_Inputs'!$B$11 * '01_Control'!$B$9 + (1-'02_Inputs'!$B$11) * '01_Control'!$B$8)) + (F9 * 100 * (0.045-0.0115) * ('02_Inputs'!$B$11 * '01_Control'!$B$9 + (1-'02_Inputs'!$B$11) * '01_Control'!$B$8)) -> 0 | G14: =-(G5 * 100 * (0.042-0.0115) * ('02_Inputs'!$B$11 * '01_Control'!$B$9 + (1-'02_Inputs'!$B$11) * '01_Control'!$B$8)) + (G6 * 100 * (0.05-0.0115) * ('02_Inputs'!$B$11 * '01_Control'!$B$9 + (1-'02_Inputs'!$B$11) * '01_Control'!$B$8)) + (G7 * 100 * (0.065-0.0115) * ('02_Inputs'!$B$11 * '01_Control'!$B$9 + (1-'02_Inputs'!$B$11) * '01_Control'!$B$8)) + (G8 * 100 * (0.055-0.0115) * ('02_Inputs'!$B$11 * '01_Control'!$B$9 + (1-'02_Inputs'!$B$11) * '01_Control'!$B$8)) + (G9 * 100 * (0.045-0.0115) * ('02_Inputs'!$B$11 * '01_Control'!$B$9 + (1-'02_Inputs'!$B$11) * '01_Control'!$B$8)) -> 0 | H14: =-(H5 * 100 * (0.042-0.0115) * ('02_Inputs'!$B$11 * '01_Control'!$B$9 + (1-'02_Inputs'!$B$11) * '01_Control'!$B$8)) + (H6 * 100 * (0.05-0.0115) * ('02_Inputs'!$B$11 * '01_Control'!$B$9 + (1-'02_Inputs'!$B$11) * '01_Control'!$B$8)) + (H7 * 100 * (0.065-0.0115) * ('02_Inputs'!$B$11 * '01_Control'!$B$9 + (1-'02_Inputs'!$B$11) * '01_Control'!$B$8)) + (H8 * 100 * (0.055-0.0115) * ('02_Inputs'!$B$11 * '01_Control'!$B$9 + (1-'02_Inputs'!$B$11) * '01_Control'!$B$8)) + (H9 * 100 * (0.045-0.0115) * ('02_Inputs'!$B$11 * '01_Control'!$B$9 + (1-'02_Inputs'!$B$11) * '01_Control'!$B$8)) -> 0 | I14: =-(I5 * 100 * (0.042-0.0115) * ('02_Inputs'!$B$11 * '01_Control'!$B$9 + (1-'02_Inputs'!$B$11) * '01_Control'!$B$8)) + (I6 * 100 * (0.05-0.0115) * ('02_Inputs'!$B$11 * '01_Control'!$B$9 + (1-'02_Inputs'!$B$11) * '01_Control'!$B$8)) + (I7 * 100 * (0.065-0.0115) * ('02_Inputs'!$B$11 * '01_Control'!$B$9 + (1-'02_Inputs'!$B$11) * '01_Control'!$B$8)) + (I8 * 100 * (0.055-0.0115) * ('02_Inputs'!$B$11 * '01_Control'!$B$9 + (1-'02_Inputs'!$B$11) * '01_Control'!$B$8)) + (I9 * 100 * (0.045-0.0115) * ('02_Inputs'!$B$11 * '01_Control'!$B$9 + (1-'02_Inputs'!$B$11) * '01_Control'!$B$8)) -> 0 | ... BI14: =-(BI5 * 100 * (0.042-0.0115) * ('02_Inputs'!$B$11 * '01_Control'!$B$9 + (1-'02_Inputs'!$B$11) * '01_Control'!$B$8)) + (BI6 * 100 * (0.05-0.0115) * ('02_Inputs'!$B$11 * '01_Control'!$B$9 + (1-'02_Inputs'!$B$11) * '01_Control'!$B$8)) + (BI7 * 100 * (0.065-0.0115) * ('02_Inputs'!$B$11 * '01_Control'!$B$9 + (1-'02_Inputs'!$B$11) * '01_Control'!$B$8)) + (BI8 * 100 * (0.055-0.0115) * ('02_Inputs'!$B$11 * '01_Control'!$B$9 + (1-'02_Inputs'!$B$11) * '01_Control'!$B$8)) + (BI9 * 100 * (0.045-0.0115) * ('02_Inputs'!$B$11 * '01_Control'!$B$9 + (1-'02_Inputs'!$B$11) * '01_Control'!$B$8)) -> 0
B16: =B13 + B14 -> 0 | C16: =C13 + C14 -> 0 | D16: =D13 + D14 -> 0 | E16: =E13 + E14 -> 0 | F16: =F13 + F14 -> 0 | G16: =G13 + G14 -> 0 | H16: =H13 + H14 -> 0 | I16: =I13 + I14 -> 0 | ... BI16: =BI13 + BI14 -> 0
B18: =B11 * 155 -> 0 | C18: =C11 * 155 -> 0 | D18: =D11 * 155 -> 0 | E18: =E11 * 155 -> 0 | F18: =F11 * 155 -> 0 | G18: =G11 * 155 -> 0 | H18: =H11 * 155 -> 0 | I18: =I11 * 155 -> 0 | ... BI18: =BI11 * 155 -> 0
B20: =SUMPRODUCT('02_Inputs'!$B$17:$B$19, '02_Inputs'!$C$17:$C$19) * 1000 / 12 + B16*0.12 -> 0 | C20: =SUMPRODUCT('02_Inputs'!$B$17:$B$19, '02_Inputs'!$C$17:$C$19) * 1000 / 12 + C16*0.12 -> 0 | D20: =SUMPRODUCT('02_Inputs'!$B$17:$B$19, '02_Inputs'!$C$17:$C$19) * 1000 / 12 + D16*0.12 -> 0 | E20: =SUMPRODUCT('02_Inputs'!$B$17:$B$19, '02_Inputs'!$C$17:$C$19) * 1000 / 12 + E16*0.12 -> 0 | F20: =SUMPRODUCT('02_Inputs'!$B$17:$B$19, '02_Inputs'!$C$17:$C$19) * 1000 / 12 + F16*0.12 -> 0 | G20: =SUMPRODUCT('02_Inputs'!$B$17:$B$19, '02_Inputs'!$C$17:$C$19) * 1000 / 12 + G16*0.12 -> 0 | H20: =SUMPRODUCT('02_Inputs'!$B$17:$B$19, '02_Inputs'!$C$17:$C$19) * 1000 / 12 + H16*0.12 -> 0 | I20: =SUMPRODUCT('02_Inputs'!$B$17:$B$19, '02_Inputs'!$C$17:$C$19) * 1000 / 12 + I16*0.12 -> 0 | ... BI20: =SUMPRODUCT('02_Inputs'!$B$17:$B$19, '02_Inputs'!$C$17:$C$19) * 1000 / 12 + BI16*0.12 -> 0
B22: 35000 | C22: 35000 | D22: 35000 | E22: 35000 | F22: 35000 | G22: 35000 | H22: 35000 | I22: 35000 | J22: 35000 | K22: 35000 | L22: 35000 | M22: 35000 | N22: 35000 | O22: 35000 | P22: 35000 | Q22: 35000 | R22: 35000 | S22: 35000 | T22: 35000 | U22: 35000 | V22: 35000 | W22: 35000 | X22: 35000 | Y22: 35000 | Z22: 35000 | AA22: 35000 | AB22: 35000 | AC22: 35000 | AD22: 35000 | AE22: 35000 | AF22: 35000 | AG22: 35000 | AH22: 35000 | AI22: 35000 | AJ22: 35000 | AK22: 35000 | AL22: 35000 | AM22: 35000 | AN22: 35000 | AO22: 35000 | AP22: 35000 | AQ22: 35000 | AR22: 35000 | AS22: 35000 | AT22: 35000 | AU22: 35000 | AV22: 35000 | AW22: 35000 | AX22: 35000 | AY22: 35000 | AZ22: 35000 | BA22: 35000 | BB22: 35000 | BC22: 35000 | BD22: 35000 | BE22: 35000 | BF22: 35000 | BG22: 35000 | BH22: 35000 | BI22: 35000
B24: =B13 * 1.2 -> 0 | C24: =C13 * 1.2 -> 0 | D24: =D13 * 1.2 -> 0 | E24: =E13 * 1.2 -> 0 | F24: =F13 * 1.2 -> 0 | G24: =G13 * 1.2 -> 0 | H24: =H13 * 1.2 -> 0 | I24: =I13 * 1.2 -> 0 | ... BI24: =BI13 * 1.2 -> 0

Sheet 04_Outputs
B3: M1 | C3: M2 | D3: M3 | E3: M4 | F3: M5 | G3: M6 | H3: M7 | I3: M8 | J3: M9 | K3: M10 | L3: M11 | M3: M12 | N3: Y2 | O3: Y3 | P3: Y4 | Q3: Y5
A6: Net Revenue | B6: ='03_Calcs'!B16 -> 0 | C6: ='03_Calcs'!C16 -> 0 | D6: ='03_Calcs'!D16 -> 0 | E6: ='03_Calcs'!E16 -> 0 | F6: ='03_Calcs'!F16 -> 0 | G6: ='03_Calcs'!G16 -> 0 | H6: ='03_Calcs'!H16 -> 0 | I6: ='03_Calcs'!I16 -> 0 | ... M6: ='03_Calcs'!M16 -> 0 | N6: =SUM('03_Calcs'!N16:Y16) -> 0 | O6: =SUM('03_Calcs'!Z16:AK16) -> 0 | P6: =SUM('03_Calcs'!AL16:AW16) -> 0 | Q6: =SUM('03_Calcs'!AX16:BI16) -> 0
A7: COGS | B7: =-'03_Calcs'!B18 -> 0 | C7: =-'03_Calcs'!C18 -> 0 | D7: =-'03_Calcs'!D18 -> 0 | E7: =-'03_Calcs'!E18 -> 0 | F7: =-'03_Calcs'!F18 -> 0 | G7: =-'03_Calcs'!G18 -> 0 | H7: =-'03_Calcs'!H18 -> 0 | I7: =-'03_Calcs'!I18 -> 0 | ... M7: =-'03_Calcs'!M18 -> 0 | N7: =-SUM('03_Calcs'!N18:Y18) -> 0 | O7: =-SUM('03_Calcs'!Z18:AK18) -> 0 | P7: =-SUM('03_Calcs'!AL18:AW18) -> 0 | Q7: =-SUM('03_Calcs'!AX18:BI18) -> 0
A8: OpEx | B8: =-'03_Calcs'!B20 -> 0 | C8: =-'03_Calcs'!C20 -> 0 | D8: =-'03_Calcs'!D20 -> 0 | E8: =-'03_Calcs'!E20 -> 0 | F8: =-'03_Calcs'!F20 -> 0 | G8: =-'03_Calcs'!G20 -> 0 | H8: =-'03_Calcs'!H20 -> 0 | I8: =-'03_Calcs'!I20 -> 0 | ... M8: =-'03_Calcs'!M20 -> 0 | N8: =-SUM('03_Calcs'!N20:Y20) -> 0 | O8: =-SUM('03_Calcs'!Z20:AK20) -> 0 | P8: =-SUM('03_Calcs'!AL20:AW20) -> 0 | Q8: =-SUM('03_Calcs'!AX20:BI20) -> 0
A9: EBITDA | B9: =SUM(B6:B8) -> 0 | C9: =SUM(C6:C8) -> 0 | D9: =SUM(D6:D8) -> 0 | E9: =SUM(E6:E8) -> 0 | F9: =SUM(F6:F8) -> 0 | G9: =SUM(G6:G8) -> 0 | H9: =SUM(H6:H8) -> 0 | I9: =SUM(I6:I8) -> 0 | ... Q9: =SUM(Q6:Q8) -> 0
A13: NPAT | B13: =B9 * 0.7 -> 0 | C13: =C9 * 0.7 -> 0 | D13: =D9 * 0.7 -> 0 | E13: =E9 * 0.7 -> 0 | F13: =F9 * 0.7 -> 0 | G13: =G9 * 0.7 -> 0 | H13: =H9 * 0.7 -> 0 | I13: =I9 * 0.7 -> 0 | ... Q13: =Q9 * 0.7 -> 0
B20: 800000 | C20: =B21 -> 0 | D20: =C21 -> 0 | E20: =D21 -> 0 | F20: =E21 -> 0 | G20: =F21 -> 0 | H20: =G21 -> 0 | I20: =H21 -> 0 | J20: =I21 -> 0 | ... Q20: =P21 -> 0
A21: Closing Cash | B21: =B9*0.8 + B20 -> 0 | C21: =C9*0.8 + C20 -> 0 | D21: =D9*0.8 + D20 -> 0 | E21: =E9*0.8 + E20 -> 0 | F21: =F9*0.8 + F20 -> 0 | G21: =G9*0.8 + G20 -> 0 | H21: =H9*0.8 + H20 -> 0 | I21: =I9*0.8 + I20 -> 0 | ... Q21: =Q9*0.8 + Q20 -> 0
A33: Total Assets | B33: =B21 + 2000000 + '03_Calcs'!B24 -> 0 | C33: =C21 + 2000000 + '03_Calcs'!C24 -> 0 | D33: =D21 + 2000000 + '03_Calcs'!D24 -> 0 | E33: =E21 + 2000000 + '03_Calcs'!E24 -> 0 | F33: =F21 + 2000000 + '03_Calcs'!F24 -> 0 | G33: =G21 + 2000000 + '03_Calcs'!G24 -> 0 | H33: =H21 + 2000000 + '03_Calcs'!H24 -> 0 | I33: =I21 + 2000000 + '03_Calcs'!I24 -> 0 | ... M33: =M21 + 2000000 + '03_Calcs'!M24 -> 0 | N33: =N21 + 2000000 + '03_Calcs'!EP24 -> 0 | O33: =O21 + 2000000 + '03_Calcs'!FB24 -> 0 | P33: =P21 + 2000000 + '03_Calcs'!FN24 -> 0 | Q33: =Q21 + 2000000 + '03_Calcs'!FZ24 -> 0
B36: 2800000 | C36: =B37 -> 0 | D36: =C37 -> 0 | E36: =D37 -> 0 | F36: =E37 -> 0 | G36: =F37 -> 0 | H36: =G37 -> 0 | I36: =H37 -> 0 | J36: =I37 -> 0 | ... Q36: =P37 -> 0
A37: Total Equity | B37: =B36 + B13 -> 0 | C37: =C36 + C13 -> 0 | D37: =D36 + D13 -> 0 | E37: =E36 + E13 -> 0 | F37: =F36 + F13 -> 0 | G37: =G36 + G13 -> 0 | H37: =H36 + H13 -> 0 | I37: =I36 + I13 -> 0 | ... Q37: =Q36 + Q13 -> 0

Sheet 05_Dashboard

Sheet 06_Checks
A1: AUDIT & COVENANTS
A4: Balance Sheet Check (Assets - Equity) | B4: =IF(ABS(Q33-Q37)<100, 'PASS', 'FAIL') -> 0
A5: Minimum Cash Covenant ($500k) | B5: =IF(MIN('04_Outputs'!B21:Q21)>500000, 'PASS', 'FAIL') -> 0
A6: Interest Cover (>4.0x) | B6: =IF(AVERAGE('04_Outputs'!B9:M9)/10000 > 4, 'PASS', 'FAIL') -> 0
